Workbook
Name __FPMExcelClient_Connection: "_FPM_BPCNW10_[http://10.87.9.254:8000/sap/bpc/]_[AMSA_PLC]_[COSTOS]_[false]_[false]\1"

Sheet MLP
A1: {=_xll.EPMDimensionOverrideRange("000","CECO",CECOS!$B$2:$B$128)} -> Expansión de CECO sobrescrita
A2: =_xll.EPMOlapMemberO("[CEBE].[PARENTH1].[JE-]","","Gr Antofagasta Miner","","000") -> Gr Antofagasta Miner
A4: =_xll.EPMOlapMemberO("[ENTITY].[PARENTH1].[1001]","","1001 - Minera Los Pelambres","","000") -> 1001 - Minera Los Pelambres
H7: =_xll.EPMOlapMemberO("[TIME].[PARENTH1].[2022.TOTAL]","","2022.TOTAL","","000") -> 2022.TOTAL | K7: =_xll.EPMOlapMemberO("[TIME].[PARENTH1].[2023.TOTAL]","","2023.TOTAL","","000") -> 2023.TOTAL | N7: =_xll.EPMOlapMemberO("[TIME].[PARENTH1].[2024.TOTAL]","","2024.TOTAL","","000") -> 2024.TOTAL | Q7: =_xll.EPMOlapMemberO("[TIME].[PARENTH1].[2025.TOTAL]","","2025.TOTAL","","000") -> 2025.TOTAL
B8: CECO Código | C8: CECO | D8: VP | E8: Item Relevante | F8: Nodo 3 | G8: CeCo Padre | H8: =_xll.EPMOlapMemberO("[CATEGORY].[].[REAL]","","Real - Real","","000") -> Real - Real | I8: =_xll.EPMOlapMemberO("[CATEGORY].[].[PLAN]","","Plan - Plan","","000") -> Plan - Plan | J8: =_xll.FPMXLClient.TechnicalCategory.EPMLocalMember("Var","001","000") -> Var | K8: =_xll.EPMOlapMemberO("[CATEGORY].[].[REAL]","","Real - Real","","000") -> Real - Real | L8: =_xll.EPMOlapMemberO("[CATEGORY].[].[PLAN]","","Plan - Plan","","000") -> Plan - Plan | M8: =_xll.FPMXLClient.TechnicalCategory.EPMLocalMember("Var","001","000") -> Var | N8: =_xll.EPMOlapMemberO("[CATEGORY].[].[REAL]","","Real - Real","","000") -> Real - Real | O8: =_xll.EPMOlapMemberO("[CATEGORY].[].[PLAN]","","Plan - Plan","","000") -> Plan - Plan | P8: =_xll.FPMXLClient.TechnicalCategory.EPMLocalMember("Var","001","000") -> Var | Q8: =_xll.EPMOlapMemberO("[CATEGORY].[].[REAL]","","Real - Real","","000") -> Real - Real | R8: =_xll.EPMOlapMemberO("[CATEGORY].[].[PLAN]","","Plan - Plan","","000") -> Plan - Plan | S8: =_xll.FPMXLClient.TechnicalCategory.EPMLocalMember("Var","001","000") -> Var
A9: =_xll.EPMOlapMemberO("[CECO].[PARENTH3].[AMSA1001AD4507]","","AMSA1001AD4507 - Comunidades RCA","","000") -> AMSA1001AD4507 - Comunidades RCA | B9: =IFERROR(SUBSTITUTE(TRIM(LEFT(A9,FIND("-",A9)-1)),"AMSA",""),"") -> 1001AD4507 | C9: =IFERROR(_xlfn.XLOOKUP(B9,'CECOS Corporativos'!$D:$D,'CECOS Corporativos'!$E:$E,""),"") -> Asuntos Públicos | D9: =IFERROR(_xlfn.XLOOKUP(B9,'CECOS Corporativos'!$D:$D,'CECOS Corporativos'!$J:$J,""),"") -> VP Asuntos Corporativos | E9: Comunidades RCA | F9: =IFERROR(TRIM(LEFT(G9,FIND("-",G9)-1)),"") -> N100100551 | G9: N100100551 - Obligaciones Legales | J9: =I9-H9 -> 0 | M9: =L9-K9 -> 0 | P9: =O9-N9 -> 0 | Q9: 0 | S9: =R9-Q9 -> 0
A10: =_xll.EPMOlapMemberO("[CECO].[PARENTH3].[AMSA1001AD4507]","","AMSA1001AD4507 - Comunidades RCA","","000") -> AMSA1001AD4507 - Comunidades RCA | B10: =IFERROR(SUBSTITUTE(TRIM(LEFT(A10,FIND("-",A10)-1)),"AMSA",""),"") -> 1001AD4507 | C10: =IFERROR(_xlfn.XLOOKUP(B10,'CECOS Corporativos'!$D:$D,'CECOS Corporativos'!$E:$E,""),"") -> Asuntos Públicos | D10: =IFERROR(_xlfn.XLOOKUP(B10,'CECOS Corporativos'!$D:$D,'CECOS Corporativos'!$J:$J,""),"") -> VP Asuntos Corporativos | E10: Liquidación Interna | F10: =IFERROR(TRIM(LEFT(G10,FIND("-",G10)-1)),"") -> N100100551 | G10: N100100551 - Obligaciones Legales | H10: -40845.34 | J10: =I10-H10 -> 40845.34 | M10: =L10-K10 -> 0 | P10: =O10-N10 -> 0 | S10: =R10-Q10 -> 0
A11: =_xll.EPMOlapMemberO("[CECO].[PARENTH3].[AMSA1001AD4514]","","AMSA1001AD4514 - Acuerdo Caimanes","","000") -> AMSA1001AD4514 - Acuerdo Caimanes | B11: =IFERROR(SUBSTITUTE(TRIM(LEFT(A11,FIND("-",A11)-1)),"AMSA",""),"") -> 1001AD4514 | C11: =IFERROR(_xlfn.XLOOKUP(B11,'CECOS Corporativos'!$D:$D,'CECOS Corporativos'!$E:$E,""),"") -> Asuntos Públicos | D11: =IFERROR(_xlfn.XLOOKUP(B11,'CECOS Corporativos'!$D:$D,'CECOS Corporativos'!$J:$J,""),"") -> VP Asuntos Corporativos | E11: Asesorías y Consulto | F11: =IFERROR(TRIM(LEFT(G11,FIND("-",G11)-1)),"") -> N100100551 | G11: N100100551 - Obligaciones Legales | J11: =I11-H11 -> 0 | M11: =L11-K11 -> 0 | N11: 12409.04 | P11: =O11-N11 -> -12409.04 | S11: =R11-Q11 -> 0
A12: =_xll.EPMOlapMemberO("[CECO].[PARENTH3].[AMSA1001AD4514]","","AMSA1001AD4514 - Acuerdo Caimanes","","000") -> AMSA1001AD4514 - Acuerdo Caimanes | B12: =IFERROR(SUBSTITUTE(TRIM(LEFT(A12,FIND("-",A12)-1)),"AMSA",""),"") -> 1001AD4514 | C12: =IFERROR(_xlfn.XLOOKUP(B12,'CECOS Corporativos'!$D:$D,'CECOS Corporativos'!$E:$E,""),"") -> Asuntos Públicos | D12: =IFERROR(_xlfn.XLOOKUP(B12,'CECOS Corporativos'!$D:$D,'CECOS Corporativos'!$J:$J,""),"") -> VP Asuntos Corporativos | E12: Servicios | F12: =IFERROR(TRIM(LEFT(G12,FIND("-",G12)-1)),"") -> N100100551 | G12: N100100551 - Obligaciones Legales | H12: 17201.81 | J12: =I12-H12 -> -17201.81 | K12: 4445.57 | M12: =L12-K12 -> -4445.57 | N12: -13.38 | O12: 108247 | P12: =O12-N12 -> 108260.38 | Q12: 0 | R12: 140064.47 | S12: =R12-Q12 -> 140064.47
A13: =_xll.EPMOlapMemberO("[CECO].[PARENTH3].[AMSA1001AD4514]","","AMSA1001AD4514 - Acuerdo Caimanes","","000") -> AMSA1001AD4514 - Acuerdo Caimanes | B13: =IFERROR(SUBSTITUTE(TRIM(LEFT(A13,FIND("-",A13)-1)),"AMSA",""),"") -> 1001AD4514 | C13: =IFERROR(_xlfn.XLOOKUP(B13,'CECOS Corporativos'!$D:$D,'CECOS Corporativos'!$E:$E,""),"") -> Asuntos Públicos | D13: =IFERROR(_xlfn.XLOOKUP(B13,'CECOS Corporativos'!$D:$D,'CECOS Corporativos'!$J:$J,""),"") -> VP Asuntos Corporativos | E13: Gastos de Viajes | F13: =IFERROR(TRIM(LEFT(G13,FIND("-",G13)-1)),"") -> N100100551 | G13: N100100551 - Obligaciones Legales | H13: 0 | J13: =I13-H13 -> 0 | M13: =L13-K13 -> 0 | P13: =O13-N13 -> 0 | S13: =R13-Q13 -> 0
A14: =_xll.EPMOlapMemberO("[CECO].[PARENTH3].[AMSA1001AD4514]","","AMSA1001AD4514 - Acuerdo Caimanes","","000") -> AMSA1001AD4514 - Acuerdo Caimanes | B14: =IFERROR(SUBSTITUTE(TRIM(LEFT(A14,FIND("-",A14)-1)),"AMSA",""),"") -> 1001AD4514 | C14: =IFERROR(_xlfn.XLOOKUP(B14,'CECOS Corporativos'!$D:$D,'CECOS Corporativos'!$E:$E,""),"") -> Asuntos Públicos | D14: =IFERROR(_xlfn.XLOOKUP(B14,'CECOS Corporativos'!$D:$D,'CECOS Corporativos'!$J:$J,""),"") -> VP Asuntos Corporativos | E14: Impuestos / Patentes | F14: =IFERROR(TRIM(LEFT(G14,FIND("-",G14)-1)),"") -> N100100551 | G14: N100100551 - Obligaciones Legales | H14: 11424.43 | J14: =I14-H14 -> -11424.43 | M14: =L14-K14 -> 0 | P14: =O14-N14 -> 0 | S14: =R14-Q14 -> 0
A15: =_xll.EPMOlapMemberO("[CECO].[PARENTH3].[AMSA1001AD4514]","","AMSA1001AD4514 - Acuerdo Caimanes","","000") -> AMSA1001AD4514 - Acuerdo Caimanes | B15: =IFERROR(SUBSTITUTE(TRIM(LEFT(A15,FIND("-",A15)-1)),"AMSA",""),"") -> 1001AD4514 | C15: =IFERROR(_xlfn.XLOOKUP(B15,'CECOS Corporativos'!$D:$D,'CECOS Corporativos'!$E:$E,""),"") -> Asuntos Públicos | D15: =IFERROR(_xlfn.XLOOKUP(B15,'CECOS Corporativos'!$D:$D,'CECOS Corporativos'!$J:$J,""),"") -> VP Asuntos Corporativos | E15: Otros Gastos | F15: =IFERROR(TRIM(LEFT(G15,FIND("-",G15)-1)),"") -> N100100551 | G15: N100100551 - Obligaciones Legales | I15: 7706 | J15: =I15-H15 -> 7706 | L15: 1141 | M15: =L15-K15 -> 1141 | P15: =O15-N15 -> 0 | S15: =R15-Q15 -> 0
A16: =_xll.EPMOlapMemberO("[CECO].[PARENTH3].[AMSA1001AD4514]","","AMSA1001AD4514 - Acuerdo Caimanes","","000") -> AMSA1001AD4514 - Acuerdo Caimanes | B16: =IFERROR(SUBSTITUTE(TRIM(LEFT(A16,FIND("-",A16)-1)),"AMSA",""),"") -> 1001AD4514 | C16: =IFERROR(_xlfn.XLOOKUP(B16,'CECOS Corporativos'!$D:$D,'CECOS Corporativos'!$E:$E,""),"") -> Asuntos Públicos | D16: =IFERROR(_xlfn.XLOOKUP(B16,'CECOS Corporativos'!$D:$D,'CECOS Corporativos'!$J:$J,""),"") -> VP Asuntos Corporativos | E16: Liquidación Interna | F16: =IFERROR(TRIM(LEFT(G16,FIND("-",G16)-1)),"") -> N100100551 | G16: N100100551 - Obligaciones Legales | H16: 8303.01 | J16: =I16-H16 -> -8303.01 | K16: 135549.49 | M16: =L16-K16 -> -135549.49 | N16: 95867.08 | P16: =O16-N16 -> -95867.08 | Q16: 133068.93 | S16: =R16-Q16 -> -133068.93
A17: =_xll.EPMOlapMemberO("[CECO].[PARENTH3].[AMSA1001AD4521]","","AMSA1001AD4521 - Comunic Externa RCA","","000") -> AMSA1001AD4521 - Comunic Externa RCA | B17: =IFERROR(SUBSTITUTE(TRIM(LEFT(A17,FIND("-",A17)-1)),"AMSA",""),"") -> 1001AD4521 | C17: =IFERROR(_xlfn.XLOOKUP(B17,'CECOS Corporativos'!$D:$D,'CECOS Corporativos'!$E:$E,""),"") -> Comunicaciones | D17: =IFERROR(_xlfn.XLOOKUP(B17,'CECOS Corporativos'!$D:$D,'CECOS Corporativos'!$J:$J,""),"") -> VP Asuntos Corporativos | E17: Servicios | F17: =IFERROR(TRIM(LEFT(G17,FIND("-",G17)-1)),"") -> N100100551 | G17: N100100551 - Obligaciones Legales | H17: 1582.48 | I17: 768786 | J17: =I17-H17 -> 767203.52 | L17: 540202 | M17: =L17-K17 -> 540202 | O17: 605859 | P17: =O17-N17 -> 605859 | R17: 769603.31 | S17: =R17-Q17 -> 769603.31
A18: =_xll.EPMOlapMemberO("[CECO].[PARENTH3].[AMSA1001AD4521]","","AMSA1001AD4521 - Comunic Externa RCA","","000") -> AMSA1001AD4521 - Comunic Externa RCA | B18: =IFERROR(SUBSTITUTE(TRIM(LEFT(A18,FIND("-",A18)-1)),"AMSA",""),"") -> 1001AD4521 | C18: =IFERROR(_xlfn.XLOOKUP(B18,'CECOS Corporativos'!$D:$D,'CECOS Corporativos'!$E:$E,""),"") -> Comunicaciones | D18: =IFERROR(_xlfn.XLOOKUP(B18,'CECOS Corporativos'!$D:$D,'CECOS Corporativos'!$J:$J,""),"") -> VP Asuntos Corporativos | E18: Liquidación Interna | F18: =IFERROR(TRIM(LEFT(G18,FIND("-",G18)-1)),"") -> N100100551 | G18: N100100551 - Obligaciones Legales | H18: 729013.91 | J18: =I18-H18 -> -729013.91 | K18: 636123.14 | M18: =L18-K18 -> -636123.14 | N18: 518147.73 | P18: =O18-N18 -> -518147.73 | Q18: 653262.76 | S18: =R18-Q18 -> -653262.76
A19: =_xll.EPMOlapMemberO("[CECO].[PARENTH3].[AMSA1001AD4500]","","AMSA1001AD4500 - Comun.Mitig. y Comp.","","000") -> AMSA1001AD4500 - Comun.Mitig. y Comp. | B19: =IFERROR(SUBSTITUTE(TRIM(LEFT(A19,FIND("-",A19)-1)),"AMSA",""),"") -> 1001AD4500 | C19: =IFERROR(_xlfn.XLOOKUP(B19,'CECOS Corporativos'!$D:$D,'CECOS Corporativos'!$E:$E,""),"") -> Asuntos Públicos | D19: =IFERROR(_xlfn.XLOOKUP(B19,'CECOS Corporativos'!$D:$D,'CECOS Corporativos'!$J:$J,""),"") -> VP Asuntos Corporativos | E19: Asesorías y Consulto | F19: =IFERROR(TRIM(LEFT(G19,FIND("-",G19)-1)),"") -> N100100552 | G19: N100100552 - Mitigación y Compens | H19: 0 | J19: =I19-H19 -> 0 | K19: 3391.41 | M19: =L19-K19 -> -3391.41 | N19: 46722.03 | P19: =O19-N19 -> -46722.03 | Q19: 28623.16 | S19: =R19-Q19 -> -28623.16
A20: =_xll.EPMOlapMemberO("[CECO].[PARENTH3].[AMSA1001AD4500]","","AMSA1001AD4500 - Comun.Mitig. y Comp.","","000") -> AMSA1001AD4500 - Comun.Mitig. y Comp. | B20: =IFERROR(SUBSTITUTE(TRIM(LEFT(A20,FIND("-",A20)-1)),"AMSA",""),"") -> 1001AD4500 | C20: =IFERROR(_xlfn.XLOOKUP(B20,'CECOS Corporativos'!$D:$D,'CECOS Corporativos'!$E:$E,""),"") -> Asuntos Públicos | D20: =IFERROR(_xlfn.XLOOKUP(B20,'CECOS Corporativos'!$D:$D,'CECOS Corporativos'!$J:$J,""),"") -> VP Asuntos Corporativos | E20: Arriendos | F20: =IFERROR(TRIM(LEFT(G20,FIND("-",G20)-1)),"") -> N100100552 | G20: N100100552 - Mitigación y Compens | H20: 0 | J20: =I20-H20 -> 0 | M20: =L20-K20 -> 0 | P20: =O20-N20 -> 0 | S20: =R20-Q20 -> 0
A21: =_xll.EPMOlapMemberO("[CECO].[PARENTH3].[AMSA1001AD4500]","","AMSA1001AD4500 - Comun.Mitig. y Comp.","","000") -> AMSA1001AD4500 - Comun.Mitig. y Comp. | B21: =IFERROR(SUBSTITUTE(TRIM(LEFT(A21,FIND("-",A21)-1)),"AMSA",""),"") -> 1001AD4500 | C21: =IFERROR(_xlfn.XLOOKUP(B21,'CECOS Corporativos'!$D:$D,'CECOS Corporativos'!$E:$E,""),"") -> Asuntos Públicos | D21: =IFERROR(_xlfn.XLOOKUP(B21,'CECOS Corporativos'!$D:$D,'CECOS Corporativos'!$J:$J,""),"") -> VP Asuntos Corporativos | E21: Servicios | F21: =IFERROR(TRIM(LEFT(G21,FIND("-",G21)-1)),"") -> N100100552 | G21: N100100552 - Mitigación y Compens | H21: 676240.12 | J21: =I21-H21 -> -676240.12 | K21: 350817.41 | M21: =L21-K21 -> -350817.41 | N21: 113225.05 | P21: =O21-N21 -> -113225.05 | Q21: 30566.79 | S21: =R21-Q21 -> -30566.79
A22: =_xll.EPMOlapMemberO("[CECO].[PARENTH3].[AMSA1001AD4500]","","AMSA1001AD4500 - Comun.Mitig. y Comp.","","000") -> AMSA1001AD4500 - Comun.Mitig. y Comp. | B22: =IFERROR(SUBSTITUTE(TRIM(LEFT(A22,FIND("-",A22)-1)),"AMSA",""),"") -> 1001AD4500 | C22: =IFERROR(_xlfn.XLOOKUP(B22,'CECOS Corporativos'!$D:$D,'CECOS Corporativos'!$E:$E,""),"") -> Asuntos Públicos | D22: =IFERROR(_xlfn.XLOOKUP(B22,'CECOS Corporativos'!$D:$D,'CECOS Corporativos'!$J:$J,""),"") -> VP Asuntos Corporativos | E22: Informática y Comuni | F22: =IFERROR(TRIM(LEFT(G22,FIND("-",G22)-1)),"") -> N100100552 | G22: N100100552 - Mitigación y Compens | H22: 1829.96 | I22: 1740 | J22: =I22-H22 -> -89.96 | K22: 1625.45 | L22: 1996 | M22: =L22-K22 -> 370.55 | N22: 1896.59 | O22: 1956 | P22: =O22-N22 -> 59.41 | Q22: 2321.69 | R22: 2112 | S22: =R22-Q22 -> -209.69
A23: =_xll.EPMOlapMemberO("[CECO].[PARENTH3].[AMSA1001AD4500]","","AMSA1001AD4500 - Comun.Mitig. y Comp.","","000") -> AMSA1001AD4500 - Comun.Mitig. y Comp. | B23: =IFERROR(SUBSTITUTE(TRIM(LEFT(A23,FIND("-",A23)-1)),"AMSA",""),"") -> 1001AD4500 | C23: =IFERROR(_xlfn.XLOOKUP(B23,'CECOS Corporativos'!$D:$D,'CECOS Corporativos'!$E:$E,""),"") -> Asuntos Públicos | D23: =IFERROR(_xlfn.XLOOKUP(B23,'CECOS Corporativos'!$D:$D,'CECOS Corporativos'!$J:$J,""),"") -> VP Asuntos Corporativos | E23: Gastos de Viajes | F23: =IFERROR(TRIM(LEFT(G23,FIND("-",G23)-1)),"") -> N100100552 | G23: N100100552 - Mitigación y Compens | J23: =I23-H23 -> 0 | M23: =L23-K23 -> 0 | N23: 0 | P23: =O23-N23 -> 0 | S23: =R23-Q23 -> 0
A24: =_xll.EPMOlapMemberO("[CECO].[PARENTH3].[AMSA1001AD4500]","","AMSA1001AD4500 - Comun.Mitig. y Comp.","","000") -> AMSA1001AD4500 - Comun.Mitig. y Comp. | B24: =IFERROR(SUBSTITUTE(TRIM(LEFT(A24,FIND("-",A24)-1)),"AMSA",""),"") -> 1001AD4500 | C24: =IFERROR(_xlfn.XLOOKUP(B24,'CECOS Corporativos'!$D:$D,'CECOS Corporativos'!$E:$E,""),"") -> Asuntos Públicos | D24: =IFERROR(_xlfn.XLOOKUP(B24,'CECOS Corporativos'!$D:$D,'CECOS Corporativos'!$J:$J,""),"") -> VP Asuntos Corporativos | E24: Impuestos / Patentes | F24: =IFERROR(TRIM(LEFT(G24,FIND("-",G24)-1)),"") -> N100100552 | G24: N100100552 - Mitigación y Compens | I24: 16767 | J24: =I24-H24 -> 16767 | M24: =L24-K24 -> 0 | P24: =O24-N24 -> 0 | S24: =R24-Q24 -> 0
A25: =_xll.EPMOlapMemberO("[CECO].[PARENTH3].[AMSA1001AD4500]","","AMSA1001AD4500 - Comun.Mitig. y Comp.","","000") -> AMSA1001AD4500 - Comun.Mitig. y Comp. | B25: =IFERROR(SUBSTITUTE(TRIM(LEFT(A25,FIND("-",A25)-1)),"AMSA",""),"") -> 1001AD4500 | C25: =IFERROR(_xlfn.XLOOKUP(B25,'CECOS Corporativos'!$D:$D,'CECOS Corporativos'!$E:$E,""),"") -> Asuntos Públicos | D25: =IFERROR(_xlfn.XLOOKUP(B25,'CECOS Corporativos'!$D:$D,'CECOS Corporativos'!$J:$J,""),"") -> VP Asuntos Corporativos | E25: Otros Gastos | F25: =IFERROR(TRIM(LEFT(G25,FIND("-",G25)-1)),"") -> N100100552 | G25: N100100552 - Mitigación y Compens | H25: -0.01 | J25: =I25-H25 -> 0.01 | K25: 0 | M25: =L25-K25 -> 0 | P25: =O25-N25 -> 0 | S25: =R25-Q25 -> 0
A26: =_xll.EPMOlapMemberO("[CECO].[PARENTH3].[AMSA1001AD4500]","","AMSA1001AD4500 - Comun.Mitig. y Comp.","","000") -> AMSA1001AD4500 - Comun.Mitig. y Comp. | B26: =IFERROR(SUBSTITUTE(TRIM(LEFT(A26,FIND("-",A26)-1)),"AMSA",""),"") -> 1001AD4500 | C26: =IFERROR(_xlfn.XLOOKUP(B26,'CECOS Corporativos'!$D:$D,'CECOS Corporativos'!$E:$E,""),"") -> Asuntos Públicos | D26: =IFERROR(_xlfn.XLOOKUP(B26,'CECOS Corporativos'!$D:$D,'CECOS Corporativos'!$J:$J,""),"") -> VP Asuntos Corporativos | E26: Liquidación Interna | F26: =IFERROR(TRIM(LEFT(G26,FIND("-",G26)-1)),"") -> N100100552 | G26: N100100552 - Mitigación y Compens | H26: 327516.76 | J26: =I26-H26 -> -327516.76 | K26: 4550.71 | M26: =L26-K26 -> -4550.71 | N26: 21763.79 | P26: =O26-N26 -> -21763.79 | Q26: 51834.24 | S26: =R26-Q26 -> -51834.24
A27: =_xll.EPMOlapMemberO("[CECO].[PARENTH3].[AMSA1001AD4533]","","AMSA1001AD4533 - Acuerdo Camisas","","000") -> AMSA1001AD4533 - Acuerdo Camisas | B27: =IFERROR(SUBSTITUTE(TRIM(LEFT(A27,FIND("-",A27)-1)),"AMSA",""),"") -> 1001AD4533 | C27: =IFERROR(_xlfn.XLOOKUP(B27,'CECOS Corporativos'!$D:$D,'CECOS Corporativos'!$E:$E,""),"") -> Asuntos Públicos | D27: =IFERROR(_xlfn.XLOOKUP(B27,'CECOS Corporativos'!$D:$D,'CECOS Corporativos'!$J:$J,""),"") -> VP Asuntos Corporativos | E27: Liquidación Interna | F27: =IFERROR(TRIM(LEFT(G27,FIND("-",G27)-1)),"") -> N100100552 | G27: N100100552 - Mitigación y Compens | J27: =I27-H27 -> 0 | K27: 9425.4 | M27: =L27-K27 -> -9425.4 | P27: =O27-N27 -> 0 | S27: =R27-Q27 -> 0
A28: =_xll.EPMOlapMemberO("[CECO].[PARENTH3].[AMSA1001AD4534]","","AMSA1001AD4534 - Acuerdo Llimpo","","000") -> AMSA1001AD4534 - Acuerdo Llimpo | B28: =IFERROR(SUBSTITUTE(TRIM(LEFT(A28,FIND("-",A28)-1)),"AMSA",""),"") -> 1001AD4534 | C28: =IFERROR(_xlfn.XLOOKUP(B28,'CECOS Corporativos'!$D:$D,'CECOS Corporativos'!$E:$E,""),"") -> Asuntos Públicos | D28: =IFERROR(_xlfn.XLOOKUP(B28,'CECOS Corporativos'!$D:$D,'CECOS Corporativos'!$J:$J,""),"") -> VP Asuntos Corporativos | E28: Servicios | F28: =IFERROR(TRIM(LEFT(G28,FIND("-",G28)-1)),"") -> N100100552 | G28: N100100552 - Mitigación y Compens | J28: =I28-H28 -> 0 | M28: =L28-K28 -> 0 | N28: 189.3 | P28: =O28-N28 -> -189.3 | R28: 321711.11 | S28: =R28-Q28 -> 321711.11
A29: =_xll.EPMOlapMemberO("[CECO].[PARENTH3].[AMSA1001AD4534]","","AMSA1001AD4534 - Acuerdo Llimpo","","000") -> AMSA1001AD4534 - Acuerdo Llimpo | B29: =IFERROR(SUBSTITUTE(TRIM(LEFT(A29,FIND("-",A29)-1)),"AMSA",""),"") -> 1001AD4534 | C29: =IFERROR(_xlfn.XLOOKUP(B29,'CECOS Corporativos'!$D:$D,'CECOS Corporativos'!$E:$E,""),"") -> Asuntos Públicos | D29: =IFERROR(_xlfn.XLOOKUP(B29,'CECOS Corporativos'!$D:$D,'CECOS Corporativos'!$J:$J,""),"") -> VP Asuntos Corporativos | E29: Liquidación Interna | F29: =IFERROR(TRIM(LEFT(G29,FIND("-",G29)-1)),"") -> N100100552 | G29: N100100552 - Mitigación y Compens | J29: =I29-H29 -> 0 | K29: 100508.48 | M29: =L29-K29 -> -100508.48 | N29: 21912.53 | P29: =O29-N29 -> -21912.53 | Q29: 2170.64 | S29: =R29-Q29 -> -2170.64
A30: =_xll.EPMOlapMemberO("[CECO].[PARENTH3].[AMSA1001AD4511]","","AMSA1001AD4511 - Somos Choapa IS","","000") -> AMSA1001AD4511 - Somos Choapa IS | B30: =IFERROR(SUBSTITUTE(TRIM(LEFT(A30,FIND("-",A30)-1)),"AMSA",""),"") -> 1001AD4511 | C30: =IFERROR(_xlfn.XLOOKUP(B30,'CECOS Corporativos'!$D:$D,'CECOS Corporativos'!$E:$E,""),"") -> Asuntos Públicos | D30: =IFERROR(_xlfn.XLOOKUP(B30,'CECOS Corporativos'!$D:$D,'CECOS Corporativos'!$J:$J,""),"") -> VP Asuntos Corporativos | E30: Servicios | F30: =IFERROR(TRIM(LEFT(G30,FIND("-",G30)-1)),"") -> N100100553 | G30: N100100553 - Inversión Social | H30: 0 | I30: 63953 | J30: =I30-H30 -> 63953 | L30: 45145 | M30: =L30-K30 -> 45145 | N30: 0 | P30: =O30-N30 -> 0 | S30: =R30-Q30 -> 0
A31: =_xll.EPMOlapMemberO("[CECO].[PARENTH3].[AMSA1001AD4511]","","AMSA1001AD4511 - Somos Choapa IS","","000") -> AMSA1001AD4511 - Somos Choapa IS | B31: =IFERROR(SUBSTITUTE(TRIM(LEFT(A31,FIND("-",A31)-1)),"AMSA",""),"") -> 1001AD4511 | C31: =IFERROR(_xlfn.XLOOKUP(B31,'CECOS Corporativos'!$D:$D,'CECOS Corporativos'!$E:$E,""),"") -> Asuntos Públicos | D31: =IFERROR(_xlfn.XLOOKUP(B31,'CECOS Corporativos'!$D:$D,'CECOS Corporativos'!$J:$J,""),"") -> VP Asuntos Corporativos | E31: Liquidación Interna | F31: =IFERROR(TRIM(LEFT(G31,FIND("-",G31)-1)),"") -> N100100553 | G31: N100100553 - Inversión Social | H31: 20445.06 | J31: =I31-H31 -> -20445.06 | K31: -1149.46 | M31: =L31-K31 -> 1149.46 | N31: 0 | P31: =O31-N31 -> 0 | Q31: 17385.71 | S31: =R31-Q31 -> -17385.71
A32: =_xll.EPMOlapMemberO("[CECO].[PARENTH3].[AMSA1001AD4518]","","AMSA1001AD4518 - Comunidades IS","","000") -> AMSA1001AD4518 - Comunidades IS | B32: =IFERROR(SUBSTITUTE(TRIM(LEFT(A32,FIND("-",A32)-1)),"AMSA",""),"") -> 1001AD4518 | C32: =IFERROR(_xlfn.XLOOKUP(B32,'CECOS Corporativos'!$D:$D,'CECOS Corporativos'!$E:$E,""),"") -> Asuntos Públicos | D32: =IFERROR(_xlfn.XLOOKUP(B32,'CECOS Corporativos'!$D:$D,'CECOS Corporativos'!$J:$J,""),"") -> VP Asuntos Corporativos | E32: Servicios | F32: =IFERROR(TRIM(LEFT(G32,FIND("-",G32)-1)),"") -> N100100553 | G32: N100100553 - Inversión Social | I32: 141065 | J32: =I32-H32 -> 141065 | L32: 136813 | M32: =L32-K32 -> 136813 | O32: 240392 | P32: =O32-N32 -> 240392 | S32: =R32-Q32 -> 0
A33: =_xll.EPMOlapMemberO("[CECO].[PARENTH3].[AMSA1001AD4518]","","AMSA1001AD4518 - Comunidades IS","","000") -> AMSA1001AD4518 - Comunidades IS | B33: =IFERROR(SUBSTITUTE(TRIM(LEFT(A33,FIND("-",A33)-1)),"AMSA",""),"") -> 1001AD4518 | C33: =IFERROR(_xlfn.XLOOKUP(B33,'CECOS Corporativos'!$D:$D,'CECOS Corporativos'!$E:$E,""),"") -> Asuntos Públicos | D33: =IFERROR(_xlfn.XLOOKUP(B33,'CECOS Corporativos'!$D:$D,'CECOS Corporativos'!$J:$J,""),"") -> VP Asuntos Corporativos | E33: Liquidación Interna | F33: =IFERROR(TRIM(LEFT(G33,FIND("-",G33)-1)),"") -> N100100553 | G33: N100100553 - Inversión Social | H33: 455677.99 | J33: =I33-H33 -> -455677.99 | K33: 119045.82 | M33: =L33-K33 -> -119045.82 | N33: 367358.45 | P33: =O33-N33 -> -367358.45 | Q33: 256213.4 | S33: =R33-Q33 -> -256213.4
A34: =_xll.EPMOlapMemberO("[CECO].[PARENTH3].[AMSA1001AD4519]","","AMSA1001AD4519 - Empleabilidad IS","","000") -> AMSA1001AD4519 - Empleabilidad IS | B34: =IFERROR(SUBSTITUTE(TRIM(LEFT(A34,FIND("-",A34)-1)),"AMSA",""),"") -> 1001AD4519 | C34: =IFERROR(_xlfn.XLOOKUP(B34,'CECOS Corporativos'!$D:$D,'CECOS Corporativos'!$E:$E,""),"") -> Empleabilidad | D34: =IFERROR(_xlfn.XLOOKUP(B34,'CECOS Corporativos'!$D:$D,'CECOS Corporativos'!$J:$J,""),"") -> VP Asuntos Corporativos | E34: Servicios | F34: =IFERROR(TRIM(LEFT(G34,FIND("-",G34)-1)),"") -> N100100553 | G34: N100100553 - Inversión Social | I34: 192641 | J34: =I34-H34 -> 192641 | L34: 174932 | M34: =L34-K34 -> 174932 | O34: 275985 | P34: =O34-N34 -> 275985 | R34: 268583.64 | S34: =R34-Q34 -> 268583.64
A35: =_xll.EPMOlapMemberO("[CECO].[PARENTH3].[AMSA1001AD4519]","","AMSA1001AD4519 - Empleabilidad IS","","000") -> AMSA1001AD4519 - Empleabilidad IS | B35: =IFERROR(SUBSTITUTE(TRIM(LEFT(A35,FIND("-",A35)-1)),"AMSA",""),"") -> 1001AD4519 | C35: =IFERROR(_xlfn.XLOOKUP(B35,'CECOS Corporativos'!$D:$D,'CECOS Corporativos'!$E:$E,""),"") -> Empleabilidad | D35: =IFERROR(_xlfn.XLOOKUP(B35,'CECOS Corporativos'!$D:$D,'CECOS Corporativos'!$J:$J,""),"") -> VP Asuntos Corporativos | E35: Liquidación Interna | F35: =IFERROR(TRIM(LEFT(G35,FIND("-",G35)-1)),"") -> N100100553 | G35: N100100553 - Inversión Social | J35: =I35-H35 -> 0 | K35: 118047.55 | M35: =L35-K35 -> -118047.55 | N35: 99445.93 | P35: =O35-N35 -> -99445.93 | Q35: 546127.44 | S35: =R35-Q35 -> -546127.44
A36: =_xll.EPMOlapMemberO("[CECO].[PARENTH3].[AMSA1001AD0506]","","AMSA1001AD0506 - VPACS Corporativo","","000") -> AMSA1001AD0506 - VPACS Corporativo | B36: =IFERROR(SUBSTITUTE(TRIM(LEFT(A36,FIND("-",A36)-1)),"AMSA",""),"") -> 1001AD0506 | C36: =IFERROR(_xlfn.XLOOKUP(B36,'CECOS Corporativos'!$D:$D,'CECOS Corporativos'!$E:$E,""),"") -> VPACS Corporativo (HH Corporativo) | D36: =IFERROR(_xlfn.XLOOKUP(B36,'CECOS Corporativos'!$D:$D,'CECOS Corporativos'!$J:$J,""),"") -> VP Asuntos Corporativos | E36: Servicios Corporativ | F36: =IFERROR(TRIM(LEFT(G36,FIND("-",G36)-1)),"") -> N100100554 | G36: N100100554 - Otros programas y Op | J36: =I36-H36 -> 0 | M36: =L36-K36 -> 0 | N36: 5119721 | O36: 5672806 | P36: =O36-N36 -> 553085 | Q36: 4238493 | R36: 4448965.6 | S36: =R36-Q36 -> 210472.56
A37: =_xll.EPMOlapMemberO("[CECO].[PARENTH3].[AMSA1001AD4513]","","AMSA1001AD4513 - Fundación","","000") -> AMSA1001AD4513 - Fundación | B37: =IFERROR(SUBSTITUTE(TRIM(LEFT(A37,FIND("-",A37)-1)),"AMSA",""),"") -> 1001AD4513 | C37: =IFERROR(_xlfn.XLOOKUP(B37,'CECOS Corporativos'!$D:$D,'CECOS Corporativos'!$E:$E,""),"") -> Fundación FMLP | D37: =IFERROR(_xlfn.XLOOKUP(B37,'CECOS Corporativos'!$D:$D,'CECOS Corporativos'!$J:$J,""),"") -> VP Asuntos Corporativos | E37: Informática y Comuni | F37: =IFERROR(TRIM(LEFT(G37,FIND("-",G37)-1)),"") -> N100100554 | G37: N100100554 - Otros programas y Op | H37: 2411.8 | J37: =I37-H37 -> -2411.8 | K37: 3832.4 | M37: =L37-K37 -> -3832.4 | N37: 7977.38 | P37: =O37-N37 -> -7977.38 | Q37: 7281.45 | S37: =R37-Q37 -> -7281.45
A38: =_xll.EPMOlapMemberO("[CECO].[PARENTH3].[AMSA1001AD4517]","","AMSA1001AD4517 - Comunicación Externa","","000") -> AMSA1001AD4517 - Comunicación Externa | B38: =IFERROR(SUBSTITUTE(TRIM(LEFT(A38,FIND("-",A38)-1)),"AMSA",""),"") -> 1001AD4517 | C38: =IFERROR(_xlfn.XLOOKUP(B38,'CECOS Corporativos'!$D:$D,'CECOS Corporativos'!$E:$E,""),"") -> Comunicaciones | D38: =IFERROR(_xlfn.XLOOKUP(B38,'CECOS Corporativos'!$D:$D,'CECOS Corporativos'!$J:$J,""),"") -> VP Asuntos Corporativos | E38: Administración Perso | F38: =IFERROR(TRIM(LEFT(G38,FIND("-",G38)-1)),"") -> N100100554 | G38: N100100554 - Otros programas y Op | H38: 0 | J38: =I38-H38 -> 0 | M38: =L38-K38 -> 0 | P38: =O38-N38 -> 0 | S38: =R38-Q38 -> 0
A39: =_xll.EPMOlapMemberO("[CECO].[PARENTH3].[AMSA1001AD4517]","","AMSA1001AD4517 - Comunicación Externa","","000") -> AMSA1001AD4517 - Comunicación Externa | B39: =IFERROR(SUBSTITUTE(TRIM(LEFT(A39,FIND("-",A39)-1)),"AMSA",""),"") -> 1001AD4517 | C39: =IFERROR(_xlfn.XLOOKUP(B39,'CECOS Corporativos'!$D:$D,'CECOS Corporativos'!$E:$E,""),"") -> Comunicaciones | D39: =IFERROR(_xlfn.XLOOKUP(B39,'CECOS Corporativos'!$D:$D,'CECOS Corporativos'!$J:$J,""),"") -> VP Asuntos Corporativos | E39: Entrenamiento | F39: =IFERROR(TRIM(LEFT(G39,FIND("-",G39)-1)),"") -> N100100554 | G39: N100100554 - Otros programas y Op | J39: =I39-H39 -> 0 | K39: -3510.93 | M39: =L39-K39 -> 3510.93 | P39: =O39-N39 -> 0 | S39: =R39-Q39 -> 0
A40: =_xll.EPMOlapMemberO("[CECO].[PARENTH3].[AMSA1001AD4517]","","AMSA1001AD4517 - Comunicación Externa","","000") -> AMSA1001AD4517 - Comunicación Externa | B40: =IFERROR(SUBSTITUTE(TRIM(LEFT(A40,FIND("-",A40)-1)),"AMSA",""),"") -> 1001AD4517 | C40: =IFERROR(_xlfn.XLOOKUP(B40,'CECOS Corporativos'!$D:$D,'CECOS Corporativos'!$E:$E,""),"") -> Comunicaciones | D40: =IFERROR(_xlfn.XLOOKUP(B40,'CECOS Corporativos'!$D:$D,'CECOS Corporativos'!$J:$J,""),"") -> VP Asuntos Corporativos | E40: Asesorías y Consulto | F40: =IFERROR(TRIM(LEFT(G40,FIND("-",G40)-1)),"") -> N100100554 | G40: N100100554 - Otros programas y Op | H40: 132591.18 | I40: 63667 | J40: =I40-H40 -> -68924.18 | K40: 172369.87 | L40: 23694 | M40: =L40-K40 -> -148675.87 | N40: 0 | O40: 46937 | P40: =O40-N40 -> 46937 | S40: =R40-Q40 -> 0
A41: =_xll.EPMOlapMemberO("[CECO].[PARENTH3].[AMSA1001AD4517]","","AMSA1001AD4517 - Comunicación Externa","","000") -> AMSA1001AD4517 - Comunicación Externa | B41: =IFERROR(SUBSTITUTE(TRIM(LEFT(A41,FIND("-",A41)-1)),"AMSA",""),"") -> 1001AD4517 | C41: =IFERROR(_xlfn.XLOOKUP(B41,'CECOS Corporativos'!$D:$D,'CECOS Corporativos'!$E:$E,""),"") -> Comunicaciones | D41: =IFERROR(_xlfn.XLOOKUP(B41,'CECOS Corporativos'!$D:$D,'CECOS Corporativos'!$J:$J,""),"") -> VP Asuntos Corporativos | E41: Servicios | F41: =IFERROR(TRIM(LEFT(G41,FIND("-",G41)-1)),"") -> N100100554 | G41: N100100554 - Otros programas y Op | H41: 0 | I41: 19181 | J41: =I41-H41 -> 19181 | K41: 107399.96 | M41: =L41-K41 -> -107399.96 | N41: -117465.5 | P41: =O41-N41 -> 117465.5 | S41: =R41-Q41 -> 0
A42: =_xll.EPMOlapMemberO("[CECO].[PARENTH3].[AMSA1001AD4517]","","AMSA1001AD4517 - Comunicación Externa","","000") -> AMSA1001AD4517 - Comunicación Externa | B42: =IFERROR(SUBSTITUTE(TRIM(LEFT(A42,FIND("-",A42)-1)),"AMSA",""),"") -> 1001AD4517 | C42: =IFERROR(_xlfn.XLOOKUP(B42,'CECOS Corporativos'!$D:$D,'CECOS Corporativos'!$E:$E,""),"") -> Comunicaciones | D42: =IFERROR(_xlfn.XLOOKUP(B42,'CECOS Corporativos'!$D:$D,'CECOS Corporativos'!$J:$J,""),"") -> VP Asuntos Corporativos | E42: Informática y Comuni | F42: =IFERROR(TRIM(LEFT(G42,FIND("-",G42)-1)),"") -> N100100554 | G42: N100100554 - Otros programas y Op | H42: 57605.28 | I42: 90100 | J42: =I42-H42 -> 32494.72 | K42: -10.25 | L42: 304314 | M42: =L42-K42 -> 304324.25 | O42: 655497 | P42: =O42-N42 -> 655497 | Q42: 14.79 | R42: 232088.88 | S42: =R42-Q42 -> 232074.09
A43: =_xll.EPMOlapMemberO("[CECO].[PARENTH3].[AMSA1001AD4517]","","AMSA1001AD4517 - Comunicación Externa","","000") -> AMSA1001AD4517 - Comunicación Externa | B43: =IFERROR(SUBSTITUTE(TRIM(LEFT(A43,FIND("-",A43)-1)),"AMSA",""),"") -> 1001AD4517 | C43: =IFERROR(_xlfn.XLOOKUP(B43,'CECOS Corporativos'!$D:$D,'CECOS Corporativos'!$E:$E,""),"") -> Comunicaciones | D43: =IFERROR(_xlfn.XLOOKUP(B43,'CECOS Corporativos'!$D:$D,'CECOS Corporativos'!$J:$J,""),"") -> VP Asuntos Corporativos | E43: Gastos de Viajes | F43: =IFERROR(TRIM(LEFT(G43,FIND("-",G43)-1)),"") -> N100100554 | G43: N100100554 - Otros programas y Op | J43: =I43-H43 -> 0 | K43: -11500.64 | M43: =L43-K43 -> 11500.64 | P43: =O43-N43 -> 0 | S43: =R43-Q43 -> 0
A44: =_xll.EPMOlapMemberO("[CECO].[PARENTH3].[AMSA1001AD4517]","","AMSA1001AD4517 - Comunicación Externa","","000") -> AMSA1001AD4517 - Comunicación Externa | B44: =IFERROR(SUBSTITUTE(TRIM(LEFT(A44,FIND("-",A44)-1)),"AMSA",""),"") -> 1001AD4517 | C44: =IFERROR(_xlfn.XLOOKUP(B44,'CECOS Corporativos'!$D:$D,'CECOS Corporativos'!$E:$E,""),"") -> Comunicaciones | D44: =IFERROR(_xlfn.XLOOKUP(B44,'CECOS Corporativos'!$D:$D,'CECOS Corporativos'!$J:$J,""),"") -> VP Asuntos Corporativos | E44: Seguros | F44: =IFERROR(TRIM(LEFT(G44,FIND("-",G44)-1)),"") -> N100100554 | G44: N100100554 - Otros programas y Op | J44: =I44-H44 -> 0 | M44: =L44-K44 -> 0 | N44: 0 | P44: =O44-N44 -> 0 | S44: =R44-Q44 -> 0
A45: =_xll.EPMOlapMemberO("[CECO].[PARENTH3].[AMSA1001AD4517]","","AMSA1001AD4517 - Comunicación Externa","","000") -> AMSA1001AD4517 - Comunicación Externa | B45: =IFERROR(SUBSTITUTE(TRIM(LEFT(A45,FIND("-",A45)-1)),"AMSA",""),"") -> 1001AD4517 | C45: =IFERROR(_xlfn.XLOOKUP(B45,'CECOS Corporativos'!$D:$D,'CECOS Corporativos'!$E:$E,""),"") -> Comunicaciones | D45: =IFERROR(_xlfn.XLOOKUP(B45,'CECOS Corporativos'!$D:$D,'CECOS Corporativos'!$J:$J,""),"") -> VP Asuntos Corporativos | E45: Impuestos / Patentes | F45: =IFERROR(TRIM(LEFT(G45,FIND("-",G45)-1)),"") -> N100100554 | G45: N100100554 - Otros programas y Op | J45: =I45-H45 -> 0 | K45: -590.06 | M45: =L45-K45 -> 590.06 | P45: =O45-N45 -> 0 | S45: =R45-Q45 -> 0
A46: =_xll.EPMOlapMemberO("[CECO].[PARENTH3].[AMSA1001AD4517]","","AMSA1001AD4517 - Comunicación Externa","","000") -> AMSA1001AD4517 - Comunicación Externa | B46: =IFERROR(SUBSTITUTE(TRIM(LEFT(A46,FIND("-",A46)-1)),"AMSA",""),"") -> 1001AD4517 | C46: =IFERROR(_xlfn.XLOOKUP(B46,'CECOS Corporativos'!$D:$D,'CECOS Corporativos'!$E:$E,""),"") -> Comunicaciones | D46: =IFERROR(_xlfn.XLOOKUP(B46,'CECOS Corporativos'!$D:$D,'CECOS Corporativos'!$J:$J,""),"") -> VP Asuntos Corporativos | E46: Otros Gastos | F46: =IFERROR(TRIM(LEFT(G46,FIND("-",G46)-1)),"") -> N100100554 | G46: N100100554 - Otros programas y Op | H46: 449118.92 | I46: 842403 | J46: =I46-H46 -> 393284.08 | K46: 102559.96 | L46: 838536 | M46: =L46-K46 -> 735976.04 | N46: 0 | O46: 777997 | P46: =O46-N46 -> 777997 | R46: 732144.68 | S46: =R46-Q46 -> 732144.68
A47: =_xll.EPMOlapMemberO("[CECO].[PARENTH3].[AMSA1001AD4517]","","AMSA1001AD4517 - Comunicación Externa","","000") -> AMSA1001AD4517 - Comunicación Externa | B47: =IFERROR(SUBSTITUTE(TRIM(LEFT(A47,FIND("-",A47)-1)),"AMSA",""),"") -> 1001AD4517 | C47: =IFERROR(_xlfn.XLOOKUP(B47,'CECOS Corporativos'!$D:$D,'CECOS Corporativos'!$E:$E,""),"") -> Comunicaciones | D47: =IFERROR(_xlfn.XLOOKUP(B47,'CECOS Corporativos'!$D:$D,'CECOS Corporativos'!$J:$J,""),"") -> VP Asuntos Corporativos | E47: Liquidación Interna | F47: =IFERROR(TRIM(LEFT(G47,FIND("-",G47)-1)),"") -> N100100554 | G47: N100100554 - Otros programas y Op | H47: 1365767.1 | J47: =I47-H47 -> -1365767.1 | K47: 2161164.9 | M47: =L47-K47 -> -2161164.9 | N47: 2156308.5 | P47: =O47-N47 -> -2156308.5 | Q47: 1874796.4 | S47: =R47-Q47 -> -1874796.4
A48: =_xll.EPMOlapMemberO("[CECO].[PARENTH3].[AMSA1001AD4520]","","AMSA1001AD4520 - Empleabilidad OP","","000") -> AMSA1001AD4520 - Empleabilidad OP | B48: =IFERROR(SUBSTITUTE(TRIM(LEFT(A48,FIND("-",A48)-1)),"AMSA",""),"") -> 1001AD4520 | C48: =IFERROR(_xlfn.XLOOKUP(B48,'CECOS Corporativos'!$D:$D,'CECOS Corporativos'!$E:$E,""),"") -> Empleabilidad | D48: =IFERROR(_xlfn.XLOOKUP(B48,'CECOS Corporativos'!$D:$D,'CECOS Corporativos'!$J:$J,""),"") -> VP Asuntos Corporativos | E48: Materiales y repuest | F48: =IFERROR(TRIM(LEFT(G48,FIND("-",G48)-1)),"") -> N100100554 | G48: N100100554 - Otros programas y Op | H48: 0 | J48: =I48-H48 -> 0 | M48: =L48-K48 -> 0 | P48: =O48-N48 -> 0 | S48: =R48-Q48 -> 0
A49: =_xll.EPMOlapMemberO("[CECO].[PARENTH3].[AMSA1001AD4520]","","AMSA1001AD4520 - Empleabilidad OP","","000") -> AMSA1001AD4520 - Empleabilidad OP | B49: =IFERROR(SUBSTITUTE(TRIM(LEFT(A49,FIND("-",A49)-1)),"AMSA",""),"") -> 1001AD4520 | C49: =IFERROR(_xlfn.XLOOKUP(B49,'CECOS Corporativos'!$D:$D,'CECOS Corporativos'!$E:$E,""),"") -> Empleabilidad | D49: =IFERROR(_xlfn.XLOOKUP(B49,'CECOS Corporativos'!$D:$D,'CECOS Corporativos'!$J:$J,""),"") -> VP Asuntos Corporativos | E49: Asesorías y Consulto | F49: =IFERROR(TRIM(LEFT(G49,FIND("-",G49)-1)),"") -> N100100554 | G49: N100100554 - Otros programas y Op | J49: =I49-H49 -> 0 | M49: =L49-K49 -> 0 | P49: =O49-N49 -> 0 | Q49: 7018.61 | R49: 99231.32 | S49: =R49-Q49 -> 92212.71
A50: =_xll.EPMOlapMemberO("[CECO].[PARENTH3].[AMSA1001AD4520]","","AMSA1001AD4520 - Empleabilidad OP","","000") -> AMSA1001AD4520 - Empleabilidad OP | B50: =IFERROR(SUBSTITUTE(TRIM(LEFT(A50,FIND("-",A50)-1)),"AMSA",""),"") -> 1001AD4520 | C50: =IFERROR(_xlfn.XLOOKUP(B50,'CECOS Corporativos'!$D:$D,'CECOS Corporativos'!$E:$E,""),"") -> Empleabilidad | D50: =IFERROR(_xlfn.XLOOKUP(B50,'CECOS Corporativos'!$D:$D,'CECOS Corporativos'!$J:$J,""),"") -> VP Asuntos Corporativos | E50: Servicios | F50: =IFERROR(TRIM(LEFT(G50,FIND("-",G50)-1)),"") -> N100100554 | G50: N100100554 - Otros programas y Op | H50: 121742.09 | I50: 292815 | J50: =I50-H50 -> 171072.91 | K50: 90916.74 | L50: 495939 | M50: =L50-K50 -> 405022.26 | N50: 41138.78 | O50: 356969 | P50: =O50-N50 -> 315830.22 | Q50: 119630.24 | R50: 445793.85 | S50: =R50-Q50 -> 326163.61
A51: =_xll.EPMOlapMemberO("[CECO].[PARENTH3].[AMSA1001AD4520]","","AMSA1001AD4520 - Empleabilidad OP","","000") -> AMSA1001AD4520 - Empleabilidad OP | B51: =IFERROR(SUBSTITUTE(TRIM(LEFT(A51,FIND("-",A51)-1)),"AMSA",""),"") -> 1001AD4520 | C51: =IFERROR(_xlfn.XLOOKUP(B51,'CECOS Corporativos'!$D:$D,'CECOS Corporativos'!$E:$E,""),"") -> Empleabilidad | D51: =IFERROR(_xlfn.XLOOKUP(B51,'CECOS Corporativos'!$D:$D,'CECOS Corporativos'!$J:$J,""),"") -> VP Asuntos Corporativos | E51: Informática y Comuni | F51: =IFERROR(TRIM(LEFT(G51,FIND("-",G51)-1)),"") -> N100100554 | G51: N100100554 - Otros programas y Op | J51: =I51-H51 -> 0 | M51: =L51-K51 -> 0 | N51: 0 | P51: =O51-N51 -> 0 | Q51: 0 | S51: =R51-Q51 -> 0
A52: =_xll.EPMOlapMemberO("[CECO].[PARENTH3].[AMSA1001AD4520]","","AMSA1001AD4520 - Empleabilidad OP","","000") -> AMSA1001AD4520 - Empleabilidad OP | B52: =IFERROR(SUBSTITUTE(TRIM(LEFT(A52,FIND("-",A52)-1)),"AMSA",""),"") -> 1001AD4520 | C52: =IFERROR(_xlfn.XLOOKUP(B52,'CECOS Corporativos'!$D:$D,'CECOS Corporativos'!$E:$E,""),"") -> Empleabilidad | D52: =IFERROR(_xlfn.XLOOKUP(B52,'CECOS Corporativos'!$D:$D,'CECOS Corporativos'!$J:$J,""),"") -> VP Asuntos Corporativos | E52: Gastos de Viajes | F52: =IFERROR(TRIM(LEFT(G52,FIND("-",G52)-1)),"") -> N100100554 | G52: N100100554 - Otros programas y Op | H52: 2363.16 | I52: 7706 | J52: =I52-H52 -> 5342.84 | K52: 47266.67 | M52: =L52-K52 -> -47266.67 | N52: 38369.4 | O52: 43271 | P52: =O52-N52 -> 4901.6 | Q52: 43984.06 | R52: 43498.68 | S52: =R52-Q52 -> -485.38
A53: =_xll.EPMOlapMemberO("[CECO].[PARENTH3].[AMSA1001AD4520]","","AMSA1001AD4520 - Empleabilidad OP","","000") -> AMSA1001AD4520 - Empleabilidad OP | B53: =IFERROR(SUBSTITUTE(TRIM(LEFT(A53,FIND("-",A53)-1)),"AMSA",""),"") -> 1001AD4520 | C53: =IFERROR(_xlfn.XLOOKUP(B53,'CECOS Corporativos'!$D:$D,'CECOS Corporativos'!$E:$E,""),"") -> Empleabilidad | D53: =IFERROR(_xlfn.XLOOKUP(B53,'CECOS Corporativos'!$D:$D,'CECOS Corporativos'!$J:$J,""),"") -> VP Asuntos Corporativos | E53: Otros Gastos | F53: =IFERROR(TRIM(LEFT(G53,FIND("-",G53)-1)),"") -> N100100554 | G53: N100100554 - Otros programas y Op | H53: 0 | J53: =I53-H53 -> 0 | M53: =L53-K53 -> 0 | P53: =O53-N53 -> 0 | S53: =R53-Q53 -> 0
A54: =_xll.EPMOlapMemberO("[CECO].[PARENTH3].[AMSA1001AD4520]","","AMSA1001AD4520 - Empleabilidad OP","","000") -> AMSA1001AD4520 - Empleabilidad OP | B54: =IFERROR(SUBSTITUTE(TRIM(LEFT(A54,FIND("-",A54)-1)),"AMSA",""),"") -> 1001AD4520 | C54: =IFERROR(_xlfn.XLOOKUP(B54,'CECOS Corporativos'!$D:$D,'CECOS Corporativos'!$E:$E,""),"") -> Empleabilidad | D54: =IFERROR(_xlfn.XLOOKUP(B54,'CECOS Corporativos'!$D:$D,'CECOS Corporativos'!$J:$J,""),"") -> VP Asuntos Corporativos | E54: Liquidación Interna | F54: =IFERROR(TRIM(LEFT(G54,FIND("-",G54)-1)),"") -> N100100554 | G54: N100100554 - Otros programas y Op | H54: 138575.32 | J54: =I54-H54 -> -138575.32 | K54: 199694.72 | M54: =L54-K54 -> -199694.72 | N54: 362222.94 | P54: =O54-N54 -> -362222.94 | Q54: 390146.56 | S54: =R54-Q54 -> -390146.56
A55: =_xll.EPMOlapMemberO("[CECO].[PARENTH3].[AMSA1001AD4523]","","AMSA1001AD4523 - Adm Plan Asu Pub C3","","000") -> AMSA1001AD4523 - Adm Plan Asu Pub C3 | B55: =IFERROR(SUBSTITUTE(TRIM(LEFT(A55,FIND("-",A55)-1)),"AMSA",""),"") -> 1001AD4523 | C55: =IFERROR(_xlfn.XLOOKUP(B55,'CECOS Corporativos'!$D:$D,'CECOS Corporativos'!$E:$E,""),"") -> Administración Plan AAPP C3 | D55: =IFERROR(_xlfn.XLOOKUP(B55,'CECOS Corporativos'!$D:$D,'CECOS Corporativos'!$J:$J,""),"") -> VP Asuntos Corporativos | E55: Asesorías y Consulto | F55: =IFERROR(TRIM(LEFT(G55,FIND("-",G55)-1)),"") -> N100100554 | G55: N100100554 - Otros programas y Op | H55: 102633.95 | I55: 193707 | J55: =I55-H55 -> 91073.05 | L55: 131983 | M55: =L55-K55 -> 131983 | O55: 198663 | P55: =O55-N55 -> 198663 | S55: =R55-Q55 -> 0
A56: =_xll.EPMOlapMemberO("[CECO].[PARENTH3].[AMSA1001AD4523]","","AMSA1001AD4523 - Adm Plan Asu Pub C3","","000") -> AMSA1001AD4523 - Adm Plan Asu Pub C3 | B56: =IFERROR(SUBSTITUTE(TRIM(LEFT(A56,FIND("-",A56)-1)),"AMSA",""),"") -> 1001AD4523 | C56: =IFERROR(_xlfn.XLOOKUP(B56,'CECOS Corporativos'!$D:$D,'CECOS Corporativos'!$E:$E,""),"") -> Administración Plan AAPP C3 | D56: =IFERROR(_xlfn.XLOOKUP(B56,'CECOS Corporativos'!$D:$D,'CECOS Corporativos'!$J:$J,""),"") -> VP Asuntos Corporativos | E56: Servicios | F56: =IFERROR(TRIM(LEFT(G56,FIND("-",G56)-1)),"") -> N100100554 | G56: N100100554 - Otros programas y Op | J56: =I56-H56 -> 0 | L56: 98517 | M56: =L56-K56 -> 98517 | N56: 32.24 | O56: 72543 | P56: =O56-N56 -> 72510.76 | S56: =R56-Q56 -> 0
A57: =_xll.EPMOlapMemberO("[CECO].[PARENTH3].[AMSA1001AD4523]","","AMSA1001AD4523 - Adm Plan Asu Pub C3","","000") -> AMSA1001AD4523 - Adm Plan Asu Pub C3 | B57: =IFERROR(SUBSTITUTE(TRIM(LEFT(A57,FIND("-",A57)-1)),"AMSA",""),"") -> 1001AD4523 | C57: =IFERROR(_xlfn.XLOOKUP(B57,'CECOS Corporativos'!$D:$D,'CECOS Corporativos'!$E:$E,""),"") -> Administración Plan AAPP C3 | D57: =IFERROR(_xlfn.XLOOKUP(B57,'CECOS Corporativos'!$D:$D,'CECOS Corporativos'!$J:$J,""),"") -> VP Asuntos Corporativos | E57: Informática y Comuni | F57: =IFERROR(TRIM(LEFT(G57,FIND("-",G57)-1)),"") -> N100100554 | G57: N100100554 - Otros programas y Op | J57: =I57-H57 -> 0 | L57: 6275 | M57: =L57-K57 -> 6275 | N57: 1640.39 | O57: 6818 | P57: =O57-N57 -> 5177.61 | S57: =R57-Q57 -> 0
A58: =_xll.EPMOlapMemberO("[CECO].[PARENTH3].[AMSA1001AD4523]","","AMSA1001AD4523 - Adm Plan Asu Pub C3","","000") -> AMSA1001AD4523 - Adm Plan Asu Pub C3 | B58: =IFERROR(SUBSTITUTE(TRIM(LEFT(A58,FIND("-",A58)-1)),"AMSA",""),"") -> 1001AD4523 | C58: =IFERROR(_xlfn.XLOOKUP(B58,'CECOS Corporativos'!$D:$D,'CECOS Corporativos'!$E:$E,""),"") -> Administración Plan AAPP C3 | D58: =IFERROR(_xlfn.XLOOKUP(B58,'CECOS Corporativos'!$D:$D,'CECOS Corporativos'!$J:$J,""),"") -> VP Asuntos Corporativos | E58: Gastos de Viajes | F58: =IFERROR(TRIM(LEFT(G58,FIND("-",G58)-1)),"") -> N100100554 | G58: N100100554 - Otros programas y Op | J58: =I58-H58 -> 0 | M58: =L58-K58 -> 0 | N58: 833.02 | P58: =O58-N58 -> -833.02 | S58: =R58-Q58 -> 0
A59: =_xll.EPMOlapMemberO("[CECO].[PARENTH3].[AMSA1001AD4523]","","AMSA1001AD4523 - Adm Plan Asu Pub C3","","000") -> AMSA1001AD4523 - Adm Plan Asu Pub C3 | B59: =IFERROR(SUBSTITUTE(TRIM(LEFT(A59,FIND("-",A59)-1)),"AMSA",""),"") -> 1001AD4523 | C59: =IFERROR(_xlfn.XLOOKUP(B59,'CECOS Corporativos'!$D:$D,'CECOS Corporativos'!$E:$E,""),"") -> Administración Plan AAPP C3 | D59: =IFERROR(_xlfn.XLOOKUP(B59,'CECOS Corporativos'!$D:$D,'CECOS Corporativos'!$J:$J,""),"") -> VP Asuntos Corporativos | E59: Impuestos / Patentes | F59: =IFERROR(TRIM(LEFT(G59,FIND("-",G59)-1)),"") -> N100100554 | G59: N100100554 - Otros programas y Op | J59: =I59-H59 -> 0 | M59: =L59-K59 -> 0 | N59: 5.85 | P59: =O59-N59 -> -5.85 | S59: =R59-Q59 -> 0
A60: =_xll.EPMOlapMemberO("[CECO].[PARENTH3].[AMSA1001AD4523]","","AMSA1001AD4523 - Adm Plan Asu Pub C3","","000") -> AMSA1001AD4523 - Adm Plan Asu Pub C3 | B60: =IFERROR(SUBSTITUTE(TRIM(LEFT(A60,FIND("-",A60)-1)),"AMSA",""),"") -> 1001AD4523 | C60: =IFERROR(_xlfn.XLOOKUP(B60,'CECOS Corporativos'!$D:$D,'CECOS Corporativos'!$E:$E,""),"") -> Administración Plan AAPP C3 | D60: =IFERROR(_xlfn.XLOOKUP(B60,'CECOS Corporativos'!$D:$D,'CECOS Corporativos'!$J:$J,""),"") -> VP Asuntos Corporativos | E60: Otros Gastos | F60: =IFERROR(TRIM(LEFT(G60,FIND("-",G60)-1)),"") -> N100100554 | G60: N100100554 - Otros programas y Op | H60: 116629.71 | I60: 102002 | J60: =I60-H60 -> -14627.71 | L60: 115689 | M60: =L60-K60 -> 115689 | O60: 131942 | P60: =O60-N60 -> 131942 | S60: =R60-Q60 -> 0
A61: =_xll.EPMOlapMemberO("[CECO].[PARENTH3].[AMSA1001AD4523]","","AMSA1001AD4523 - Adm Plan Asu Pub C3","","000") -> AMSA1001AD4523 - Adm Plan Asu Pub C3 | B61: =IFERROR(SUBSTITUTE(TRIM(LEFT(A61,FIND("-",A61)-1)),"AMSA",""),"") -> 1001AD4523 | C61: =IFERROR(_xlfn.XLOOKUP(B61,'CECOS Corporativos'!$D:$D,'CECOS Corporativos'!$E:$E,""),"") -> Administración Plan AAPP C3 | D61: =IFERROR(_xlfn.XLOOKUP(B61,'CECOS Corporativos'!$D:$D,'CECOS Corporativos'!$J:$J,""),"") -> VP Asuntos Corporativos | E61: Subrepartos | F61: =IFERROR(TRIM(LEFT(G61,FIND("-",G61)-1)),"") -> N100100554 | G61: N100100554 - Otros programas y Op | H61: 8544.96 | I61: 7758.75 | J61: =I61-H61 -> -786.21 | K61: 11463.57 | L61: 8075.44 | M61: =L61-K61 -> -3388.13 | N61: 8842.98 | O61: 7147.89 | P61: =O61-N61 -> -1695.09 | Q61: 10616.85 | R61: 9635.45 | S61: =R61-Q61 -> -981.4
A62: =_xll.EPMOlapMemberO("[CECO].[PARENTH3].[AMSA1001AD4523]","","AMSA1001AD4523 - Adm Plan Asu Pub C3","","000") -> AMSA1001AD4523 - Adm Plan Asu Pub C3 | B62: =IFERROR(SUBSTITUTE(TRIM(LEFT(A62,FIND("-",A62)-1)),"AMSA",""),"") -> 1001AD4523 | C62: =IFERROR(_xlfn.XLOOKUP(B62,'CECOS Corporativos'!$D:$D,'CECOS Corporativos'!$E:$E,""),"") -> Administración Plan AAPP C3 | D62: =IFERROR(_xlfn.XLOOKUP(B62,'CECOS Corporativos'!$D:$D,'CECOS Corporativos'!$J:$J,""),"") -> VP Asuntos Corporativos | E62: Servicios Corporativ | F62: =IFERROR(TRIM(LEFT(G62,FIND("-",G62)-1)),"") -> N100100554 | G62: N100100554 - Otros programas y Op | H62: 4015206.8 | I62: 4139256 | J62: =I62-H62 -> 124049.23 | K62: 4390348.8 | L62: 3985382 | M62: =L62-K62 -> -404966.78 | N62: -21701.78 | O62: 4916780 | P62: =O62-N62 -> 4938481.8 | S62: =R62-Q62 -> 0
A63: =_xll.EPMOlapMemberO("[CECO].[PARENTH3].[AMSA1001AD4524]","","AMSA1001AD4524 - Somos Choapa Op","","000") -> AMSA1001AD4524 - Somos Choapa Op | B63: =IFERROR(SUBSTITUTE(TRIM(LEFT(A63,FIND("-",A63)-1)),"AMSA",""),"") -> 1001AD4524 | C63: =IFERROR(_xlfn.XLOOKUP(B63,'CECOS Corporativos'!$D:$D,'CECOS Corporativos'!$E:$E,""),"") -> Asuntos Públicos | D63: =IFERROR(_xlfn.XLOOKUP(B63,'CECOS Corporativos'!$D:$D,'CECOS Corporativos'!$J:$J,""),"") -> VP Asuntos Corporativos | E63: Asesorías y Consulto | F63: =IFERROR(TRIM(LEFT(G63,FIND("-",G63)-1)),"") -> N100100554 | G63: N100100554 - Otros programas y Op | I63: 1695204 | J63: =I63-H63 -> 1695204 | L63: 1240446 | M63: =L63-K63 -> 1240446 | O63: 995059 | P63: =O63-N63 -> 995059 | R63: 1309033.3 | S63: =R63-Q63 -> 1309033.3
A64: =_xll.EPMOlapMemberO("[CECO].[PARENTH3].[AMSA1001AD4524]","","AMSA1001AD4524 - Somos Choapa Op","","000") -> AMSA1001AD4524 - Somos Choapa Op | B64: =IFERROR(SUBSTITUTE(TRIM(LEFT(A64,FIND("-",A64)-1)),"AMSA",""),"") -> 1001AD4524 | C64: =IFERROR(_xlfn.XLOOKUP(B64,'CECOS Corporativos'!$D:$D,'CECOS Corporativos'!$E:$E,""),"") -> Asuntos Públicos | D64: =IFERROR(_xlfn.XLOOKUP(B64,'CECOS Corporativos'!$D:$D,'CECOS Corporativos'!$J:$J,""),"") -> VP Asuntos Corporativos | E64: Servicios | F64: =IFERROR(TRIM(LEFT(G64,FIND("-",G64)-1)),"") -> N100100554 | G64: N100100554 - Otros programas y Op | H64: 35736.38 | I64: 33391 | J64: =I64-H64 -> -2345.38 | K64: 137076.1 | L64: 5462 | M64: =L64-K64 -> -131614.1 | N64: 169512.86 | O64: 126206 | P64: =O64-N64 -> -43306.86 | Q64: 250989.3 | R64: 205259.32 | S64: =R64-Q64 -> -45729.98
A65: =_xll.EPMOlapMemberO("[CECO].[PARENTH3].[AMSA1001AD4524]","","AMSA1001AD4524 - Somos Choapa Op","","000") -> AMSA1001AD4524 - Somos Choapa Op | B65: =IFERROR(SUBSTITUTE(TRIM(LEFT(A65,FIND("-",A65)-1)),"AMSA",""),"") -> 1001AD4524 | C65: =IFERROR(_xlfn.XLOOKUP(B65,'CECOS Corporativos'!$D:$D,'CECOS Corporativos'!$E:$E,""),"") -> Asuntos Públicos | D65: =IFERROR(_xlfn.XLOOKUP(B65,'CECOS Corporativos'!$D:$D,'CECOS Corporativos'!$J:$J,""),"") -> VP Asuntos Corporativos | E65: Gastos de Viajes | F65: =IFERROR(TRIM(LEFT(G65,FIND("-",G65)-1)),"") -> N100100554 | G65: N100100554 - Otros programas y Op | H65: 13882.53 | J65: =I65-H65 -> -13882.53 | K65: 58020.68 | L65: 8203 | M65: =L65-K65 -> -49817.68 | N65: 71592.3 | O65: 18029 | P65: =O65-N65 -> -53563.3 | Q65: 87820.83 | R65: 61170 | S65: =R65-Q65 -> -26650.83
A66: =_xll.EPMOlapMemberO("[CECO].[PARENTH3].[AMSA1001AD4524]","","AMSA1001AD4524 - Somos Choapa Op","","000") -> AMSA1001AD4524 - Somos Choapa Op | B66: =IFERROR(SUBSTITUTE(TRIM(LEFT(A66,FIND("-",A66)-1)),"AMSA",""),"") -> 1001AD4524 | C66: =IFERROR(_xlfn.XLOOKUP(B66,'CECOS Corporativos'!$D:$D,'CECOS Corporativos'!$E:$E,""),"") -> Asuntos Públicos | D66: =IFERROR(_xlfn.XLOOKUP(B66,'CECOS Corporativos'!$D:$D,'CECOS Corporativos'!$J:$J,""),"") -> VP Asuntos Corporativos | E66: Otros Gastos | F66: =IFERROR(TRIM(LEFT(G66,FIND("-",G66)-1)),"") -> N100100554 | G66: N100100554 - Otros programas y Op | H66: 0 | J66: =I66-H66 -> 0 | M66: =L66-K66 -> 0 | P66: =O66-N66 -> 0 | S66: =R66-Q66 -> 0
A67: =_xll.EPMOlapMemberO("[CECO].[PARENTH3].[AMSA1001AD4524]","","AMSA1001AD4524 - Somos Choapa Op","","000") -> AMSA1001AD4524 - Somos Choapa Op | B67: =IFERROR(SUBSTITUTE(TRIM(LEFT(A67,FIND("-",A67)-1)),"AMSA",""),"") -> 1001AD4524 | C67: =IFERROR(_xlfn.XLOOKUP(B67,'CECOS Corporativos'!$D:$D,'CECOS Corporativos'!$E:$E,""),"") -> Asuntos Públicos | D67: =IFERROR(_xlfn.XLOOKUP(B67,'CECOS Corporativos'!$D:$D,'CECOS Corporativos'!$J:$J,""),"") -> VP Asuntos Corporativos | E67: Liquidación Interna | F67: =IFERROR(TRIM(LEFT(G67,FIND("-",G67)-1)),"") -> N100100554 | G67: N100100554 - Otros programas y Op | H67: 2489940.3 | J67: =I67-H67 -> -2489940.3 | K67: 1839973.2 | M67: =L67-K67 -> -1839973.2 | N67: 1155148.8 | P67: =O67-N67 -> -1155148.8 | Q67: 1949350.8 | S67: =R67-Q67 -> -1949350.8
A68: =_xll.EPMOlapMemberO("[CECO].[PARENTH3].[AMSA1001AD4525]","","AMSA1001AD4525 - Comun Exter Op","","000") -> AMSA1001AD4525 - Comun Exter Op | B68: =IFERROR(SUBSTITUTE(TRIM(LEFT(A68,FIND("-",A68)-1)),"AMSA",""),"") -> 1001AD4525 | C68: =IFERROR(_xlfn.XLOOKUP(B68,'CECOS Corporativos'!$D:$D,'CECOS Corporativos'!$E:$E,""),"") -> Comunicaciones | D68: =IFERROR(_xlfn.XLOOKUP(B68,'CECOS Corporativos'!$D:$D,'CECOS Corporativos'!$J:$J,""),"") -> VP Asuntos Corporativos | E68: Asesorías y Consulto | F68: =IFERROR(TRIM(LEFT(G68,FIND("-",G68)-1)),"") -> N100100554 | G68: N100100554 - Otros programas y Op | H68: 0 | J68: =I68-H68 -> 0 | M68: =L68-K68 -> 0 | P68: =O68-N68 -> 0 | S68: =R68-Q68 -> 0
A69: =_xll.EPMOlapMemberO("[CECO].[PARENTH3].[AMSA1001AD4525]","","AMSA1001AD4525 - Comun Exter Op","","000") -> AMSA1001AD4525 - Comun Exter Op | B69: =IFERROR(SUBSTITUTE(TRIM(LEFT(A69,FIND("-",A69)-1)),"AMSA",""),"") -> 1001AD4525 | C69: =IFERROR(_xlfn.XLOOKUP(B69,'CECOS Corporativos'!$D:$D,'CECOS Corporativos'!$E:$E,""),"") -> Comunicaciones | D69: =IFERROR(_xlfn.XLOOKUP(B69,'CECOS Corporativos'!$D:$D,'CECOS Corporativos'!$J:$J,""),"") -> VP Asuntos Corporativos | E69: Servicios | F69: =IFERROR(TRIM(LEFT(G69,FIND("-",G69)-1)),"") -> N100100554 | G69: N100100554 - Otros programas y Op | I69: 439405 | J69: =I69-H69 -> 439405 | K69: -0.2 | L69: 437806 | M69: =L69-K69 -> 437806.2 | O69: 498814 | P69: =O69-N69 -> 498814 | R69: 589804.79 | S69: =R69-Q69 -> 589804.79
A70: =_xll.EPMOlapMemberO("[CECO].[PARENTH3].[AMSA1001AD4525]","","AMSA1001AD4525 - Comun Exter Op","","000") -> AMSA1001AD4525 - Comun Exter Op | B70: =IFERROR(SUBSTITUTE(TRIM(LEFT(A70,FIND("-",A70)-1)),"AMSA",""),"") -> 1001AD4525 | C70: =IFERROR(_xlfn.XLOOKUP(B70,'CECOS Corporativos'!$D:$D,'CECOS Corporativos'!$E:$E,""),"") -> Comunicaciones | D70: =IFERROR(_xlfn.XLOOKUP(B70,'CECOS Corporativos'!$D:$D,'CECOS Corporativos'!$J:$J,""),"") -> VP Asuntos Corporativos | E70: Informática y Comuni | F70: =IFERROR(TRIM(LEFT(G70,FIND("-",G70)-1)),"") -> N100100554 | G70: N100100554 - Otros programas y Op | I70: 354458 | J70: =I70-H70 -> 354458 | K70: 68525.34 | L70: 177855 | M70: =L70-K70 -> 109329.66 | N70: -217.25 | O70: 163467 | P70: =O70-N70 -> 163684.25 | R70: 90395.68 | S70: =R70-Q70 -> 90395.68
A71: =_xll.EPMOlapMemberO("[CECO].[PARENTH3].[AMSA1001AD4525]","","AMSA1001AD4525 - Comun Exter Op","","000") -> AMSA1001AD4525 - Comun Exter Op | B71: =IFERROR(SUBSTITUTE(TRIM(LEFT(A71,FIND("-",A71)-1)),"AMSA",""),"") -> 1001AD4525 | C71: =IFERROR(_xlfn.XLOOKUP(B71,'CECOS Corporativos'!$D:$D,'CECOS Corporativos'!$E:$E,""),"") -> Comunicaciones | D71: =IFERROR(_xlfn.XLOOKUP(B71,'CECOS Corporativos'!$D:$D,'CECOS Corporativos'!$J:$J,""),"") -> VP Asuntos Corporativos | E71: Gastos de Viajes | F71: =IFERROR(TRIM(LEFT(G71,FIND("-",G71)-1)),"") -> N100100554 | G71: N100100554 - Otros programas y Op | H71: 256.38 | J71: =I71-H71 -> -256.38 | M71: =L71-K71 -> 0 | P71: =O71-N71 -> 0 | S71: =R71-Q71 -> 0
A72: =_xll.EPMOlapMemberO("[CECO].[PARENTH3].[AMSA1001AD4525]","","AMSA1001AD4525 - Comun Exter Op","","000") -> AMSA1001AD4525 - Comun Exter Op | B72: =IFERROR(SUBSTITUTE(TRIM(LEFT(A72,FIND("-",A72)-1)),"AMSA",""),"") -> 1001AD4525 | C72: =IFERROR(_xlfn.XLOOKUP(B72,'CECOS Corporativos'!$D:$D,'CECOS Corporativos'!$E:$E,""),"") -> Comunicaciones | D72: =IFERROR(_xlfn.XLOOKUP(B72,'CECOS Corporativos'!$D:$D,'CECOS Corporativos'!$J:$J,""),"") -> VP Asuntos Corporativos | E72: Liquidación Interna | F72: =IFERROR(TRIM(LEFT(G72,FIND("-",G72)-1)),"") -> N100100554 | G72: N100100554 - Otros programas y Op | H72: 618942.79 | J72: =I72-H72 -> -618942.79 | K72: 832436.94 | M72: =L72-K72 -> -832436.94 | N72: 598236.41 | P72: =O72-N72 -> -598236.41 | Q72: 647595.74 | S72: =R72-Q72 -> -647595.74
A73: =_xll.EPMOlapMemberO("[CECO].[PARENTH3].[AMSA1001AD4526]","","AMSA1001AD4526 - Comunidades Op","","000") -> AMSA1001AD4526 - Comunidades Op | B73: =IFERROR(SUBSTITUTE(TRIM(LEFT(A73,FIND("-",A73)-1)),"AMSA",""),"") -> 1001AD4526 | C73: =IFERROR(_xlfn.XLOOKUP(B73,'CECOS Corporativos'!$D:$D,'CECOS Corporativos'!$E:$E,""),"") -> Asuntos Públicos | D73: =IFERROR(_xlfn.XLOOKUP(B73,'CECOS Corporativos'!$D:$D,'CECOS Corporativos'!$J:$J,""),"") -> VP Asuntos Corporativos | E73: Materiales y repuest | F73: =IFERROR(TRIM(LEFT(G73,FIND("-",G73)-1)),"") -> N100100554 | G73: N100100554 - Otros programas y Op | H73: 0 | J73: =I73-H73 -> 0 | M73: =L73-K73 -> 0 | P73: =O73-N73 -> 0 | S73: =R73-Q73 -> 0
A74: =_xll.EPMOlapMemberO("[CECO].[PARENTH3].[AMSA1001AD4526]","","AMSA1001AD4526 - Comunidades Op","","000") -> AMSA1001AD4526 - Comunidades Op | B74: =IFERROR(SUBSTITUTE(TRIM(LEFT(A74,FIND("-",A74)-1)),"AMSA",""),"") -> 1001AD4526 | C74: =IFERROR(_xlfn.XLOOKUP(B74,'CECOS Corporativos'!$D:$D,'CECOS Corporativos'!$E:$E,""),"") -> Asuntos Públicos | D74: =IFERROR(_xlfn.XLOOKUP(B74,'CECOS Corporativos'!$D:$D,'CECOS Corporativos'!$J:$J,""),"") -> VP Asuntos Corporativos | E74: Arriendos | F74: =IFERROR(TRIM(LEFT(G74,FIND("-",G74)-1)),"") -> N100100554 | G74: N100100554 - Otros programas y Op | H74: 1141.04 | J74: =I74-H74 -> -1141.04 | K74: 382.95 | M74: =L74-K74 -> -382.95 | P74: =O74-N74 -> 0 | Q74: 230.03 | S74: =R74-Q74 -> -230.03
A75: =_xll.EPMOlapMemberO("[CECO].[PARENTH3].[AMSA1001AD4526]","","AMSA1001AD4526 - Comunidades Op","","000") -> AMSA1001AD4526 - Comunidades Op | B75: =IFERROR(SUBSTITUTE(TRIM(LEFT(A75,FIND("-",A75)-1)),"AMSA",""),"") -> 1001AD4526 | C75: =IFERROR(_xlfn.XLOOKUP(B75,'CECOS Corporativos'!$D:$D,'CECOS Corporativos'!$E:$E,""),"") -> Asuntos Públicos | D75: =IFERROR(_xlfn.XLOOKUP(B75,'CECOS Corporativos'!$D:$D,'CECOS Corporativos'!$J:$J,""),"") -> VP Asuntos Corporativos | E75: Servicios | F75: =IFERROR(TRIM(LEFT(G75,FIND("-",G75)-1)),"") -> N100100554 | G75: N100100554 - Otros programas y Op | H75: 1140192 | I75: 1046736 | J75: =I75-H75 -> -93456.01 | K75: 1446736 | L75: 877132 | M75: =L75-K75 -> -569604.01 | N75: 2163463.3 | O75: 1542363 | P75: =O75-N75 -> -621100.34 | Q75: 2151188.3 | R75: 2347798.2 | S75: =R75-Q75 -> 196609.93
A76: =_xll.EPMOlapMemberO("[CECO].[PARENTH3].[AMSA1001AD4526]","","AMSA1001AD4526 - Comunidades Op","","000") -> AMSA1001AD4526 - Comunidades Op | B76: =IFERROR(SUBSTITUTE(TRIM(LEFT(A76,FIND("-",A76)-1)),"AMSA",""),"") -> 1001AD4526 | C76: =IFERROR(_xlfn.XLOOKUP(B76,'CECOS Corporativos'!$D:$D,'CECOS Corporativos'!$E:$E,""),"") -> Asuntos Públicos | D76: =IFERROR(_xlfn.XLOOKUP(B76,'CECOS Corporativos'!$D:$D,'CECOS Corporativos'!$J:$J,""),"") -> VP Asuntos Corporativos | E76: Gastos de Viajes | F76: =IFERROR(TRIM(LEFT(G76,FIND("-",G76)-1)),"") -> N100100554 | G76: N100100554 - Otros programas y Op | H76: 5027.05 | J76: =I76-H76 -> -5027.05 | K76: 35598.99 | L76: 5468 | M76: =L76-K76 -> -30130.99 | N76: 3093.95 | O76: 18029 | P76: =O76-N76 -> 14935.05 | Q76: 681.59 | S76: =R76-Q76 -> -681.59
A77: =_xll.EPMOlapMemberO("[CECO].[PARENTH3].[AMSA1001AD4526]","","AMSA1001AD4526 - Comunidades Op","","000") -> AMSA1001AD4526 - Comunidades Op | B77: =IFERROR(SUBSTITUTE(TRIM(LEFT(A77,FIND("-",A77)-1)),"AMSA",""),"") -> 1001AD4526 | C77: =IFERROR(_xlfn.XLOOKUP(B77,'CECOS Corporativos'!$D:$D,'CECOS Corporativos'!$E:$E,""),"") -> Asuntos Públicos | D77: =IFERROR(_xlfn.XLOOKUP(B77,'CECOS Corporativos'!$D:$D,'CECOS Corporativos'!$J:$J,""),"") -> VP Asuntos Corporativos | E77: Otros Gastos | F77: =IFERROR(TRIM(LEFT(G77,FIND("-",G77)-1)),"") -> N100100554 | G77: N100100554 - Otros programas y Op | H77: 0 | J77: =I77-H77 -> 0 | M77: =L77-K77 -> 0 | P77: =O77-N77 -> 0 | S77: =R77-Q77 -> 0
A78: =_xll.EPMOlapMemberO("[CECO].[PARENTH3].[AMSA1001AD4526]","","AMSA1001AD4526 - Comunidades Op","","000") -> AMSA1001AD4526 - Comunidades Op | B78: =IFERROR(SUBSTITUTE(TRIM(LEFT(A78,FIND("-",A78)-1)),"AMSA",""),"") -> 1001AD4526 | C78: =IFERROR(_xlfn.XLOOKUP(B78,'CECOS Corporativos'!$D:$D,'CECOS Corporativos'!$E:$E,""),"") -> Asuntos Públicos | D78: =IFERROR(_xlfn.XLOOKUP(B78,'CECOS Corporativos'!$D:$D,'CECOS Corporativos'!$J:$J,""),"") -> VP Asuntos Corporativos | E78: Liquidación Interna | F78: =IFERROR(TRIM(LEFT(G78,FIND("-",G78)-1)),"") -> N100100554 | G78: N100100554 - Otros programas y Op | H78: 47517.75 | J78: =I78-H78 -> -47517.75 | K78: 1023.63 | M78: =L78-K78 -> -1023.63 | N78: 455755.41 | P78: =O78-N78 -> -455755.41 | Q78: 122995.09 | S78: =R78-Q78 -> -122995.09
A79: =_xll.EPMOlapMemberO("[CECO].[PARENTH3].[AMSA1001AD4541]","","AMSA1001AD4541 - Comunicaciones Corp","","000") -> AMSA1001AD4541 - Comunicaciones Corp | B79: =IFERROR(SUBSTITUTE(TRIM(LEFT(A79,FIND("-",A79)-1)),"AMSA",""),"") -> 1001AD4541 | C79: =IFERROR(_xlfn.XLOOKUP(B79,'CECOS Corporativos'!$D:$D,'CECOS Corporativos'!$E:$E,""),"") -> Comunicaciones Corporativo | D79: =IFERROR(_xlfn.XLOOKUP(B79,'CECOS Corporativos'!$D:$D,'CECOS Corporativos'!$J:$J,""),"") -> VP Asuntos Corporativos | E79: Entrenamiento | F79: =IFERROR(TRIM(LEFT(G79,FIND("-",G79)-1)),"") -> N100100554 | G79: N100100554 - Otros programas y Op | J79: =I79-H79 -> 0 | M79: =L79-K79 -> 0 | P79: =O79-N79 -> 0 | Q79: 108.48 | S79: =R79-Q79 -> -108.48
A80: =_xll.EPMOlapMemberO("[CECO].[PARENTH3].[AMSA1001AD4541]","","AMSA1001AD4541 - Comunicaciones Corp","","000") -> AMSA1001AD4541 - Comunicaciones Corp | B80: =IFERROR(SUBSTITUTE(TRIM(LEFT(A80,FIND("-",A80)-1)),"AMSA",""),"") -> 1001AD4541 | C80: =IFERROR(_xlfn.XLOOKUP(B80,'CECOS Corporativos'!$D:$D,'CECOS Corporativos'!$E:$E,""),"") -> Comunicaciones Corporativo | D80: =IFERROR(_xlfn.XLOOKUP(B80,'CECOS Corporativos'!$D:$D,'CECOS Corporativos'!$J:$J,""),"") -> VP Asuntos Corporativos | E80: Asesorías y Consulto | F80: =IFERROR(TRIM(LEFT(G80,FIND("-",G80)-1)),"") -> N100100554 | G80: N100100554 - Otros programas y Op | J80: =I80-H80 -> 0 | M80: =L80-K80 -> 0 | N80: 92514.6 | O80: 43332 | P80: =O80-N80 -> -49182.6 | Q80: 210.34 | S80: =R80-Q80 -> -210.34
A81: =_xll.EPMOlapMemberO("[CECO].[PARENTH3].[AMSA1001AD4541]","","AMSA1001AD4541 - Comunicaciones Corp","","000") -> AMSA1001AD4541 - Comunicaciones Corp | B81: =IFERROR(SUBSTITUTE(TRIM(LEFT(A81,FIND("-",A81)-1)),"AMSA",""),"") -> 1001AD4541 | C81: =IFERROR(_xlfn.XLOOKUP(B81,'CECOS Corporativos'!$D:$D,'CECOS Corporativos'!$E:$E,""),"") -> Comunicaciones Corporativo | D81: =IFERROR(_xlfn.XLOOKUP(B81,'CECOS Corporativos'!$D:$D,'CECOS Corporativos'!$J:$J,""),"") -> VP Asuntos Corporativos | E81: Informática y Comuni | F81: =IFERROR(TRIM(LEFT(G81,FIND("-",G81)-1)),"") -> N100100554 | G81: N100100554 - Otros programas y Op | J81: =I81-H81 -> 0 | M81: =L81-K81 -> 0 | O81: 44440 | P81: =O81-N81 -> 44440 | Q81: 10933.44 | R81: 98815.53 | S81: =R81-Q81 -> 87882.09
A82: =_xll.EPMOlapMemberO("[CECO].[PARENTH3].[AMSA1001AD4541]","","AMSA1001AD4541 - Comunicaciones Corp","","000") -> AMSA1001AD4541 - Comunicaciones Corp | B82: =IFERROR(SUBSTITUTE(TRIM(LEFT(A82,FIND("-",A82)-1)),"AMSA",""),"") -> 1001AD4541 | C82: =IFERROR(_xlfn.XLOOKUP(B82,'CECOS Corporativos'!$D:$D,'CECOS Corporativos'!$E:$E,""),"") -> Comunicaciones Corporativo | D82: =IFERROR(_xlfn.XLOOKUP(B82,'CECOS Corporativos'!$D:$D,'CECOS Corporativos'!$J:$J,""),"") -> VP Asuntos Corporativos | E82: Gastos de Viajes | F82: =IFERROR(TRIM(LEFT(G82,FIND("-",G82)-1)),"") -> N100100554 | G82: N100100554 - Otros programas y Op | J82: =I82-H82 -> 0 | M82: =L82-K82 -> 0 | P82: =O82-N82 -> 0 | Q82: 67.26 | S82: =R82-Q82 -> -67.26
A83: =_xll.EPMOlapMemberO("[CECO].[PARENTH3].[AMSA1001AD4541]","","AMSA1001AD4541 - Comunicaciones Corp","","000") -> AMSA1001AD4541 - Comunicaciones Corp | B83: =IFERROR(SUBSTITUTE(TRIM(LEFT(A83,FIND("-",A83)-1)),"AMSA",""),"") -> 1001AD4541 | C83: =IFERROR(_xlfn.XLOOKUP(B83,'CECOS Corporativos'!$D:$D,'CECOS Corporativos'!$E:$E,""),"") -> Comunicaciones Corporativo | D83: =IFERROR(_xlfn.XLOOKUP(B83,'CECOS Corporativos'!$D:$D,'CECOS Corporativos'!$J:$J,""),"") -> VP Asuntos Corporativos | E83: Otros Gastos | F83: =IFERROR(TRIM(LEFT(G83,FIND("-",G83)-1)),"") -> N100100554 | G83: N100100554 - Otros programas y Op | J83: =I83-H83 -> 0 | M83: =L83-K83 -> 0 | N83: 193865.39 | O83: 235755 | P83: =O83-N83 -> 41889.61 | Q83: 467654.84 | R83: 309461.72 | S83: =R83-Q83 -> -158193.12
A84: =_xll.EPMOlapMemberO("[CECO].[PARENTH3].[AMSA1001AD4542]","","AMSA1001AD4542 - AAPP Corporativo","","000") -> AMSA1001AD4542 - AAPP Corporativo | B84: =IFERROR(SUBSTITUTE(TRIM(LEFT(A84,FIND("-",A84)-1)),"AMSA",""),"") -> 1001AD4542 | C84: =IFERROR(_xlfn.XLOOKUP(B84,'CECOS Corporativos'!$D:$D,'CECOS Corporativos'!$E:$E,""),"") -> AAPP Corporativo | D84: =IFERROR(_xlfn.XLOOKUP(B84,'CECOS Corporativos'!$D:$D,'CECOS Corporativos'!$J:$J,""),"") -> VP Asuntos Corporativos | E84: Entrenamiento | F84: =IFERROR(TRIM(LEFT(G84,FIND("-",G84)-1)),"") -> N100100554 | G84: N100100554 - Otros programas y Op | J84: =I84-H84 -> 0 | M84: =L84-K84 -> 0 | N84: 0.34 | P84: =O84-N84 -> -0.34 | S84: =R84-Q84 -> 0
A85: =_xll.EPMOlapMemberO("[CECO].[PARENTH3].[AMSA1001AD4542]","","AMSA1001AD4542 - AAPP Corporativo","","000") -> AMSA1001AD4542 - AAPP Corporativo | B85: =IFERROR(SUBSTITUTE(TRIM(LEFT(A85,FIND("-",A85)-1)),"AMSA",""),"") -> 1001AD4542 | C85: =IFERROR(_xlfn.XLOOKUP(B85,'CECOS Corporativos'!$D:$D,'CECOS Corporativos'!$E:$E,""),"") -> AAPP Corporativo | D85: =IFERROR(_xlfn.XLOOKUP(B85,'CECOS Corporativos'!$D:$D,'CECOS Corporativos'!$J:$J,""),"") -> VP Asuntos Corporativos | E85: Asesorías y Consulto | F85: =IFERROR(TRIM(LEFT(G85,FIND("-",G85)-1)),"") -> N100100554 | G85: N100100554 - Otros programas y Op | J85: =I85-H85 -> 0 | M85: =L85-K85 -> 0 | N85: 205174.12 | O85: 181952 | P85: =O85-N85 -> -23222.12 | Q85: 149889.08 | R85: 176648.68 | S85: =R85-Q85 -> 26759.6
A86: =_xll.EPMOlapMemberO("[CECO].[PARENTH3].[AMSA1001AD4542]","","AMSA1001AD4542 - AAPP Corporativo","","000") -> AMSA1001AD4542 - AAPP Corporativo | B86: =IFERROR(SUBSTITUTE(TRIM(LEFT(A86,FIND("-",A86)-1)),"AMSA",""),"") -> 1001AD4542 | C86: =IFERROR(_xlfn.XLOOKUP(B86,'CECOS Corporativos'!$D:$D,'CECOS Corporativos'!$E:$E,""),"") -> AAPP Corporativo | D86: =IFERROR(_xlfn.XLOOKUP(B86,'CECOS Corporativos'!$D:$D,'CECOS Corporativos'!$J:$J,""),"") -> VP Asuntos Corporativos | E86: Servicios | F86: =IFERROR(TRIM(LEFT(G86,FIND("-",G86)-1)),"") -> N100100554 | G86: N100100554 - Otros programas y Op | J86: =I86-H86 -> 0 | M86: =L86-K86 -> 0 | N86: -6779.52 | P86: =O86-N86 -> 6779.52 | Q86: 50.94 | S86: =R86-Q86 -> -50.94
A87: =_xll.EPMOlapMemberO("[CECO].[PARENTH3].[AMSA1001AD4542]","","AMSA1001AD4542 - AAPP Corporativo","","000") -> AMSA1001AD4542 - AAPP Corporativo | B87: =IFERROR(SUBSTITUTE(TRIM(LEFT(A87,FIND("-",A87)-1)),"AMSA",""),"") -> 1001AD4542 | C87: =IFERROR(_xlfn.XLOOKUP(B87,'CECOS Corporativos'!$D:$D,'CECOS Corporativos'!$E:$E,""),"") -> AAPP Corporativo | D87: =IFERROR(_xlfn.XLOOKUP(B87,'CECOS Corporativos'!$D:$D,'CECOS Corporativos'!$J:$J,""),"") -> VP Asuntos Corporativos | E87: Gastos de Viajes | F87: =IFERROR(TRIM(LEFT(G87,FIND("-",G87)-1)),"") -> N100100554 | G87: N100100554 - Otros programas y Op | J87: =I87-H87 -> 0 | M87: =L87-K87 -> 0 | N87: 2754.08 | P87: =O87-N87 -> -2754.08 | Q87: 10163.82 | S87: =R87-Q87 -> -10163.82
A88: =_xll.EPMOlapMemberO("[CECO].[PARENTH3].[AMSA1001AD4542]","","AMSA1001AD4542 - AAPP Corporativo","","000") -> AMSA1001AD4542 - AAPP Corporativo | B88: =IFERROR(SUBSTITUTE(TRIM(LEFT(A88,FIND("-",A88)-1)),"AMSA",""),"") -> 1001AD4542 | C88: =IFERROR(_xlfn.XLOOKUP(B88,'CECOS Corporativos'!$D:$D,'CECOS Corporativos'!$E:$E,""),"") -> AAPP Corporativo | D88: =IFERROR(_xlfn.XLOOKUP(B88,'CECOS Corporativos'!$D:$D,'CECOS Corporativos'!$J:$J,""),"") -> VP Asuntos Corporativos | E88: Impuestos / Patentes | F88: =IFERROR(TRIM(LEFT(G88,FIND("-",G88)-1)),"") -> N100100554 | G88: N100100554 - Otros programas y Op | J88: =I88-H88 -> 0 | M88: =L88-K88 -> 0 | N88: 27.11 | P88: =O88-N88 -> -27.11 | Q88: 222.54 | S88: =R88-Q88 -> -222.54
A89: =_xll.EPMOlapMemberO("[CECO].[PARENTH3].[AMSA1001AD4542]","","AMSA1001AD4542 - AAPP Corporativo","","000") -> AMSA1001AD4542 - AAPP Corporativo | B89: =IFERROR(SUBSTITUTE(TRIM(LEFT(A89,FIND("-",A89)-1)),"AMSA",""),"") -> 1001AD4542 | C89: =IFERROR(_xlfn.XLOOKUP(B89,'CECOS Corporativos'!$D:$D,'CECOS Corporativos'!$E:$E,""),"") -> AAPP Corporativo | D89: =IFERROR(_xlfn.XLOOKUP(B89,'CECOS Corporativos'!$D:$D,'CECOS Corporativos'!$J:$J,""),"") -> VP Asuntos Corporativos | E89: Otros Gastos | F89: =IFERROR(TRIM(LEFT(G89,FIND("-",G89)-1)),"") -> N100100554 | G89: N100100554 - Otros programas y Op | J89: =I89-H89 -> 0 | M89: =L89-K89 -> 0 | N89: 1067.57 | P89: =O89-N89 -> -1067.57 | Q89: 26333.31 | R89: 43056.41 | S89: =R89-Q89 -> 16723.1
A90: =_xll.EPMOlapMemberO("[CECO].[PARENTH3].[AMSA1001AD0502]","","AMSA1001AD0502 - Corporativo","","000") -> AMSA1001AD0502 - Corporativo | B90: =IFERROR(SUBSTITUTE(TRIM(LEFT(A90,FIND("-",A90)-1)),"AMSA",""),"") -> 1001AD0502 | C90: =IFERROR(_xlfn.XLOOKUP(B90,'CECOS Corporativos'!$D:$D,'CECOS Corporativos'!$E:$E,""),"") -> Auditoría (HH Corporativo) | D90: =IFERROR(_xlfn.XLOOKUP(B90,'CECOS Corporativos'!$D:$D,'CECOS Corporativos'!$J:$J,""),"") -> Auditoría (HH Corporativo) | E90: Materiales y repuest | F90: =IFERROR(TRIM(LEFT(G90,FIND("-",G90)-1)),"") -> N1001AD050 | G90: N1001AD050 - Gerencia General | J90: =I90-H90 -> 0 | M90: =L90-K90 -> 0 | N90: 25.91 | P90: =O90-N90 -> -25.91 | S90: =R90-Q90 -> 0
A91: =_xll.EPMOlapMemberO("[CECO].[PARENTH3].[AMSA1001AD0502]","","AMSA1001AD0502 - Corporativo","","000") -> AMSA1001AD0502 - Corporativo | B91: =IFERROR(SUBSTITUTE(TRIM(LEFT(A91,FIND("-",A91)-1)),"AMSA",""),"") -> 1001AD0502 | C91: =IFERROR(_xlfn.XLOOKUP(B91,'CECOS Corporativos'!$D:$D,'CECOS Corporativos'!$E:$E,""),"") -> Auditoría (HH Corporativo) | D91: =IFERROR(_xlfn.XLOOKUP(B91,'CECOS Corporativos'!$D:$D,'CECOS Corporativos'!$J:$J,""),"") -> Auditoría (HH Corporativo) | E91: Entrenamiento | F91: =IFERROR(TRIM(LEFT(G91,FIND("-",G91)-1)),"") -> N1001AD050 | G91: N1001AD050 - Gerencia General | H91: 1973.53 | J91: =I91-H91 -> -1973.53 | K91: 0 | M91: =L91-K91 -> 0 | P91: =O91-N91 -> 0 | S91: =R91-Q91 -> 0
A92: =_xll.EPMOlapMemberO("[CECO].[PARENTH3].[AMSA1001AD0502]","","AMSA1001AD0502 - Corporativo","","000") -> AMSA1001AD0502 - Corporativo | B92: =IFERROR(SUBSTITUTE(TRIM(LEFT(A92,FIND("-",A92)-1)),"AMSA",""),"") -> 1001AD0502 | C92: =IFERROR(_xlfn.XLOOKUP(B92,'CECOS Corporativos'!$D:$D,'CECOS Corporativos'!$E:$E,""),"") -> Auditoría (HH Corporativo) | D92: =IFERROR(_xlfn.XLOOKUP(B92,'CECOS Corporativos'!$D:$D,'CECOS Corporativos'!$J:$J,""),"") -> Auditoría (HH Corporativo) | E92: Asesorías y Consulto | F92: =IFERROR(TRIM(LEFT(G92,FIND("-",G92)-1)),"") -> N1001AD050 | G92: N1001AD050 - Gerencia General | H92: 602598.19 | J92: =I92-H92 -> -602598.19 | K92: 22342.65 | M92: =L92-K92 -> -22342.65 | N92: 0 | P92: =O92-N92 -> 0 | S92: =R92-Q92 -> 0
A93: =_xll.EPMOlapMemberO("[CECO].[PARENTH3].[AMSA1001AD0502]","","AMSA1001AD0502 - Corporativo","","000") -> AMSA1001AD0502 - Corporativo | B93: =IFERROR(SUBSTITUTE(TRIM(LEFT(A93,FIND("-",A93)-1)),"AMSA",""),"") -> 1001AD0502 | C93: =IFERROR(_xlfn.XLOOKUP(B93,'CECOS Corporativos'!$D:$D,'CECOS Corporativos'!$E:$E,""),"") -> Auditoría (HH Corporativo) | D93: =IFERROR(_xlfn.XLOOKUP(B93,'CECOS Corporativos'!$D:$D,'CECOS Corporativos'!$J:$J,""),"") -> Auditoría (HH Corporativo) | E93: Servicios | F93: =IFERROR(TRIM(LEFT(G93,FIND("-",G93)-1)),"") -> N1001AD050 | G93: N1001AD050 - Gerencia General | H93: 568865.01 | J93: =I93-H93 -> -568865.01 | K93: -6365.58 | M93: =L93-K93 -> 6365.58 | N93: -113.29 | O93: 0 | P93: =O93-N93 -> 113.29 | S93: =R93-Q93 -> 0
A94: =_xll.EPMOlapMemberO("[CECO].[PARENTH3].[AMSA1001AD0502]","","AMSA1001AD0502 - Corporativo","","000") -> AMSA1001AD0502 - Corporativo | B94: =IFERROR(SUBSTITUTE(TRIM(LEFT(A94,FIND("-",A94)-1)),"AMSA",""),"") -> 1001AD0502 | C94: =IFERROR(_xlfn.XLOOKUP(B94,'CECOS Corporativos'!$D:$D,'CECOS Corporativos'!$E:$E,""),"") -> Auditoría (HH Corporativo) | D94: =IFERROR(_xlfn.XLOOKUP(B94,'CECOS Corporativos'!$D:$D,'CECOS Corporativos'!$J:$J,""),"") -> Auditoría (HH Corporativo) | E94: Informática y Comuni | F94: =IFERROR(TRIM(LEFT(G94,FIND("-",G94)-1)),"") -> N1001AD050 | G94: N1001AD050 - Gerencia General | H94: 51350 | J94: =I94-H94 -> -51350 | K94: 0 | M94: =L94-K94 -> 0 | P94: =O94-N94 -> 0 | S94: =R94-Q94 -> 0
A95: =_xll.EPMOlapMemberO("[CECO].[PARENTH3].[AMSA1001AD0502]","","AMSA1001AD0502 - Corporativo","","000") -> AMSA1001AD0502 - Corporativo | B95: =IFERROR(SUBSTITUTE(TRIM(LEFT(A95,FIND("-",A95)-1)),"AMSA",""),"") -> 1001AD0502 | C95: =IFERROR(_xlfn.XLOOKUP(B95,'CECOS Corporativos'!$D:$D,'CECOS Corporativos'!$E:$E,""),"") -> Auditoría (HH Corporativo) | D95: =IFERROR(_xlfn.XLOOKUP(B95,'CECOS Corporativos'!$D:$D,'CECOS Corporativos'!$J:$J,""),"") -> Auditoría (HH Corporativo) | E95: Gastos de Viajes | F95: =IFERROR(TRIM(LEFT(G95,FIND("-",G95)-1)),"") -> N1001AD050 | G95: N1001AD050 - Gerencia General | H95: 171.75 | J95: =I95-H95 -> -171.75 | K95: 0 | M95: =L95-K95 -> 0 | P95: =O95-N95 -> 0 | S95: =R95-Q95 -> 0
A96: =_xll.EPMOlapMemberO("[CECO].[PARENTH3].[AMSA1001AD0502]","","AMSA1001AD0502 - Corporativo","","000") -> AMSA1001AD0502 - Corporativo | B96: =IFERROR(SUBSTITUTE(TRIM(LEFT(A96,FIND("-",A96)-1)),"AMSA",""),"") -> 1001AD0502 | C96: =IFERROR(_xlfn.XLOOKUP(B96,'CECOS Corporativos'!$D:$D,'CECOS Corporativos'!$E:$E,""),"") -> Auditoría (HH Corporativo) | D96: =IFERROR(_xlfn.XLOOKUP(B96,'CECOS Corporativos'!$D:$D,'CECOS Corporativos'!$J:$J,""),"") -> Auditoría (HH Corporativo) | E96: PCC Programa Competi | F96: =IFERROR(TRIM(LEFT(G96,FIND("-",G96)-1)),"") -> N1001AD050 | G96: N1001AD050 - Gerencia General | J96: =I96-H96 -> 0 | M96: =L96-K96 -> 0 | O96: 0 | P96: =O96-N96 -> 0 | S96: =R96-Q96 -> 0
A97: =_xll.EPMOlapMemberO("[CECO].[PARENTH3].[AMSA1001AD0502]","","AMSA1001AD0502 - Corporativo","","000") -> AMSA1001AD0502 - Corporativo | B97: =IFERROR(SUBSTITUTE(TRIM(LEFT(A97,FIND("-",A97)-1)),"AMSA",""),"") -> 1001AD0502 | C97: =IFERROR(_xlfn.XLOOKUP(B97,'CECOS Corporativos'!$D:$D,'CECOS Corporativos'!$E:$E,""),"") -> Auditoría (HH Corporativo) | D97: =IFERROR(_xlfn.XLOOKUP(B97,'CECOS Corporativos'!$D:$D,'CECOS Corporativos'!$J:$J,""),"") -> Auditoría (HH Corporativo) | E97: Servicios Corporativ | F97: =IFERROR(TRIM(LEFT(G97,FIND("-",G97)-1)),"") -> N1001AD050 | G97: N1001AD050 - Gerencia General | H97: 1511076.5 | I97: 2041296 | J97: =I97-H97 -> 530219.51 | K97: 2216676.3 | L97: 2017323 | M97: =L97-K97 -> -199353.26 | N97: 483656.74 | O97: 511858 | P97: =O97-N97 -> 28201.26 | Q97: 517868 | R97: 543582.32 | S97: =R97-Q97 -> 25714.32
A98: =_xll.EPMOlapMemberO("[CECO].[PARENTH3].[AMSA1001AD0503]","","AMSA1001AD0503 - Desarrollo Corp","","000") -> AMSA1001AD0503 - Desarrollo Corp | B98: =IFERROR(SUBSTITUTE(TRIM(LEFT(A98,FIND("-",A98)-1)),"AMSA",""),"") -> 1001AD0503 | C98: =IFERROR(_xlfn.XLOOKUP(B98,'CECOS Corporativos'!$D:$D,'CECOS Corporativos'!$E:$E,""),"") -> VP Desarrollo | D98: =IFERROR(_xlfn.XLOOKUP(B98,'CECOS Corporativos'!$D:$D,'CECOS Corporativos'!$J:$J,""),"") -> VP Desarrollo | E98: Administración Perso | F98: =IFERROR(TRIM(LEFT(G98,FIND("-",G98)-1)),"") -> N1001AD050 | G98: N1001AD050 - Gerencia General | J98: =I98-H98 -> 0 | K98: 20643.63 | M98: =L98-K98 -> -20643.63 | P98: =O98-N98 -> 0 | S98: =R98-Q98 -> 0
A99: =_xll.EPMOlapMemberO("[CECO].[PARENTH3].[AMSA1001AD0503]","","AMSA1001AD0503 - Desarrollo Corp","","000") -> AMSA1001AD0503 - Desarrollo Corp | B99: =IFERROR(SUBSTITUTE(TRIM(LEFT(A99,FIND("-",A99)-1)),"AMSA",""),"") -> 1001AD0503 | C99: =IFERROR(_xlfn.XLOOKUP(B99,'CECOS Corporativos'!$D:$D,'CECOS Corporativos'!$E:$E,""),"") -> VP Desarrollo | D99: =IFERROR(_xlfn.XLOOKUP(B99,'CECOS Corporativos'!$D:$D,'CECOS Corporativos'!$J:$J,""),"") -> VP Desarrollo | E99: Asesorías y Consulto | F99: =IFERROR(TRIM(LEFT(G99,FIND("-",G99)-1)),"") -> N1001AD050 | G99: N1001AD050 - Gerencia General | H99: 8485.81 | J99: =I99-H99 -> -8485.81 | K99: 48251.8 | L99: 29888 | M99: =L99-K99 -> -18363.8 | N99: 1641.97 | P99: =O99-N99 -> -1641.97 | S99: =R99-Q99 -> 0
A100: =_xll.EPMOlapMemberO("[CECO].[PARENTH3].[AMSA1001AD0503]","","AMSA1001AD0503 - Desarrollo Corp","","000") -> AMSA1001AD0503 - Desarrollo Corp | B100: =IFERROR(SUBSTITUTE(TRIM(LEFT(A100,FIND("-",A100)-1)),"AMSA",""),"") -> 1001AD0503 | C100: =IFERROR(_xlfn.XLOOKUP(B100,'CECOS Corporativos'!$D:$D,'CECOS Corporativos'!$E:$E,""),"") -> VP Desarrollo | D100: =IFERROR(_xlfn.XLOOKUP(B100,'CECOS Corporativos'!$D:$D,'CECOS Corporativos'!$J:$J,""),"") -> VP Desarrollo | E100: Arriendos | F100: =IFERROR(TRIM(LEFT(G100,FIND("-",G100)-1)),"") -> N1001AD050 | G100: N1001AD050 - Gerencia General | H100: 313.95 | J100: =I100-H100 -> -313.95 | K100: 147.87 | M100: =L100-K100 -> -147.87 | P100: =O100-N100 -> 0 | S100: =R100-Q100 -> 0
A101: =_xll.EPMOlapMemberO("[CECO].[PARENTH3].[AMSA1001AD0503]","","AMSA1001AD0503 - Desarrollo Corp","","000") -> AMSA1001AD0503 - Desarrollo Corp | B101: =IFERROR(SUBSTITUTE(TRIM(LEFT(A101,FIND("-",A101)-1)),"AMSA",""),"") -> 1001AD0503 | C101: =IFERROR(_xlfn.XLOOKUP(B101,'CECOS Corporativos'!$D:$D,'CECOS Corporativos'!$E:$E,""),"") -> VP Desarrollo | D101: =IFERROR(_xlfn.XLOOKUP(B101,'CECOS Corporativos'!$D:$D,'CECOS Corporativos'!$J:$J,""),"") -> VP Desarrollo | E101: Servicios | F101: =IFERROR(TRIM(LEFT(G101,FIND("-",G101)-1)),"") -> N1001AD050 | G101: N1001AD050 - Gerencia General | H101: 19.3 | J101: =I101-H101 -> -19.3 | K101: 3000 | M101: =L101-K101 -> -3000 | N101: -1.84 | P101: =O101-N101 -> 1.84 | Q101: -1535.82 | S101: =R101-Q101 -> 1535.82
A102: =_xll.EPMOlapMemberO("[CECO].[PARENTH3].[AMSA1001AD0503]","","AMSA1001AD0503 - Desarrollo Corp","","000") -> AMSA1001AD0503 - Desarrollo Corp | B102: =IFERROR(SUBSTITUTE(TRIM(LEFT(A102,FIND("-",A102)-1)),"AMSA",""),"") -> 1001AD0503 | C102: =IFERROR(_xlfn.XLOOKUP(B102,'CECOS Corporativos'!$D:$D,'CECOS Corporativos'!$E:$E,""),"") -> VP Desarrollo | D102: =IFERROR(_xlfn.XLOOKUP(B102,'CECOS Corporativos'!$D:$D,'CECOS Corporativos'!$J:$J,""),"") -> VP Desarrollo | E102: Informática y Comuni | F102: =IFERROR(TRIM(LEFT(G102,FIND("-",G102)-1)),"") -> N1001AD050 | G102: N1001AD050 - Gerencia General | J102: =I102-H102 -> 0 | M102: =L102-K102 -> 0 | N102: 7733.47 | P102: =O102-N102 -> -7733.47 | Q102: 13710.42 | R102: 12523.96 | S102: =R102-Q102 -> -1186.46
A103: =_xll.EPMOlapMemberO("[CECO].[PARENTH3].[AMSA1001AD0503]","","AMSA1001AD0503 - Desarrollo Corp","","000") -> AMSA1001AD0503 - Desarrollo Corp | B103: =IFERROR(SUBSTITUTE(TRIM(LEFT(A103,FIND("-",A103)-1)),"AMSA",""),"") -> 1001AD0503 | C103: =IFERROR(_xlfn.XLOOKUP(B103,'CECOS Corporativos'!$D:$D,'CECOS Corporativos'!$E:$E,""),"") -> VP Desarrollo | D103: =IFERROR(_xlfn.XLOOKUP(B103,'CECOS Corporativos'!$D:$D,'CECOS Corporativos'!$J:$J,""),"") -> VP Desarrollo | E103: Gastos de Viajes | F103: =IFERROR(TRIM(LEFT(G103,FIND("-",G103)-1)),"") -> N1001AD050 | G103: N1001AD050 - Gerencia General | H103: 893.44 | I103: 10617.2 | J103: =I103-H103 -> 9723.76 | K103: 0 | L103: 8460 | M103: =L103-K103 -> 8460 | O103: 8608 | P103: =O103-N103 -> 8608 | R103: 5406.54 | S103: =R103-Q103 -> 5406.54
...

Sheet ANT
A1: {=_xll.EPMDimensionOverrideRange("000","CECO",CECOS!$B$2:$B$128)} -> Expansión de CECO sobrescrita
A2: =_xll.EPMOlapMemberO("[CEBE].[PARENTH1].[JE-]","","Gr Antofagasta Miner","","000") -> Gr Antofagasta Miner
A4: =_xll.EPMOlapMemberO("[ENTITY].[PARENTH1].[1003]","","1003 - Minera Antucoya","","000") -> 1003 - Minera Antucoya
I7: =_xll.EPMOlapMemberO("[TIME].[PARENTH1].[2022.TOTAL]","","2022.TOTAL","","000") -> 2022.TOTAL | L7: =_xll.EPMOlapMemberO("[TIME].[PARENTH1].[2023.TOTAL]","","2023.TOTAL","","000") -> 2023.TOTAL | O7: =_xll.EPMOlapMemberO("[TIME].[PARENTH1].[2024.TOTAL]","","2024.TOTAL","","000") -> 2024.TOTAL | R7: =_xll.EPMOlapMemberO("[TIME].[PARENTH1].[2025.TOTAL]","","2025.TOTAL","","000") -> 2025.TOTAL
B8: CECO Código | C8: CECO | D8: VP | E8: Item Relevante | F8: Nodo 3 | G8: CeCo Padre | H8: =_xll.EPMOlapMemberO("[CATEGORY].[].[REAL]","","Real - Real","","000") -> #NAME? | I8: =_xll.EPMOlapMemberO("[CATEGORY].[].[PLAN]","","Plan - Plan","","000") -> #NAME? | J8: =_xll.FPMXLClient.TechnicalCategory.EPMLocalMember("Var","001","000") -> Var | K8: =_xll.EPMOlapMemberO("[CATEGORY].[].[REAL]","","Real - Real","","000") -> #NAME? | L8: =_xll.EPMOlapMemberO("[CATEGORY].[].[PLAN]","","Plan - Plan","","000") -> #NAME? | M8: =_xll.FPMXLClient.TechnicalCategory.EPMLocalMember("Var","001","000") -> Var | N8: =_xll.EPMOlapMemberO("[CATEGORY].[].[REAL]","","Real - Real","","000") -> #NAME? | O8: =_xll.EPMOlapMemberO("[CATEGORY].[].[PLAN]","","Plan - Plan","","000") -> #NAME? | P8: =_xll.FPMXLClient.TechnicalCategory.EPMLocalMember("Var","001","000") -> Var | Q8: =_xll.EPMOlapMemberO("[CATEGORY].[].[REAL]","","Real - Real","","000") -> #NAME? | R8: =_xll.EPMOlapMemberO("[CATEGORY].[].[PLAN]","","Plan - Plan","","000") -> #NAME? | S8: =_xll.FPMXLClient.TechnicalCategory.EPMLocalMember("Var","001","000") -> Var
A9: =_xll.EPMOlapMemberO("[CECO].[PARENTH3].[AMSA1003AD0507]","","AMSA1003AD0507 - VPACS Corporativo","","000") -> AMSA1003AD0507 - VPACS Corporativo | B9: =IFERROR(SUBSTITUTE(TRIM(LEFT(A9,FIND("-",A9)-1)),"AMSA",""),"") -> 1003AD0507 | C9: =IFERROR(_xlfn.XLOOKUP(B9,'CECOS Corporativos'!$D:$D,'CECOS Corporativos'!$E:$E,""),"") -> VPACS Corporativo (HH Corporativo) | D9: =IFERROR(_xlfn.XLOOKUP(B9,'CECOS Corporativos'!$D:$D,'CECOS Corporativos'!$J:$J,""),"") -> VP Asuntos Corporativos | E9: =_xll.EPMOlapMemberO("[CLACO].[PARENTH7].[AMSASERV_CORP]","","Servicios Corporativ","","000") -> Servicios Corporativ | F9: =IFERROR(TRIM(LEFT(G9,FIND("-",G9)-1)),"") -> N100300500 | G9: N100300500 - Antucoya No Operacio | H9: =IFERROR(_xlfn.XLOOKUP(F9,'CECOS Corporativos'!$K:$K,'CECOS Corporativos'!$D:$D,""),"") -> 1003AD4505 | K9: =J9-I9 -> 0 | N9: =M9-L9 -> 0 | O9: 1044408 | P9: 1157235 | Q9: =P9-O9 -> 112827 | R9: 961205 | S9: 1008932.3 | T9: =S9-R9 -> 47727.31
A10: =_xll.EPMOlapMemberO("[CECO].[PARENTH3].[AMSA1003AD4505]","","AMSA1003AD4505 - Asunt Publ y Comunid","","000") -> AMSA1003AD4505 - Asunt Publ y Comunid | B10: =IFERROR(SUBSTITUTE(TRIM(LEFT(A10,FIND("-",A10)-1)),"AMSA",""),"") -> 1003AD4505 | C10: =IFERROR(_xlfn.XLOOKUP(B10,'CECOS Corporativos'!$D:$D,'CECOS Corporativos'!$E:$E,""),"") -> Asuntos Públicos y Comunidades | D10: =IFERROR(_xlfn.XLOOKUP(B10,'CECOS Corporativos'!$D:$D,'CECOS Corporativos'!$J:$J,""),"") -> VP Asuntos Corporativos | E10: =_xll.EPMOlapMemberO("[CLACO].[PARENTH7].[AMSAMAT_Y_REP.2]","","Materiales y repuest","","000") -> Materiales y repuest | F10: =IFERROR(TRIM(LEFT(G10,FIND("-",G10)-1)),"") -> N100300500 | G10: N100300500 - Antucoya No Operacio | H10: =IFERROR(_xlfn.XLOOKUP(F10,'CECOS Corporativos'!$K:$K,'CECOS Corporativos'!$D:$D,""),"") -> 1003AD4505 | I10: 602.29 | K10: =J10-I10 -> -602.29 | N10: =M10-L10 -> 0 | Q10: =P10-O10 -> 0 | T10: =S10-R10 -> 0
A11: =_xll.EPMOlapMemberO("[CECO].[PARENTH3].[AMSA1003AD4505]","","AMSA1003AD4505 - Asunt Publ y Comunid","","000") -> AMSA1003AD4505 - Asunt Publ y Comunid | B11: =IFERROR(SUBSTITUTE(TRIM(LEFT(A11,FIND("-",A11)-1)),"AMSA",""),"") -> 1003AD4505 | C11: =IFERROR(_xlfn.XLOOKUP(B11,'CECOS Corporativos'!$D:$D,'CECOS Corporativos'!$E:$E,""),"") -> Asuntos Públicos y Comunidades | D11: =IFERROR(_xlfn.XLOOKUP(B11,'CECOS Corporativos'!$D:$D,'CECOS Corporativos'!$J:$J,""),"") -> VP Asuntos Corporativos | E11: =_xll.EPMOlapMemberO("[CLACO].[PARENTH7].[AMSAADM_PERSON]","","Administración Perso","","000") -> Administración Perso | F11: =IFERROR(TRIM(LEFT(G11,FIND("-",G11)-1)),"") -> N100300500 | G11: N100300500 - Antucoya No Operacio | H11: =IFERROR(_xlfn.XLOOKUP(F11,'CECOS Corporativos'!$K:$K,'CECOS Corporativos'!$D:$D,""),"") -> 1003AD4505 | I11: -1427.15 | K11: =J11-I11 -> 1427.15 | N11: =M11-L11 -> 0 | Q11: =P11-O11 -> 0 | T11: =S11-R11 -> 0
A12: =_xll.EPMOlapMemberO("[CECO].[PARENTH3].[AMSA1003AD4505]","","AMSA1003AD4505 - Asunt Publ y Comunid","","000") -> AMSA1003AD4505 - Asunt Publ y Comunid | B12: =IFERROR(SUBSTITUTE(TRIM(LEFT(A12,FIND("-",A12)-1)),"AMSA",""),"") -> 1003AD4505 | C12: =IFERROR(_xlfn.XLOOKUP(B12,'CECOS Corporativos'!$D:$D,'CECOS Corporativos'!$E:$E,""),"") -> Asuntos Públicos y Comunidades | D12: =IFERROR(_xlfn.XLOOKUP(B12,'CECOS Corporativos'!$D:$D,'CECOS Corporativos'!$J:$J,""),"") -> VP Asuntos Corporativos | E12: =_xll.EPMOlapMemberO("[CLACO].[PARENTH7].[AMSAENTRENAMI]","","Entrenamiento","","000") -> Entrenamiento | F12: =IFERROR(TRIM(LEFT(G12,FIND("-",G12)-1)),"") -> N100300500 | G12: N100300500 - Antucoya No Operacio | H12: =IFERROR(_xlfn.XLOOKUP(F12,'CECOS Corporativos'!$K:$K,'CECOS Corporativos'!$D:$D,""),"") -> 1003AD4505 | K12: =J12-I12 -> 0 | N12: =M12-L12 -> 0 | Q12: =P12-O12 -> 0 | R12: 1350.37 | T12: =S12-R12 -> -1350.37
A13: =_xll.EPMOlapMemberO("[CECO].[PARENTH3].[AMSA1003AD4505]","","AMSA1003AD4505 - Asunt Publ y Comunid","","000") -> AMSA1003AD4505 - Asunt Publ y Comunid | B13: =IFERROR(SUBSTITUTE(TRIM(LEFT(A13,FIND("-",A13)-1)),"AMSA",""),"") -> 1003AD4505 | C13: =IFERROR(_xlfn.XLOOKUP(B13,'CECOS Corporativos'!$D:$D,'CECOS Corporativos'!$E:$E,""),"") -> Asuntos Públicos y Comunidades | D13: =IFERROR(_xlfn.XLOOKUP(B13,'CECOS Corporativos'!$D:$D,'CECOS Corporativos'!$J:$J,""),"") -> VP Asuntos Corporativos | E13: =_xll.EPMOlapMemberO("[CLACO].[PARENTH7].[AMSAASESORIAS]","","Asesorías y Consulto","","000") -> Asesorías y Consulto | F13: =IFERROR(TRIM(LEFT(G13,FIND("-",G13)-1)),"") -> N100300500 | G13: N100300500 - Antucoya No Operacio | H13: =IFERROR(_xlfn.XLOOKUP(F13,'CECOS Corporativos'!$K:$K,'CECOS Corporativos'!$D:$D,""),"") -> 1003AD4505 | I13: 120720.09 | J13: 74702 | K13: =J13-I13 -> -46018.09 | L13: 125189.99 | M13: 17279 | N13: =M13-L13 -> -107910.99 | O13: 21760.51 | Q13: =P13-O13 -> -21760.51 | R13: 29750.19 | S13: 10433.84 | T13: =S13-R13 -> -19316.35
A14: =_xll.EPMOlapMemberO("[CECO].[PARENTH3].[AMSA1003AD4505]","","AMSA1003AD4505 - Asunt Publ y Comunid","","000") -> AMSA1003AD4505 - Asunt Publ y Comunid | B14: =IFERROR(SUBSTITUTE(TRIM(LEFT(A14,FIND("-",A14)-1)),"AMSA",""),"") -> 1003AD4505 | C14: =IFERROR(_xlfn.XLOOKUP(B14,'CECOS Corporativos'!$D:$D,'CECOS Corporativos'!$E:$E,""),"") -> Asuntos Públicos y Comunidades | D14: =IFERROR(_xlfn.XLOOKUP(B14,'CECOS Corporativos'!$D:$D,'CECOS Corporativos'!$J:$J,""),"") -> VP Asuntos Corporativos | E14: =_xll.EPMOlapMemberO("[CLACO].[PARENTH7].[AMSASERVICIOS]","","Servicios","","000") -> Servicios | F14: =IFERROR(TRIM(LEFT(G14,FIND("-",G14)-1)),"") -> N100300500 | G14: N100300500 - Antucoya No Operacio | H14: =IFERROR(_xlfn.XLOOKUP(F14,'CECOS Corporativos'!$K:$K,'CECOS Corporativos'!$D:$D,""),"") -> 1003AD4505 | I14: 259648.63 | J14: 432257 | K14: =J14-I14 -> 172608.37 | L14: 203961.93 | N14: =M14-L14 -> -203961.93 | O14: 174781.97 | P14: 47518 | Q14: =P14-O14 -> -127263.97 | R14: 95903.09 | S14: 45206.35 | T14: =S14-R14 -> -50696.74
A15: =_xll.EPMOlapMemberO("[CECO].[PARENTH3].[AMSA1003AD4505]","","AMSA1003AD4505 - Asunt Publ y Comunid","","000") -> AMSA1003AD4505 - Asunt Publ y Comunid | B15: =IFERROR(SUBSTITUTE(TRIM(LEFT(A15,FIND("-",A15)-1)),"AMSA",""),"") -> 1003AD4505 | C15: =IFERROR(_xlfn.XLOOKUP(B15,'CECOS Corporativos'!$D:$D,'CECOS Corporativos'!$E:$E,""),"") -> Asuntos Públicos y Comunidades | D15: =IFERROR(_xlfn.XLOOKUP(B15,'CECOS Corporativos'!$D:$D,'CECOS Corporativos'!$J:$J,""),"") -> VP Asuntos Corporativos | E15: =_xll.EPMOlapMemberO("[CLACO].[PARENTH7].[AMSAINFORMATIC]","","Informática y Comuni","","000") -> Informática y Comuni | F15: =IFERROR(TRIM(LEFT(G15,FIND("-",G15)-1)),"") -> N100300500 | G15: N100300500 - Antucoya No Operacio | H15: =IFERROR(_xlfn.XLOOKUP(F15,'CECOS Corporativos'!$K:$K,'CECOS Corporativos'!$D:$D,""),"") -> 1003AD4505 | I15: 167.37 | K15: =J15-I15 -> -167.37 | L15: 0 | N15: =M15-L15 -> 0 | Q15: =P15-O15 -> 0 | T15: =S15-R15 -> 0
A16: =_xll.EPMOlapMemberO("[CECO].[PARENTH3].[AMSA1003AD4505]","","AMSA1003AD4505 - Asunt Publ y Comunid","","000") -> AMSA1003AD4505 - Asunt Publ y Comunid | B16: =IFERROR(SUBSTITUTE(TRIM(LEFT(A16,FIND("-",A16)-1)),"AMSA",""),"") -> 1003AD4505 | C16: =IFERROR(_xlfn.XLOOKUP(B16,'CECOS Corporativos'!$D:$D,'CECOS Corporativos'!$E:$E,""),"") -> Asuntos Públicos y Comunidades | D16: =IFERROR(_xlfn.XLOOKUP(B16,'CECOS Corporativos'!$D:$D,'CECOS Corporativos'!$J:$J,""),"") -> VP Asuntos Corporativos | E16: =_xll.EPMOlapMemberO("[CLACO].[PARENTH7].[AMSAG_VIAJES]","","Gastos de Viajes","","000") -> Gastos de Viajes | F16: =IFERROR(TRIM(LEFT(G16,FIND("-",G16)-1)),"") -> N100300500 | G16: N100300500 - Antucoya No Operacio | H16: =IFERROR(_xlfn.XLOOKUP(F16,'CECOS Corporativos'!$K:$K,'CECOS Corporativos'!$D:$D,""),"") -> 1003AD4505 | I16: 113522.3 | J16: 11481.47 | K16: =J16-I16 -> -102040.83 | L16: 2254.49 | N16: =M16-L16 -> -2254.49 | O16: 1815.48 | Q16: =P16-O16 -> -1815.48 | R16: 740.54 | T16: =S16-R16 -> -740.54
A17: =_xll.EPMOlapMemberO("[CECO].[PARENTH3].[AMSA1003AD4505]","","AMSA1003AD4505 - Asunt Publ y Comunid","","000") -> AMSA1003AD4505 - Asunt Publ y Comunid | B17: =IFERROR(SUBSTITUTE(TRIM(LEFT(A17,FIND("-",A17)-1)),"AMSA",""),"") -> 1003AD4505 | C17: =IFERROR(_xlfn.XLOOKUP(B17,'CECOS Corporativos'!$D:$D,'CECOS Corporativos'!$E:$E,""),"") -> Asuntos Públicos y Comunidades | D17: =IFERROR(_xlfn.XLOOKUP(B17,'CECOS Corporativos'!$D:$D,'CECOS Corporativos'!$J:$J,""),"") -> VP Asuntos Corporativos | E17: =_xll.EPMOlapMemberO("[CLACO].[PARENTH7].[AMSAGGENERALES.2]","","Otros Gastos","","000") -> Otros Gastos | F17: =IFERROR(TRIM(LEFT(G17,FIND("-",G17)-1)),"") -> N100300500 | G17: N100300500 - Antucoya No Operacio | H17: =IFERROR(_xlfn.XLOOKUP(F17,'CECOS Corporativos'!$K:$K,'CECOS Corporativos'!$D:$D,""),"") -> 1003AD4505 | I17: 86772 | J17: 53254 | K17: =J17-I17 -> -33518 | L17: 81508.05 | M17: 22767 | N17: =M17-L17 -> -58741.05 | O17: 9308.79 | P17: 8443 | Q17: =P17-O17 -> -865.79 | R17: 30489.02 | S17: 24861.15 | T17: =S17-R17 -> -5627.87
A18: =_xll.EPMOlapMemberO("[CECO].[PARENTH3].[AMSA1003AD4505]","","AMSA1003AD4505 - Asunt Publ y Comunid","","000") -> AMSA1003AD4505 - Asunt Publ y Comunid | B18: =IFERROR(SUBSTITUTE(TRIM(LEFT(A18,FIND("-",A18)-1)),"AMSA",""),"") -> 1003AD4505 | C18: =IFERROR(_xlfn.XLOOKUP(B18,'CECOS Corporativos'!$D:$D,'CECOS Corporativos'!$E:$E,""),"") -> Asuntos Públicos y Comunidades | D18: =IFERROR(_xlfn.XLOOKUP(B18,'CECOS Corporativos'!$D:$D,'CECOS Corporativos'!$J:$J,""),"") -> VP Asuntos Corporativos | E18: =_xll.EPMOlapMemberO("[CLACO].[PARENTH7].[AMSALIQUIDACIO.SEC]","","Liquidación Interna","","000") -> Liquidación Interna | F18: =IFERROR(TRIM(LEFT(G18,FIND("-",G18)-1)),"") -> N100300500 | G18: N100300500 - Antucoya No Operacio | H18: =IFERROR(_xlfn.XLOOKUP(F18,'CECOS Corporativos'!$K:$K,'CECOS Corporativos'!$D:$D,""),"") -> 1003AD4505 | K18: =J18-I18 -> 0 | N18: =M18-L18 -> 0 | Q18: =P18-O18 -> 0 | R18: 2770.78 | T18: =S18-R18 -> -2770.78
A19: =_xll.EPMOlapMemberO("[CECO].[PARENTH3].[AMSA1003AD4505]","","AMSA1003AD4505 - Asunt Publ y Comunid","","000") -> AMSA1003AD4505 - Asunt Publ y Comunid | B19: =IFERROR(SUBSTITUTE(TRIM(LEFT(A19,FIND("-",A19)-1)),"AMSA",""),"") -> 1003AD4505 | C19: =IFERROR(_xlfn.XLOOKUP(B19,'CECOS Corporativos'!$D:$D,'CECOS Corporativos'!$E:$E,""),"") -> Asuntos Públicos y Comunidades | D19: =IFERROR(_xlfn.XLOOKUP(B19,'CECOS Corporativos'!$D:$D,'CECOS Corporativos'!$J:$J,""),"") -> VP Asuntos Corporativos | E19: =_xll.EPMOlapMemberO("[CLACO].[PARENTH7].[AMSASERV_CORP]","","Servicios Corporativ","","000") -> Servicios Corporativ | F19: =IFERROR(TRIM(LEFT(G19,FIND("-",G19)-1)),"") -> N100300500 | G19: N100300500 - Antucoya No Operacio | H19: =IFERROR(_xlfn.XLOOKUP(F19,'CECOS Corporativos'!$K:$K,'CECOS Corporativos'!$D:$D,""),"") -> 1003AD4505 | I19: 424984.07 | J19: 438111 | K19: =J19-I19 -> 13126.93 | L19: 603209.21 | M19: 547565 | N19: =M19-L19 -> -55644.21 | O19: 14533.79 | Q19: =P19-O19 -> -14533.79 | T19: =S19-R19 -> 0
A20: =_xll.EPMOlapMemberO("[CECO].[PARENTH3].[AMSA1003AD4509]","","AMSA1003AD4509 - AAPP Corporativo","","000") -> AMSA1003AD4509 - AAPP Corporativo | B20: =IFERROR(SUBSTITUTE(TRIM(LEFT(A20,FIND("-",A20)-1)),"AMSA",""),"") -> 1003AD4509 | C20: =IFERROR(_xlfn.XLOOKUP(B20,'CECOS Corporativos'!$D:$D,'CECOS Corporativos'!$E:$E,""),"") -> AAPP Corporativo | D20: =IFERROR(_xlfn.XLOOKUP(B20,'CECOS Corporativos'!$D:$D,'CECOS Corporativos'!$J:$J,""),"") -> VP Asuntos Corporativos | E20: =_xll.EPMOlapMemberO("[CLACO].[PARENTH7].[AMSAASESORIAS]","","Asesorías y Consulto","","000") -> Asesorías y Consulto | F20: =IFERROR(TRIM(LEFT(G20,FIND("-",G20)-1)),"") -> N100300500 | G20: N100300500 - Antucoya No Operacio | H20: =IFERROR(_xlfn.XLOOKUP(F20,'CECOS Corporativos'!$K:$K,'CECOS Corporativos'!$D:$D,""),"") -> 1003AD4505 | K20: =J20-I20 -> 0 | M20: 43671 | N20: =M20-L20 -> 43671 | O20: 37752.3 | P20: 29594 | Q20: =P20-O20 -> -8158.3 | R20: 43338.26 | S20: 28730.53 | T20: =S20-R20 -> -14607.73
A21: =_xll.EPMOlapMemberO("[CECO].[PARENTH3].[AMSA1003AD4509]","","AMSA1003AD4509 - AAPP Corporativo","","000") -> AMSA1003AD4509 - AAPP Corporativo | B21: =IFERROR(SUBSTITUTE(TRIM(LEFT(A21,FIND("-",A21)-1)),"AMSA",""),"") -> 1003AD4509 | C21: =IFERROR(_xlfn.XLOOKUP(B21,'CECOS Corporativos'!$D:$D,'CECOS Corporativos'!$E:$E,""),"") -> AAPP Corporativo | D21: =IFERROR(_xlfn.XLOOKUP(B21,'CECOS Corporativos'!$D:$D,'CECOS Corporativos'!$J:$J,""),"") -> VP Asuntos Corporativos | E21: =_xll.EPMOlapMemberO("[CLACO].[PARENTH7].[AMSASERVICIOS]","","Servicios","","000") -> Servicios | F21: =IFERROR(TRIM(LEFT(G21,FIND("-",G21)-1)),"") -> N100300500 | G21: N100300500 - Antucoya No Operacio | H21: =IFERROR(_xlfn.XLOOKUP(F21,'CECOS Corporativos'!$K:$K,'CECOS Corporativos'!$D:$D,""),"") -> 1003AD4505 | K21: =J21-I21 -> 0 | M21: 61271 | N21: =M21-L21 -> 61271 | Q21: =P21-O21 -> 0 | T21: =S21-R21 -> 0
A22: =_xll.EPMOlapMemberO("[CECO].[PARENTH3].[AMSA1003AD4509]","","AMSA1003AD4509 - AAPP Corporativo","","000") -> AMSA1003AD4509 - AAPP Corporativo | B22: =IFERROR(SUBSTITUTE(TRIM(LEFT(A22,FIND("-",A22)-1)),"AMSA",""),"") -> 1003AD4509 | C22: =IFERROR(_xlfn.XLOOKUP(B22,'CECOS Corporativos'!$D:$D,'CECOS Corporativos'!$E:$E,""),"") -> AAPP Corporativo | D22: =IFERROR(_xlfn.XLOOKUP(B22,'CECOS Corporativos'!$D:$D,'CECOS Corporativos'!$J:$J,""),"") -> VP Asuntos Corporativos | E22: =_xll.EPMOlapMemberO("[CLACO].[PARENTH7].[AMSAINFORMATIC]","","Informática y Comuni","","000") -> Informática y Comuni | F22: =IFERROR(TRIM(LEFT(G22,FIND("-",G22)-1)),"") -> N100300500 | G22: N100300500 - Antucoya No Operacio | H22: =IFERROR(_xlfn.XLOOKUP(F22,'CECOS Corporativos'!$K:$K,'CECOS Corporativos'!$D:$D,""),"") -> 1003AD4505 | K22: =J22-I22 -> 0 | M22: 4681 | N22: =M22-L22 -> 4681 | Q22: =P22-O22 -> 0 | T22: =S22-R22 -> 0
A23: =_xll.EPMOlapMemberO("[CECO].[PARENTH3].[AMSA1003AD4509]","","AMSA1003AD4509 - AAPP Corporativo","","000") -> AMSA1003AD4509 - AAPP Corporativo | B23: =IFERROR(SUBSTITUTE(TRIM(LEFT(A23,FIND("-",A23)-1)),"AMSA",""),"") -> 1003AD4509 | C23: =IFERROR(_xlfn.XLOOKUP(B23,'CECOS Corporativos'!$D:$D,'CECOS Corporativos'!$E:$E,""),"") -> AAPP Corporativo | D23: =IFERROR(_xlfn.XLOOKUP(B23,'CECOS Corporativos'!$D:$D,'CECOS Corporativos'!$J:$J,""),"") -> VP Asuntos Corporativos | E23: =_xll.EPMOlapMemberO("[CLACO].[PARENTH7].[AMSAGGENERALES.2]","","Otros Gastos","","000") -> Otros Gastos | F23: =IFERROR(TRIM(LEFT(G23,FIND("-",G23)-1)),"") -> N100300500 | G23: N100300500 - Antucoya No Operacio | H23: =IFERROR(_xlfn.XLOOKUP(F23,'CECOS Corporativos'!$K:$K,'CECOS Corporativos'!$D:$D,""),"") -> 1003AD4505 | K23: =J23-I23 -> 0 | M23: 43383 | N23: =M23-L23 -> 43383 | Q23: =P23-O23 -> 0 | R23: 4819.5 | S23: 8611.28 | T23: =S23-R23 -> 3791.78
A24: =_xll.EPMOlapMemberO("[CECO].[PARENTH3].[AMSA1003AD4510]","","AMSA1003AD4510 - Comunicaciones Corpo","","000") -> AMSA1003AD4510 - Comunicaciones Corpo | B24: =IFERROR(SUBSTITUTE(TRIM(LEFT(A24,FIND("-",A24)-1)),"AMSA",""),"") -> 1003AD4510 | C24: =IFERROR(_xlfn.XLOOKUP(B24,'CECOS Corporativos'!$D:$D,'CECOS Corporativos'!$E:$E,""),"") -> Comunicaciones Corporativo | D24: =IFERROR(_xlfn.XLOOKUP(B24,'CECOS Corporativos'!$D:$D,'CECOS Corporativos'!$J:$J,""),"") -> VP Asuntos Corporativos | E24: =_xll.EPMOlapMemberO("[CLACO].[PARENTH7].[AMSAASESORIAS]","","Asesorías y Consulto","","000") -> Asesorías y Consulto | F24: =IFERROR(TRIM(LEFT(G24,FIND("-",G24)-1)),"") -> N100300500 | G24: N100300500 - Antucoya No Operacio | H24: =IFERROR(_xlfn.XLOOKUP(F24,'CECOS Corporativos'!$K:$K,'CECOS Corporativos'!$D:$D,""),"") -> 1003AD4505 | K24: =J24-I24 -> 0 | M24: 4736 | N24: =M24-L24 -> 4736 | O24: 16139.91 | P24: 8666 | Q24: =P24-O24 -> -7473.91 | R24: 917.75 | T24: =S24-R24 -> -917.75
A25: =_xll.EPMOlapMemberO("[CECO].[PARENTH3].[AMSA1003AD4510]","","AMSA1003AD4510 - Comunicaciones Corpo","","000") -> AMSA1003AD4510 - Comunicaciones Corpo | B25: =IFERROR(SUBSTITUTE(TRIM(LEFT(A25,FIND("-",A25)-1)),"AMSA",""),"") -> 1003AD4510 | C25: =IFERROR(_xlfn.XLOOKUP(B25,'CECOS Corporativos'!$D:$D,'CECOS Corporativos'!$E:$E,""),"") -> Comunicaciones Corporativo | D25: =IFERROR(_xlfn.XLOOKUP(B25,'CECOS Corporativos'!$D:$D,'CECOS Corporativos'!$J:$J,""),"") -> VP Asuntos Corporativos | E25: =_xll.EPMOlapMemberO("[CLACO].[PARENTH7].[AMSAINFORMATIC]","","Informática y Comuni","","000") -> Informática y Comuni | F25: =IFERROR(TRIM(LEFT(G25,FIND("-",G25)-1)),"") -> N100300500 | G25: N100300500 - Antucoya No Operacio | H25: =IFERROR(_xlfn.XLOOKUP(F25,'CECOS Corporativos'!$K:$K,'CECOS Corporativos'!$D:$D,""),"") -> 1003AD4505 | K25: =J25-I25 -> 0 | M25: 13713 | N25: =M25-L25 -> 13713 | P25: 8888 | Q25: =P25-O25 -> 8888 | R25: 2909.19 | S25: 19771.32 | T25: =S25-R25 -> 16862.13
A26: =_xll.EPMOlapMemberO("[CECO].[PARENTH3].[AMSA1003AD4510]","","AMSA1003AD4510 - Comunicaciones Corpo","","000") -> AMSA1003AD4510 - Comunicaciones Corpo | B26: =IFERROR(SUBSTITUTE(TRIM(LEFT(A26,FIND("-",A26)-1)),"AMSA",""),"") -> 1003AD4510 | C26: =IFERROR(_xlfn.XLOOKUP(B26,'CECOS Corporativos'!$D:$D,'CECOS Corporativos'!$E:$E,""),"") -> Comunicaciones Corporativo | D26: =IFERROR(_xlfn.XLOOKUP(B26,'CECOS Corporativos'!$D:$D,'CECOS Corporativos'!$J:$J,""),"") -> VP Asuntos Corporativos | E26: =_xll.EPMOlapMemberO("[CLACO].[PARENTH7].[AMSAGGENERALES.2]","","Otros Gastos","","000") -> Otros Gastos | F26: =IFERROR(TRIM(LEFT(G26,FIND("-",G26)-1)),"") -> N100300500 | G26: N100300500 - Antucoya No Operacio | H26: =IFERROR(_xlfn.XLOOKUP(F26,'CECOS Corporativos'!$K:$K,'CECOS Corporativos'!$D:$D,""),"") -> 1003AD4505 | K26: =J26-I26 -> 0 | M26: 22307 | N26: =M26-L26 -> 22307 | O26: 41968.58 | P26: 48594 | Q26: =P26-O26 -> 6625.42 | R26: 85781.4 | S26: 61736.33 | T26: =S26-R26 -> -24045.07
A27: =_xll.EPMOlapMemberO("[CECO].[PARENTH3].[AMSA1003AD4512]","","AMSA1003AD4512 - AAPP y RRII","","000") -> AMSA1003AD4512 - AAPP y RRII | B27: =IFERROR(SUBSTITUTE(TRIM(LEFT(A27,FIND("-",A27)-1)),"AMSA",""),"") -> 1003AD4512 | C27: =IFERROR(_xlfn.XLOOKUP(B27,'CECOS Corporativos'!$D:$D,'CECOS Corporativos'!$E:$E,""),"") -> AAPP y RRII | D27: =IFERROR(_xlfn.XLOOKUP(B27,'CECOS Corporativos'!$D:$D,'CECOS Corporativos'!$J:$J,""),"") -> VP Asuntos Corporativos | E27: =_xll.EPMOlapMemberO("[CLACO].[PARENTH7].[AMSAASESORIAS]","","Asesorías y Consulto","","000") -> Asesorías y Consulto | F27: =IFERROR(TRIM(LEFT(G27,FIND("-",G27)-1)),"") -> N100300500 | G27: N100300500 - Antucoya No Operacio | H27: =IFERROR(_xlfn.XLOOKUP(F27,'CECOS Corporativos'!$K:$K,'CECOS Corporativos'!$D:$D,""),"") -> 1003AD4505 | K27: =J27-I27 -> 0 | N27: =M27-L27 -> 0 | Q27: =P27-O27 -> 0 | R27: 20884.4 | T27: =S27-R27 -> -20884.4
A28: =_xll.EPMOlapMemberO("[CECO].[PARENTH3].[AMSA1003AD4512]","","AMSA1003AD4512 - AAPP y RRII","","000") -> AMSA1003AD4512 - AAPP y RRII | B28: =IFERROR(SUBSTITUTE(TRIM(LEFT(A28,FIND("-",A28)-1)),"AMSA",""),"") -> 1003AD4512 | C28: =IFERROR(_xlfn.XLOOKUP(B28,'CECOS Corporativos'!$D:$D,'CECOS Corporativos'!$E:$E,""),"") -> AAPP y RRII | D28: =IFERROR(_xlfn.XLOOKUP(B28,'CECOS Corporativos'!$D:$D,'CECOS Corporativos'!$J:$J,""),"") -> VP Asuntos Corporativos | E28: =_xll.EPMOlapMemberO("[CLACO].[PARENTH7].[AMSASERVICIOS]","","Servicios","","000") -> Servicios | F28: =IFERROR(TRIM(LEFT(G28,FIND("-",G28)-1)),"") -> N100300500 | G28: N100300500 - Antucoya No Operacio | H28: =IFERROR(_xlfn.XLOOKUP(F28,'CECOS Corporativos'!$K:$K,'CECOS Corporativos'!$D:$D,""),"") -> 1003AD4505 | K28: =J28-I28 -> 0 | M28: 34884 | N28: =M28-L28 -> 34884 | O28: 0 | P28: 40750 | Q28: =P28-O28 -> 40750 | R28: 2183.03 | S28: 6284.96 | T28: =S28-R28 -> 4101.93
A29: =_xll.EPMOlapMemberO("[CECO].[PARENTH3].[AMSA1003AD4512]","","AMSA1003AD4512 - AAPP y RRII","","000") -> AMSA1003AD4512 - AAPP y RRII | B29: =IFERROR(SUBSTITUTE(TRIM(LEFT(A29,FIND("-",A29)-1)),"AMSA",""),"") -> 1003AD4512 | C29: =IFERROR(_xlfn.XLOOKUP(B29,'CECOS Corporativos'!$D:$D,'CECOS Corporativos'!$E:$E,""),"") -> AAPP y RRII | D29: =IFERROR(_xlfn.XLOOKUP(B29,'CECOS Corporativos'!$D:$D,'CECOS Corporativos'!$J:$J,""),"") -> VP Asuntos Corporativos | E29: =_xll.EPMOlapMemberO("[CLACO].[PARENTH7].[AMSAINFORMATIC]","","Informática y Comuni","","000") -> Informática y Comuni | F29: =IFERROR(TRIM(LEFT(G29,FIND("-",G29)-1)),"") -> N100300500 | G29: N100300500 - Antucoya No Operacio | H29: =IFERROR(_xlfn.XLOOKUP(F29,'CECOS Corporativos'!$K:$K,'CECOS Corporativos'!$D:$D,""),"") -> 1003AD4505 | K29: =J29-I29 -> 0 | N29: =M29-L29 -> 0 | O29: 8067.77 | P29: 6060 | Q29: =P29-O29 -> -2007.77 | R29: 1827.2 | T29: =S29-R29 -> -1827.2
A30: =_xll.EPMOlapMemberO("[CECO].[PARENTH3].[AMSA1003AD4512]","","AMSA1003AD4512 - AAPP y RRII","","000") -> AMSA1003AD4512 - AAPP y RRII | B30: =IFERROR(SUBSTITUTE(TRIM(LEFT(A30,FIND("-",A30)-1)),"AMSA",""),"") -> 1003AD4512 | C30: =IFERROR(_xlfn.XLOOKUP(B30,'CECOS Corporativos'!$D:$D,'CECOS Corporativos'!$E:$E,""),"") -> AAPP y RRII | D30: =IFERROR(_xlfn.XLOOKUP(B30,'CECOS Corporativos'!$D:$D,'CECOS Corporativos'!$J:$J,""),"") -> VP Asuntos Corporativos | E30: =_xll.EPMOlapMemberO("[CLACO].[PARENTH7].[AMSAGGENERALES.2]","","Otros Gastos","","000") -> Otros Gastos | F30: =IFERROR(TRIM(LEFT(G30,FIND("-",G30)-1)),"") -> N100300500 | G30: N100300500 - Antucoya No Operacio | H30: =IFERROR(_xlfn.XLOOKUP(F30,'CECOS Corporativos'!$K:$K,'CECOS Corporativos'!$D:$D,""),"") -> 1003AD4505 | K30: =J30-I30 -> 0 | L30: 11763.98 | M30: 102191 | N30: =M30-L30 -> 90427.02 | O30: 100366.71 | P30: 48972 | Q30: =P30-O30 -> -51394.71 | R30: 30256.64 | S30: 26601.59 | T30: =S30-R30 -> -3655.05
A31: =_xll.EPMOlapMemberO("[CECO].[PARENTH3].[AMSA1003AD0503]","","AMSA1003AD0503 - Corporativo","","000") -> AMSA1003AD0503 - Corporativo | B31: =IFERROR(SUBSTITUTE(TRIM(LEFT(A31,FIND("-",A31)-1)),"AMSA",""),"") -> 1003AD0503 | C31: =IFERROR(_xlfn.XLOOKUP(B31,'CECOS Corporativos'!$D:$D,'CECOS Corporativos'!$E:$E,""),"") -> Auditoría (HH Corporativo) | D31: =IFERROR(_xlfn.XLOOKUP(B31,'CECOS Corporativos'!$D:$D,'CECOS Corporativos'!$J:$J,""),"") -> Auditoría (HH Corporativo) | E31: =_xll.EPMOlapMemberO("[CLACO].[PARENTH7].[AMSAASESORIAS]","","Asesorías y Consulto","","000") -> Asesorías y Consulto | F31: =IFERROR(TRIM(LEFT(G31,FIND("-",G31)-1)),"") -> N1003AD050 | G31: N1003AD050 - Gerencia General | H31: =IFERROR(_xlfn.XLOOKUP(F31,'CECOS Corporativos'!$K:$K,'CECOS Corporativos'!$D:$D,""),"") -> 1003AD0508 | I31: -13231.9 | K31: =J31-I31 -> 13231.9 | N31: =M31-L31 -> 0 | Q31: =P31-O31 -> 0 | T31: =S31-R31 -> 0
A32: =_xll.EPMOlapMemberO("[CECO].[PARENTH3].[AMSA1003AD0503]","","AMSA1003AD0503 - Corporativo","","000") -> AMSA1003AD0503 - Corporativo | B32: =IFERROR(SUBSTITUTE(TRIM(LEFT(A32,FIND("-",A32)-1)),"AMSA",""),"") -> 1003AD0503 | C32: =IFERROR(_xlfn.XLOOKUP(B32,'CECOS Corporativos'!$D:$D,'CECOS Corporativos'!$E:$E,""),"") -> Auditoría (HH Corporativo) | D32: =IFERROR(_xlfn.XLOOKUP(B32,'CECOS Corporativos'!$D:$D,'CECOS Corporativos'!$J:$J,""),"") -> Auditoría (HH Corporativo) | E32: =_xll.EPMOlapMemberO("[CLACO].[PARENTH7].[AMSASERMANTO.REPA]","","Servicios Mantenimie","","000") -> Servicios Mantenimie | F32: =IFERROR(TRIM(LEFT(G32,FIND("-",G32)-1)),"") -> N1003AD050 | G32: N1003AD050 - Gerencia General | H32: =IFERROR(_xlfn.XLOOKUP(F32,'CECOS Corporativos'!$K:$K,'CECOS Corporativos'!$D:$D,""),"") -> 1003AD0508 | K32: =J32-I32 -> 0 | N32: =M32-L32 -> 0 | Q32: =P32-O32 -> 0 | R32: 16.97 | T32: =S32-R32 -> -16.97
A33: =_xll.EPMOlapMemberO("[CECO].[PARENTH3].[AMSA1003AD0503]","","AMSA1003AD0503 - Corporativo","","000") -> AMSA1003AD0503 - Corporativo | B33: =IFERROR(SUBSTITUTE(TRIM(LEFT(A33,FIND("-",A33)-1)),"AMSA",""),"") -> 1003AD0503 | C33: =IFERROR(_xlfn.XLOOKUP(B33,'CECOS Corporativos'!$D:$D,'CECOS Corporativos'!$E:$E,""),"") -> Auditoría (HH Corporativo) | D33: =IFERROR(_xlfn.XLOOKUP(B33,'CECOS Corporativos'!$D:$D,'CECOS Corporativos'!$J:$J,""),"") -> Auditoría (HH Corporativo) | E33: =_xll.EPMOlapMemberO("[CLACO].[PARENTH7].[AMSAG_VIAJES]","","Gastos de Viajes","","000") -> Gastos de Viajes | F33: =IFERROR(TRIM(LEFT(G33,FIND("-",G33)-1)),"") -> N1003AD050 | G33: N1003AD050 - Gerencia General | H33: =IFERROR(_xlfn.XLOOKUP(F33,'CECOS Corporativos'!$K:$K,'CECOS Corporativos'!$D:$D,""),"") -> 1003AD0508 | I33: 0 | K33: =J33-I33 -> 0 | N33: =M33-L33 -> 0 | Q33: =P33-O33 -> 0 | T33: =S33-R33 -> 0
A34: =_xll.EPMOlapMemberO("[CECO].[PARENTH3].[AMSA1003AD0503]","","AMSA1003AD0503 - Corporativo","","000") -> AMSA1003AD0503 - Corporativo | B34: =IFERROR(SUBSTITUTE(TRIM(LEFT(A34,FIND("-",A34)-1)),"AMSA",""),"") -> 1003AD0503 | C34: =IFERROR(_xlfn.XLOOKUP(B34,'CECOS Corporativos'!$D:$D,'CECOS Corporativos'!$E:$E,""),"") -> Auditoría (HH Corporativo) | D34: =IFERROR(_xlfn.XLOOKUP(B34,'CECOS Corporativos'!$D:$D,'CECOS Corporativos'!$J:$J,""),"") -> Auditoría (HH Corporativo) | E34: =_xll.EPMOlapMemberO("[CLACO].[PARENTH7].[AMSASERV_CORP]","","Servicios Corporativ","","000") -> Servicios Corporativ | F34: =IFERROR(TRIM(LEFT(G34,FIND("-",G34)-1)),"") -> N1003AD050 | G34: N1003AD050 - Gerencia General | H34: =IFERROR(_xlfn.XLOOKUP(F34,'CECOS Corporativos'!$K:$K,'CECOS Corporativos'!$D:$D,""),"") -> 1003AD0508 | I34: 385777.39 | J34: 397697 | K34: =J34-I34 -> 11919.61 | L34: 457194.15 | M34: 416198 | N34: =M34-L34 -> -40996.15 | O34: 185195.85 | P34: 184267 | Q34: =P34-O34 -> -928.85 | R34: 223942 | S34: 235062.76 | T34: =S34-R34 -> 11120.76
A35: =_xll.EPMOlapMemberO("[CECO].[PARENTH3].[AMSA1003AD0504]","","AMSA1003AD0504 - Desarrollo Corp","","000") -> AMSA1003AD0504 - Desarrollo Corp | B35: =IFERROR(SUBSTITUTE(TRIM(LEFT(A35,FIND("-",A35)-1)),"AMSA",""),"") -> 1003AD0504 | C35: =IFERROR(_xlfn.XLOOKUP(B35,'CECOS Corporativos'!$D:$D,'CECOS Corporativos'!$E:$E,""),"") -> VP Desarrollo | D35: =IFERROR(_xlfn.XLOOKUP(B35,'CECOS Corporativos'!$D:$D,'CECOS Corporativos'!$J:$J,""),"") -> VP Desarrollo | E35: =_xll.EPMOlapMemberO("[CLACO].[PARENTH7].[AMSAASESORIAS]","","Asesorías y Consulto","","000") -> Asesorías y Consulto | F35: =IFERROR(TRIM(LEFT(G35,FIND("-",G35)-1)),"") -> N1003AD050 | G35: N1003AD050 - Gerencia General | H35: =IFERROR(_xlfn.XLOOKUP(F35,'CECOS Corporativos'!$K:$K,'CECOS Corporativos'!$D:$D,""),"") -> 1003AD0508 | I35: 52498.85 | K35: =J35-I35 -> -52498.85 | L35: 67660.5 | M35: 40784 | N35: =M35-L35 -> -26876.5 | O35: -3302.73 | Q35: =P35-O35 -> 3302.73 | T35: =S35-R35 -> 0
A36: =_xll.EPMOlapMemberO("[CECO].[PARENTH3].[AMSA1003AD0504]","","AMSA1003AD0504 - Desarrollo Corp","","000") -> AMSA1003AD0504 - Desarrollo Corp | B36: =IFERROR(SUBSTITUTE(TRIM(LEFT(A36,FIND("-",A36)-1)),"AMSA",""),"") -> 1003AD0504 | C36: =IFERROR(_xlfn.XLOOKUP(B36,'CECOS Corporativos'!$D:$D,'CECOS Corporativos'!$E:$E,""),"") -> VP Desarrollo | D36: =IFERROR(_xlfn.XLOOKUP(B36,'CECOS Corporativos'!$D:$D,'CECOS Corporativos'!$J:$J,""),"") -> VP Desarrollo | E36: =_xll.EPMOlapMemberO("[CLACO].[PARENTH7].[AMSASERVICIOS]","","Servicios","","000") -> Servicios | F36: =IFERROR(TRIM(LEFT(G36,FIND("-",G36)-1)),"") -> N1003AD050 | G36: N1003AD050 - Gerencia General | H36: =IFERROR(_xlfn.XLOOKUP(F36,'CECOS Corporativos'!$K:$K,'CECOS Corporativos'!$D:$D,""),"") -> 1003AD0508 | K36: =J36-I36 -> 0 | L36: 178.41 | N36: =M36-L36 -> -178.41 | Q36: =P36-O36 -> 0 | R36: -38500 | T36: =S36-R36 -> 38500
A37: =_xll.EPMOlapMemberO("[CECO].[PARENTH3].[AMSA1003AD0504]","","AMSA1003AD0504 - Desarrollo Corp","","000") -> AMSA1003AD0504 - Desarrollo Corp | B37: =IFERROR(SUBSTITUTE(TRIM(LEFT(A37,FIND("-",A37)-1)),"AMSA",""),"") -> 1003AD0504 | C37: =IFERROR(_xlfn.XLOOKUP(B37,'CECOS Corporativos'!$D:$D,'CECOS Corporativos'!$E:$E,""),"") -> VP Desarrollo | D37: =IFERROR(_xlfn.XLOOKUP(B37,'CECOS Corporativos'!$D:$D,'CECOS Corporativos'!$J:$J,""),"") -> VP Desarrollo | E37: =_xll.EPMOlapMemberO("[CLACO].[PARENTH7].[AMSASERMANTO.REPA]","","Servicios Mantenimie","","000") -> Servicios Mantenimie | F37: =IFERROR(TRIM(LEFT(G37,FIND("-",G37)-1)),"") -> N1003AD050 | G37: N1003AD050 - Gerencia General | H37: =IFERROR(_xlfn.XLOOKUP(F37,'CECOS Corporativos'!$K:$K,'CECOS Corporativos'!$D:$D,""),"") -> 1003AD0508 | K37: =J37-I37 -> 0 | N37: =M37-L37 -> 0 | Q37: =P37-O37 -> 0 | R37: 2211.36 | T37: =S37-R37 -> -2211.36
A38: =_xll.EPMOlapMemberO("[CECO].[PARENTH3].[AMSA1003AD0504]","","AMSA1003AD0504 - Desarrollo Corp","","000") -> AMSA1003AD0504 - Desarrollo Corp | B38: =IFERROR(SUBSTITUTE(TRIM(LEFT(A38,FIND("-",A38)-1)),"AMSA",""),"") -> 1003AD0504 | C38: =IFERROR(_xlfn.XLOOKUP(B38,'CECOS Corporativos'!$D:$D,'CECOS Corporativos'!$E:$E,""),"") -> VP Desarrollo | D38: =IFERROR(_xlfn.XLOOKUP(B38,'CECOS Corporativos'!$D:$D,'CECOS Corporativos'!$J:$J,""),"") -> VP Desarrollo | E38: =_xll.EPMOlapMemberO("[CLACO].[PARENTH7].[AMSAINFORMATIC]","","Informática y Comuni","","000") -> Informática y Comuni | F38: =IFERROR(TRIM(LEFT(G38,FIND("-",G38)-1)),"") -> N1003AD050 | G38: N1003AD050 - Gerencia General | H38: =IFERROR(_xlfn.XLOOKUP(F38,'CECOS Corporativos'!$K:$K,'CECOS Corporativos'!$D:$D,""),"") -> 1003AD0508 | K38: =J38-I38 -> 0 | N38: =M38-L38 -> 0 | O38: 7733.47 | Q38: =P38-O38 -> -7733.47 | R38: 12358.67 | S38: 12523.96 | T38: =S38-R38 -> 165.29
A39: =_xll.EPMOlapMemberO("[CECO].[PARENTH3].[AMSA1003AD0504]","","AMSA1003AD0504 - Desarrollo Corp","","000") -> AMSA1003AD0504 - Desarrollo Corp | B39: =IFERROR(SUBSTITUTE(TRIM(LEFT(A39,FIND("-",A39)-1)),"AMSA",""),"") -> 1003AD0504 | C39: =IFERROR(_xlfn.XLOOKUP(B39,'CECOS Corporativos'!$D:$D,'CECOS Corporativos'!$E:$E,""),"") -> VP Desarrollo | D39: =IFERROR(_xlfn.XLOOKUP(B39,'CECOS Corporativos'!$D:$D,'CECOS Corporativos'!$J:$J,""),"") -> VP Desarrollo | E39: =_xll.EPMOlapMemberO("[CLACO].[PARENTH7].[AMSAG_VIAJES]","","Gastos de Viajes","","000") -> Gastos de Viajes | F39: =IFERROR(TRIM(LEFT(G39,FIND("-",G39)-1)),"") -> N1003AD050 | G39: N1003AD050 - Gerencia General | H39: =IFERROR(_xlfn.XLOOKUP(F39,'CECOS Corporativos'!$K:$K,'CECOS Corporativos'!$D:$D,""),"") -> 1003AD0508 | J39: 11222.19 | K39: =J39-I39 -> 11222.19 | L39: 1116 | M39: 14439.57 | N39: =M39-L39 -> 13323.57 | O39: 816.36 | P39: 14694 | Q39: =P39-O39 -> 13877.64 | R39: 248.5 | S39: 8893.45 | T39: =S39-R39 -> 8644.95
A40: =_xll.EPMOlapMemberO("[CECO].[PARENTH3].[AMSA1003AD0504]","","AMSA1003AD0504 - Desarrollo Corp","","000") -> AMSA1003AD0504 - Desarrollo Corp | B40: =IFERROR(SUBSTITUTE(TRIM(LEFT(A40,FIND("-",A40)-1)),"AMSA",""),"") -> 1003AD0504 | C40: =IFERROR(_xlfn.XLOOKUP(B40,'CECOS Corporativos'!$D:$D,'CECOS Corporativos'!$E:$E,""),"") -> VP Desarrollo | D40: =IFERROR(_xlfn.XLOOKUP(B40,'CECOS Corporativos'!$D:$D,'CECOS Corporativos'!$J:$J,""),"") -> VP Desarrollo | E40: =_xll.EPMOlapMemberO("[CLACO].[PARENTH7].[AMSASERV_CORP]","","Servicios Corporativ","","000") -> Servicios Corporativ | F40: =IFERROR(TRIM(LEFT(G40,FIND("-",G40)-1)),"") -> N1003AD050 | G40: N1003AD050 - Gerencia General | H40: =IFERROR(_xlfn.XLOOKUP(F40,'CECOS Corporativos'!$K:$K,'CECOS Corporativos'!$D:$D,""),"") -> 1003AD0508 | K40: =J40-I40 -> 0 | N40: =M40-L40 -> 0 | O40: 0 | P40: 196128 | Q40: =P40-O40 -> 196128 | R40: 352306 | S40: 369803.1 | T40: =S40-R40 -> 17497.1
A41: =_xll.EPMOlapMemberO("[CECO].[PARENTH3].[AMSA1003AD0505]","","AMSA1003AD0505 - Estrateg e Inn Corp","","000") -> AMSA1003AD0505 - Estrateg e Inn Corp | B41: =IFERROR(SUBSTITUTE(TRIM(LEFT(A41,FIND("-",A41)-1)),"AMSA",""),"") -> 1003AD0505 | C41: =IFERROR(_xlfn.XLOOKUP(B41,'CECOS Corporativos'!$D:$D,'CECOS Corporativos'!$E:$E,""),"") -> Estrategia e Innovación Corp | D41: =IFERROR(_xlfn.XLOOKUP(B41,'CECOS Corporativos'!$D:$D,'CECOS Corporativos'!$J:$J,""),"") -> VP Estrategia e Innovación | E41: =_xll.EPMOlapMemberO("[CLACO].[PARENTH7].[AMSAASESORIAS]","","Asesorías y Consulto","","000") -> Asesorías y Consulto | F41: =IFERROR(TRIM(LEFT(G41,FIND("-",G41)-1)),"") -> N1003AD050 | G41: N1003AD050 - Gerencia General | H41: =IFERROR(_xlfn.XLOOKUP(F41,'CECOS Corporativos'!$K:$K,'CECOS Corporativos'!$D:$D,""),"") -> 1003AD0508 | I41: 59124.74 | J41: 117472 | K41: =J41-I41 -> 58347.26 | L41: 39542.77 | M41: 132551 | N41: =M41-L41 -> 93008.23 | O41: -10.68 | Q41: =P41-O41 -> 10.68 | T41: =S41-R41 -> 0
A42: =_xll.EPMOlapMemberO("[CECO].[PARENTH3].[AMSA1003AD0505]","","AMSA1003AD0505 - Estrateg e Inn Corp","","000") -> AMSA1003AD0505 - Estrateg e Inn Corp | B42: =IFERROR(SUBSTITUTE(TRIM(LEFT(A42,FIND("-",A42)-1)),"AMSA",""),"") -> 1003AD0505 | C42: =IFERROR(_xlfn.XLOOKUP(B42,'CECOS Corporativos'!$D:$D,'CECOS Corporativos'!$E:$E,""),"") -> Estrategia e Innovación Corp | D42: =IFERROR(_xlfn.XLOOKUP(B42,'CECOS Corporativos'!$D:$D,'CECOS Corporativos'!$J:$J,""),"") -> VP Estrategia e Innovación | E42: =_xll.EPMOlapMemberO("[CLACO].[PARENTH7].[AMSASERVICIOS]","","Servicios","","000") -> Servicios | F42: =IFERROR(TRIM(LEFT(G42,FIND("-",G42)-1)),"") -> N1003AD050 | G42: N1003AD050 - Gerencia General | H42: =IFERROR(_xlfn.XLOOKUP(F42,'CECOS Corporativos'!$K:$K,'CECOS Corporativos'!$D:$D,""),"") -> 1003AD0508 | K42: =J42-I42 -> 0 | L42: 99482 | M42: 92157 | N42: =M42-L42 -> -7325 | O42: 40090 | P42: 79595 | Q42: =P42-O42 -> 39505 | R42: 73987.92 | S42: 61819.31 | T42: =S42-R42 -> -12168.61
A43: =_xll.EPMOlapMemberO("[CECO].[PARENTH3].[AMSA1003AD0505]","","AMSA1003AD0505 - Estrateg e Inn Corp","","000") -> AMSA1003AD0505 - Estrateg e Inn Corp | B43: =IFERROR(SUBSTITUTE(TRIM(LEFT(A43,FIND("-",A43)-1)),"AMSA",""),"") -> 1003AD0505 | C43: =IFERROR(_xlfn.XLOOKUP(B43,'CECOS Corporativos'!$D:$D,'CECOS Corporativos'!$E:$E,""),"") -> Estrategia e Innovación Corp | D43: =IFERROR(_xlfn.XLOOKUP(B43,'CECOS Corporativos'!$D:$D,'CECOS Corporativos'!$J:$J,""),"") -> VP Estrategia e Innovación | E43: =_xll.EPMOlapMemberO("[CLACO].[PARENTH7].[AMSAINFORMATIC]","","Informática y Comuni","","000") -> Informática y Comuni | F43: =IFERROR(TRIM(LEFT(G43,FIND("-",G43)-1)),"") -> N1003AD050 | G43: N1003AD050 - Gerencia General | H43: =IFERROR(_xlfn.XLOOKUP(F43,'CECOS Corporativos'!$K:$K,'CECOS Corporativos'!$D:$D,""),"") -> 1003AD0508 | K43: =J43-I43 -> 0 | L43: 206740.22 | M43: 186223 | N43: =M43-L43 -> -20517.22 | O43: 218153.77 | P43: 245637 | Q43: =P43-O43 -> 27483.23 | R43: 454956.39 | S43: 460933.75 | T43: =S43-R43 -> 5977.36
A44: =_xll.EPMOlapMemberO("[CECO].[PARENTH3].[AMSA1003AD0505]","","AMSA1003AD0505 - Estrateg e Inn Corp","","000") -> AMSA1003AD0505 - Estrateg e Inn Corp | B44: =IFERROR(SUBSTITUTE(TRIM(LEFT(A44,FIND("-",A44)-1)),"AMSA",""),"") -> 1003AD0505 | C44: =IFERROR(_xlfn.XLOOKUP(B44,'CECOS Corporativos'!$D:$D,'CECOS Corporativos'!$E:$E,""),"") -> Estrategia e Innovación Corp | D44: =IFERROR(_xlfn.XLOOKUP(B44,'CECOS Corporativos'!$D:$D,'CECOS Corporativos'!$J:$J,""),"") -> VP Estrategia e Innovación | E44: =_xll.EPMOlapMemberO("[CLACO].[PARENTH7].[AMSAG_VIAJES]","","Gastos de Viajes","","000") -> Gastos de Viajes | F44: =IFERROR(TRIM(LEFT(G44,FIND("-",G44)-1)),"") -> N1003AD050 | G44: N1003AD050 - Gerencia General | H44: =IFERROR(_xlfn.XLOOKUP(F44,'CECOS Corporativos'!$K:$K,'CECOS Corporativos'!$D:$D,""),"") -> 1003AD0508 | K44: =J44-I44 -> 0 | N44: =M44-L44 -> 0 | Q44: =P44-O44 -> 0 | R44: 1495.67 | T44: =S44-R44 -> -1495.67
A45: =_xll.EPMOlapMemberO("[CECO].[PARENTH3].[AMSA1003AD0505]","","AMSA1003AD0505 - Estrateg e Inn Corp","","000") -> AMSA1003AD0505 - Estrateg e Inn Corp | B45: =IFERROR(SUBSTITUTE(TRIM(LEFT(A45,FIND("-",A45)-1)),"AMSA",""),"") -> 1003AD0505 | C45: =IFERROR(_xlfn.XLOOKUP(B45,'CECOS Corporativos'!$D:$D,'CECOS Corporativos'!$E:$E,""),"") -> Estrategia e Innovación Corp | D45: =IFERROR(_xlfn.XLOOKUP(B45,'CECOS Corporativos'!$D:$D,'CECOS Corporativos'!$J:$J,""),"") -> VP Estrategia e Innovación | E45: =_xll.EPMOlapMemberO("[CLACO].[PARENTH7].[AMSAGGENERALES.2]","","Otros Gastos","","000") -> Otros Gastos | F45: =IFERROR(TRIM(LEFT(G45,FIND("-",G45)-1)),"") -> N1003AD050 | G45: N1003AD050 - Gerencia General | H45: =IFERROR(_xlfn.XLOOKUP(F45,'CECOS Corporativos'!$K:$K,'CECOS Corporativos'!$D:$D,""),"") -> 1003AD0508 | K45: =J45-I45 -> 0 | L45: 11228.29 | N45: =M45-L45 -> -11228.29 | O45: 0 | Q45: =P45-O45 -> 0 | T45: =S45-R45 -> 0
A46: =_xll.EPMOlapMemberO("[CECO].[PARENTH3].[AMSA1003AD0505]","","AMSA1003AD0505 - Estrateg e Inn Corp","","000") -> AMSA1003AD0505 - Estrateg e Inn Corp | B46: =IFERROR(SUBSTITUTE(TRIM(LEFT(A46,FIND("-",A46)-1)),"AMSA",""),"") -> 1003AD0505 | C46: =IFERROR(_xlfn.XLOOKUP(B46,'CECOS Corporativos'!$D:$D,'CECOS Corporativos'!$E:$E,""),"") -> Estrategia e Innovación Corp | D46: =IFERROR(_xlfn.XLOOKUP(B46,'CECOS Corporativos'!$D:$D,'CECOS Corporativos'!$J:$J,""),"") -> VP Estrategia e Innovación | E46: =_xll.EPMOlapMemberO("[CLACO].[PARENTH7].[AMSASERV_CORP]","","Servicios Corporativ","","000") -> Servicios Corporativ | F46: =IFERROR(TRIM(LEFT(G46,FIND("-",G46)-1)),"") -> N1003AD050 | G46: N1003AD050 - Gerencia General | H46: =IFERROR(_xlfn.XLOOKUP(F46,'CECOS Corporativos'!$K:$K,'CECOS Corporativos'!$D:$D,""),"") -> 1003AD0508 | I46: 40205 | J46: 41449 | K46: =J46-I46 -> 1244 | L46: 111045.23 | M46: 99613 | N46: =M46-L46 -> -11432.23 | O46: 642163.77 | P46: 711536 | Q46: =P46-O46 -> 69372.23 | R46: 666099 | S46: 699176.36 | T46: =S46-R46 -> 33077.36
A47: =_xll.EPMOlapMemberO("[CECO].[PARENTH3].[AMSA1003AD0506]","","AMSA1003AD0506 - Operaciones Corp","","000") -> AMSA1003AD0506 - Operaciones Corp | B47: =IFERROR(SUBSTITUTE(TRIM(LEFT(A47,FIND("-",A47)-1)),"AMSA",""),"") -> 1003AD0506 | C47: =IFERROR(_xlfn.XLOOKUP(B47,'CECOS Corporativos'!$D:$D,'CECOS Corporativos'!$E:$E,""),"") -> Operaciones Corp (Distribuibles) | D47: =IFERROR(_xlfn.XLOOKUP(B47,'CECOS Corporativos'!$D:$D,'CECOS Corporativos'!$J:$J,""),"") -> VP Planificación y Servicios Técnicos | E47: =_xll.EPMOlapMemberO("[CLACO].[PARENTH7].[AMSAENTRENAMI]","","Entrenamiento","","000") -> Entrenamiento | F47: =IFERROR(TRIM(LEFT(G47,FIND("-",G47)-1)),"") -> N1003AD050 | G47: N1003AD050 - Gerencia General | H47: =IFERROR(_xlfn.XLOOKUP(F47,'CECOS Corporativos'!$K:$K,'CECOS Corporativos'!$D:$D,""),"") -> 1003AD0508 | I47: 33500 | K47: =J47-I47 -> -33500 | N47: =M47-L47 -> 0 | O47: 98114 | P47: 28125 | Q47: =P47-O47 -> -69989 | R47: 86319.24 | T47: =S47-R47 -> -86319.24
A48: =_xll.EPMOlapMemberO("[CECO].[PARENTH3].[AMSA1003AD0506]","","AMSA1003AD0506 - Operaciones Corp","","000") -> AMSA1003AD0506 - Operaciones Corp | B48: =IFERROR(SUBSTITUTE(TRIM(LEFT(A48,FIND("-",A48)-1)),"AMSA",""),"") -> 1003AD0506 | C48: =IFERROR(_xlfn.XLOOKUP(B48,'CECOS Corporativos'!$D:$D,'CECOS Corporativos'!$E:$E,""),"") -> Operaciones Corp (Distribuibles) | D48: =IFERROR(_xlfn.XLOOKUP(B48,'CECOS Corporativos'!$D:$D,'CECOS Corporativos'!$J:$J,""),"") -> VP Planificación y Servicios Técnicos | E48: =_xll.EPMOlapMemberO("[CLACO].[PARENTH7].[AMSAASESORIAS]","","Asesorías y Consulto","","000") -> Asesorías y Consulto | F48: =IFERROR(TRIM(LEFT(G48,FIND("-",G48)-1)),"") -> N1003AD050 | G48: N1003AD050 - Gerencia General | H48: =IFERROR(_xlfn.XLOOKUP(F48,'CECOS Corporativos'!$K:$K,'CECOS Corporativos'!$D:$D,""),"") -> 1003AD0508 | I48: 320169.5 | J48: 223816 | K48: =J48-I48 -> -96353.5 | L48: 178198.98 | M48: 220967 | N48: =M48-L48 -> 42768.02 | O48: 9582.22 | P48: 118500 | Q48: =P48-O48 -> 108917.78 | R48: 49330.97 | S48: 90000.97 | T48: =S48-R48 -> 40670
A49: =_xll.EPMOlapMemberO("[CECO].[PARENTH3].[AMSA1003AD0506]","","AMSA1003AD0506 - Operaciones Corp","","000") -> AMSA1003AD0506 - Operaciones Corp | B49: =IFERROR(SUBSTITUTE(TRIM(LEFT(A49,FIND("-",A49)-1)),"AMSA",""),"") -> 1003AD0506 | C49: =IFERROR(_xlfn.XLOOKUP(B49,'CECOS Corporativos'!$D:$D,'CECOS Corporativos'!$E:$E,""),"") -> Operaciones Corp (Distribuibles) | D49: =IFERROR(_xlfn.XLOOKUP(B49,'CECOS Corporativos'!$D:$D,'CECOS Corporativos'!$J:$J,""),"") -> VP Planificación y Servicios Técnicos | E49: =_xll.EPMOlapMemberO("[CLACO].[PARENTH7].[AMSASERVICIOS]","","Servicios","","000") -> Servicios | F49: =IFERROR(TRIM(LEFT(G49,FIND("-",G49)-1)),"") -> N1003AD050 | G49: N1003AD050 - Gerencia General | H49: =IFERROR(_xlfn.XLOOKUP(F49,'CECOS Corporativos'!$K:$K,'CECOS Corporativos'!$D:$D,""),"") -> 1003AD0508 | K49: =J49-I49 -> 0 | N49: =M49-L49 -> 0 | O49: 44854.26 | P49: 101978 | Q49: =P49-O49 -> 57123.74 | R49: 230372.12 | S49: 283661.01 | T49: =S49-R49 -> 53288.89
A50: =_xll.EPMOlapMemberO("[CECO].[PARENTH3].[AMSA1003AD0506]","","AMSA1003AD0506 - Operaciones Corp","","000") -> AMSA1003AD0506 - Operaciones Corp | B50: =IFERROR(SUBSTITUTE(TRIM(LEFT(A50,FIND("-",A50)-1)),"AMSA",""),"") -> 1003AD0506 | C50: =IFERROR(_xlfn.XLOOKUP(B50,'CECOS Corporativos'!$D:$D,'CECOS Corporativos'!$E:$E,""),"") -> Operaciones Corp (Distribuibles) | D50: =IFERROR(_xlfn.XLOOKUP(B50,'CECOS Corporativos'!$D:$D,'CECOS Corporativos'!$J:$J,""),"") -> VP Planificación y Servicios Técnicos | E50: =_xll.EPMOlapMemberO("[CLACO].[PARENTH7].[AMSAINFORMATIC]","","Informática y Comuni","","000") -> Informática y Comuni | F50: =IFERROR(TRIM(LEFT(G50,FIND("-",G50)-1)),"") -> N1003AD050 | G50: N1003AD050 - Gerencia General | H50: =IFERROR(_xlfn.XLOOKUP(F50,'CECOS Corporativos'!$K:$K,'CECOS Corporativos'!$D:$D,""),"") -> 1003AD0508 | I50: 11281.29 | J50: 16043 | K50: =J50-I50 -> 4761.71 | L50: 28156.58 | N50: =M50-L50 -> -28156.58 | O50: 36905.09 | Q50: =P50-O50 -> -36905.09 | R50: 34580.06 | T50: =S50-R50 -> -34580.06
A51: =_xll.EPMOlapMemberO("[CECO].[PARENTH3].[AMSA1003AD0506]","","AMSA1003AD0506 - Operaciones Corp","","000") -> AMSA1003AD0506 - Operaciones Corp | B51: =IFERROR(SUBSTITUTE(TRIM(LEFT(A51,FIND("-",A51)-1)),"AMSA",""),"") -> 1003AD0506 | C51: =IFERROR(_xlfn.XLOOKUP(B51,'CECOS Corporativos'!$D:$D,'CECOS Corporativos'!$E:$E,""),"") -> Operaciones Corp (Distribuibles) | D51: =IFERROR(_xlfn.XLOOKUP(B51,'CECOS Corporativos'!$D:$D,'CECOS Corporativos'!$J:$J,""),"") -> VP Planificación y Servicios Técnicos | E51: =_xll.EPMOlapMemberO("[CLACO].[PARENTH7].[AMSAGGENERALES.2]","","Otros Gastos","","000") -> Otros Gastos | F51: =IFERROR(TRIM(LEFT(G51,FIND("-",G51)-1)),"") -> N1003AD050 | G51: N1003AD050 - Gerencia General | H51: =IFERROR(_xlfn.XLOOKUP(F51,'CECOS Corporativos'!$K:$K,'CECOS Corporativos'!$D:$D,""),"") -> 1003AD0508 | K51: =J51-I51 -> 0 | N51: =M51-L51 -> 0 | Q51: =P51-O51 -> 0 | R51: 4809.88 | T51: =S51-R51 -> -4809.88
A52: =_xll.EPMOlapMemberO("[CECO].[PARENTH3].[AMSA1003AD0506]","","AMSA1003AD0506 - Operaciones Corp","","000") -> AMSA1003AD0506 - Operaciones Corp | B52: =IFERROR(SUBSTITUTE(TRIM(LEFT(A52,FIND("-",A52)-1)),"AMSA",""),"") -> 1003AD0506 | C52: =IFERROR(_xlfn.XLOOKUP(B52,'CECOS Corporativos'!$D:$D,'CECOS Corporativos'!$E:$E,""),"") -> Operaciones Corp (Distribuibles) | D52: =IFERROR(_xlfn.XLOOKUP(B52,'CECOS Corporativos'!$D:$D,'CECOS Corporativos'!$J:$J,""),"") -> VP Planificación y Servicios Técnicos | E52: =_xll.EPMOlapMemberO("[CLACO].[PARENTH7].[AMSASERV_CORP]","","Servicios Corporativ","","000") -> Servicios Corporativ | F52: =IFERROR(TRIM(LEFT(G52,FIND("-",G52)-1)),"") -> N1003AD050 | G52: N1003AD050 - Gerencia General | H52: =IFERROR(_xlfn.XLOOKUP(F52,'CECOS Corporativos'!$K:$K,'CECOS Corporativos'!$D:$D,""),"") -> 1003AD0508 | K52: =J52-I52 -> 0 | N52: =M52-L52 -> 0 | O52: 841858.32 | P52: 932804 | Q52: =P52-O52 -> 90945.68 | R52: 913518 | S52: 958884.43 | T52: =S52-R52 -> 45366.43
A53: =_xll.EPMOlapMemberO("[CECO].[PARENTH3].[AMSA1003AD0508]","","AMSA1003AD0508 - Finanzas Corporativo","","000") -> AMSA1003AD0508 - Finanzas Corporativo | B53: =IFERROR(SUBSTITUTE(TRIM(LEFT(A53,FIND("-",A53)-1)),"AMSA",""),"") -> 1003AD0508 | C53: =IFERROR(_xlfn.XLOOKUP(B53,'CECOS Corporativos'!$D:$D,'CECOS Corporativos'!$E:$E,""),"") -> Finanzas Corporativo (HH Corporativo) | D53: =IFERROR(_xlfn.XLOOKUP(B53,'CECOS Corporativos'!$D:$D,'CECOS Corporativos'!$J:$J,""),"") -> VP Finanzas | E53: =_xll.EPMOlapMemberO("[CLACO].[PARENTH7].[AMSASERV_CORP]","","Servicios Corporativ","","000") -> Servicios Corporativ | F53: =IFERROR(TRIM(LEFT(G53,FIND("-",G53)-1)),"") -> N1003AD050 | G53: N1003AD050 - Gerencia General | H53: =IFERROR(_xlfn.XLOOKUP(F53,'CECOS Corporativos'!$K:$K,'CECOS Corporativos'!$D:$D,""),"") -> 1003AD0508 | K53: =J53-I53 -> 0 | N53: =M53-L53 -> 0 | O53: 2313464 | P53: 2563388 | Q53: =P53-O53 -> 249924 | R53: 2343174 | S53: 2459527.5 | T53: =S53-R53 -> 116353.51
A54: =_xll.EPMOlapMemberO("[CECO].[PARENTH3].[AMSA1003AD0509]","","AMSA1003AD0509 - Legal Corporativo","","000") -> AMSA1003AD0509 - Legal Corporativo | B54: =IFERROR(SUBSTITUTE(TRIM(LEFT(A54,FIND("-",A54)-1)),"AMSA",""),"") -> 1003AD0509 | C54: =IFERROR(_xlfn.XLOOKUP(B54,'CECOS Corporativos'!$D:$D,'CECOS Corporativos'!$E:$E,""),"") -> Legal Corporativo (HH Corporativo) | D54: =IFERROR(_xlfn.XLOOKUP(B54,'CECOS Corporativos'!$D:$D,'CECOS Corporativos'!$J:$J,""),"") -> VP Legal | E54: =_xll.EPMOlapMemberO("[CLACO].[PARENTH7].[AMSAMAT_Y_REP.2]","","Materiales y repuest","","000") -> Materiales y repuest | F54: =IFERROR(TRIM(LEFT(G54,FIND("-",G54)-1)),"") -> N1003AD050 | G54: N1003AD050 - Gerencia General | H54: =IFERROR(_xlfn.XLOOKUP(F54,'CECOS Corporativos'!$K:$K,'CECOS Corporativos'!$D:$D,""),"") -> 1003AD0508 | K54: =J54-I54 -> 0 | N54: =M54-L54 -> 0 | Q54: =P54-O54 -> 0 | R54: 93.06 | T54: =S54-R54 -> -93.06
A55: =_xll.EPMOlapMemberO("[CECO].[PARENTH3].[AMSA1003AD0509]","","AMSA1003AD0509 - Legal Corporativo","","000") -> AMSA1003AD0509 - Legal Corporativo | B55: =IFERROR(SUBSTITUTE(TRIM(LEFT(A55,FIND("-",A55)-1)),"AMSA",""),"") -> 1003AD0509 | C55: =IFERROR(_xlfn.XLOOKUP(B55,'CECOS Corporativos'!$D:$D,'CECOS Corporativos'!$E:$E,""),"") -> Legal Corporativo (HH Corporativo) | D55: =IFERROR(_xlfn.XLOOKUP(B55,'CECOS Corporativos'!$D:$D,'CECOS Corporativos'!$J:$J,""),"") -> VP Legal | E55: =_xll.EPMOlapMemberO("[CLACO].[PARENTH7].[AMSASERV_CORP]","","Servicios Corporativ","","000") -> Servicios Corporativ | F55: =IFERROR(TRIM(LEFT(G55,FIND("-",G55)-1)),"") -> N1003AD050 | G55: N1003AD050 - Gerencia General | H55: =IFERROR(_xlfn.XLOOKUP(F55,'CECOS Corporativos'!$K:$K,'CECOS Corporativos'!$D:$D,""),"") -> 1003AD0508 | K55: =J55-I55 -> 0 | N55: =M55-L55 -> 0 | O55: 236055 | P55: 261554 | Q55: =P55-O55 -> 25499 | R55: 260914 | S55: 273869.84 | T55: =S55-R55 -> 12955.84
A56: =_xll.EPMOlapMemberO("[CECO].[PARENTH3].[AMSA1003AD0511]","","AMSA1003AD0511 - Reporting VPACS Corp","","000") -> AMSA1003AD0511 - Reporting VPACS Corp | B56: =IFERROR(SUBSTITUTE(TRIM(LEFT(A56,FIND("-",A56)-1)),"AMSA",""),"") -> 1003AD0511 | C56: =IFERROR(_xlfn.XLOOKUP(B56,'CECOS Corporativos'!$D:$D,'CECOS Corporativos'!$E:$E,""),"") -> Reporting VPACS Corporativo | D56: =IFERROR(_xlfn.XLOOKUP(B56,'CECOS Corporativos'!$D:$D,'CECOS Corporativos'!$J:$J,""),"") -> VP Sustentabilidad | E56: =_xll.EPMOlapMemberO("[CLACO].[PARENTH7].[AMSAASESORIAS]","","Asesorías y Consulto","","000") -> Asesorías y Consulto | F56: =IFERROR(TRIM(LEFT(G56,FIND("-",G56)-1)),"") -> N1003AD050 | G56: N1003AD050 - Gerencia General | H56: =IFERROR(_xlfn.XLOOKUP(F56,'CECOS Corporativos'!$K:$K,'CECOS Corporativos'!$D:$D,""),"") -> 1003AD0508 | K56: =J56-I56 -> 0 | N56: =M56-L56 -> 0 | O56: -77.71 | Q56: =P56-O56 -> 77.71 | T56: =S56-R56 -> 0
A57: =_xll.EPMOlapMemberO("[CECO].[PARENTH3].[AMSA1003AD0511]","","AMSA1003AD0511 - Reporting VPACS Corp","","000") -> AMSA1003AD0511 - Reporting VPACS Corp | B57: =IFERROR(SUBSTITUTE(TRIM(LEFT(A57,FIND("-",A57)-1)),"AMSA",""),"") -> 1003AD0511 | C57: =IFERROR(_xlfn.XLOOKUP(B57,'CECOS Corporativos'!$D:$D,'CECOS Corporativos'!$E:$E,""),"") -> Reporting VPACS Corporativo | D57: =IFERROR(_xlfn.XLOOKUP(B57,'CECOS Corporativos'!$D:$D,'CECOS Corporativos'!$J:$J,""),"") -> VP Sustentabilidad | E57: =_xll.EPMOlapMemberO("[CLACO].[PARENTH7].[AMSASERVICIOS]","","Servicios","","000") -> Servicios | F57: =IFERROR(TRIM(LEFT(G57,FIND("-",G57)-1)),"") -> N1003AD050 | G57: N1003AD050 - Gerencia General | H57: =IFERROR(_xlfn.XLOOKUP(F57,'CECOS Corporativos'!$K:$K,'CECOS Corporativos'!$D:$D,""),"") -> 1003AD0508 | K57: =J57-I57 -> 0 | N57: =M57-L57 -> 0 | O57: 79921.95 | P57: 66444 | Q57: =P57-O57 -> -13477.95 | R57: 48552.15 | S57: 65098.27 | T57: =S57-R57 -> 16546.12
A58: =_xll.EPMOlapMemberO("[CECO].[PARENTH3].[AMSA1003AD0511]","","AMSA1003AD0511 - Reporting VPACS Corp","","000") -> AMSA1003AD0511 - Reporting VPACS Corp | B58: =IFERROR(SUBSTITUTE(TRIM(LEFT(A58,FIND("-",A58)-1)),"AMSA",""),"") -> 1003AD0511 | C58: =IFERROR(_xlfn.XLOOKUP(B58,'CECOS Corporativos'!$D:$D,'CECOS Corporativos'!$E:$E,""),"") -> Reporting VPACS Corporativo | D58: =IFERROR(_xlfn.XLOOKUP(B58,'CECOS Corporativos'!$D:$D,'CECOS Corporativos'!$J:$J,""),"") -> VP Sustentabilidad | E58: =_xll.EPMOlapMemberO("[CLACO].[PARENTH7].[AMSAINFORMATIC]","","Informática y Comuni","","000") -> Informática y Comuni | F58: =IFERROR(TRIM(LEFT(G58,FIND("-",G58)-1)),"") -> N1003AD050 | G58: N1003AD050 - Gerencia General | H58: =IFERROR(_xlfn.XLOOKUP(F58,'CECOS Corporativos'!$K:$K,'CECOS Corporativos'!$D:$D,""),"") -> 1003AD0508 | K58: =J58-I58 -> 0 | N58: =M58-L58 -> 0 | O58: 945.5 | P58: 5499 | Q58: =P58-O58 -> 4553.5 | T58: =S58-R58 -> 0
A59: =_xll.EPMOlapMemberO("[CECO].[PARENTH3].[AMSA1003AD0511]","","AMSA1003AD0511 - Reporting VPACS Corp","","000") -> AMSA1003AD0511 - Reporting VPACS Corp | B59: =IFERROR(SUBSTITUTE(TRIM(LEFT(A59,FIND("-",A59)-1)),"AMSA",""),"") -> 1003AD0511 | C59: =IFERROR(_xlfn.XLOOKUP(B59,'CECOS Corporativos'!$D:$D,'CECOS Corporativos'!$E:$E,""),"") -> Reporting VPACS Corporativo | D59: =IFERROR(_xlfn.XLOOKUP(B59,'CECOS Corporativos'!$D:$D,'CECOS Corporativos'!$J:$J,""),"") -> VP Sustentabilidad | E59: =_xll.EPMOlapMemberO("[CLACO].[PARENTH7].[AMSAGGENERALES.2]","","Otros Gastos","","000") -> Otros Gastos | F59: =IFERROR(TRIM(LEFT(G59,FIND("-",G59)-1)),"") -> N1003AD050 | G59: N1003AD050 - Gerencia General | H59: =IFERROR(_xlfn.XLOOKUP(F59,'CECOS Corporativos'!$K:$K,'CECOS Corporativos'!$D:$D,""),"") -> 1003AD0508 | K59: =J59-I59 -> 0 | N59: =M59-L59 -> 0 | O59: 40840.65 | P59: 49478 | Q59: =P59-O59 -> 8637.35 | R59: 54135.64 | S59: 51929.12 | T59: =S59-R59 -> -2206.52
A60: =_xll.EPMOlapMemberO("[CECO].[PARENTH3].[AMSA1003AD3502]","","AMSA1003AD3502 - Finanzas","","000") -> AMSA1003AD3502 - Finanzas | B60: =IFERROR(SUBSTITUTE(TRIM(LEFT(A60,FIND("-",A60)-1)),"AMSA",""),"") -> 1003AD3502 | C60: =IFERROR(_xlfn.XLOOKUP(B60,'CECOS Corporativos'!$D:$D,'CECOS Corporativos'!$E:$E,""),"") -> Gerencia de Inversiones & Finanzas | D60: =IFERROR(_xlfn.XLOOKUP(B60,'CECOS Corporativos'!$D:$D,'CECOS Corporativos'!$J:$J,""),"") -> VP Finanzas | E60: =_xll.EPMOlapMemberO("[CLACO].[PARENTH7].[AMSAMAT_Y_REP.2]","","Materiales y repuest","","000") -> Materiales y repuest | F60: =IFERROR(TRIM(LEFT(G60,FIND("-",G60)-1)),"") -> N1003AD350 | G60: N1003AD350 - Administración y Fin | H60: =IFERROR(_xlfn.XLOOKUP(F60,'CECOS Corporativos'!$K:$K,'CECOS Corporativos'!$D:$D,""),"") | K60: =J60-I60 -> 0 | N60: =M60-L60 -> 0 | O60: 52.88 | Q60: =P60-O60 -> -52.88 | T60: =S60-R60 -> 0
A61: =_xll.EPMOlapMemberO("[CECO].[PARENTH3].[AMSA1003AD3502]","","AMSA1003AD3502 - Finanzas","","000") -> AMSA1003AD3502 - Finanzas | B61: =IFERROR(SUBSTITUTE(TRIM(LEFT(A61,FIND("-",A61)-1)),"AMSA",""),"") -> 1003AD3502 | C61: =IFERROR(_xlfn.XLOOKUP(B61,'CECOS Corporativos'!$D:$D,'CECOS Corporativos'!$E:$E,""),"") -> Gerencia de Inversiones & Finanzas | D61: =IFERROR(_xlfn.XLOOKUP(B61,'CECOS Corporativos'!$D:$D,'CECOS Corporativos'!$J:$J,""),"") -> VP Finanzas | E61: =_xll.EPMOlapMemberO("[CLACO].[PARENTH7].[AMSAENTRENAMI]","","Entrenamiento","","000") -> Entrenamiento | F61: =IFERROR(TRIM(LEFT(G61,FIND("-",G61)-1)),"") -> N1003AD350 | G61: N1003AD350 - Administración y Fin | H61: =IFERROR(_xlfn.XLOOKUP(F61,'CECOS Corporativos'!$K:$K,'CECOS Corporativos'!$D:$D,""),"") | K61: =J61-I61 -> 0 | L61: 0 | N61: =M61-L61 -> 0 | Q61: =P61-O61 -> 0 | T61: =S61-R61 -> 0
A62: =_xll.EPMOlapMemberO("[CECO].[PARENTH3].[AMSA1003AD3502]","","AMSA1003AD3502 - Finanzas","","000") -> AMSA1003AD3502 - Finanzas | B62: =IFERROR(SUBSTITUTE(TRIM(LEFT(A62,FIND("-",A62)-1)),"AMSA",""),"") -> 1003AD3502 | C62: =IFERROR(_xlfn.XLOOKUP(B62,'CECOS Corporativos'!$D:$D,'CECOS Corporativos'!$E:$E,""),"") -> Gerencia de Inversiones & Finanzas | D62: =IFERROR(_xlfn.XLOOKUP(B62,'CECOS Corporativos'!$D:$D,'CECOS Corporativos'!$J:$J,""),"") -> VP Finanzas | E62: =_xll.EPMOlapMemberO("[CLACO].[PARENTH7].[AMSAASESORIAS]","","Asesorías y Consulto","","000") -> Asesorías y Consulto | F62: =IFERROR(TRIM(LEFT(G62,FIND("-",G62)-1)),"") -> N1003AD350 | G62: N1003AD350 - Administración y Fin | H62: =IFERROR(_xlfn.XLOOKUP(F62,'CECOS Corporativos'!$K:$K,'CECOS Corporativos'!$D:$D,""),"") | I62: 26014.17 | J62: 80136 | K62: =J62-I62 -> 54121.83 | L62: 4685.63 | M62: 1404 | N62: =M62-L62 -> -3281.63 | O62: 1334.01 | P62: 1471 | Q62: =P62-O62 -> 136.99 | R62: -0.25 | S62: 1355.56 | T62: =S62-R62 -> 1355.81
A63: =_xll.EPMOlapMemberO("[CECO].[PARENTH3].[AMSA1003AD3502]","","AMSA1003AD3502 - Finanzas","","000") -> AMSA1003AD3502 - Finanzas | B63: =IFERROR(SUBSTITUTE(TRIM(LEFT(A63,FIND("-",A63)-1)),"AMSA",""),"") -> 1003AD3502 | C63: =IFERROR(_xlfn.XLOOKUP(B63,'CECOS Corporativos'!$D:$D,'CECOS Corporativos'!$E:$E,""),"") -> Gerencia de Inversiones & Finanzas | D63: =IFERROR(_xlfn.XLOOKUP(B63,'CECOS Corporativos'!$D:$D,'CECOS Corporativos'!$J:$J,""),"") -> VP Finanzas | E63: =_xll.EPMOlapMemberO("[CLACO].[PARENTH7].[AMSAARRIENDOS]","","Arriendos","","000") -> Arriendos | F63: =IFERROR(TRIM(LEFT(G63,FIND("-",G63)-1)),"") -> N1003AD350 | G63: N1003AD350 - Administración y Fin | H63: =IFERROR(_xlfn.XLOOKUP(F63,'CECOS Corporativos'!$K:$K,'CECOS Corporativos'!$D:$D,""),"") | I63: 0 | K63: =J63-I63 -> 0 | N63: =M63-L63 -> 0 | O63: 0 | Q63: =P63-O63 -> 0 | T63: =S63-R63 -> 0
A64: =_xll.EPMOlapMemberO("[CECO].[PARENTH3].[AMSA1003AD3502]","","AMSA1003AD3502 - Finanzas","","000") -> AMSA1003AD3502 - Finanzas | B64: =IFERROR(SUBSTITUTE(TRIM(LEFT(A64,FIND("-",A64)-1)),"AMSA",""),"") -> 1003AD3502 | C64: =IFERROR(_xlfn.XLOOKUP(B64,'CECOS Corporativos'!$D:$D,'CECOS Corporativos'!$E:$E,""),"") -> Gerencia de Inversiones & Finanzas | D64: =IFERROR(_xlfn.XLOOKUP(B64,'CECOS Corporativos'!$D:$D,'CECOS Corporativos'!$J:$J,""),"") -> VP Finanzas | E64: =_xll.EPMOlapMemberO("[CLACO].[PARENTH7].[AMSASERVICIOS]","","Servicios","","000") -> Servicios | F64: =IFERROR(TRIM(LEFT(G64,FIND("-",G64)-1)),"") -> N1003AD350 | G64: N1003AD350 - Administración y Fin | H64: =IFERROR(_xlfn.XLOOKUP(F64,'CECOS Corporativos'!$K:$K,'CECOS Corporativos'!$D:$D,""),"") | K64: =J64-I64 -> 0 | L64: 108.66 | N64: =M64-L64 -> -108.66 | Q64: =P64-O64 -> 0 | R64: 5.54 | T64: =S64-R64 -> -5.54
A65: =_xll.EPMOlapMemberO("[CECO].[PARENTH3].[AMSA1003AD3502]","","AMSA1003AD3502 - Finanzas","","000") -> AMSA1003AD3502 - Finanzas | B65: =IFERROR(SUBSTITUTE(TRIM(LEFT(A65,FIND("-",A65)-1)),"AMSA",""),"") -> 1003AD3502 | C65: =IFERROR(_xlfn.XLOOKUP(B65,'CECOS Corporativos'!$D:$D,'CECOS Corporativos'!$E:$E,""),"") -> Gerencia de Inversiones & Finanzas | D65: =IFERROR(_xlfn.XLOOKUP(B65,'CECOS Corporativos'!$D:$D,'CECOS Corporativos'!$J:$J,""),"") -> VP Finanzas | E65: =_xll.EPMOlapMemberO("[CLACO].[PARENTH7].[AMSAINFORMATIC]","","Informática y Comuni","","000") -> Informática y Comuni | F65: =IFERROR(TRIM(LEFT(G65,FIND("-",G65)-1)),"") -> N1003AD350 | G65: N1003AD350 - Administración y Fin | H65: =IFERROR(_xlfn.XLOOKUP(F65,'CECOS Corporativos'!$K:$K,'CECOS Corporativos'!$D:$D,""),"") | I65: 3704.92 | J65: 1235 | K65: =J65-I65 -> -2469.92 | L65: 883.17 | M65: 1247 | N65: =M65-L65 -> 363.83 | O65: 546.65 | P65: 1200 | Q65: =P65-O65 -> 653.35 | R65: 3617 | S65: 800 | T65: =S65-R65 -> -2817
A66: =_xll.EPMOlapMemberO("[CECO].[PARENTH3].[AMSA1003AD3502]","","AMSA1003AD3502 - Finanzas","","000") -> AMSA1003AD3502 - Finanzas | B66: =IFERROR(SUBSTITUTE(TRIM(LEFT(A66,FIND("-",A66)-1)),"AMSA",""),"") -> 1003AD3502 | C66: =IFERROR(_xlfn.XLOOKUP(B66,'CECOS Corporativos'!$D:$D,'CECOS Corporativos'!$E:$E,""),"") -> Gerencia de Inversiones & Finanzas | D66: =IFERROR(_xlfn.XLOOKUP(B66,'CECOS Corporativos'!$D:$D,'CECOS Corporativos'!$J:$J,""),"") -> VP Finanzas | E66: =_xll.EPMOlapMemberO("[CLACO].[PARENTH7].[AMSAG_VIAJES]","","Gastos de Viajes","","000") -> Gastos de Viajes | F66: =IFERROR(TRIM(LEFT(G66,FIND("-",G66)-1)),"") -> N1003AD350 | G66: N1003AD350 - Administración y Fin | H66: =IFERROR(_xlfn.XLOOKUP(F66,'CECOS Corporativos'!$K:$K,'CECOS Corporativos'!$D:$D,""),"") | I66: -1.35 | K66: =J66-I66 -> 1.35 | L66: 0 | N66: =M66-L66 -> 0 | Q66: =P66-O66 -> 0 | T66: =S66-R66 -> 0
A67: =_xll.EPMOlapMemberO("[CECO].[PARENTH3].[AMSA1003AD3502]","","AMSA1003AD3502 - Finanzas","","000") -> AMSA1003AD3502 - Finanzas | B67: =IFERROR(SUBSTITUTE(TRIM(LEFT(A67,FIND("-",A67)-1)),"AMSA",""),"") -> 1003AD3502 | C67: =IFERROR(_xlfn.XLOOKUP(B67,'CECOS Corporativos'!$D:$D,'CECOS Corporativos'!$E:$E,""),"") -> Gerencia de Inversiones & Finanzas | D67: =IFERROR(_xlfn.XLOOKUP(B67,'CECOS Corporativos'!$D:$D,'CECOS Corporativos'!$J:$J,""),"") -> VP Finanzas | E67: =_xll.EPMOlapMemberO("[CLACO].[PARENTH7].[AMSASEGUROS]","","Seguros","","000") -> Seguros | F67: =IFERROR(TRIM(LEFT(G67,FIND("-",G67)-1)),"") -> N1003AD350 | G67: N1003AD350 - Administración y Fin | H67: =IFERROR(_xlfn.XLOOKUP(F67,'CECOS Corporativos'!$K:$K,'CECOS Corporativos'!$D:$D,""),"") | K67: =J67-I67 -> 0 | L67: 21534 | N67: =M67-L67 -> -21534 | O67: 0 | Q67: =P67-O67 -> 0 | T67: =S67-R67 -> 0
A68: =_xll.EPMOlapMemberO("[CECO].[PARENTH3].[AMSA1003AD3502]","","AMSA1003AD3502 - Finanzas","","000") -> AMSA1003AD3502 - Finanzas | B68: =IFERROR(SUBSTITUTE(TRIM(LEFT(A68,FIND("-",A68)-1)),"AMSA",""),"") -> 1003AD3502 | C68: =IFERROR(_xlfn.XLOOKUP(B68,'CECOS Corporativos'!$D:$D,'CECOS Corporativos'!$E:$E,""),"") -> Gerencia de Inversiones & Finanzas | D68: =IFERROR(_xlfn.XLOOKUP(B68,'CECOS Corporativos'!$D:$D,'CECOS Corporativos'!$J:$J,""),"") -> VP Finanzas | E68: =_xll.EPMOlapMemberO("[CLACO].[PARENTH7].[AMSAGGENERALES.2]","","Otros Gastos","","000") -> Otros Gastos | F68: =IFERROR(TRIM(LEFT(G68,FIND("-",G68)-1)),"") -> N1003AD350 | G68: N1003AD350 - Administración y Fin | H68: =IFERROR(_xlfn.XLOOKUP(F68,'CECOS Corporativos'!$K:$K,'CECOS Corporativos'!$D:$D,""),"") | J68: 3082 | K68: =J68-I68 -> 3082 | L68: 0 | M68: 2731 | N68: =M68-L68 -> 2731 | O68: 0 | Q68: =P68-O68 -> 0 | T68: =S68-R68 -> 0
A69: =_xll.EPMOlapMemberO("[CECO].[PARENTH3].[AMSA1003AD3502]","","AMSA1003AD3502 - Finanzas","","000") -> AMSA1003AD3502 - Finanzas | B69: =IFERROR(SUBSTITUTE(TRIM(LEFT(A69,FIND("-",A69)-1)),"AMSA",""),"") -> 1003AD3502 | C69: =IFERROR(_xlfn.XLOOKUP(B69,'CECOS Corporativos'!$D:$D,'CECOS Corporativos'!$E:$E,""),"") -> Gerencia de Inversiones & Finanzas | D69: =IFERROR(_xlfn.XLOOKUP(B69,'CECOS Corporativos'!$D:$D,'CECOS Corporativos'!$J:$J,""),"") -> VP Finanzas | E69: =_xll.EPMOlapMemberO("[CLACO].[PARENTH7].[AMSASERV_CORP]","","Servicios Corporativ","","000") -> Servicios Corporativ | F69: =IFERROR(TRIM(LEFT(G69,FIND("-",G69)-1)),"") -> N1003AD350 | G69: N1003AD350 - Administración y Fin | H69: =IFERROR(_xlfn.XLOOKUP(F69,'CECOS Corporativos'!$K:$K,'CECOS Corporativos'!$D:$D,""),"") | I69: 267002.17 | J69: 275248 | K69: =J69-I69 -> 8245.83 | L69: 291831.1 | M69: 264907 | N69: =M69-L69 -> -26924.1 | O69: -0.1 | Q69: =P69-O69 -> 0.1 | T69: =S69-R69 -> 0
A70: =_xll.EPMOlapMemberO("[CECO].[PARENTH3].[AMSA1003AD3503]","","AMSA1003AD3503 - Contabilidad","","000") -> AMSA1003AD3503 - Contabilidad | B70: =IFERROR(SUBSTITUTE(TRIM(LEFT(A70,FIND("-",A70)-1)),"AMSA",""),"") -> 1003AD3503 | C70: =IFERROR(_xlfn.XLOOKUP(B70,'CECOS Corporativos'!$D:$D,'CECOS Corporativos'!$E:$E,""),"") -> Gerencia Contabilidad Corporativa | D70: =IFERROR(_xlfn.XLOOKUP(B70,'CECOS Corporativos'!$D:$D,'CECOS Corporativos'!$J:$J,""),"") -> VP Finanzas | E70: =_xll.EPMOlapMemberO("[CLACO].[PARENTH7].[AMSAMAT_Y_REP.2]","","Materiales y repuest","","000") -> Materiales y repuest | F70: =IFERROR(TRIM(LEFT(G70,FIND("-",G70)-1)),"") -> N1003AD350 | G70: N1003AD350 - Administración y Fin | H70: =IFERROR(_xlfn.XLOOKUP(F70,'CECOS Corporativos'!$K:$K,'CECOS Corporativos'!$D:$D,""),"") | J70: 205 | K70: =J70-I70 -> 205 | L70: 186.74 | M70: 245 | N70: =M70-L70 -> 58.26 | P70: 243 | Q70: =P70-O70 -> 243 | S70: 242.3 | T70: =S70-R70 -> 242.3
A71: =_xll.EPMOlapMemberO("[CECO].[PARENTH3].[AMSA1003AD3503]","","AMSA1003AD3503 - Contabilidad","","000") -> AMSA1003AD3503 - Contabilidad | B71: =IFERROR(SUBSTITUTE(TRIM(LEFT(A71,FIND("-",A71)-1)),"AMSA",""),"") -> 1003AD3503 | C71: =IFERROR(_xlfn.XLOOKUP(B71,'CECOS Corporativos'!$D:$D,'CECOS Corporativos'!$E:$E,""),"") -> Gerencia Contabilidad Corporativa | D71: =IFERROR(_xlfn.XLOOKUP(B71,'CECOS Corporativos'!$D:$D,'CECOS Corporativos'!$J:$J,""),"") -> VP Finanzas | E71: =_xll.EPMOlapMemberO("[CLACO].[PARENTH7].[AMSAASESORIAS]","","Asesorías y Consulto","","000") -> Asesorías y Consulto | F71: =IFERROR(TRIM(LEFT(G71,FIND("-",G71)-1)),"") -> N1003AD350 | G71: N1003AD350 - Administración y Fin | H71: =IFERROR(_xlfn.XLOOKUP(F71,'CECOS Corporativos'!$K:$K,'CECOS Corporativos'!$D:$D,""),"") | I71: 185093.78 | J71: 193038 | K71: =J71-I71 -> 7944.22 | L71: 157636.71 | M71: 191615 | N71: =M71-L71 -> 33978.29 | O71: 151621.16 | P71: 217093 | Q71: =P71-O71 -> 65471.84 | R71: 186026.14 | S71: 192253.72 | T71: =S71-R71 -> 6227.58
A72: =_xll.EPMOlapMemberO("[CECO].[PARENTH3].[AMSA1003AD3503]","","AMSA1003AD3503 - Contabilidad","","000") -> AMSA1003AD3503 - Contabilidad | B72: =IFERROR(SUBSTITUTE(TRIM(LEFT(A72,FIND("-",A72)-1)),"AMSA",""),"") -> 1003AD3503 | C72: =IFERROR(_xlfn.XLOOKUP(B72,'CECOS Corporativos'!$D:$D,'CECOS Corporativos'!$E:$E,""),"") -> Gerencia Contabilidad Corporativa | D72: =IFERROR(_xlfn.XLOOKUP(B72,'CECOS Corporativos'!$D:$D,'CECOS Corporativos'!$J:$J,""),"") -> VP Finanzas | E72: =_xll.EPMOlapMemberO("[CLACO].[PARENTH7].[AMSASERVICIOS]","","Servicios","","000") -> Servicios | F72: =IFERROR(TRIM(LEFT(G72,FIND("-",G72)-1)),"") -> N1003AD350 | G72: N1003AD350 - Administración y Fin | H72: =IFERROR(_xlfn.XLOOKUP(F72,'CECOS Corporativos'!$K:$K,'CECOS Corporativos'!$D:$D,""),"") | I72: 390.45 | J72: 1555 | K72: =J72-I72 -> 1164.55 | L72: 42.68 | M72: 463 | N72: =M72-L72 -> 420.32 | O72: 1087.2 | P72: 531 | Q72: =P72-O72 -> -556.2 | R72: 0 | S72: 922.14 | T72: =S72-R72 -> 922.14
A73: =_xll.EPMOlapMemberO("[CECO].[PARENTH3].[AMSA1003AD3503]","","AMSA1003AD3503 - Contabilidad","","000") -> AMSA1003AD3503 - Contabilidad | B73: =IFERROR(SUBSTITUTE(TRIM(LEFT(A73,FIND("-",A73)-1)),"AMSA",""),"") -> 1003AD3503 | C73: =IFERROR(_xlfn.XLOOKUP(B73,'CECOS Corporativos'!$D:$D,'CECOS Corporativos'!$E:$E,""),"") -> Gerencia Contabilidad Corporativa | D73: =IFERROR(_xlfn.XLOOKUP(B73,'CECOS Corporativos'!$D:$D,'CECOS Corporativos'!$J:$J,""),"") -> VP Finanzas | E73: =_xll.EPMOlapMemberO("[CLACO].[PARENTH7].[AMSAINFORMATIC]","","Informática y Comuni","","000") -> Informática y Comuni | F73: =IFERROR(TRIM(LEFT(G73,FIND("-",G73)-1)),"") -> N1003AD350 | G73: N1003AD350 - Administración y Fin | H73: =IFERROR(_xlfn.XLOOKUP(F73,'CECOS Corporativos'!$K:$K,'CECOS Corporativos'!$D:$D,""),"") | I73: 32409.27 | J73: 37921 | K73: =J73-I73 -> 5511.73 | L73: 48910.78 | M73: 41293 | N73: =M73-L73 -> -7617.78 | O73: 43340.41 | P73: 41920 | Q73: =P73-O73 -> -1420.41 | R73: 42824.84 | S73: 43273.51 | T73: =S73-R73 -> 448.67
A74: =_xll.EPMOlapMemberO("[CECO].[PARENTH3].[AMSA1003AD3503]","","AMSA1003AD3503 - Contabilidad","","000") -> AMSA1003AD3503 - Contabilidad | B74: =IFERROR(SUBSTITUTE(TRIM(LEFT(A74,FIND("-",A74)-1)),"AMSA",""),"") -> 1003AD3503 | C74: =IFERROR(_xlfn.XLOOKUP(B74,'CECOS Corporativos'!$D:$D,'CECOS Corporativos'!$E:$E,""),"") -> Gerencia Contabilidad Corporativa | D74: =IFERROR(_xlfn.XLOOKUP(B74,'CECOS Corporativos'!$D:$D,'CECOS Corporativos'!$J:$J,""),"") -> VP Finanzas | E74: =_xll.EPMOlapMemberO("[CLACO].[PARENTH7].[AMSAG_VIAJES]","","Gastos de Viajes","","000") -> Gastos de Viajes | F74: =IFERROR(TRIM(LEFT(G74,FIND("-",G74)-1)),"") -> N1003AD350 | G74: N1003AD350 - Administración y Fin | H74: =IFERROR(_xlfn.XLOOKUP(F74,'CECOS Corporativos'!$K:$K,'CECOS Corporativos'!$D:$D,""),"") | I74: 7418.07 | J74: 7829.63 | K74: =J74-I74 -> 411.56 | L74: 4525.65 | M74: 18518.71 | N74: =M74-L74 -> 13993.06 | O74: 3907.97 | P74: 9241 | Q74: =P74-O74 -> 5333.03 | R74: 2937.43 | S74: 11535.47 | T74: =S74-R74 -> 8598.04
A75: =_xll.EPMOlapMemberO("[CECO].[PARENTH3].[AMSA1003AD3503]","","AMSA1003AD3503 - Contabilidad","","000") -> AMSA1003AD3503 - Contabilidad | B75: =IFERROR(SUBSTITUTE(TRIM(LEFT(A75,FIND("-",A75)-1)),"AMSA",""),"") -> 1003AD3503 | C75: =IFERROR(_xlfn.XLOOKUP(B75,'CECOS Corporativos'!$D:$D,'CECOS Corporativos'!$E:$E,""),"") -> Gerencia Contabilidad Corporativa | D75: =IFERROR(_xlfn.XLOOKUP(B75,'CECOS Corporativos'!$D:$D,'CECOS Corporativos'!$J:$J,""),"") -> VP Finanzas | E75: =_xll.EPMOlapMemberO("[CLACO].[PARENTH7].[AMSASERV_CORP]","","Servicios Corporativ","","000") -> Servicios Corporativ | F75: =IFERROR(TRIM(LEFT(G75,FIND("-",G75)-1)),"") -> N1003AD350 | G75: N1003AD350 - Administración y Fin | H75: =IFERROR(_xlfn.XLOOKUP(F75,'CECOS Corporativos'!$K:$K,'CECOS Corporativos'!$D:$D,""),"") | I75: 585417.94 | J75: 603717 | K75: =J75-I75 -> 18299.06 | L75: 712385.89 | M75: 641674 | N75: =M75-L75 -> -70711.89 | O75: 32607.84 | P75: 37422 | Q75: =P75-O75 -> 4814.16 | R75: 33469.29 | S75: 36973.84 | T75: =S75-R75 -> 3504.55
A76: =_xll.EPMOlapMemberO("[CECO].[PARENTH3].[AMSA1003AD3507]","","AMSA1003AD3507 - Control Inter y Ries","","000") -> AMSA1003AD3507 - Control Inter y Ries | B76: =IFERROR(SUBSTITUTE(TRIM(LEFT(A76,FIND("-",A76)-1)),"AMSA",""),"") -> 1003AD3507 | C76: =IFERROR(_xlfn.XLOOKUP(B76,'CECOS Corporativos'!$D:$D,'CECOS Corporativos'!$E:$E,""),"") -> Grcia. Riesgos, Compliance y Control Interno | D76: =IFERROR(_xlfn.XLOOKUP(B76,'CECOS Corporativos'!$D:$D,'CECOS Corporativos'!$J:$J,""),"") -> VP Finanzas | E76: =_xll.EPMOlapMemberO("[CLACO].[PARENTH7].[AMSAMAT_Y_REP.2]","","Materiales y repuest","","000") -> Materiales y repuest | F76: =IFERROR(TRIM(LEFT(G76,FIND("-",G76)-1)),"") -> N1003AD350 | G76: N1003AD350 - Administración y Fin | H76: =IFERROR(_xlfn.XLOOKUP(F76,'CECOS Corporativos'!$K:$K,'CECOS Corporativos'!$D:$D,""),"") | I76: 1694.16 | K76: =J76-I76 -> -1694.16 | N76: =M76-L76 -> 0 | Q76: =P76-O76 -> 0 | T76: =S76-R76 -> 0
A77: =_xll.EPMOlapMemberO("[CECO].[PARENTH3].[AMSA1003AD3507]","","AMSA1003AD3507 - Control Inter y Ries","","000") -> AMSA1003AD3507 - Control Inter y Ries | B77: =IFERROR(SUBSTITUTE(TRIM(LEFT(A77,FIND("-",A77)-1)),"AMSA",""),"") -> 1003AD3507 | C77: =IFERROR(_xlfn.XLOOKUP(B77,'CECOS Corporativos'!$D:$D,'CECOS Corporativos'!$E:$E,""),"") -> Grcia. Riesgos, Compliance y Control Interno | D77: =IFERROR(_xlfn.XLOOKUP(B77,'CECOS Corporativos'!$D:$D,'CECOS Corporativos'!$J:$J,""),"") -> VP Finanzas | E77: =_xll.EPMOlapMemberO("[CLACO].[PARENTH7].[AMSAENTRENAMI]","","Entrenamiento","","000") -> Entrenamiento | F77: =IFERROR(TRIM(LEFT(G77,FIND("-",G77)-1)),"") -> N1003AD350 | G77: N1003AD350 - Administración y Fin | H77: =IFERROR(_xlfn.XLOOKUP(F77,'CECOS Corporativos'!$K:$K,'CECOS Corporativos'!$D:$D,""),"") | I77: -8.71 | J77: 9630 | K77: =J77-I77 -> 9638.71 | M77: 5833 | N77: =M77-L77 -> 5833 | O77: 518.35 | P77: 4241 | Q77: =P77-O77 -> 3722.65 | S77: 1076.55 | T77: =S77-R77 -> 1076.55
A78: =_xll.EPMOlapMemberO("[CECO].[PARENTH3].[AMSA1003AD3507]","","AMSA1003AD3507 - Control Inter y Ries","","000") -> AMSA1003AD3507 - Control Inter y Ries | B78: =IFERROR(SUBSTITUTE(TRIM(LEFT(A78,FIND("-",A78)-1)),"AMSA",""),"") -> 1003AD3507 | C78: =IFERROR(_xlfn.XLOOKUP(B78,'CECOS Corporativos'!$D:$D,'CECOS Corporativos'!$E:$E,""),"") -> Grcia. Riesgos, Compliance y Control Interno | D78: =IFERROR(_xlfn.XLOOKUP(B78,'CECOS Corporativos'!$D:$D,'CECOS Corporativos'!$J:$J,""),"") -> VP Finanzas | E78: =_xll.EPMOlapMemberO("[CLACO].[PARENTH7].[AMSAASESORIAS]","","Asesorías y Consulto","","000") -> Asesorías y Consulto | F78: =IFERROR(TRIM(LEFT(G78,FIND("-",G78)-1)),"") -> N1003AD350 | G78: N1003AD350 - Administración y Fin | H78: =IFERROR(_xlfn.XLOOKUP(F78,'CECOS Corporativos'!$K:$K,'CECOS Corporativos'!$D:$D,""),"") | I78: -4218.91 | J78: 5135 | K78: =J78-I78 -> 9353.91 | L78: 29975.35 | M78: 24998 | N78: =M78-L78 -> -4977.35 | O78: 1595.56 | P78: 13978 | Q78: =P78-O78 -> 12382.44 | R78: 7263.97 | S78: 13056 | T78: =S78-R78 -> 5792.03
A79: =_xll.EPMOlapMemberO("[CECO].[PARENTH3].[AMSA1003AD3507]","","AMSA1003AD3507 - Control Inter y Ries","","000") -> AMSA1003AD3507 - Control Inter y Ries | B79: =IFERROR(SUBSTITUTE(TRIM(LEFT(A79,FIND("-",A79)-1)),"AMSA",""),"") -> 1003AD3507 | C79: =IFERROR(_xlfn.XLOOKUP(B79,'CECOS Corporativos'!$D:$D,'CECOS Corporativos'!$E:$E,""),"") -> Grcia. Riesgos, Compliance y Control Interno | D79: =IFERROR(_xlfn.XLOOKUP(B79,'CECOS Corporativos'!$D:$D,'CECOS Corporativos'!$J:$J,""),"") -> VP Finanzas | E79: =_xll.EPMOlapMemberO("[CLACO].[PARENTH7].[AMSASERVICIOS]","","Servicios","","000") -> Servicios | F79: =IFERROR(TRIM(LEFT(G79,FIND("-",G79)-1)),"") -> N1003AD350 | G79: N1003AD350 - Administración y Fin | H79: =IFERROR(_xlfn.XLOOKUP(F79,'CECOS Corporativos'!$K:$K,'CECOS Corporativos'!$D:$D,""),"") | I79: 52121.63 | J79: 60846 | K79: =J79-I79 -> 8724.37 | L79: 62264.84 | M79: 42772 | N79: =M79-L79 -> -19492.84 | O79: 76193.37 | P79: 89262 | Q79: =P79-O79 -> 13068.63 | R79: 74339.79 | S79: 87673.54 | T79: =S79-R79 -> 13333.75
A80: =_xll.EPMOlapMemberO("[CECO].[PARENTH3].[AMSA1003AD3507]","","AMSA1003AD3507 - Control Inter y Ries","","000") -> AMSA1003AD3507 - Control Inter y Ries | B80: =IFERROR(SUBSTITUTE(TRIM(LEFT(A80,FIND("-",A80)-1)),"AMSA",""),"") -> 1003AD3507 | C80: =IFERROR(_xlfn.XLOOKUP(B80,'CECOS Corporativos'!$D:$D,'CECOS Corporativos'!$E:$E,""),"") -> Grcia. Riesgos, Compliance y Control Interno | D80: =IFERROR(_xlfn.XLOOKUP(B80,'CECOS Corporativos'!$D:$D,'CECOS Corporativos'!$J:$J,""),"") -> VP Finanzas | E80: =_xll.EPMOlapMemberO("[CLACO].[PARENTH7].[AMSAINFORMATIC]","","Informática y Comuni","","000") -> Informática y Comuni | F80: =IFERROR(TRIM(LEFT(G80,FIND("-",G80)-1)),"") -> N1003AD350 | G80: N1003AD350 - Administración y Fin | H80: =IFERROR(_xlfn.XLOOKUP(F80,'CECOS Corporativos'!$K:$K,'CECOS Corporativos'!$D:$D,""),"") | I80: 26631.28 | J80: 33292 | K80: =J80-I80 -> 6660.72 | L80: 29903.67 | M80: 41336 | N80: =M80-L80 -> 11432.33 | O80: 40875.86 | P80: 34432 | Q80: =P80-O80 -> -6443.86 | R80: 56003.94 | S80: 68092.85 | T80: =S80-R80 -> 12088.91
A81: =_xll.EPMOlapMemberO("[CECO].[PARENTH3].[AMSA1003AD3507]","","AMSA1003AD3507 - Control Inter y Ries","","000") -> AMSA1003AD3507 - Control Inter y Ries | B81: =IFERROR(SUBSTITUTE(TRIM(LEFT(A81,FIND("-",A81)-1)),"AMSA",""),"") -> 1003AD3507 | C81: =IFERROR(_xlfn.XLOOKUP(B81,'CECOS Corporativos'!$D:$D,'CECOS Corporativos'!$E:$E,""),"") -> Grcia. Riesgos, Compliance y Control Interno | D81: =IFERROR(_xlfn.XLOOKUP(B81,'CECOS Corporativos'!$D:$D,'CECOS Corporativos'!$J:$J,""),"") -> VP Finanzas | E81: =_xll.EPMOlapMemberO("[CLACO].[PARENTH7].[AMSAG_VIAJES]","","Gastos de Viajes","","000") -> Gastos de Viajes | F81: =IFERROR(TRIM(LEFT(G81,FIND("-",G81)-1)),"") -> N1003AD350 | G81: N1003AD350 - Administración y Fin | H81: =IFERROR(_xlfn.XLOOKUP(F81,'CECOS Corporativos'!$K:$K,'CECOS Corporativos'!$D:$D,""),"") | J81: 10765.4 | K81: =J81-I81 -> 10765.4 | N81: =M81-L81 -> 0 | Q81: =P81-O81 -> 0 | T81: =S81-R81 -> 0
A82: =_xll.EPMOlapMemberO("[CECO].[PARENTH3].[AMSA1003AD3507]","","AMSA1003AD3507 - Control Inter y Ries","","000") -> AMSA1003AD3507 - Control Inter y Ries | B82: =IFERROR(SUBSTITUTE(TRIM(LEFT(A82,FIND("-",A82)-1)),"AMSA",""),"") -> 1003AD3507 | C82: =IFERROR(_xlfn.XLOOKUP(B82,'CECOS Corporativos'!$D:$D,'CECOS Corporativos'!$E:$E,""),"") -> Grcia. Riesgos, Compliance y Control Interno | D82: =IFERROR(_xlfn.XLOOKUP(B82,'CECOS Corporativos'!$D:$D,'CECOS Corporativos'!$J:$J,""),"") -> VP Finanzas | E82: =_xll.EPMOlapMemberO("[CLACO].[PARENTH7].[AMSAGGENERALES.2]","","Otros Gastos","","000") -> Otros Gastos | F82: =IFERROR(TRIM(LEFT(G82,FIND("-",G82)-1)),"") -> N1003AD350 | G82: N1003AD350 - Administración y Fin | H82: =IFERROR(_xlfn.XLOOKUP(F82,'CECOS Corporativos'!$K:$K,'CECOS Corporativos'!$D:$D,""),"") | I82: 3393.96 | J82: 2691 | K82: =J82-I82 -> -702.96 | L82: 2582.16 | M82: 3379 | N82: =M82-L82 -> 796.84 | O82: 701.72 | P82: 3649 | Q82: =P82-O82 -> 2947.28 | R82: 3078.72 | S82: 2910.97 | T82: =S82-R82 -> -167.75
A83: =_xll.EPMOlapMemberO("[CECO].[PARENTH3].[AMSA1003AD3507]","","AMSA1003AD3507 - Control Inter y Ries","","000") -> AMSA1003AD3507 - Control Inter y Ries | B83: =IFERROR(SUBSTITUTE(TRIM(LEFT(A83,FIND("-",A83)-1)),"AMSA",""),"") -> 1003AD3507 | C83: =IFERROR(_xlfn.XLOOKUP(B83,'CECOS Corporativos'!$D:$D,'CECOS Corporativos'!$E:$E,""),"") -> Grcia. Riesgos, Compliance y Control Interno | D83: =IFERROR(_xlfn.XLOOKUP(B83,'CECOS Corporativos'!$D:$D,'CECOS Corporativos'!$J:$J,""),"") -> VP Finanzas | E83: =_xll.EPMOlapMemberO("[CLACO].[PARENTH7].[AMSASERV_CORP]","","Servicios Corporativ","","000") -> Servicios Corporativ | F83: =IFERROR(TRIM(LEFT(G83,FIND("-",G83)-1)),"") -> N1003AD350 | G83: N1003AD350 - Administración y Fin | H83: =IFERROR(_xlfn.XLOOKUP(F83,'CECOS Corporativos'!$K:$K,'CECOS Corporativos'!$D:$D,""),"") | I83: 212098.52 | J83: 218709 | K83: =J83-I83 -> 6610.48 | L83: 288577.24 | M83: 261955 | N83: =M83-L83 -> -26622.24 | O83: -0.24 | Q83: =P83-O83 -> 0.24 | T83: =S83-R83 -> 0
A84: =_xll.EPMOlapMemberO("[CECO].[PARENTH3].[AMSA1003AD3509]","","AMSA1003AD3509 - TICA Corporativo","","000") -> AMSA1003AD3509 - TICA Corporativo | B84: =IFERROR(SUBSTITUTE(TRIM(LEFT(A84,FIND("-",A84)-1)),"AMSA",""),"") -> 1003AD3509 | C84: =IFERROR(_xlfn.XLOOKUP(B84,'CECOS Corporativos'!$D:$D,'CECOS Corporativos'!$E:$E,""),"") -> TICA Distribuible | D84: =IFERROR(_xlfn.XLOOKUP(B84,'CECOS Corporativos'!$D:$D,'CECOS Corporativos'!$J:$J,""),"") -> VP Estrategia e Innovación | E84: =_xll.EPMOlapMemberO("[CLACO].[PARENTH7].[AMSAMAT_Y_REP.2]","","Materiales y repuest","","000") -> Materiales y repuest | F84: =IFERROR(TRIM(LEFT(G84,FIND("-",G84)-1)),"") -> N1003AD350 | G84: N1003AD350 - Administración y Fin | H84: =IFERROR(_xlfn.XLOOKUP(F84,'CECOS Corporativos'!$K:$K,'CECOS Corporativos'!$D:$D,""),"") | I84: 140831.19 | J84: 89579 | K84: =J84-I84 -> -51252.19 | L84: 55479.57 | M84: 67357 | N84: =M84-L84 -> 11877.43 | O84: 43887.11 | P84: 50077 | Q84: =P84-O84 -> 6189.89 | R84: 38520.82 | S84: 49801.66 | T84: =S84-R84 -> 11280.84
A85: =_xll.EPMOlapMemberO("[CECO].[PARENTH3].[AMSA1003AD3509]","","AMSA1003AD3509 - TICA Corporativo","","000") -> AMSA1003AD3509 - TICA Corporativo | B85: =IFERROR(SUBSTITUTE(TRIM(LEFT(A85,FIND("-",A85)-1)),"AMSA",""),"") -> 1003AD3509 | C85: =IFERROR(_xlfn.XLOOKUP(B85,'CECOS Corporativos'!$D:$D,'CECOS Corporativos'!$E:$E,""),"") -> TICA Distribuible | D85: =IFERROR(_xlfn.XLOOKUP(B85,'CECOS Corporativos'!$D:$D,'CECOS Corporativos'!$J:$J,""),"") -> VP Estrategia e Innovación | E85: =_xll.EPMOlapMemberO("[CLACO].[PARENTH7].[AMSACOMBUSTIBL]","","Combustibles / Lubr","","000") -> Combustibles / Lubr | F85: =IFERROR(TRIM(LEFT(G85,FIND("-",G85)-1)),"") -> N1003AD350 | G85: N1003AD350 - Administración y Fin | H85: =IFERROR(_xlfn.XLOOKUP(F85,'CECOS Corporativos'!$K:$K,'CECOS Corporativos'!$D:$D,""),"") | I85: 0 | J85: 6103 | K85: =J85-I85 -> 6103 | L85: 1117.3 | M85: 5413 | N85: =M85-L85 -> 4295.7 | O85: 2866.24 | P85: 2164 | Q85: =P85-O85 -> -702.24 | R85: 3241.5 | S85: 2039.04 | T85: =S85-R85 -> -1202.46
A86: =_xll.EPMOlapMemberO("[CECO].[PARENTH3].[AMSA1003AD3509]","","AMSA1003AD3509 - TICA Corporativo","","000") -> AMSA1003AD3509 - TICA Corporativo | B86: =IFERROR(SUBSTITUTE(TRIM(LEFT(A86,FIND("-",A86)-1)),"AMSA",""),"") -> 1003AD3509 | C86: =IFERROR(_xlfn.XLOOKUP(B86,'CECOS Corporativos'!$D:$D,'CECOS Corporativos'!$E:$E,""),"") -> TICA Distribuible | D86: =IFERROR(_xlfn.XLOOKUP(B86,'CECOS Corporativos'!$D:$D,'CECOS Corporativos'!$J:$J,""),"") -> VP Estrategia e Innovación | E86: =_xll.EPMOlapMemberO("[CLACO].[PARENTH7].[AMSAENTRENAMI]","","Entrenamiento","","000") -> Entrenamiento | F86: =IFERROR(TRIM(LEFT(G86,FIND("-",G86)-1)),"") -> N1003AD350 | G86: N1003AD350 - Administración y Fin | H86: =IFERROR(_xlfn.XLOOKUP(F86,'CECOS Corporativos'!$K:$K,'CECOS Corporativos'!$D:$D,""),"") | I86: -0.01 | K86: =J86-I86 -> 0.01 | N86: =M86-L86 -> 0 | Q86: =P86-O86 -> 0 | T86: =S86-R86 -> 0
A87: =_xll.EPMOlapMemberO("[CECO].[PARENTH3].[AMSA1003AD3509]","","AMSA1003AD3509 - TICA Corporativo","","000") -> AMSA1003AD3509 - TICA Corporativo | B87: =IFERROR(SUBSTITUTE(TRIM(LEFT(A87,FIND("-",A87)-1)),"AMSA",""),"") -> 1003AD3509 | C87: =IFERROR(_xlfn.XLOOKUP(B87,'CECOS Corporativos'!$D:$D,'CECOS Corporativos'!$E:$E,""),"") -> TICA Distribuible | D87: =IFERROR(_xlfn.XLOOKUP(B87,'CECOS Corporativos'!$D:$D,'CECOS Corporativos'!$J:$J,""),"") -> VP Estrategia e Innovación | E87: =_xll.EPMOlapMemberO("[CLACO].[PARENTH7].[AMSAASESORIAS]","","Asesorías y Consulto","","000") -> Asesorías y Consulto | F87: =IFERROR(TRIM(LEFT(G87,FIND("-",G87)-1)),"") -> N1003AD350 | G87: N1003AD350 - Administración y Fin | H87: =IFERROR(_xlfn.XLOOKUP(F87,'CECOS Corporativos'!$K:$K,'CECOS Corporativos'!$D:$D,""),"") | I87: -1.16 | K87: =J87-I87 -> 1.16 | N87: =M87-L87 -> 0 | Q87: =P87-O87 -> 0 | T87: =S87-R87 -> 0
A88: =_xll.EPMOlapMemberO("[CECO].[PARENTH3].[AMSA1003AD3509]","","AMSA1003AD3509 - TICA Corporativo","","000") -> AMSA1003AD3509 - TICA Corporativo | B88: =IFERROR(SUBSTITUTE(TRIM(LEFT(A88,FIND("-",A88)-1)),"AMSA",""),"") -> 1003AD3509 | C88: =IFERROR(_xlfn.XLOOKUP(B88,'CECOS Corporativos'!$D:$D,'CECOS Corporativos'!$E:$E,""),"") -> TICA Distribuible | D88: =IFERROR(_xlfn.XLOOKUP(B88,'CECOS Corporativos'!$D:$D,'CECOS Corporativos'!$J:$J,""),"") -> VP Estrategia e Innovación | E88: =_xll.EPMOlapMemberO("[CLACO].[PARENTH7].[AMSAARRIENDOS]","","Arriendos","","000") -> Arriendos | F88: =IFERROR(TRIM(LEFT(G88,FIND("-",G88)-1)),"") -> N1003AD350 | G88: N1003AD350 - Administración y Fin | H88: =IFERROR(_xlfn.XLOOKUP(F88,'CECOS Corporativos'!$K:$K,'CECOS Corporativos'!$D:$D,""),"") | I88: 9440.15 | J88: 9432 | K88: =J88-I88 -> -8.15 | L88: 9048.29 | M88: 10254 | N88: =M88-L88 -> 1205.71 | O88: 9191.98 | P88: 10818 | Q88: =P88-O88 -> 1626.02 | R88: 10150.87 | S88: 10194.96 | T88: =S88-R88 -> 44.09
A89: =_xll.EPMOlapMemberO("[CECO].[PARENTH3].[AMSA1003AD3509]","","AMSA1003AD3509 - TICA Corporativo","","000") -> AMSA1003AD3509 - TICA Corporativo | B89: =IFERROR(SUBSTITUTE(TRIM(LEFT(A89,FIND("-",A89)-1)),"AMSA",""),"") -> 1003AD3509 | C89: =IFERROR(_xlfn.XLOOKUP(B89,'CECOS Corporativos'!$D:$D,'CECOS Corporativos'!$E:$E,""),"") -> TICA Distribuible | D89: =IFERROR(_xlfn.XLOOKUP(B89,'CECOS Corporativos'!$D:$D,'CECOS Corporativos'!$J:$J,""),"") -> VP Estrategia e Innovación | E89: =_xll.EPMOlapMemberO("[CLACO].[PARENTH7].[AMSASERVICIOS]","","Servicios","","000") -> Servicios | F89: =IFERROR(TRIM(LEFT(G89,FIND("-",G89)-1)),"") -> N1003AD350 | G89: N1003AD350 - Administración y Fin | H89: =IFERROR(_xlfn.XLOOKUP(F89,'CECOS Corporativos'!$K:$K,'CECOS Corporativos'!$D:$D,""),"") | I89: 11039.22 | J89: 5147 | K89: =J89-I89 -> -5892.22 | L89: 12386.95 | M89: 2068 | N89: =M89-L89 -> -10318.95 | O89: -36359.17 | Q89: =P89-O89 -> 36359.17 | R89: -1916.74 | T89: =S89-R89 -> 1916.74
A90: =_xll.EPMOlapMemberO("[CECO].[PARENTH3].[AMSA1003AD3509]","","AMSA1003AD3509 - TICA Corporativo","","000") -> AMSA1003AD3509 - TICA Corporativo | B90: =IFERROR(SUBSTITUTE(TRIM(LEFT(A90,FIND("-",A90)-1)),"AMSA",""),"") -> 1003AD3509 | C90: =IFERROR(_xlfn.XLOOKUP(B90,'CECOS Corporativos'!$D:$D,'CECOS Corporativos'!$E:$E,""),"") -> TICA Distribuible | D90: =IFERROR(_xlfn.XLOOKUP(B90,'CECOS Corporativos'!$D:$D,'CECOS Corporativos'!$J:$J,""),"") -> VP Estrategia e Innovación | E90: =_xll.EPMOlapMemberO("[CLACO].[PARENTH7].[AMSASERMANTO.REPA]","","Servicios Mantenimie","","000") -> Servicios Mantenimie | F90: =IFERROR(TRIM(LEFT(G90,FIND("-",G90)-1)),"") -> N1003AD350 | G90: N1003AD350 - Administración y Fin | H90: =IFERROR(_xlfn.XLOOKUP(F90,'CECOS Corporativos'!$K:$K,'CECOS Corporativos'!$D:$D,""),"") | I90: 45865 | K90: =J90-I90 -> -45865 | N90: =M90-L90 -> 0 | Q90: =P90-O90 -> 0 | T90: =S90-R90 -> 0
A91: =_xll.EPMOlapMemberO("[CECO].[PARENTH3].[AMSA1003AD3509]","","AMSA1003AD3509 - TICA Corporativo","","000") -> AMSA1003AD3509 - TICA Corporativo | B91: =IFERROR(SUBSTITUTE(TRIM(LEFT(A91,FIND("-",A91)-1)),"AMSA",""),"") -> 1003AD3509 | C91: =IFERROR(_xlfn.XLOOKUP(B91,'CECOS Corporativos'!$D:$D,'CECOS Corporativos'!$E:$E,""),"") -> TICA Distribuible | D91: =IFERROR(_xlfn.XLOOKUP(B91,'CECOS Corporativos'!$D:$D,'CECOS Corporativos'!$J:$J,""),"") -> VP Estrategia e Innovación | E91: =_xll.EPMOlapMemberO("[CLACO].[PARENTH7].[AMSAINFORMATIC]","","Informática y Comuni","","000") -> Informática y Comuni | F91: =IFERROR(TRIM(LEFT(G91,FIND("-",G91)-1)),"") -> N1003AD350 | G91: N1003AD350 - Administración y Fin | H91: =IFERROR(_xlfn.XLOOKUP(F91,'CECOS Corporativos'!$K:$K,'CECOS Corporativos'!$D:$D,""),"") | I91: 3479963 | J91: 3846562 | K91: =J91-I91 -> 366599.06 | L91: 3750913.5 | M91: 3741669 | N91: =M91-L91 -> -9244.47 | O91: 3179441.4 | P91: 3356648 | Q91: =P91-O91 -> 177206.58 | R91: 3691664.1 | S91: 3820958.2 | T91: =S91-R91 -> 129294.11
A92: =_xll.EPMOlapMemberO("[CECO].[PARENTH3].[AMSA1003AD3509]","","AMSA1003AD3509 - TICA Corporativo","","000") -> AMSA1003AD3509 - TICA Corporativo | B92: =IFERROR(SUBSTITUTE(TRIM(LEFT(A92,FIND("-",A92)-1)),"AMSA",""),"") -> 1003AD3509 | C92: =IFERROR(_xlfn.XLOOKUP(B92,'CECOS Corporativos'!$D:$D,'CECOS Corporativos'!$E:$E,""),"") -> TICA Distribuible | D92: =IFERROR(_xlfn.XLOOKUP(B92,'CECOS Corporativos'!$D:$D,'CECOS Corporativos'!$J:$J,""),"") -> VP Estrategia e Innovación | E92: =_xll.EPMOlapMemberO("[CLACO].[PARENTH7].[AMSAG_VIAJES]","","Gastos de Viajes","","000") -> Gastos de Viajes | F92: =IFERROR(TRIM(LEFT(G92,FIND("-",G92)-1)),"") -> N1003AD350 | G92: N1003AD350 - Administración y Fin | H92: =IFERROR(_xlfn.XLOOKUP(F92,'CECOS Corporativos'!$K:$K,'CECOS Corporativos'!$D:$D,""),"") | I92: 13988.85 | J92: 13518.48 | K92: =J92-I92 -> -470.37 | L92: 16683.7 | M92: 27736.31 | N92: =M92-L92 -> 11052.61 | O92: 21933.45 | P92: 28331 | Q92: =P92-O92 -> 6397.55 | R92: 13747.79 | S92: 25149.49 | T92: =S92-R92 -> 11401.7
A93: =_xll.EPMOlapMemberO("[CECO].[PARENTH3].[AMSA1003AD3509]","","AMSA1003AD3509 - TICA Corporativo","","000") -> AMSA1003AD3509 - TICA Corporativo | B93: =IFERROR(SUBSTITUTE(TRIM(LEFT(A93,FIND("-",A93)-1)),"AMSA",""),"") -> 1003AD3509 | C93: =IFERROR(_xlfn.XLOOKUP(B93,'CECOS Corporativos'!$D:$D,'CECOS Corporativos'!$E:$E,""),"") -> TICA Distribuible | D93: =IFERROR(_xlfn.XLOOKUP(B93,'CECOS Corporativos'!$D:$D,'CECOS Corporativos'!$J:$J,""),"") -> VP Estrategia e Innovación | E93: =_xll.EPMOlapMemberO("[CLACO].[PARENTH7].[AMSAGGENERALES.2]","","Otros Gastos","","000") -> Otros Gastos | F93: =IFERROR(TRIM(LEFT(G93,FIND("-",G93)-1)),"") -> N1003AD350 | G93: N1003AD350 - Administración y Fin | H93: =IFERROR(_xlfn.XLOOKUP(F93,'CECOS Corporativos'!$K:$K,'CECOS Corporativos'!$D:$D,""),"") | I93: 440.45 | K93: =J93-I93 -> -440.45 | L93: 730.13 | N93: =M93-L93 -> -730.13 | O93: 30329.51 | P93: 32453 | Q93: =P93-O93 -> 2123.49 | R93: 186.97 | T93: =S93-R93 -> -186.97
A94: =_xll.EPMOlapMemberO("[CECO].[PARENTH3].[AMSA1003AD3509]","","AMSA1003AD3509 - TICA Corporativo","","000") -> AMSA1003AD3509 - TICA Corporativo | B94: =IFERROR(SUBSTITUTE(TRIM(LEFT(A94,FIND("-",A94)-1)),"AMSA",""),"") -> 1003AD3509 | C94: =IFERROR(_xlfn.XLOOKUP(B94,'CECOS Corporativos'!$D:$D,'CECOS Corporativos'!$E:$E,""),"") -> TICA Distribuible | D94: =IFERROR(_xlfn.XLOOKUP(B94,'CECOS Corporativos'!$D:$D,'CECOS Corporativos'!$J:$J,""),"") -> VP Estrategia e Innovación | E94: =_xll.EPMOlapMemberO("[CLACO].[PARENTH7].[AMSASERV_CORP]","","Servicios Corporativ","","000") -> Servicios Corporativ | F94: =IFERROR(TRIM(LEFT(G94,FIND("-",G94)-1)),"") -> N1003AD350 | G94: N1003AD350 - Administración y Fin | H94: =IFERROR(_xlfn.XLOOKUP(F94,'CECOS Corporativos'!$K:$K,'CECOS Corporativos'!$D:$D,""),"") | I94: 884672.55 | J94: 896172 | K94: =J94-I94 -> 11499.45 | L94: 830881.42 | M94: 899513 | N94: =M94-L94 -> 68631.58 | O94: 885672.58 | P94: 884676 | Q94: =P94-O94 -> -996.58 | R94: 1412020.9 | S94: 1457606.5 | T94: =S94-R94 -> 45585.61
A95: =_xll.EPMOlapMemberO("[CECO].[PARENTH3].[AMSA1003AD3510]","","AMSA1003AD3510 - Abaste. Corporativos","","000") -> AMSA1003AD3510 - Abaste. Corporativos | B95: =IFERROR(SUBSTITUTE(TRIM(LEFT(A95,FIND("-",A95)-1)),"AMSA",""),"") -> 1003AD3510 | C95: =IFERROR(_xlfn.XLOOKUP(B95,'CECOS Corporativos'!$D:$D,'CECOS Corporativos'!$E:$E,""),"") -> Gerencia de Abastecimiento Corporativo | D95: =IFERROR(_xlfn.XLOOKUP(B95,'CECOS Corporativos'!$D:$D,'CECOS Corporativos'!$J:$J,""),"") -> VP Finanzas | E95: =_xll.EPMOlapMemberO("[CLACO].[PARENTH7].[AMSAEXPLOSIVOS]","","Explosivos y Accesor","","000") -> Explosivos y Accesor | F95: =IFERROR(TRIM(LEFT(G95,FIND("-",G95)-1)),"") -> N1003AD350 | G95: N1003AD350 - Administración y Fin | H95: =IFERROR(_xlfn.XLOOKUP(F95,'CECOS Corporativos'!$K:$K,'CECOS Corporativos'!$D:$D,""),"") | I95: 21102.75 | K95: =J95-I95 -> -21102.75 | L95: 0 | N95: =M95-L95 -> 0 | O95: 0 | Q95: =P95-O95 -> 0 | T95: =S95-R95 -> 0
A96: =_xll.EPMOlapMemberO("[CECO].[PARENTH3].[AMSA1003AD3510]","","AMSA1003AD3510 - Abaste. Corporativos","","000") -> AMSA1003AD3510 - Abaste. Corporativos | B96: =IFERROR(SUBSTITUTE(TRIM(LEFT(A96,FIND("-",A96)-1)),"AMSA",""),"") -> 1003AD3510 | C96: =IFERROR(_xlfn.XLOOKUP(B96,'CECOS Corporativos'!$D:$D,'CECOS Corporativos'!$E:$E,""),"") -> Gerencia de Abastecimiento Corporativo | D96: =IFERROR(_xlfn.XLOOKUP(B96,'CECOS Corporativos'!$D:$D,'CECOS Corporativos'!$J:$J,""),"") -> VP Finanzas | E96: =_xll.EPMOlapMemberO("[CLACO].[PARENTH7].[AMSAADM_PERSON]","","Administración Perso","","000") -> Administración Perso | F96: =IFERROR(TRIM(LEFT(G96,FIND("-",G96)-1)),"") -> N1003AD350 | G96: N1003AD350 - Administración y Fin | H96: =IFERROR(_xlfn.XLOOKUP(F96,'CECOS Corporativos'!$K:$K,'CECOS Corporativos'!$D:$D,""),"") | K96: =J96-I96 -> 0 | L96: 25713.73 | N96: =M96-L96 -> -25713.73 | O96: 0 | Q96: =P96-O96 -> 0 | R96: 8167.44 | T96: =S96-R96 -> -8167.44
A97: =_xll.EPMOlapMemberO("[CECO].[PARENTH3].[AMSA1003AD3510]","","AMSA1003AD3510 - Abaste. Corporativos","","000") -> AMSA1003AD3510 - Abaste. Corporativos | B97: =IFERROR(SUBSTITUTE(TRIM(LEFT(A97,FIND("-",A97)-1)),"AMSA",""),"") -> 1003AD3510 | C97: =IFERROR(_xlfn.XLOOKUP(B97,'CECOS Corporativos'!$D:$D,'CECOS Corporativos'!$E:$E,""),"") -> Gerencia de Abastecimiento Corporativo | D97: =IFERROR(_xlfn.XLOOKUP(B97,'CECOS Corporativos'!$D:$D,'CECOS Corporativos'!$J:$J,""),"") -> VP Finanzas | E97: =_xll.EPMOlapMemberO("[CLACO].[PARENTH7].[AMSAENTRENAMI]","","Entrenamiento","","000") -> Entrenamiento | F97: =IFERROR(TRIM(LEFT(G97,FIND("-",G97)-1)),"") -> N1003AD350 | G97: N1003AD350 - Administración y Fin | H97: =IFERROR(_xlfn.XLOOKUP(F97,'CECOS Corporativos'!$K:$K,'CECOS Corporativos'!$D:$D,""),"") | J97: 3834 | K97: =J97-I97 -> 3834 | L97: 612 | M97: 2611 | N97: =M97-L97 -> 1999 | Q97: =P97-O97 -> 0 | R97: 21137.96 | S97: 22791.15 | T97: =S97-R97 -> 1653.19
A98: =_xll.EPMOlapMemberO("[CECO].[PARENTH3].[AMSA1003AD3510]","","AMSA1003AD3510 - Abaste. Corporativos","","000") -> AMSA1003AD3510 - Abaste. Corporativos | B98: =IFERROR(SUBSTITUTE(TRIM(LEFT(A98,FIND("-",A98)-1)),"AMSA",""),"") -> 1003AD3510 | C98: =IFERROR(_xlfn.XLOOKUP(B98,'CECOS Corporativos'!$D:$D,'CECOS Corporativos'!$E:$E,""),"") -> Gerencia de Abastecimiento Corporativo | D98: =IFERROR(_xlfn.XLOOKUP(B98,'CECOS Corporativos'!$D:$D,'CECOS Corporativos'!$J:$J,""),"") -> VP Finanzas | E98: =_xll.EPMOlapMemberO("[CLACO].[PARENTH7].[AMSAASESORIAS]","","Asesorías y Consulto","","000") -> Asesorías y Consulto | F98: =IFERROR(TRIM(LEFT(G98,FIND("-",G98)-1)),"") -> N1003AD350 | G98: N1003AD350 - Administración y Fin | H98: =IFERROR(_xlfn.XLOOKUP(F98,'CECOS Corporativos'!$K:$K,'CECOS Corporativos'!$D:$D,""),"") | I98: 1881.76 | J98: 5142 | K98: =J98-I98 -> 3260.24 | L98: 3857 | M98: 30958 | N98: =M98-L98 -> 27101 | O98: 36965.03 | P98: 3012 | Q98: =P98-O98 -> -33953.03 | R98: 0 | T98: =S98-R98 -> 0
A99: =_xll.EPMOlapMemberO("[CECO].[PARENTH3].[AMSA1003AD3510]","","AMSA1003AD3510 - Abaste. Corporativos","","000") -> AMSA1003AD3510 - Abaste. Corporativos | B99: =IFERROR(SUBSTITUTE(TRIM(LEFT(A99,FIND("-",A99)-1)),"AMSA",""),"") -> 1003AD3510 | C99: =IFERROR(_xlfn.XLOOKUP(B99,'CECOS Corporativos'!$D:$D,'CECOS Corporativos'!$E:$E,""),"") -> Gerencia de Abastecimiento Corporativo | D99: =IFERROR(_xlfn.XLOOKUP(B99,'CECOS Corporativos'!$D:$D,'CECOS Corporativos'!$J:$J,""),"") -> VP Finanzas | E99: =_xll.EPMOlapMemberO("[CLACO].[PARENTH7].[AMSASERVICIOS]","","Servicios","","000") -> Servicios | F99: =IFERROR(TRIM(LEFT(G99,FIND("-",G99)-1)),"") -> N1003AD350 | G99: N1003AD350 - Administración y Fin | H99: =IFERROR(_xlfn.XLOOKUP(F99,'CECOS Corporativos'!$K:$K,'CECOS Corporativos'!$D:$D,""),"") | I99: 131827.18 | J99: 281578 | K99: =J99-I99 -> 149750.82 | L99: 169903.6 | M99: 205785 | N99: =M99-L99 -> 35881.4 | O99: 57462.7 | P99: 156912 | Q99: =P99-O99 -> 99449.3 | R99: 76612.75 | S99: 161934.87 | T99: =S99-R99 -> 85322.12
A100: =_xll.EPMOlapMemberO("[CECO].[PARENTH3].[AMSA1003AD3510]","","AMSA1003AD3510 - Abaste. Corporativos","","000") -> AMSA1003AD3510 - Abaste. Corporativos | B100: =IFERROR(SUBSTITUTE(TRIM(LEFT(A100,FIND("-",A100)-1)),"AMSA",""),"") -> 1003AD3510 | C100: =IFERROR(_xlfn.XLOOKUP(B100,'CECOS Corporativos'!$D:$D,'CECOS Corporativos'!$E:$E,""),"") -> Gerencia de Abastecimiento Corporativo | D100: =IFERROR(_xlfn.XLOOKUP(B100,'CECOS Corporativos'!$D:$D,'CECOS Corporativos'!$J:$J,""),"") -> VP Finanzas | E100: =_xll.EPMOlapMemberO("[CLACO].[PARENTH7].[AMSAINFORMATIC]","","Informática y Comuni","","000") -> Informática y Comuni | F100: =IFERROR(TRIM(LEFT(G100,FIND("-",G100)-1)),"") -> N1003AD350 | G100: N1003AD350 - Administración y Fin | H100: =IFERROR(_xlfn.XLOOKUP(F100,'CECOS Corporativos'!$K:$K,'CECOS Corporativos'!$D:$D,""),"") | I100: 25647.27 | K100: =J100-I100 -> -25647.27 | L100: 74087.45 | M100: 92181 | N100: =M100-L100 -> 18093.55 | O100: 109612.59 | P100: 79128 | Q100: =P100-O100 -> -30484.59 | R100: 93322.99 | S100: 76171.5 | T100: =S100-R100 -> -17151.49
A101: =_xll.EPMOlapMemberO("[CECO].[PARENTH3].[AMSA1003AD3510]","","AMSA1003AD3510 - Abaste. Corporativos","","000") -> AMSA1003AD3510 - Abaste. Corporativos | B101: =IFERROR(SUBSTITUTE(TRIM(LEFT(A101,FIND("-",A101)-1)),"AMSA",""),"") -> 1003AD3510 | C101: =IFERROR(_xlfn.XLOOKUP(B101,'CECOS Corporativos'!$D:$D,'CECOS Corporativos'!$E:$E,""),"") -> Gerencia de Abastecimiento Corporativo | D101: =IFERROR(_xlfn.XLOOKUP(B101,'CECOS Corporativos'!$D:$D,'CECOS Corporativos'!$J:$J,""),"") -> VP Finanzas | E101: =_xll.EPMOlapMemberO("[CLACO].[PARENTH7].[AMSAG_VIAJES]","","Gastos de Viajes","","000") -> Gastos de Viajes | F101: =IFERROR(TRIM(LEFT(G101,FIND("-",G101)-1)),"") -> N1003AD350 | G101: N1003AD350 - Administración y Fin | H101: =IFERROR(_xlfn.XLOOKUP(F101,'CECOS Corporativos'!$K:$K,'CECOS Corporativos'!$D:$D,""),"") | K101: =J101-I101 -> 0 | L101: 3750 | N101: =M101-L101 -> -3750 | O101: 0 | Q101: =P101-O101 -> 0 | T101: =S101-R101 -> 0
A102: =_xll.EPMOlapMemberO("[CECO].[PARENTH3].[AMSA1003AD3510]","","AMSA1003AD3510 - Abaste. Corporativos","","000") -> AMSA1003AD3510 - Abaste. Corporativos | B102: =IFERROR(SUBSTITUTE(TRIM(LEFT(A102,FIND("-",A102)-1)),"AMSA",""),"") -> 1003AD3510 | C102: =IFERROR(_xlfn.XLOOKUP(B102,'CECOS Corporativos'!$D:$D,'CECOS Corporativos'!$E:$E,""),"") -> Gerencia de Abastecimiento Corporativo | D102: =IFERROR(_xlfn.XLOOKUP(B102,'CECOS Corporativos'!$D:$D,'CECOS Corporativos'!$J:$J,""),"") -> VP Finanzas | E102: =_xll.EPMOlapMemberO("[CLACO].[PARENTH7].[AMSAGGENERALES.2]","","Otros Gastos","","000") -> Otros Gastos | F102: =IFERROR(TRIM(LEFT(G102,FIND("-",G102)-1)),"") -> N1003AD350 | G102: N1003AD350 - Administración y Fin | H102: =IFERROR(_xlfn.XLOOKUP(F102,'CECOS Corporativos'!$K:$K,'CECOS Corporativos'!$D:$D,""),"") | K102: =J102-I102 -> 0 | L102: 561 | N102: =M102-L102 -> -561 | Q102: =P102-O102 -> 0 | T102: =S102-R102 -> 0
A103: =_xll.EPMOlapMemberO("[CECO].[PARENTH3].[AMSA1003AD3510]","","AMSA1003AD3510 - Abaste. Corporativos","","000") -> AMSA1003AD3510 - Abaste. Corporativos | B103: =IFERROR(SUBSTITUTE(TRIM(LEFT(A103,FIND("-",A103)-1)),"AMSA",""),"") -> 1003AD3510 | C103: =IFERROR(_xlfn.XLOOKUP(B103,'CECOS Corporativos'!$D:$D,'CECOS Corporativos'!$E:$E,""),"") -> Gerencia de Abastecimiento Corporativo | D103: =IFERROR(_xlfn.XLOOKUP(B103,'CECOS Corporativos'!$D:$D,'CECOS Corporativos'!$J:$J,""),"") -> VP Finanzas | E103: =_xll.EPMOlapMemberO("[CLACO].[PARENTH7].[AMSASERV_CORP]","","Servicios Corporativ","","000") -> Servicios Corporativ | F103: =IFERROR(TRIM(LEFT(G103,FIND("-",G103)-1)),"") -> N1003AD350 | G103: N1003AD350 - Administración y Fin | H103: =IFERROR(_xlfn.XLOOKUP(F103,'CECOS Corporativos'!$K:$K,'CECOS Corporativos'!$D:$D,""),"") | I103: 636176.75 | J103: 626101 | K103: =J103-I103 -> -10075.75 | L103: 674434.84 | M103: 612220 | N103: =M103-L103 -> -62214.84 | O103: 76317.85 | Q103: =P103-O103 -> -76317.85 | R103: 0 | T103: =S103-R103 -> 0
...

Sheet CEN
A1: {=_xll.EPMDimensionOverrideRange("000","CECO",CECOS!$B$2:$B$128)} -> Expansión de CECO sobrescrita
A2: =_xll.EPMOlapMemberO("[CEBE].[PARENTH1].[JE-]","","Gr Antofagasta Miner","","000") -> Gr Antofagasta Miner
A4: =_xll.EPMOlapMemberO("[ENTITY].[PARENTH1].[1002]","","1002 - Minera Centinela","","000") -> 1002 - Minera Centinela
I7: =_xll.EPMOlapMemberO("[TIME].[PARENTH1].[2022.TOTAL]","","2022.TOTAL","","000") -> 2022.TOTAL | L7: =_xll.EPMOlapMemberO("[TIME].[PARENTH1].[2023.TOTAL]","","2023.TOTAL","","000") -> 2023.TOTAL | O7: =_xll.EPMOlapMemberO("[TIME].[PARENTH1].[2024.TOTAL]","","2024.TOTAL","","000") -> 2024.TOTAL | R7: =_xll.EPMOlapMemberO("[TIME].[PARENTH1].[2025.TOTAL]","","2025.TOTAL","","000") -> 2025.TOTAL
B8: CECO Código | C8: CECO | D8: VP | E8: Item Relevante | F8: Nodo 3 | G8: CeCo Padre | H8: =_xll.EPMOlapMemberO("[CATEGORY].[].[REAL]","","Real - Real","","000") -> #NAME? | I8: =_xll.EPMOlapMemberO("[CATEGORY].[].[PLAN]","","Plan - Plan","","000") -> #NAME? | J8: =_xll.FPMXLClient.TechnicalCategory.EPMLocalMember("Var","001","000") -> Var | K8: =_xll.EPMOlapMemberO("[CATEGORY].[].[REAL]","","Real - Real","","000") -> #NAME? | L8: =_xll.EPMOlapMemberO("[CATEGORY].[].[PLAN]","","Plan - Plan","","000") -> #NAME? | M8: =_xll.FPMXLClient.TechnicalCategory.EPMLocalMember("Var","001","000") -> Var | N8: =_xll.EPMOlapMemberO("[CATEGORY].[].[REAL]","","Real - Real","","000") -> #NAME? | O8: =_xll.EPMOlapMemberO("[CATEGORY].[].[PLAN]","","Plan - Plan","","000") -> #NAME? | P8: =_xll.FPMXLClient.TechnicalCategory.EPMLocalMember("Var","001","000") -> Var | Q8: =_xll.EPMOlapMemberO("[CATEGORY].[].[REAL]","","Real - Real","","000") -> #NAME? | R8: =_xll.EPMOlapMemberO("[CATEGORY].[].[PLAN]","","Plan - Plan","","000") -> #NAME? | S8: =_xll.FPMXLClient.TechnicalCategory.EPMLocalMember("Var","001","000") -> Var
A9: =_xll.EPMOlapMemberO("[CECO].[PARENTH3].[AMSA1002AD0507]","","AMSA1002AD0507 - VPACS Corporativo","","000") -> AMSA1002AD0507 - VPACS Corporativo | B9: =IFERROR(SUBSTITUTE(TRIM(LEFT(A9,FIND("-",A9)-1)),"AMSA",""),"") -> 1002AD0507 | C9: =IFERROR(_xlfn.XLOOKUP(B9,'CECOS Corporativos'!$D:$D,'CECOS Corporativos'!$E:$E,""),"") -> VPACS Corporativo (HH Corporativo) | D9: =IFERROR(_xlfn.XLOOKUP(B9,'CECOS Corporativos'!$D:$D,'CECOS Corporativos'!$J:$J,""),"") -> VP Asuntos Corporativos | E9: =_xll.EPMOlapMemberO("[CLACO].[PARENTH7].[AMSASERVICIOS]","","Servicios","","000") -> Servicios | F9: =IFERROR(TRIM(LEFT(G9,FIND("-",G9)-1)),"") -> N100200500 | G9: N100200500 - Centinela No Operaci | H9: =IFERROR(_xlfn.XLOOKUP(F9,'CECOS Corporativos'!$K:$K,'CECOS Corporativos'!$D:$D,""),"") -> 1002AD4503 | K9: =J9-I9 -> 0 | N9: =M9-L9 -> 0 | Q9: =P9-O9 -> 0 | R9: 56088 | T9: =S9-R9 -> -56088
A10: =_xll.EPMOlapMemberO("[CECO].[PARENTH3].[AMSA1002AD0507]","","AMSA1002AD0507 - VPACS Corporativo","","000") -> AMSA1002AD0507 - VPACS Corporativo | B10: =IFERROR(SUBSTITUTE(TRIM(LEFT(A10,FIND("-",A10)-1)),"AMSA",""),"") -> 1002AD0507 | C10: =IFERROR(_xlfn.XLOOKUP(B10,'CECOS Corporativos'!$D:$D,'CECOS Corporativos'!$E:$E,""),"") -> VPACS Corporativo (HH Corporativo) | D10: =IFERROR(_xlfn.XLOOKUP(B10,'CECOS Corporativos'!$D:$D,'CECOS Corporativos'!$J:$J,""),"") -> VP Asuntos Corporativos | E10: =_xll.EPMOlapMemberO("[CLACO].[PARENTH7].[AMSASERV_CORP]","","Servicios Corporativ","","000") -> Servicios Corporativ | F10: =IFERROR(TRIM(LEFT(G10,FIND("-",G10)-1)),"") -> N100200500 | G10: N100200500 - Centinela No Operaci | H10: =IFERROR(_xlfn.XLOOKUP(F10,'CECOS Corporativos'!$K:$K,'CECOS Corporativos'!$D:$D,""),"") -> 1002AD4503 | K10: =J10-I10 -> 0 | N10: =M10-L10 -> 0 | O10: 1619199 | P10: 1794121 | Q10: =P10-O10 -> 174922 | R10: 1437573 | S10: 1508957.8 | T10: =S10-R10 -> 71384.79
A11: =_xll.EPMOlapMemberO("[CECO].[PARENTH3].[AMSA1002AD0510]","","AMSA1002AD0510 - Proyectos Corporativ","","000") -> AMSA1002AD0510 - Proyectos Corporativ | B11: =IFERROR(SUBSTITUTE(TRIM(LEFT(A11,FIND("-",A11)-1)),"AMSA",""),"") -> 1002AD0510 | C11: =IFERROR(_xlfn.XLOOKUP(B11,'CECOS Corporativos'!$D:$D,'CECOS Corporativos'!$E:$E,""),"") -> Proyectos Corporativo (HH Corporativo) | D11: =IFERROR(_xlfn.XLOOKUP(B11,'CECOS Corporativos'!$D:$D,'CECOS Corporativos'!$J:$J,""),"") -> VP Proyectos | E11: =_xll.EPMOlapMemberO("[CLACO].[PARENTH7].[AMSASERV_CORP]","","Servicios Corporativ","","000") -> Servicios Corporativ | F11: =IFERROR(TRIM(LEFT(G11,FIND("-",G11)-1)),"") -> N100200500 | G11: N100200500 - Centinela No Operaci | H11: =IFERROR(_xlfn.XLOOKUP(F11,'CECOS Corporativos'!$K:$K,'CECOS Corporativos'!$D:$D,""),"") -> 1002AD4503 | K11: =J11-I11 -> 0 | N11: =M11-L11 -> 0 | O11: 956728 | P11: 1060081 | Q11: =P11-O11 -> 103353 | R11: 1676413 | S11: 1759660.8 | T11: =S11-R11 -> 83247.83
A12: =_xll.EPMOlapMemberO("[CECO].[PARENTH3].[AMSA1002AD4503]","","AMSA1002AD4503 - Asunt Publ y Comunid","","000") -> AMSA1002AD4503 - Asunt Publ y Comunid | B12: =IFERROR(SUBSTITUTE(TRIM(LEFT(A12,FIND("-",A12)-1)),"AMSA",""),"") -> 1002AD4503 | C12: =IFERROR(_xlfn.XLOOKUP(B12,'CECOS Corporativos'!$D:$D,'CECOS Corporativos'!$E:$E,""),"") -> Asuntos Públicos y Comunidades | D12: =IFERROR(_xlfn.XLOOKUP(B12,'CECOS Corporativos'!$D:$D,'CECOS Corporativos'!$J:$J,""),"") -> VP Asuntos Corporativos | E12: =_xll.EPMOlapMemberO("[CLACO].[PARENTH7].[AMSAMAT_Y_REP.2]","","Materiales y repuest","","000") -> Materiales y repuest | F12: =IFERROR(TRIM(LEFT(G12,FIND("-",G12)-1)),"") -> N100200500 | G12: N100200500 - Centinela No Operaci | H12: =IFERROR(_xlfn.XLOOKUP(F12,'CECOS Corporativos'!$K:$K,'CECOS Corporativos'!$D:$D,""),"") -> 1002AD4503 | I12: 6099.19 | K12: =J12-I12 -> -6099.19 | L12: 411.8 | N12: =M12-L12 -> -411.8 | O12: 30952.66 | Q12: =P12-O12 -> -30952.66 | R12: 3866.85 | T12: =S12-R12 -> -3866.85
A13: =_xll.EPMOlapMemberO("[CECO].[PARENTH3].[AMSA1002AD4503]","","AMSA1002AD4503 - Asunt Publ y Comunid","","000") -> AMSA1002AD4503 - Asunt Publ y Comunid | B13: =IFERROR(SUBSTITUTE(TRIM(LEFT(A13,FIND("-",A13)-1)),"AMSA",""),"") -> 1002AD4503 | C13: =IFERROR(_xlfn.XLOOKUP(B13,'CECOS Corporativos'!$D:$D,'CECOS Corporativos'!$E:$E,""),"") -> Asuntos Públicos y Comunidades | D13: =IFERROR(_xlfn.XLOOKUP(B13,'CECOS Corporativos'!$D:$D,'CECOS Corporativos'!$J:$J,""),"") -> VP Asuntos Corporativos | E13: =_xll.EPMOlapMemberO("[CLACO].[PARENTH7].[AMSAADM_PERSON]","","Administración Perso","","000") -> Administración Perso | F13: =IFERROR(TRIM(LEFT(G13,FIND("-",G13)-1)),"") -> N100200500 | G13: N100200500 - Centinela No Operaci | H13: =IFERROR(_xlfn.XLOOKUP(F13,'CECOS Corporativos'!$K:$K,'CECOS Corporativos'!$D:$D,""),"") -> 1002AD4503 | I13: 16184.98 | K13: =J13-I13 -> -16184.98 | N13: =M13-L13 -> 0 | P13: 6020 | Q13: =P13-O13 -> 6020 | T13: =S13-R13 -> 0
A14: =_xll.EPMOlapMemberO("[CECO].[PARENTH3].[AMSA1002AD4503]","","AMSA1002AD4503 - Asunt Publ y Comunid","","000") -> AMSA1002AD4503 - Asunt Publ y Comunid | B14: =IFERROR(SUBSTITUTE(TRIM(LEFT(A14,FIND("-",A14)-1)),"AMSA",""),"") -> 1002AD4503 | C14: =IFERROR(_xlfn.XLOOKUP(B14,'CECOS Corporativos'!$D:$D,'CECOS Corporativos'!$E:$E,""),"") -> Asuntos Públicos y Comunidades | D14: =IFERROR(_xlfn.XLOOKUP(B14,'CECOS Corporativos'!$D:$D,'CECOS Corporativos'!$J:$J,""),"") -> VP Asuntos Corporativos | E14: =_xll.EPMOlapMemberO("[CLACO].[PARENTH7].[AMSAENTRENAMI]","","Entrenamiento","","000") -> Entrenamiento | F14: =IFERROR(TRIM(LEFT(G14,FIND("-",G14)-1)),"") -> N100200500 | G14: N100200500 - Centinela No Operaci | H14: =IFERROR(_xlfn.XLOOKUP(F14,'CECOS Corporativos'!$K:$K,'CECOS Corporativos'!$D:$D,""),"") -> 1002AD4503 | I14: 56972.36 | J14: 12805.59 | K14: =J14-I14 -> -44166.77 | L14: -28553.15 | N14: =M14-L14 -> 28553.15 | Q14: =P14-O14 -> 0 | R14: 7432.24 | T14: =S14-R14 -> -7432.24
A15: =_xll.EPMOlapMemberO("[CECO].[PARENTH3].[AMSA1002AD4503]","","AMSA1002AD4503 - Asunt Publ y Comunid","","000") -> AMSA1002AD4503 - Asunt Publ y Comunid | B15: =IFERROR(SUBSTITUTE(TRIM(LEFT(A15,FIND("-",A15)-1)),"AMSA",""),"") -> 1002AD4503 | C15: =IFERROR(_xlfn.XLOOKUP(B15,'CECOS Corporativos'!$D:$D,'CECOS Corporativos'!$E:$E,""),"") -> Asuntos Públicos y Comunidades | D15: =IFERROR(_xlfn.XLOOKUP(B15,'CECOS Corporativos'!$D:$D,'CECOS Corporativos'!$J:$J,""),"") -> VP Asuntos Corporativos | E15: =_xll.EPMOlapMemberO("[CLACO].[PARENTH7].[AMSAASESORIAS]","","Asesorías y Consulto","","000") -> Asesorías y Consulto | F15: =IFERROR(TRIM(LEFT(G15,FIND("-",G15)-1)),"") -> N100200500 | G15: N100200500 - Centinela No Operaci | H15: =IFERROR(_xlfn.XLOOKUP(F15,'CECOS Corporativos'!$K:$K,'CECOS Corporativos'!$D:$D,""),"") -> 1002AD4503 | I15: -133414.95 | J15: 249199.39 | K15: =J15-I15 -> 382614.34 | L15: 291807.59 | M15: 74825.01 | N15: =M15-L15 -> -216982.58 | O15: 195349.83 | Q15: =P15-O15 -> -195349.83 | R15: 198513.33 | S15: 92005.46 | T15: =S15-R15 -> -106507.87
A16: =_xll.EPMOlapMemberO("[CECO].[PARENTH3].[AMSA1002AD4503]","","AMSA1002AD4503 - Asunt Publ y Comunid","","000") -> AMSA1002AD4503 - Asunt Publ y Comunid | B16: =IFERROR(SUBSTITUTE(TRIM(LEFT(A16,FIND("-",A16)-1)),"AMSA",""),"") -> 1002AD4503 | C16: =IFERROR(_xlfn.XLOOKUP(B16,'CECOS Corporativos'!$D:$D,'CECOS Corporativos'!$E:$E,""),"") -> Asuntos Públicos y Comunidades | D16: =IFERROR(_xlfn.XLOOKUP(B16,'CECOS Corporativos'!$D:$D,'CECOS Corporativos'!$J:$J,""),"") -> VP Asuntos Corporativos | E16: =_xll.EPMOlapMemberO("[CLACO].[PARENTH7].[AMSAARRIENDOS]","","Arriendos","","000") -> Arriendos | F16: =IFERROR(TRIM(LEFT(G16,FIND("-",G16)-1)),"") -> N100200500 | G16: N100200500 - Centinela No Operaci | H16: =IFERROR(_xlfn.XLOOKUP(F16,'CECOS Corporativos'!$K:$K,'CECOS Corporativos'!$D:$D,""),"") -> 1002AD4503 | I16: 3702.07 | J16: 10371.26 | K16: =J16-I16 -> 6669.19 | N16: =M16-L16 -> 0 | Q16: =P16-O16 -> 0 | T16: =S16-R16 -> 0
A17: =_xll.EPMOlapMemberO("[CECO].[PARENTH3].[AMSA1002AD4503]","","AMSA1002AD4503 - Asunt Publ y Comunid","","000") -> AMSA1002AD4503 - Asunt Publ y Comunid | B17: =IFERROR(SUBSTITUTE(TRIM(LEFT(A17,FIND("-",A17)-1)),"AMSA",""),"") -> 1002AD4503 | C17: =IFERROR(_xlfn.XLOOKUP(B17,'CECOS Corporativos'!$D:$D,'CECOS Corporativos'!$E:$E,""),"") -> Asuntos Públicos y Comunidades | D17: =IFERROR(_xlfn.XLOOKUP(B17,'CECOS Corporativos'!$D:$D,'CECOS Corporativos'!$J:$J,""),"") -> VP Asuntos Corporativos | E17: =_xll.EPMOlapMemberO("[CLACO].[PARENTH7].[AMSASERVICIOS]","","Servicios","","000") -> Servicios | F17: =IFERROR(TRIM(LEFT(G17,FIND("-",G17)-1)),"") -> N100200500 | G17: N100200500 - Centinela No Operaci | H17: =IFERROR(_xlfn.XLOOKUP(F17,'CECOS Corporativos'!$K:$K,'CECOS Corporativos'!$D:$D,""),"") -> 1002AD4503 | I17: 501737.25 | J17: 596701.4 | K17: =J17-I17 -> 94964.15 | L17: 726458.72 | M17: 295618.97 | N17: =M17-L17 -> -430839.75 | O17: 411520.85 | P17: 269054 | Q17: =P17-O17 -> -142466.85 | R17: -253680.99 | S17: 113015.86 | T17: =S17-R17 -> 366696.85
A18: =_xll.EPMOlapMemberO("[CECO].[PARENTH3].[AMSA1002AD4503]","","AMSA1002AD4503 - Asunt Publ y Comunid","","000") -> AMSA1002AD4503 - Asunt Publ y Comunid | B18: =IFERROR(SUBSTITUTE(TRIM(LEFT(A18,FIND("-",A18)-1)),"AMSA",""),"") -> 1002AD4503 | C18: =IFERROR(_xlfn.XLOOKUP(B18,'CECOS Corporativos'!$D:$D,'CECOS Corporativos'!$E:$E,""),"") -> Asuntos Públicos y Comunidades | D18: =IFERROR(_xlfn.XLOOKUP(B18,'CECOS Corporativos'!$D:$D,'CECOS Corporativos'!$J:$J,""),"") -> VP Asuntos Corporativos | E18: =_xll.EPMOlapMemberO("[CLACO].[PARENTH7].[AMSAINFORMATIC]","","Informática y Comuni","","000") -> Informática y Comuni | F18: =IFERROR(TRIM(LEFT(G18,FIND("-",G18)-1)),"") -> N100200500 | G18: N100200500 - Centinela No Operaci | H18: =IFERROR(_xlfn.XLOOKUP(F18,'CECOS Corporativos'!$K:$K,'CECOS Corporativos'!$D:$D,""),"") -> 1002AD4503 | I18: -4887.59 | J18: 25628.9 | K18: =J18-I18 -> 30516.49 | L18: 14874.66 | N18: =M18-L18 -> -14874.66 | O18: 113.31 | Q18: =P18-O18 -> -113.31 | R18: 45 | T18: =S18-R18 -> -45
A19: =_xll.EPMOlapMemberO("[CECO].[PARENTH3].[AMSA1002AD4503]","","AMSA1002AD4503 - Asunt Publ y Comunid","","000") -> AMSA1002AD4503 - Asunt Publ y Comunid | B19: =IFERROR(SUBSTITUTE(TRIM(LEFT(A19,FIND("-",A19)-1)),"AMSA",""),"") -> 1002AD4503 | C19: =IFERROR(_xlfn.XLOOKUP(B19,'CECOS Corporativos'!$D:$D,'CECOS Corporativos'!$E:$E,""),"") -> Asuntos Públicos y Comunidades | D19: =IFERROR(_xlfn.XLOOKUP(B19,'CECOS Corporativos'!$D:$D,'CECOS Corporativos'!$J:$J,""),"") -> VP Asuntos Corporativos | E19: =_xll.EPMOlapMemberO("[CLACO].[PARENTH7].[AMSAG_VIAJES]","","Gastos de Viajes","","000") -> Gastos de Viajes | F19: =IFERROR(TRIM(LEFT(G19,FIND("-",G19)-1)),"") -> N100200500 | G19: N100200500 - Centinela No Operaci | H19: =IFERROR(_xlfn.XLOOKUP(F19,'CECOS Corporativos'!$K:$K,'CECOS Corporativos'!$D:$D,""),"") -> 1002AD4503 | I19: 160310 | J19: 19629.73 | K19: =J19-I19 -> -140680.27 | L19: 11554.01 | N19: =M19-L19 -> -11554.01 | O19: 2482.34 | Q19: =P19-O19 -> -2482.34 | R19: 0 | T19: =S19-R19 -> 0
A20: =_xll.EPMOlapMemberO("[CECO].[PARENTH3].[AMSA1002AD4503]","","AMSA1002AD4503 - Asunt Publ y Comunid","","000") -> AMSA1002AD4503 - Asunt Publ y Comunid | B20: =IFERROR(SUBSTITUTE(TRIM(LEFT(A20,FIND("-",A20)-1)),"AMSA",""),"") -> 1002AD4503 | C20: =IFERROR(_xlfn.XLOOKUP(B20,'CECOS Corporativos'!$D:$D,'CECOS Corporativos'!$E:$E,""),"") -> Asuntos Públicos y Comunidades | D20: =IFERROR(_xlfn.XLOOKUP(B20,'CECOS Corporativos'!$D:$D,'CECOS Corporativos'!$J:$J,""),"") -> VP Asuntos Corporativos | E20: =_xll.EPMOlapMemberO("[CLACO].[PARENTH7].[AMSASEGUROS]","","Seguros","","000") -> Seguros | F20: =IFERROR(TRIM(LEFT(G20,FIND("-",G20)-1)),"") -> N100200500 | G20: N100200500 - Centinela No Operaci | H20: =IFERROR(_xlfn.XLOOKUP(F20,'CECOS Corporativos'!$K:$K,'CECOS Corporativos'!$D:$D,""),"") -> 1002AD4503 | K20: =J20-I20 -> 0 | L20: 3216.81 | N20: =M20-L20 -> -3216.81 | O20: 0 | Q20: =P20-O20 -> 0 | T20: =S20-R20 -> 0
A21: =_xll.EPMOlapMemberO("[CECO].[PARENTH3].[AMSA1002AD4503]","","AMSA1002AD4503 - Asunt Publ y Comunid","","000") -> AMSA1002AD4503 - Asunt Publ y Comunid | B21: =IFERROR(SUBSTITUTE(TRIM(LEFT(A21,FIND("-",A21)-1)),"AMSA",""),"") -> 1002AD4503 | C21: =IFERROR(_xlfn.XLOOKUP(B21,'CECOS Corporativos'!$D:$D,'CECOS Corporativos'!$E:$E,""),"") -> Asuntos Públicos y Comunidades | D21: =IFERROR(_xlfn.XLOOKUP(B21,'CECOS Corporativos'!$D:$D,'CECOS Corporativos'!$J:$J,""),"") -> VP Asuntos Corporativos | E21: =_xll.EPMOlapMemberO("[CLACO].[PARENTH7].[AMSAIMP_PATEN]","","Impuestos / Patentes","","000") -> Impuestos / Patentes | F21: =IFERROR(TRIM(LEFT(G21,FIND("-",G21)-1)),"") -> N100200500 | G21: N100200500 - Centinela No Operaci | H21: =IFERROR(_xlfn.XLOOKUP(F21,'CECOS Corporativos'!$K:$K,'CECOS Corporativos'!$D:$D,""),"") -> 1002AD4503 | J21: 19125.53 | K21: =J21-I21 -> 19125.53 | N21: =M21-L21 -> 0 | Q21: =P21-O21 -> 0 | T21: =S21-R21 -> 0
A22: =_xll.EPMOlapMemberO("[CECO].[PARENTH3].[AMSA1002AD4503]","","AMSA1002AD4503 - Asunt Publ y Comunid","","000") -> AMSA1002AD4503 - Asunt Publ y Comunid | B22: =IFERROR(SUBSTITUTE(TRIM(LEFT(A22,FIND("-",A22)-1)),"AMSA",""),"") -> 1002AD4503 | C22: =IFERROR(_xlfn.XLOOKUP(B22,'CECOS Corporativos'!$D:$D,'CECOS Corporativos'!$E:$E,""),"") -> Asuntos Públicos y Comunidades | D22: =IFERROR(_xlfn.XLOOKUP(B22,'CECOS Corporativos'!$D:$D,'CECOS Corporativos'!$J:$J,""),"") -> VP Asuntos Corporativos | E22: =_xll.EPMOlapMemberO("[CLACO].[PARENTH7].[AMSAGGENERALES.2]","","Otros Gastos","","000") -> Otros Gastos | F22: =IFERROR(TRIM(LEFT(G22,FIND("-",G22)-1)),"") -> N100200500 | G22: N100200500 - Centinela No Operaci | H22: =IFERROR(_xlfn.XLOOKUP(F22,'CECOS Corporativos'!$K:$K,'CECOS Corporativos'!$D:$D,""),"") -> 1002AD4503 | I22: 359972.61 | J22: 228180.37 | K22: =J22-I22 -> -131792.24 | L22: 83680.15 | M22: 6872.64 | N22: =M22-L22 -> -76807.51 | O22: 174659.67 | P22: 109012 | Q22: =P22-O22 -> -65647.67 | R22: 45270.65 | S22: 73273.34 | T22: =S22-R22 -> 28002.69
A23: =_xll.EPMOlapMemberO("[CECO].[PARENTH3].[AMSA1002AD4503]","","AMSA1002AD4503 - Asunt Publ y Comunid","","000") -> AMSA1002AD4503 - Asunt Publ y Comunid | B23: =IFERROR(SUBSTITUTE(TRIM(LEFT(A23,FIND("-",A23)-1)),"AMSA",""),"") -> 1002AD4503 | C23: =IFERROR(_xlfn.XLOOKUP(B23,'CECOS Corporativos'!$D:$D,'CECOS Corporativos'!$E:$E,""),"") -> Asuntos Públicos y Comunidades | D23: =IFERROR(_xlfn.XLOOKUP(B23,'CECOS Corporativos'!$D:$D,'CECOS Corporativos'!$J:$J,""),"") -> VP Asuntos Corporativos | E23: =_xll.EPMOlapMemberO("[CLACO].[PARENTH7].[AMSALIQUIDACIO.SEC]","","Liquidación Interna","","000") -> Liquidación Interna | F23: =IFERROR(TRIM(LEFT(G23,FIND("-",G23)-1)),"") -> N100200500 | G23: N100200500 - Centinela No Operaci | H23: =IFERROR(_xlfn.XLOOKUP(F23,'CECOS Corporativos'!$K:$K,'CECOS Corporativos'!$D:$D,""),"") -> 1002AD4503 | K23: =J23-I23 -> 0 | N23: =M23-L23 -> 0 | Q23: =P23-O23 -> 0 | R23: 79731.59 | T23: =S23-R23 -> -79731.59
A24: =_xll.EPMOlapMemberO("[CECO].[PARENTH3].[AMSA1002AD4503]","","AMSA1002AD4503 - Asunt Publ y Comunid","","000") -> AMSA1002AD4503 - Asunt Publ y Comunid | B24: =IFERROR(SUBSTITUTE(TRIM(LEFT(A24,FIND("-",A24)-1)),"AMSA",""),"") -> 1002AD4503 | C24: =IFERROR(_xlfn.XLOOKUP(B24,'CECOS Corporativos'!$D:$D,'CECOS Corporativos'!$E:$E,""),"") -> Asuntos Públicos y Comunidades | D24: =IFERROR(_xlfn.XLOOKUP(B24,'CECOS Corporativos'!$D:$D,'CECOS Corporativos'!$J:$J,""),"") -> VP Asuntos Corporativos | E24: =_xll.EPMOlapMemberO("[CLACO].[PARENTH7].[AMSASERV_CORP]","","Servicios Corporativ","","000") -> Servicios Corporativ | F24: =IFERROR(TRIM(LEFT(G24,FIND("-",G24)-1)),"") -> N100200500 | G24: N100200500 - Centinela No Operaci | H24: =IFERROR(_xlfn.XLOOKUP(F24,'CECOS Corporativos'!$K:$K,'CECOS Corporativos'!$D:$D,""),"") -> 1002AD4503 | I24: 674324.87 | J24: 695156.69 | K24: =J24-I24 -> 20831.82 | L24: 1061140.6 | M24: 963261.93 | N24: =M24-L24 -> -97878.69 | O24: -0.62 | Q24: =P24-O24 -> 0.62 | T24: =S24-R24 -> 0
A25: =_xll.EPMOlapMemberO("[CECO].[PARENTH3].[AMSA1002AD4506]","","AMSA1002AD4506 - AAPP Corporativo","","000") -> AMSA1002AD4506 - AAPP Corporativo | B25: =IFERROR(SUBSTITUTE(TRIM(LEFT(A25,FIND("-",A25)-1)),"AMSA",""),"") -> 1002AD4506 | C25: =IFERROR(_xlfn.XLOOKUP(B25,'CECOS Corporativos'!$D:$D,'CECOS Corporativos'!$E:$E,""),"") -> AAPP Corporativo | D25: =IFERROR(_xlfn.XLOOKUP(B25,'CECOS Corporativos'!$D:$D,'CECOS Corporativos'!$J:$J,""),"") -> VP Asuntos Corporativos | E25: =_xll.EPMOlapMemberO("[CLACO].[PARENTH7].[AMSAASESORIAS]","","Asesorías y Consulto","","000") -> Asesorías y Consulto | F25: =IFERROR(TRIM(LEFT(G25,FIND("-",G25)-1)),"") -> N100200500 | G25: N100200500 - Centinela No Operaci | H25: =IFERROR(_xlfn.XLOOKUP(F25,'CECOS Corporativos'!$K:$K,'CECOS Corporativos'!$D:$D,""),"") -> 1002AD4503 | K25: =J25-I25 -> 0 | L25: 35378.77 | M25: 74155.03 | N25: =M25-L25 -> 38776.26 | O25: 77685.49 | P25: 62355 | Q25: =P25-O25 -> -15330.49 | R25: 74003.82 | S25: 60536.58 | T25: =S25-R25 -> -13467.24
A26: =_xll.EPMOlapMemberO("[CECO].[PARENTH3].[AMSA1002AD4506]","","AMSA1002AD4506 - AAPP Corporativo","","000") -> AMSA1002AD4506 - AAPP Corporativo | B26: =IFERROR(SUBSTITUTE(TRIM(LEFT(A26,FIND("-",A26)-1)),"AMSA",""),"") -> 1002AD4506 | C26: =IFERROR(_xlfn.XLOOKUP(B26,'CECOS Corporativos'!$D:$D,'CECOS Corporativos'!$E:$E,""),"") -> AAPP Corporativo | D26: =IFERROR(_xlfn.XLOOKUP(B26,'CECOS Corporativos'!$D:$D,'CECOS Corporativos'!$J:$J,""),"") -> VP Asuntos Corporativos | E26: =_xll.EPMOlapMemberO("[CLACO].[PARENTH7].[AMSASERVICIOS]","","Servicios","","000") -> Servicios | F26: =IFERROR(TRIM(LEFT(G26,FIND("-",G26)-1)),"") -> N100200500 | G26: N100200500 - Centinela No Operaci | H26: =IFERROR(_xlfn.XLOOKUP(F26,'CECOS Corporativos'!$K:$K,'CECOS Corporativos'!$D:$D,""),"") -> 1002AD4503 | K26: =J26-I26 -> 0 | L26: 29994.58 | M26: 66610.29 | N26: =M26-L26 -> 36615.71 | O26: 0 | Q26: =P26-O26 -> 0 | T26: =S26-R26 -> 0
A27: =_xll.EPMOlapMemberO("[CECO].[PARENTH3].[AMSA1002AD4506]","","AMSA1002AD4506 - AAPP Corporativo","","000") -> AMSA1002AD4506 - AAPP Corporativo | B27: =IFERROR(SUBSTITUTE(TRIM(LEFT(A27,FIND("-",A27)-1)),"AMSA",""),"") -> 1002AD4506 | C27: =IFERROR(_xlfn.XLOOKUP(B27,'CECOS Corporativos'!$D:$D,'CECOS Corporativos'!$E:$E,""),"") -> AAPP Corporativo | D27: =IFERROR(_xlfn.XLOOKUP(B27,'CECOS Corporativos'!$D:$D,'CECOS Corporativos'!$J:$J,""),"") -> VP Asuntos Corporativos | E27: =_xll.EPMOlapMemberO("[CLACO].[PARENTH7].[AMSAINFORMATIC]","","Informática y Comuni","","000") -> Informática y Comuni | F27: =IFERROR(TRIM(LEFT(G27,FIND("-",G27)-1)),"") -> N100200500 | G27: N100200500 - Centinela No Operaci | H27: =IFERROR(_xlfn.XLOOKUP(F27,'CECOS Corporativos'!$K:$K,'CECOS Corporativos'!$D:$D,""),"") -> 1002AD4503 | K27: =J27-I27 -> 0 | L27: 0 | M27: 4688.22 | N27: =M27-L27 -> 4688.22 | Q27: =P27-O27 -> 0 | T27: =S27-R27 -> 0
A28: =_xll.EPMOlapMemberO("[CECO].[PARENTH3].[AMSA1002AD4506]","","AMSA1002AD4506 - AAPP Corporativo","","000") -> AMSA1002AD4506 - AAPP Corporativo | B28: =IFERROR(SUBSTITUTE(TRIM(LEFT(A28,FIND("-",A28)-1)),"AMSA",""),"") -> 1002AD4506 | C28: =IFERROR(_xlfn.XLOOKUP(B28,'CECOS Corporativos'!$D:$D,'CECOS Corporativos'!$E:$E,""),"") -> AAPP Corporativo | D28: =IFERROR(_xlfn.XLOOKUP(B28,'CECOS Corporativos'!$D:$D,'CECOS Corporativos'!$J:$J,""),"") -> VP Asuntos Corporativos | E28: =_xll.EPMOlapMemberO("[CLACO].[PARENTH7].[AMSAG_VIAJES]","","Gastos de Viajes","","000") -> Gastos de Viajes | F28: =IFERROR(TRIM(LEFT(G28,FIND("-",G28)-1)),"") -> N100200500 | G28: N100200500 - Centinela No Operaci | H28: =IFERROR(_xlfn.XLOOKUP(F28,'CECOS Corporativos'!$K:$K,'CECOS Corporativos'!$D:$D,""),"") -> 1002AD4503 | K28: =J28-I28 -> 0 | L28: 137.79 | N28: =M28-L28 -> -137.79 | Q28: =P28-O28 -> 0 | R28: 76.71 | T28: =S28-R28 -> -76.71
A29: =_xll.EPMOlapMemberO("[CECO].[PARENTH3].[AMSA1002AD4506]","","AMSA1002AD4506 - AAPP Corporativo","","000") -> AMSA1002AD4506 - AAPP Corporativo | B29: =IFERROR(SUBSTITUTE(TRIM(LEFT(A29,FIND("-",A29)-1)),"AMSA",""),"") -> 1002AD4506 | C29: =IFERROR(_xlfn.XLOOKUP(B29,'CECOS Corporativos'!$D:$D,'CECOS Corporativos'!$E:$E,""),"") -> AAPP Corporativo | D29: =IFERROR(_xlfn.XLOOKUP(B29,'CECOS Corporativos'!$D:$D,'CECOS Corporativos'!$J:$J,""),"") -> VP Asuntos Corporativos | E29: =_xll.EPMOlapMemberO("[CLACO].[PARENTH7].[AMSAGGENERALES.2]","","Otros Gastos","","000") -> Otros Gastos | F29: =IFERROR(TRIM(LEFT(G29,FIND("-",G29)-1)),"") -> N100200500 | G29: N100200500 - Centinela No Operaci | H29: =IFERROR(_xlfn.XLOOKUP(F29,'CECOS Corporativos'!$K:$K,'CECOS Corporativos'!$D:$D,""),"") -> 1002AD4503 | K29: =J29-I29 -> 0 | L29: 87258.77 | M29: 86766.79 | N29: =M29-L29 -> -491.98 | O29: 755.32 | Q29: =P29-O29 -> -755.32 | R29: 12048.75 | S29: 21528.2 | T29: =S29-R29 -> 9479.45
A30: =_xll.EPMOlapMemberO("[CECO].[PARENTH3].[AMSA1002AD4507]","","AMSA1002AD4507 - Comunica Corporativo","","000") -> AMSA1002AD4507 - Comunica Corporativo | B30: =IFERROR(SUBSTITUTE(TRIM(LEFT(A30,FIND("-",A30)-1)),"AMSA",""),"") -> 1002AD4507 | C30: =IFERROR(_xlfn.XLOOKUP(B30,'CECOS Corporativos'!$D:$D,'CECOS Corporativos'!$E:$E,""),"") -> Comunicaciones Corporativo | D30: =IFERROR(_xlfn.XLOOKUP(B30,'CECOS Corporativos'!$D:$D,'CECOS Corporativos'!$J:$J,""),"") -> VP Asuntos Corporativos | E30: =_xll.EPMOlapMemberO("[CLACO].[PARENTH7].[AMSAASESORIAS]","","Asesorías y Consulto","","000") -> Asesorías y Consulto | F30: =IFERROR(TRIM(LEFT(G30,FIND("-",G30)-1)),"") -> N100200500 | G30: N100200500 - Centinela No Operaci | H30: =IFERROR(_xlfn.XLOOKUP(F30,'CECOS Corporativos'!$K:$K,'CECOS Corporativos'!$D:$D,""),"") -> 1002AD4503 | K30: =J30-I30 -> 0 | L30: 22211.97 | M30: 11850.89 | N30: =M30-L30 -> -10361.08 | O30: 40349.74 | P30: 21666 | Q30: =P30-O30 -> -18683.74 | R30: 1001.26 | T30: =S30-R30 -> -1001.26
A31: =_xll.EPMOlapMemberO("[CECO].[PARENTH3].[AMSA1002AD4507]","","AMSA1002AD4507 - Comunica Corporativo","","000") -> AMSA1002AD4507 - Comunica Corporativo | B31: =IFERROR(SUBSTITUTE(TRIM(LEFT(A31,FIND("-",A31)-1)),"AMSA",""),"") -> 1002AD4507 | C31: =IFERROR(_xlfn.XLOOKUP(B31,'CECOS Corporativos'!$D:$D,'CECOS Corporativos'!$E:$E,""),"") -> Comunicaciones Corporativo | D31: =IFERROR(_xlfn.XLOOKUP(B31,'CECOS Corporativos'!$D:$D,'CECOS Corporativos'!$J:$J,""),"") -> VP Asuntos Corporativos | E31: =_xll.EPMOlapMemberO("[CLACO].[PARENTH7].[AMSAINFORMATIC]","","Informática y Comuni","","000") -> Informática y Comuni | F31: =IFERROR(TRIM(LEFT(G31,FIND("-",G31)-1)),"") -> N100200500 | G31: N100200500 - Centinela No Operaci | H31: =IFERROR(_xlfn.XLOOKUP(F31,'CECOS Corporativos'!$K:$K,'CECOS Corporativos'!$D:$D,""),"") -> 1002AD4503 | K31: =J31-I31 -> 0 | M31: 34349.83 | N31: =M31-L31 -> 34349.83 | P31: 22220 | Q31: =P31-O31 -> 22220 | R31: 4848.66 | S31: 49388.64 | T31: =S31-R31 -> 44539.98
A32: =_xll.EPMOlapMemberO("[CECO].[PARENTH3].[AMSA1002AD4507]","","AMSA1002AD4507 - Comunica Corporativo","","000") -> AMSA1002AD4507 - Comunica Corporativo | B32: =IFERROR(SUBSTITUTE(TRIM(LEFT(A32,FIND("-",A32)-1)),"AMSA",""),"") -> 1002AD4507 | C32: =IFERROR(_xlfn.XLOOKUP(B32,'CECOS Corporativos'!$D:$D,'CECOS Corporativos'!$E:$E,""),"") -> Comunicaciones Corporativo | D32: =IFERROR(_xlfn.XLOOKUP(B32,'CECOS Corporativos'!$D:$D,'CECOS Corporativos'!$J:$J,""),"") -> VP Asuntos Corporativos | E32: =_xll.EPMOlapMemberO("[CLACO].[PARENTH7].[AMSAGGENERALES.2]","","Otros Gastos","","000") -> Otros Gastos | F32: =IFERROR(TRIM(LEFT(G32,FIND("-",G32)-1)),"") -> N100200500 | G32: N100200500 - Centinela No Operaci | H32: =IFERROR(_xlfn.XLOOKUP(F32,'CECOS Corporativos'!$K:$K,'CECOS Corporativos'!$D:$D,""),"") -> 1002AD4503 | K32: =J32-I32 -> 0 | M32: 55781.81 | N32: =M32-L32 -> 55781.81 | O32: 95677.2 | P32: 114820 | Q32: =P32-O32 -> 19142.8 | R32: 423094.47 | S32: 154757.55 | T32: =S32-R32 -> -268336.92
A33: =_xll.EPMOlapMemberO("[CECO].[PARENTH3].[AMSA1002AD4509]","","AMSA1002AD4509 - AAPP y RRII","","000") -> AMSA1002AD4509 - AAPP y RRII | B33: =IFERROR(SUBSTITUTE(TRIM(LEFT(A33,FIND("-",A33)-1)),"AMSA",""),"") -> 1002AD4509 | C33: =IFERROR(_xlfn.XLOOKUP(B33,'CECOS Corporativos'!$D:$D,'CECOS Corporativos'!$E:$E,""),"") -> AAPP y RRII | D33: =IFERROR(_xlfn.XLOOKUP(B33,'CECOS Corporativos'!$D:$D,'CECOS Corporativos'!$J:$J,""),"") -> VP Asuntos Corporativos | E33: =_xll.EPMOlapMemberO("[CLACO].[PARENTH7].[AMSASERVICIOS]","","Servicios","","000") -> Servicios | F33: =IFERROR(TRIM(LEFT(G33,FIND("-",G33)-1)),"") -> N100200500 | G33: N100200500 - Centinela No Operaci | H33: =IFERROR(_xlfn.XLOOKUP(F33,'CECOS Corporativos'!$K:$K,'CECOS Corporativos'!$D:$D,""),"") -> 1002AD4503 | K33: =J33-I33 -> 0 | M33: 34888.2 | N33: =M33-L33 -> 34888.2 | O33: 0 | P33: 101875 | Q33: =P33-O33 -> 101875 | R33: 1189.13 | S33: 4224.32 | T33: =S33-R33 -> 3035.19
A34: =_xll.EPMOlapMemberO("[CECO].[PARENTH3].[AMSA1002AD4509]","","AMSA1002AD4509 - AAPP y RRII","","000") -> AMSA1002AD4509 - AAPP y RRII | B34: =IFERROR(SUBSTITUTE(TRIM(LEFT(A34,FIND("-",A34)-1)),"AMSA",""),"") -> 1002AD4509 | C34: =IFERROR(_xlfn.XLOOKUP(B34,'CECOS Corporativos'!$D:$D,'CECOS Corporativos'!$E:$E,""),"") -> AAPP y RRII | D34: =IFERROR(_xlfn.XLOOKUP(B34,'CECOS Corporativos'!$D:$D,'CECOS Corporativos'!$J:$J,""),"") -> VP Asuntos Corporativos | E34: =_xll.EPMOlapMemberO("[CLACO].[PARENTH7].[AMSAINFORMATIC]","","Informática y Comuni","","000") -> Informática y Comuni | F34: =IFERROR(TRIM(LEFT(G34,FIND("-",G34)-1)),"") -> N100200500 | G34: N100200500 - Centinela No Operaci | H34: =IFERROR(_xlfn.XLOOKUP(F34,'CECOS Corporativos'!$K:$K,'CECOS Corporativos'!$D:$D,""),"") -> 1002AD4503 | K34: =J34-I34 -> 0 | N34: =M34-L34 -> 0 | O34: 813.11 | P34: 15144 | Q34: =P34-O34 -> 14330.89 | R34: -813.11 | T34: =S34-R34 -> 813.11
A35: =_xll.EPMOlapMemberO("[CECO].[PARENTH3].[AMSA1002AD4509]","","AMSA1002AD4509 - AAPP y RRII","","000") -> AMSA1002AD4509 - AAPP y RRII | B35: =IFERROR(SUBSTITUTE(TRIM(LEFT(A35,FIND("-",A35)-1)),"AMSA",""),"") -> 1002AD4509 | C35: =IFERROR(_xlfn.XLOOKUP(B35,'CECOS Corporativos'!$D:$D,'CECOS Corporativos'!$E:$E,""),"") -> AAPP y RRII | D35: =IFERROR(_xlfn.XLOOKUP(B35,'CECOS Corporativos'!$D:$D,'CECOS Corporativos'!$J:$J,""),"") -> VP Asuntos Corporativos | E35: =_xll.EPMOlapMemberO("[CLACO].[PARENTH7].[AMSAG_VIAJES]","","Gastos de Viajes","","000") -> Gastos de Viajes | F35: =IFERROR(TRIM(LEFT(G35,FIND("-",G35)-1)),"") -> N100200500 | G35: N100200500 - Centinela No Operaci | H35: =IFERROR(_xlfn.XLOOKUP(F35,'CECOS Corporativos'!$K:$K,'CECOS Corporativos'!$D:$D,""),"") -> 1002AD4503 | K35: =J35-I35 -> 0 | L35: 61.46 | N35: =M35-L35 -> -61.46 | Q35: =P35-O35 -> 0 | T35: =S35-R35 -> 0
A36: =_xll.EPMOlapMemberO("[CECO].[PARENTH3].[AMSA1002AD4509]","","AMSA1002AD4509 - AAPP y RRII","","000") -> AMSA1002AD4509 - AAPP y RRII | B36: =IFERROR(SUBSTITUTE(TRIM(LEFT(A36,FIND("-",A36)-1)),"AMSA",""),"") -> 1002AD4509 | C36: =IFERROR(_xlfn.XLOOKUP(B36,'CECOS Corporativos'!$D:$D,'CECOS Corporativos'!$E:$E,""),"") -> AAPP y RRII | D36: =IFERROR(_xlfn.XLOOKUP(B36,'CECOS Corporativos'!$D:$D,'CECOS Corporativos'!$J:$J,""),"") -> VP Asuntos Corporativos | E36: =_xll.EPMOlapMemberO("[CLACO].[PARENTH7].[AMSAGGENERALES.2]","","Otros Gastos","","000") -> Otros Gastos | F36: =IFERROR(TRIM(LEFT(G36,FIND("-",G36)-1)),"") -> N100200500 | G36: N100200500 - Centinela No Operaci | H36: =IFERROR(_xlfn.XLOOKUP(F36,'CECOS Corporativos'!$K:$K,'CECOS Corporativos'!$D:$D,""),"") -> 1002AD4503 | K36: =J36-I36 -> 0 | L36: 192821.59 | M36: 353748.37 | N36: =M36-L36 -> 160926.78 | O36: 54849.57 | P36: 203946.67 | Q36: =P36-O36 -> 149097.1 | R36: 95248.46 | S36: 153405.33 | T36: =S36-R36 -> 58156.87
A37: =_xll.EPMOlapMemberO("[CECO].[PARENTH3].[AMSA1002AD4509]","","AMSA1002AD4509 - AAPP y RRII","","000") -> AMSA1002AD4509 - AAPP y RRII | B37: =IFERROR(SUBSTITUTE(TRIM(LEFT(A37,FIND("-",A37)-1)),"AMSA",""),"") -> 1002AD4509 | C37: =IFERROR(_xlfn.XLOOKUP(B37,'CECOS Corporativos'!$D:$D,'CECOS Corporativos'!$E:$E,""),"") -> AAPP y RRII | D37: =IFERROR(_xlfn.XLOOKUP(B37,'CECOS Corporativos'!$D:$D,'CECOS Corporativos'!$J:$J,""),"") -> VP Asuntos Corporativos | E37: =_xll.EPMOlapMemberO("[CLACO].[PARENTH7].[AMSALIQUIDACIO.SEC]","","Liquidación Interna","","000") -> Liquidación Interna | F37: =IFERROR(TRIM(LEFT(G37,FIND("-",G37)-1)),"") -> N100200500 | G37: N100200500 - Centinela No Operaci | H37: =IFERROR(_xlfn.XLOOKUP(F37,'CECOS Corporativos'!$K:$K,'CECOS Corporativos'!$D:$D,""),"") -> 1002AD4503 | K37: =J37-I37 -> 0 | N37: =M37-L37 -> 0 | Q37: =P37-O37 -> 0 | R37: -56233.19 | T37: =S37-R37 -> 56233.19
A38: =_xll.EPMOlapMemberO("[CECO].[PARENTH3].[AMSA1002AD0503]","","AMSA1002AD0503 - Corporativo","","000") -> AMSA1002AD0503 - Corporativo | B38: =IFERROR(SUBSTITUTE(TRIM(LEFT(A38,FIND("-",A38)-1)),"AMSA",""),"") -> 1002AD0503 | C38: =IFERROR(_xlfn.XLOOKUP(B38,'CECOS Corporativos'!$D:$D,'CECOS Corporativos'!$E:$E,""),"") -> Auditoría (HH Corporativo) | D38: =IFERROR(_xlfn.XLOOKUP(B38,'CECOS Corporativos'!$D:$D,'CECOS Corporativos'!$J:$J,""),"") -> Auditoría (HH Corporativo) | E38: =_xll.EPMOlapMemberO("[CLACO].[PARENTH7].[AMSAMAT_Y_REP.2]","","Materiales y repuest","","000") -> Materiales y repuest | F38: =IFERROR(TRIM(LEFT(G38,FIND("-",G38)-1)),"") -> N1002AD050 | G38: N1002AD050 - Gerencia General | H38: =IFERROR(_xlfn.XLOOKUP(F38,'CECOS Corporativos'!$K:$K,'CECOS Corporativos'!$D:$D,""),"") -> 1002AD0508 | K38: =J38-I38 -> 0 | L38: 294.94 | N38: =M38-L38 -> -294.94 | Q38: =P38-O38 -> 0 | T38: =S38-R38 -> 0
