Workbook

Sheet Consolidado Propios
A1: Dotación Histórica AMSA — Consolidado por Vicepresidencia y Gerencia 2022–2026
A2: Dotación Propia Actividad Corporativa · Promedio anual (N°) · Real vs Presupuesto
A4: Vicepresidencia / Gerencia | B4: 2022 | D4: 2023 | F4: 2024 | H4: 2025 | J4: 2026 YTD | L4: 2026 FY
B5: Real | C5: Ppto | D5: Real | E5: Ppto | F5: Real | G5: Ppto | H5: Real | I5: Ppto | J5: Real | K5: Ppto | L5: Ppto
A6: Auditoria | B6: =IF(COUNT(B7:B7)=0,"",SUM(B7:B7)) -> 11.666667 | C6: =IF(COUNT(C7:C7)=0,"",SUM(C7:C7)) -> 12 | D6: =IF(COUNT(D7:D7)=0,"",SUM(D7:D7)) -> 11.5 | E6: =IF(COUNT(E7:E7)=0,"",SUM(E7:E7)) -> 12 | F6: =IF(COUNT(F7:F7)=0,"",SUM(F7:F7)) -> 13.416667 | G6: =IF(COUNT(G7:G7)=0,"",SUM(G7:G7)) -> 14 | H6: =IF(COUNT(H7:H7)=0,"",SUM(H7:H7)) -> 14.416667 | I6: =IF(COUNT(I7:I7)=0,"",SUM(I7:I7)) -> 15 | ... L6: =IF(COUNT(L7:L7)=0,"",SUM(L7:L7)) -> 15
A7: Auditoria | B7: =IFERROR(AVERAGE('2022'!H8:S8),"") -> 11.666667 | C7: =IFERROR(AVERAGE('2022'!H9:S9),"") -> 12 | D7: =IFERROR(AVERAGE('2023'!G7:R7),"") -> 11.5 | E7: =IFERROR(AVERAGE('2023'!G8:R8),"") -> 12 | F7: =IFERROR(AVERAGE('2024'!G7:R7),"") -> 13.416667 | G7: =IFERROR(AVERAGE('2024'!G8:R8),"") -> 14 | H7: =IFERROR(AVERAGE('2025'!G7:R7),"") -> 14.416667 | I7: =IFERROR(AVERAGE('2025'!G8:R8),"") -> 15 | J7: =IFERROR(AVERAGE('2026'!G7:K7),"") -> 15 | K7: =IFERROR(AVERAGE('2026'!G8:K8),"") -> 15 | L7: =IFERROR(AVERAGE('2026'!G8:R8),"") -> 15
A8: Directorio | B8: =IF(COUNT(B9:B9)=0,"",SUM(B9:B9)) -> 3 | C8: =IF(COUNT(C9:C9)=0,"",SUM(C9:C9)) -> 3 | D8: =IF(COUNT(D9:D9)=0,"",SUM(D9:D9)) -> 3 | E8: =IF(COUNT(E9:E9)=0,"",SUM(E9:E9)) -> 3 | F8: =IF(COUNT(F9:F9)=0,"",SUM(F9:F9)) -> 3 | G8: =IF(COUNT(G9:G9)=0,"",SUM(G9:G9)) -> 3 | H8: =IF(COUNT(H9:H9)=0,"",SUM(H9:H9)) -> 3 | I8: =IF(COUNT(I9:I9)=0,"",SUM(I9:I9)) -> 3 | ... L8: =IF(COUNT(L9:L9)=0,"",SUM(L9:L9)) -> 3
A9: Directorio | B9: =IFERROR(AVERAGE('2022'!H10:S10),"") -> 3 | C9: =IFERROR(AVERAGE('2022'!H11:S11),"") -> 3 | D9: =IFERROR(AVERAGE('2023'!G9:R9),"") -> 3 | E9: =IFERROR(AVERAGE('2023'!G10:R10),"") -> 3 | F9: =IFERROR(AVERAGE('2024'!G9:R9),"") -> 3 | G9: =IFERROR(AVERAGE('2024'!G10:R10),"") -> 3 | H9: =IFERROR(AVERAGE('2025'!G9:R9),"") -> 3 | I9: =IFERROR(AVERAGE('2025'!G10:R10),"") -> 3 | J9: =IFERROR(AVERAGE('2026'!G9:K9),"") -> 3 | K9: =IFERROR(AVERAGE('2026'!G10:K10),"") -> 3 | L9: =IFERROR(AVERAGE('2026'!G10:R10),"") -> 3
A10: Presidencia Ejecutiva | B10: =IF(COUNT(B11:B11)=0,"",SUM(B11:B11)) -> 1.8333333 | C10: =IF(COUNT(C11:C11)=0,"",SUM(C11:C11)) -> 2 | D10: =IF(COUNT(D11:D11)=0,"",SUM(D11:D11)) -> 2 | E10: =IF(COUNT(E11:E11)=0,"",SUM(E11:E11)) -> 2 | F10: =IF(COUNT(F11:F11)=0,"",SUM(F11:F11)) -> 2 | G10: =IF(COUNT(G11:G11)=0,"",SUM(G11:G11)) -> 2 | H10: =IF(COUNT(H11:H11)=0,"",SUM(H11:H11)) -> 2 | I10: =IF(COUNT(I11:I11)=0,"",SUM(I11:I11)) -> 2 | ... L10: =IF(COUNT(L11:L11)=0,"",SUM(L11:L11)) -> 2
A11: Presidencia Ejecutiva | B11: =IFERROR(AVERAGE('2022'!H12:S12),"") -> 1.8333333 | C11: =IFERROR(AVERAGE('2022'!H13:S13),"") -> 2 | D11: =IFERROR(AVERAGE('2023'!G11:R11),"") -> 2 | E11: =IFERROR(AVERAGE('2023'!G12:R12),"") -> 2 | F11: =IFERROR(AVERAGE('2024'!G11:R11),"") -> 2 | G11: =IFERROR(AVERAGE('2024'!G12:R12),"") -> 2 | H11: =IFERROR(AVERAGE('2025'!G11:R11),"") -> 2 | I11: =IFERROR(AVERAGE('2025'!G12:R12),"") -> 2 | J11: =IFERROR(AVERAGE('2026'!G11:K11),"") -> 2 | K11: =IFERROR(AVERAGE('2026'!G12:K12),"") -> 2 | L11: =IFERROR(AVERAGE('2026'!G12:R12),"") -> 2
A12: Vicepresidencia Comercialización | B12: =IF(COUNT(B13:B15)=0,"",SUM(B13:B15)) -> 19 | C12: =IF(COUNT(C13:C15)=0,"",SUM(C13:C15)) -> 19 | D12: =IF(COUNT(D13:D15)=0,"",SUM(D13:D15)) -> 18.166667 | E12: =IF(COUNT(E13:E15)=0,"",SUM(E13:E15)) -> 19.083333 | F12: =IF(COUNT(F13:F15)=0,"",SUM(F13:F15)) -> 18.833333 | G12: =IF(COUNT(G13:G15)=0,"",SUM(G13:G15)) -> 19.75 | H12: =IF(COUNT(H13:H15)=0,"",SUM(H13:H15)) -> 18.75 | I12: =IF(COUNT(I13:I15)=0,"",SUM(I13:I15)) -> 20 | ... L12: =IF(COUNT(L13:L15)=0,"",SUM(L13:L15)) -> 19
A13: Ventas Cátodos Molibdeno y Hedge | B13: =IFERROR(AVERAGE('2022'!H28:S28),"") -> 5.25 | C13: =IFERROR(AVERAGE('2022'!H29:S29),"") -> 6 | D13: =IFERROR(AVERAGE('2023'!G27:R27),"") -> 4.1666667 | E13: =IFERROR(AVERAGE('2023'!G28:R28),"") -> 4.25 | F13: =IFERROR(AVERAGE('2024'!G27:R27),"") -> 4.8333333 | G13: =IFERROR(AVERAGE('2024'!G28:R28),"") -> 5.75 | H13: =IFERROR(AVERAGE('2025'!G13:R13),"") -> 5 | I13: =IFERROR(AVERAGE('2025'!G14:R14),"") -> 5 | J13: =IFERROR(AVERAGE('2026'!G13:K13),"") -> 5 | K13: =IFERROR(AVERAGE('2026'!G14:K14),"") -> 5 | L13: =IFERROR(AVERAGE('2026'!G14:R14),"") -> 5
A14: Ventas Concentrado Acido | B14: =IFERROR(AVERAGE('2022'!H30:S30),"") -> 4 | C14: =IFERROR(AVERAGE('2022'!H31:S31),"") -> 3 | D14: =IFERROR(AVERAGE('2023'!G29:R29),"") -> 4 | E14: =IFERROR(AVERAGE('2023'!G30:R30),"") -> 4 | F14: =IFERROR(AVERAGE('2024'!G29:R29),"") -> 4.6666667 | G14: =IFERROR(AVERAGE('2024'!G30:R30),"") -> 4 | H14: =IFERROR(AVERAGE('2025'!G15:R15),"") -> 4.9166667 | I14: =IFERROR(AVERAGE('2025'!G16:R16),"") -> 5 | J14: =IFERROR(AVERAGE('2026'!G15:K15),"") -> 5 | K14: =IFERROR(AVERAGE('2026'!G16:K16),"") -> 5 | L14: =IFERROR(AVERAGE('2026'!G16:R16),"") -> 5
A15: Vicepresidencia Comercialización | B15: =IFERROR(AVERAGE('2022'!H32:S32),"") -> 9.75 | C15: =IFERROR(AVERAGE('2022'!H33:S33),"") -> 10 | D15: =IFERROR(AVERAGE('2023'!G31:R31),"") -> 10 | E15: =IFERROR(AVERAGE('2023'!G32:R32),"") -> 10.833333 | F15: =IFERROR(AVERAGE('2024'!G31:R31),"") -> 9.3333333 | G15: =IFERROR(AVERAGE('2024'!G32:R32),"") -> 10 | H15: =IFERROR(AVERAGE('2025'!G17:R17),"") -> 8.8333333 | I15: =IFERROR(AVERAGE('2025'!G18:R18),"") -> 10 | J15: =IFERROR(AVERAGE('2026'!G17:K17),"") -> 9 | K15: =IFERROR(AVERAGE('2026'!G18:K18),"") -> 9 | L15: =IFERROR(AVERAGE('2026'!G18:R18),"") -> 9
A16: Vicepresidencia de Asuntos Corporativos | B16: =IF(COUNT(B17:B21)=0,"",SUM(B17:B21)) | C16: =IF(COUNT(C17:C21)=0,"",SUM(C17:C21)) | D16: =IF(COUNT(D17:D21)=0,"",SUM(D17:D21)) | E16: =IF(COUNT(E17:E21)=0,"",SUM(E17:E21)) | F16: =IF(COUNT(F17:F21)=0,"",SUM(F17:F21)) -> 19.666667 | G16: =IF(COUNT(G17:G21)=0,"",SUM(G17:G21)) -> 0 | H16: =IF(COUNT(H17:H21)=0,"",SUM(H17:H21)) -> 45.25 | I16: =IF(COUNT(I17:I21)=0,"",SUM(I17:I21)) -> 49 | ... L16: =IF(COUNT(L17:L21)=0,"",SUM(L17:L21)) -> 52
A17: Asuntos Públicos Corporativo | F17: =IFERROR(AVERAGE('2024'!G33:R33),"") -> 1.6666667 | G17: =IFERROR(AVERAGE('2024'!G34:R34),"") -> 0 | H17: =IFERROR(AVERAGE('2025'!G19:R19),"") -> 2.1666667 | I17: =IFERROR(AVERAGE('2025'!G20:R20),"") -> 5
A18: Asuntos Públicos Norte | F18: =IFERROR(AVERAGE('2024'!G37:R37),"") -> 5.5833333 | G18: =IFERROR(AVERAGE('2024'!G38:R38),"") -> 0 | H18: =IFERROR(AVERAGE('2025'!G21:R21),"") -> 12.416667 | I18: =IFERROR(AVERAGE('2025'!G22:R22),"") -> 13 | J18: =IFERROR(AVERAGE('2026'!G21:K21),"") -> 13 | K18: =IFERROR(AVERAGE('2026'!G22:K22),"") -> 15 | L18: =IFERROR(AVERAGE('2026'!G22:R22),"") -> 15
A19: Asuntos Publicos MLP | F19: =IFERROR(AVERAGE('2024'!G35:R35),"") -> 8.0833333 | G19: =IFERROR(AVERAGE('2024'!G36:R36),"") -> 0 | H19: =IFERROR(AVERAGE('2025'!G23:R23),"") -> 18.583333 | I19: =IFERROR(AVERAGE('2025'!G24:R24),"") -> 20 | J19: =IFERROR(AVERAGE('2026'!G19:K19),"") -> 17.4 | K19: =IFERROR(AVERAGE('2026'!G20:K20),"") -> 18 | L19: =IFERROR(AVERAGE('2026'!G20:R20),"") -> 18
A20: Comunicaciones | F20: =IFERROR(AVERAGE('2024'!G39:R39),"") -> 3.3333333 | G20: =IFERROR(AVERAGE('2024'!G40:R40),"") -> 0 | H20: =IFERROR(AVERAGE('2025'!G25:R25),"") -> 7.5833333 | I20: =IFERROR(AVERAGE('2025'!G26:R26),"") -> 8 | J20: =IFERROR(AVERAGE('2026'!G23:K23),"") -> 7.8 | K20: =IFERROR(AVERAGE('2026'!G24:K24),"") -> 8 | L20: =IFERROR(AVERAGE('2026'!G24:R24),"") -> 8
A21: Vicepresidencia Asuntos Corporativos | F21: =IFERROR(AVERAGE('2024'!G41:R41),"") -> 1 | G21: =IFERROR(AVERAGE('2024'!G42:R42),"") -> 0 | H21: =IFERROR(AVERAGE('2025'!G27:R27),"") -> 4.5 | I21: =IFERROR(AVERAGE('2025'!G28:R28),"") -> 3 | J21: =IFERROR(AVERAGE('2026'!G25:K25),"") -> 10.4 | K21: =IFERROR(AVERAGE('2026'!G26:K26),"") -> 11 | L21: =IFERROR(AVERAGE('2026'!G26:R26),"") -> 11
A22: Vicepresidencia de Proyectos | B22: =IF(COUNT(B23:B26)=0,"",SUM(B23:B26)) -> 13.25 | C22: =IF(COUNT(C23:C26)=0,"",SUM(C23:C26)) -> 15 | D22: =IF(COUNT(D23:D26)=0,"",SUM(D23:D26)) -> 12.333333 | E22: =IF(COUNT(E23:E26)=0,"",SUM(E23:E26)) -> 14 | F22: =IF(COUNT(F23:F26)=0,"",SUM(F23:F26)) -> 15 | G22: =IF(COUNT(G23:G26)=0,"",SUM(G23:G26)) -> 14 | H22: =IF(COUNT(H23:H26)=0,"",SUM(H23:H26)) -> 23.666667 | I22: =IF(COUNT(I23:I26)=0,"",SUM(I23:I26)) -> 27 | ... L22: =IF(COUNT(L23:L26)=0,"",SUM(L23:L26)) -> 27
A23: Finanzas VPP | B23: =IFERROR(AVERAGE('2022'!H34:S34),"") -> 7 | C23: =IFERROR(AVERAGE('2022'!H35:S35),"") -> 8 | D23: =IFERROR(AVERAGE('2023'!G33:R33),"") -> 6.1666667 | E23: =IFERROR(AVERAGE('2023'!G34:R34),"") -> 7 | F23: =IFERROR(AVERAGE('2024'!G43:R43),"") -> 7.5833333 | G23: =IFERROR(AVERAGE('2024'!G44:R44),"") -> 7 | H23: =IFERROR(AVERAGE('2025'!G29:R29),"") -> 12.166667 | I23: =IFERROR(AVERAGE('2025'!G30:R30),"") -> 14 | J23: =IFERROR(AVERAGE('2026'!G27:K27),"") -> 13 | K23: =IFERROR(AVERAGE('2026'!G28:K28),"") -> 14 | L23: =IFERROR(AVERAGE('2026'!G28:R28),"") -> 14
A24: Ingenieria y Construccion | B24: =IFERROR(AVERAGE('2022'!H36:S36),"") -> 4 | C24: =IFERROR(AVERAGE('2022'!H37:S37),"") -> 5 | D24: =IFERROR(AVERAGE('2023'!G35:R35),"") -> 4 | E24: =IFERROR(AVERAGE('2023'!G36:R36),"") -> 5 | F24: =IFERROR(AVERAGE('2024'!G45:R45),"") -> 3.3333333 | G24: =IFERROR(AVERAGE('2024'!G46:R46),"") -> 5 | H24: =IFERROR(AVERAGE('2025'!G31:R31),"") -> 2.1666667 | I24: =IFERROR(AVERAGE('2025'!G32:R32),"") -> 5 | J24: =IFERROR(AVERAGE('2026'!G29:K29),"") -> 2 | K24: =IFERROR(AVERAGE('2026'!G30:K30),"") -> 5 | L24: =IFERROR(AVERAGE('2026'!G30:R30),"") -> 5
A25: Proyecto MLP Largo Plazo | F25: =IFERROR(AVERAGE('2024'!G47:R47),"") -> 0 | G25: =IFERROR(AVERAGE('2024'!G48:R48),"") -> 0
A26: Vicepresidencia de Proyectos + Proyecto INCO | B26: =IFERROR(AVERAGE('2022'!H38:S38),"") -> 2.25 | C26: =IFERROR(AVERAGE('2022'!H39:S39),"") -> 2 | D26: =IFERROR(AVERAGE('2023'!G37:R37),"") -> 2.1666667 | E26: =IFERROR(AVERAGE('2023'!G38:R38),"") -> 2 | F26: =IFERROR(AVERAGE('2024'!G49:R49),"") -> 4.0833333 | G26: =IFERROR(AVERAGE('2024'!G50:R50),"") -> 2 | H26: =IFERROR(AVERAGE('2025'!G33:R33),"") -> 9.3333333 | I26: =IFERROR(AVERAGE('2025'!G34:R34),"") -> 8 | J26: =IFERROR(AVERAGE('2026'!G31:K31),"") -> 9.4 | K26: =IFERROR(AVERAGE('2026'!G32:K32),"") -> 8 | L26: =IFERROR(AVERAGE('2026'!G32:R32),"") -> 8
A27: Vicepresidencia Desarrollo | B27: =IF(COUNT(B28:B32)=0,"",SUM(B28:B32)) -> 16.916667 | C27: =IF(COUNT(C28:C32)=0,"",SUM(C28:C32)) -> 17.666667 | D27: =IF(COUNT(D28:D32)=0,"",SUM(D28:D32)) -> 17.333333 | E27: =IF(COUNT(E28:E32)=0,"",SUM(E28:E32)) -> 17.5 | F27: =IF(COUNT(F28:F32)=0,"",SUM(F28:F32)) -> 18.25 | G27: =IF(COUNT(G28:G32)=0,"",SUM(G28:G32)) -> 16.75 | H27: =IF(COUNT(H28:H32)=0,"",SUM(H28:H32)) -> 21.333333 | I27: =IF(COUNT(I28:I32)=0,"",SUM(I28:I32)) -> 22 | ... L27: =IF(COUNT(L28:L32)=0,"",SUM(L28:L32)) -> 21
A28: Administración MIC | B28: =IFERROR(AVERAGE('2022'!H40:S40),"") -> 4.6666667 | C28: =IFERROR(AVERAGE('2022'!H41:S41),"") -> 3.6666667 | D28: =IFERROR(AVERAGE('2023'!G39:R39),"") -> 2.75 | E28: =IFERROR(AVERAGE('2023'!G40:R40),"") -> 3.5 | F28: =IFERROR(AVERAGE('2024'!G51:R51),"") -> 2 | G28: =IFERROR(AVERAGE('2024'!G52:R52),"") -> 2.75 | H28: =IFERROR(AVERAGE('2025'!G35:R35),"") -> 2 | I28: =IFERROR(AVERAGE('2025'!G36:R36),"") -> 3 | J28: =IFERROR(AVERAGE('2026'!G33:K33),"") -> 2 | K28: =IFERROR(AVERAGE('2026'!G34:K34),"") -> 2 | L28: =IFERROR(AVERAGE('2026'!G34:R34),"") -> 2
A29: Desarrollo | B29: =IFERROR(AVERAGE('2022'!H42:S42),"") -> 8 | C29: =IFERROR(AVERAGE('2022'!H43:S43),"") -> 9 | D29: =IFERROR(AVERAGE('2023'!G41:R41),"") -> 9 | E29: =IFERROR(AVERAGE('2023'!G42:R42),"") -> 9 | F29: =IFERROR(AVERAGE('2024'!G53:R53),"") -> 9 | G29: =IFERROR(AVERAGE('2024'!G54:R54),"") -> 9 | H29: =IFERROR(AVERAGE('2025'!G37:R37),"") -> 9 | I29: =IFERROR(AVERAGE('2025'!G38:R38),"") -> 9 | J29: =IFERROR(AVERAGE('2026'!G35:K35),"") -> 8.2 | K29: =IFERROR(AVERAGE('2026'!G36:K36),"") -> 9 | L29: =IFERROR(AVERAGE('2026'!G36:R36),"") -> 9
A30: Exploraciones Global | D30: =IFERROR(AVERAGE('2023'!G43:R43),"") -> 0.5 | E30: =IFERROR(AVERAGE('2023'!G44:R44),"") -> 0
A31: Geología | D31: =IFERROR(AVERAGE('2023'!G45:R45),"") -> 0.25 | E31: =IFERROR(AVERAGE('2023'!G46:R46),"") -> 0
A32: Vicepresidencia Desarrollo | B32: =IFERROR(AVERAGE('2022'!H44:S44),"") -> 4.25 | C32: =IFERROR(AVERAGE('2022'!H45:S45),"") -> 5 | D32: =IFERROR(AVERAGE('2023'!G47:R47),"") -> 4.8333333 | E32: =IFERROR(AVERAGE('2023'!G48:R48),"") -> 5 | F32: =IFERROR(AVERAGE('2024'!G55:R55),"") -> 7.25 | G32: =IFERROR(AVERAGE('2024'!G56:R56),"") -> 5 | H32: =IFERROR(AVERAGE('2025'!G39:R39),"") -> 10.333333 | I32: =IFERROR(AVERAGE('2025'!G40:R40),"") -> 10 | J32: =IFERROR(AVERAGE('2026'!G37:K37),"") -> 7.8 | K32: =IFERROR(AVERAGE('2026'!G38:K38),"") -> 10 | L32: =IFERROR(AVERAGE('2026'!G38:R38),"") -> 10
A33: Vicepresidencia Estrategia e Innovación | B33: =IF(COUNT(B34:B40)=0,"",SUM(B34:B40)) -> 79.083333 | C33: =IF(COUNT(C34:C40)=0,"",SUM(C34:C40)) -> 83.25 | D33: =IF(COUNT(D34:D40)=0,"",SUM(D34:D40)) -> 76 | E33: =IF(COUNT(E34:E40)=0,"",SUM(E34:E40)) -> 85 | F33: =IF(COUNT(F34:F40)=0,"",SUM(F34:F40)) -> 78.666667 | G33: =IF(COUNT(G34:G40)=0,"",SUM(G34:G40)) -> 78.416667 | H33: =IF(COUNT(H34:H40)=0,"",SUM(H34:H40)) -> 75.5 | I33: =IF(COUNT(I34:I40)=0,"",SUM(I34:I40)) -> 80.75 | ... L33: =IF(COUNT(L34:L40)=0,"",SUM(L34:L40)) -> 81
A34: Data y Analítica Avanzada | B34: =IFERROR(AVERAGE('2022'!H46:S46),"") -> 5.1666667 | C34: =IFERROR(AVERAGE('2022'!H47:S47),"") -> 5.25 | D34: =IFERROR(AVERAGE('2023'!G49:R49),"") -> 6.6666667 | E34: =IFERROR(AVERAGE('2023'!G50:R50),"") -> 5 | F34: =IFERROR(AVERAGE('2024'!G57:R57),"") -> 7.75 | G34: =IFERROR(AVERAGE('2024'!G58:R58),"") -> 8 | H34: =IFERROR(AVERAGE('2025'!G41:R41),"") -> 8 | I34: =IFERROR(AVERAGE('2025'!G42:R42),"") -> 8 | J34: =IFERROR(AVERAGE('2026'!G39:K39),"") -> 8.2 | K34: =IFERROR(AVERAGE('2026'!G40:K40),"") -> 8 | L34: =IFERROR(AVERAGE('2026'!G40:R40),"") -> 8
A35: Innovación + Energía y Recursos Hídricos | B35: =IFERROR(AVERAGE('2022'!H50:S50),"") -> 10.166667 | C35: =IFERROR(AVERAGE('2022'!H51:S51),"") -> 12 | D35: =IFERROR(AVERAGE('2023'!G53:R53),"") -> 9.0833333 | E35: =IFERROR(AVERAGE('2023'!G54:R54),"") -> 14 | F35: =IFERROR(AVERAGE('2024'!G59:R59),"") -> 6 | G35: =IFERROR(AVERAGE('2024'!G60:R60),"") -> 6 | H35: =IFERROR(AVERAGE('2025'!G43:R43),"") -> 5.25 | I35: =IFERROR(AVERAGE('2025'!G44:R44),"") -> 6 | J35: =IFERROR(AVERAGE('2026'!G41:K41),"") -> 4.8 | K35: =IFERROR(AVERAGE('2026'!G42:K42),"") -> 5 | L35: =IFERROR(AVERAGE('2026'!G42:R42),"") -> 5
A36: Proyecto Descarbonización | F36: =IFERROR(AVERAGE('2024'!G61:R61),"") -> 4.9166667 | G36: =IFERROR(AVERAGE('2024'!G62:R62),"") -> 0 | H36: =IFERROR(AVERAGE('2025'!G45:R45),"") -> 4.9166667 | I36: =IFERROR(AVERAGE('2025'!G46:R46),"") -> 5 | J36: =IFERROR(AVERAGE('2026'!G43:K43),"") -> 5 | K36: =IFERROR(AVERAGE('2026'!G44:K44),"") -> 5 | L36: =IFERROR(AVERAGE('2026'!G44:R44),"") -> 5
A37: Tecnologia | F37: =IFERROR(AVERAGE('2024'!G63:R63),"") -> 54.166667 | G37: =IFERROR(AVERAGE('2024'!G64:R64),"") -> 55.416667 | H37: =IFERROR(AVERAGE('2025'!G47:R47),"") -> 52.666667 | I37: =IFERROR(AVERAGE('2025'!G48:R48),"") -> 56 | J37: =IFERROR(AVERAGE('2026'!G45:K45),"") -> 51.6 | K37: =IFERROR(AVERAGE('2026'!G46:K46),"") -> 57 | L37: =IFERROR(AVERAGE('2026'!G46:R46),"") -> 57
A38: Estrategia Recursos Mineros | B38: =IFERROR(AVERAGE('2022'!H48:S48),"") -> 3.9166667 | C38: =IFERROR(AVERAGE('2022'!H49:S49),"") -> 4 | D38: =IFERROR(AVERAGE('2023'!G51:R51),"") -> 2 | E38: =IFERROR(AVERAGE('2023'!G52:R52),"") -> 4
A39: TICA | B39: =IFERROR(AVERAGE('2022'!H52:S52),"") -> 53.916667 | C39: =IFERROR(AVERAGE('2022'!H53:S53),"") -> 55 | D39: =IFERROR(AVERAGE('2023'!G55:R55),"") -> 51.583333 | E39: =IFERROR(AVERAGE('2023'!G56:R56),"") -> 56
A40: Vicepresidencia Estrategia e Innovación | B40: =IFERROR(AVERAGE('2022'!H54:S54),"") -> 5.9166667 | C40: =IFERROR(AVERAGE('2022'!H55:S55),"") -> 7 | D40: =IFERROR(AVERAGE('2023'!G57:R57),"") -> 6.6666667 | E40: =IFERROR(AVERAGE('2023'!G58:R58),"") -> 6 | F40: =IFERROR(AVERAGE('2024'!G65:R65),"") -> 5.8333333 | G40: =IFERROR(AVERAGE('2024'!G66:R66),"") -> 9 | H40: =IFERROR(AVERAGE('2025'!G49:R49),"") -> 4.6666667 | I40: =IFERROR(AVERAGE('2025'!G50:R50),"") -> 5.75 | J40: =IFERROR(AVERAGE('2026'!G47:K47),"") -> 4.8 | K40: =IFERROR(AVERAGE('2026'!G48:K48),"") -> 6 | L40: =IFERROR(AVERAGE('2026'!G48:R48),"") -> 6
A41: Vicepresidencia Finanzas | B41: =IF(COUNT(B42:B50)=0,"",SUM(B42:B50)) -> 110.66667 | C41: =IF(COUNT(C42:C50)=0,"",SUM(C42:C50)) -> 114.16667 | D41: =IF(COUNT(D42:D50)=0,"",SUM(D42:D50)) -> 116 | E41: =IF(COUNT(E42:E50)=0,"",SUM(E42:E50)) -> 120.41667 | F41: =IF(COUNT(F42:F50)=0,"",SUM(F42:F50)) -> 121.66667 | G41: =IF(COUNT(G42:G50)=0,"",SUM(G42:G50)) -> 126 | H41: =IF(COUNT(H42:H50)=0,"",SUM(H42:H50)) -> 114.91667 | I41: =IF(COUNT(I42:I50)=0,"",SUM(I42:I50)) -> 128.75 | ... L41: =IF(COUNT(L42:L50)=0,"",SUM(L42:L50)) -> 119
A42: Abastecimiento | B42: =IFERROR(AVERAGE('2022'!H56:S56),"") -> 34.083333 | C42: =IFERROR(AVERAGE('2022'!H57:S57),"") -> 37.416667 | D42: =IFERROR(AVERAGE('2023'!G59:R59),"") -> 36.25 | E42: =IFERROR(AVERAGE('2023'!G60:R60),"") -> 38 | F42: =IFERROR(AVERAGE('2024'!G67:R67),"") -> 35.333333 | G42: =IFERROR(AVERAGE('2024'!G68:R68),"") -> 38 | H42: =IFERROR(AVERAGE('2025'!G51:R51),"") -> 31.666667 | I42: =IFERROR(AVERAGE('2025'!G52:R52),"") -> 38 | J42: =IFERROR(AVERAGE('2026'!G49:K49),"") -> 30.4 | K42: =IFERROR(AVERAGE('2026'!G50:K50),"") -> 33 | L42: =IFERROR(AVERAGE('2026'!G50:R50),"") -> 33
A43: Contabilidad | B43: =IFERROR(AVERAGE('2022'!H58:S58),"") -> 31.583333 | C43: =IFERROR(AVERAGE('2022'!H59:S59),"") -> 30 | D43: =IFERROR(AVERAGE('2023'!G61:R61),"") -> 34.916667 | E43: =IFERROR(AVERAGE('2023'!G62:R62),"") -> 36.166667 | F43: =IFERROR(AVERAGE('2024'!G69:R69),"") -> 34.666667 | G43: =IFERROR(AVERAGE('2024'!G70:R70),"") -> 36 | H43: =IFERROR(AVERAGE('2025'!G53:R53),"") -> 33.083333 | I43: =IFERROR(AVERAGE('2025'!G54:R54),"") -> 36 | J43: =IFERROR(AVERAGE('2026'!G51:K51),"") -> 32.8 | K43: =IFERROR(AVERAGE('2026'!G52:K52),"") -> 34 | L43: =IFERROR(AVERAGE('2026'!G52:R52),"") -> 34
A44: Energía y Servicios Estratégicos | F44: =IFERROR(AVERAGE('2024'!G73:R73),"") -> 1.25 | H44: =IFERROR(AVERAGE('2025'!G55:R55),"") -> 3 | I44: =IFERROR(AVERAGE('2025'!G56:R56),"") -> 3 | J44: =IFERROR(AVERAGE('2026'!G53:K53),"") -> 3 | K44: =IFERROR(AVERAGE('2026'!G54:K54),"") -> 3 | L44: =IFERROR(AVERAGE('2026'!G54:R54),"") -> 3
A45: Finanzas e Impuestos + Planificación Financiera | B45: =IFERROR(AVERAGE('2022'!H60:S60),"") -> 25.5 | C45: =IFERROR(AVERAGE('2022'!H61:S61),"") -> 26.5 | D45: =IFERROR(AVERAGE('2023'!G65:R65),"") -> 24.333333 | E45: =IFERROR(AVERAGE('2023'!G66:R66),"") -> 26 | F45: =IFERROR(AVERAGE('2024'!G74:R74),"") -> 27.25 | G45: =IFERROR(AVERAGE('2024'!G75:R75),"") -> 28 | H45: =IFERROR(AVERAGE('2025'!G57:R57),"") -> 26.25 | I45: =IFERROR(AVERAGE('2025'!G58:R58),"") -> 28 | J45: =IFERROR(AVERAGE('2026'!G55:K55),"") -> 26.4 | K45: =IFERROR(AVERAGE('2026'!G56:K56),"") -> 27 | L45: =IFERROR(AVERAGE('2026'!G56:R56),"") -> 27
A46: Gerencia Competitividad | F46: =IFERROR(AVERAGE('2024'!G76:R76),"") -> 0.91666667 | I46: =IFERROR(AVERAGE('2025'!G59:R59),"") -> 3
A47: Planificacion y Control de Gestion | B47: =IFERROR(AVERAGE('2022'!H62:S62),"") -> 9.75 | C47: =IFERROR(AVERAGE('2022'!H63:S63),"") -> 10.25 | D47: =IFERROR(AVERAGE('2023'!G67:R67),"") -> 9.9166667 | E47: =IFERROR(AVERAGE('2023'!G68:R68),"") -> 10 | F47: =IFERROR(AVERAGE('2024'!G77:R77),"") -> 9.0833333 | G47: =IFERROR(AVERAGE('2024'!G78:R78),"") -> 10 | H47: =IFERROR(AVERAGE('2025'!G60:R60),"") -> 9.6666667 | I47: =IFERROR(AVERAGE('2025'!G61:R61),"") -> 9.75 | J47: =IFERROR(AVERAGE('2026'!G57:K57),"") -> 9.2 | K47: =IFERROR(AVERAGE('2026'!G58:K58),"") -> 10 | L47: =IFERROR(AVERAGE('2026'!G58:R58),"") -> 10
A48: Riesgo Compliance y Control Interno | B48: =IFERROR(AVERAGE('2022'!H64:S64),"") -> 7.3333333 | C48: =IFERROR(AVERAGE('2022'!H65:S65),"") -> 8 | D48: =IFERROR(AVERAGE('2023'!G69:R69),"") -> 7.75 | E48: =IFERROR(AVERAGE('2023'!G70:R70),"") -> 8.25 | F48: =IFERROR(AVERAGE('2024'!G79:R79),"") -> 8.5 | G48: =IFERROR(AVERAGE('2024'!G80:R80),"") -> 9 | H48: =IFERROR(AVERAGE('2025'!G62:R62),"") -> 9.25 | I48: =IFERROR(AVERAGE('2025'!G63:R63),"") -> 9 | J48: =IFERROR(AVERAGE('2026'!G59:K59),"") -> 7.4 | K48: =IFERROR(AVERAGE('2026'!G60:K60),"") -> 10 | L48: =IFERROR(AVERAGE('2026'!G60:R60),"") -> 10
A49: Energia y Recursos Hidricos | D49: =IFERROR(AVERAGE('2023'!G63:R63),"") -> 0.5 | E49: =IFERROR(AVERAGE('2023'!G64:R64),"") -> 0 | F49: =IFERROR(AVERAGE('2024'!G71:R71),"") -> 1.3333333 | G49: =IFERROR(AVERAGE('2024'!G72:R72),"") -> 2
A50: Vicepresidencia Finanzas | B50: =IFERROR(AVERAGE('2022'!H66:S66),"") -> 2.4166667 | C50: =IFERROR(AVERAGE('2022'!H67:S67),"") -> 2 | D50: =IFERROR(AVERAGE('2023'!G71:R71),"") -> 2.3333333 | E50: =IFERROR(AVERAGE('2023'!G72:R72),"") -> 2 | F50: =IFERROR(AVERAGE('2024'!G81:R81),"") -> 3.3333333 | G50: =IFERROR(AVERAGE('2024'!G82:R82),"") -> 3 | H50: =IFERROR(AVERAGE('2025'!G64:R64),"") -> 2 | I50: =IFERROR(AVERAGE('2025'!G65:R65),"") -> 2 | J50: =IFERROR(AVERAGE('2026'!G61:K61),"") -> 1.6 | K50: =IFERROR(AVERAGE('2026'!G62:K62),"") -> 2 | L50: =IFERROR(AVERAGE('2026'!G62:R62),"") -> 2
A51: Vicepresidencia Legal | B51: =IF(COUNT(B52:B54)=0,"",SUM(B52:B54)) -> 17 | C51: =IF(COUNT(C52:C54)=0,"",SUM(C52:C54)) -> 19 | D51: =IF(COUNT(D52:D54)=0,"",SUM(D52:D54)) -> 18.666667 | E51: =IF(COUNT(E52:E54)=0,"",SUM(E52:E54)) -> 20 | F51: =IF(COUNT(F52:F54)=0,"",SUM(F52:F54)) -> 19 | G51: =IF(COUNT(G52:G54)=0,"",SUM(G52:G54)) -> 20 | H51: =IF(COUNT(H52:H54)=0,"",SUM(H52:H54)) -> 18.583333 | I51: =IF(COUNT(I52:I54)=0,"",SUM(I52:I54)) -> 20 | ... L51: =IF(COUNT(L52:L54)=0,"",SUM(L52:L54)) -> 20
A52: Legal | B52: =IFERROR(AVERAGE('2022'!H68:S68),"") -> 7 | C52: =IFERROR(AVERAGE('2022'!H69:S69),"") -> 8 | D52: =IFERROR(AVERAGE('2023'!G73:R73),"") -> 7.8333333 | E52: =IFERROR(AVERAGE('2023'!G74:R74),"") -> 9 | F52: =IFERROR(AVERAGE('2024'!G83:R83),"") -> 8 | G52: =IFERROR(AVERAGE('2024'!G84:R84),"") -> 9 | H52: =IFERROR(AVERAGE('2025'!G66:R66),"") -> 7.5 | I52: =IFERROR(AVERAGE('2025'!G67:R67),"") -> 9 | J52: =IFERROR(AVERAGE('2026'!G63:K63),"") -> 5.8 | K52: =IFERROR(AVERAGE('2026'!G64:K64),"") -> 9 | L52: =IFERROR(AVERAGE('2026'!G64:R64),"") -> 9
A53: Propiedad Minera | B53: =IFERROR(AVERAGE('2022'!H70:S70),"") -> 8 | C53: =IFERROR(AVERAGE('2022'!H71:S71),"") -> 9 | D53: =IFERROR(AVERAGE('2023'!G75:R75),"") -> 8.8333333 | E53: =IFERROR(AVERAGE('2023'!G76:R76),"") -> 9 | F53: =IFERROR(AVERAGE('2024'!G85:R85),"") -> 9 | G53: =IFERROR(AVERAGE('2024'!G86:R86),"") -> 9 | H53: =IFERROR(AVERAGE('2025'!G68:R68),"") -> 9 | I53: =IFERROR(AVERAGE('2025'!G69:R69),"") -> 9 | J53: =IFERROR(AVERAGE('2026'!G65:K65),"") -> 9 | K53: =IFERROR(AVERAGE('2026'!G66:K66),"") -> 9 | L53: =IFERROR(AVERAGE('2026'!G66:R66),"") -> 9
A54: Vicepresidencia Legal | B54: =IFERROR(AVERAGE('2022'!H72:S72),"") -> 2 | C54: =IFERROR(AVERAGE('2022'!H73:S73),"") -> 2 | D54: =IFERROR(AVERAGE('2023'!G77:R77),"") -> 2 | E54: =IFERROR(AVERAGE('2023'!G78:R78),"") -> 2 | F54: =IFERROR(AVERAGE('2024'!G87:R87),"") -> 2 | G54: =IFERROR(AVERAGE('2024'!G88:R88),"") -> 2 | H54: =IFERROR(AVERAGE('2025'!G70:R70),"") -> 2.0833333 | I54: =IFERROR(AVERAGE('2025'!G71:R71),"") -> 2 | J54: =IFERROR(AVERAGE('2026'!G67:K67),"") -> 3.8 | K54: =IFERROR(AVERAGE('2026'!G68:K68),"") -> 2 | L54: =IFERROR(AVERAGE('2026'!G68:R68),"") -> 2
A55: Vicepresidencia Operaciones | B55: =IF(COUNT(B56:B59)=0,"",SUM(B56:B59)) -> 16.75 | C55: =IF(COUNT(C56:C59)=0,"",SUM(C56:C59)) -> 17.25 | D55: =IF(COUNT(D56:D59)=0,"",SUM(D56:D59)) -> 8.25 | E55: =IF(COUNT(E56:E59)=0,"",SUM(E56:E59)) -> 15.5 | F55: =IF(COUNT(F56:F59)=0,"",SUM(F56:F59)) -> 1.25 | G55: =IF(COUNT(G56:G59)=0,"",SUM(G56:G59)) -> 0 | H55: =IF(COUNT(H56:H59)=0,"",SUM(H56:H59)) -> 3 | I55: =IF(COUNT(I56:I59)=0,"",SUM(I56:I59)) | ... L55: =IF(COUNT(L56:L59)=0,"",SUM(L56:L59)) -> 3
A56: Mantenimiento y Excelencia Operacional | B56: =IFERROR(AVERAGE('2022'!H74:S74),"") -> 5.75 | C56: =IFERROR(AVERAGE('2022'!H75:S75),"") -> 6 | D56: =IFERROR(AVERAGE('2023'!G79:R79),"") -> 2.6666667 | E56: =IFERROR(AVERAGE('2023'!G80:R80),"") -> 5.25
A57: Minería | B57: =IFERROR(AVERAGE('2022'!H76:S76),"") -> 3.4166667 | C57: =IFERROR(AVERAGE('2022'!H77:S77),"") -> 3.25 | D57: =IFERROR(AVERAGE('2023'!G81:R81),"") -> 2.0833333 | E57: =IFERROR(AVERAGE('2023'!G82:R82),"") -> 3
A58: Procesos + Tanques y Releves | B58: =IFERROR(AVERAGE('2022'!H78:S78),"") -> 4.5 | C58: =IFERROR(AVERAGE('2022'!H79:S79),"") -> 6 | D58: =IFERROR(AVERAGE('2023'!G83:R83),"") -> 2.0833333 | E58: =IFERROR(AVERAGE('2023'!G84:R84),"") -> 4.25
A59: Vicepresidencia Operaciones | B59: =IFERROR(AVERAGE('2022'!H80:S80),"") -> 3.0833333 | C59: =IFERROR(AVERAGE('2022'!H81:S81),"") -> 2 | D59: =IFERROR(AVERAGE('2023'!G85:R85),"") -> 1.4166667 | E59: =IFERROR(AVERAGE('2023'!G86:R86),"") -> 3 | F59: =IFERROR(AVERAGE('2024'!G89:R89),"") -> 1.25 | G59: =IFERROR(AVERAGE('2024'!G90:R90),"") -> 0 | H59: =IFERROR(AVERAGE('2025'!G72:R72),"") -> 3 | J59: =IFERROR(AVERAGE('2026'!G69:K69),"") -> 3 | K59: =IFERROR(AVERAGE('2026'!G70:K70),"") -> 3 | L59: =IFERROR(AVERAGE('2026'!G70:R70),"") -> 3
A60: Vicepresidencia Personas y Organización | B60: =IF(COUNT(B61:B64)=0,"",SUM(B61:B64)) | C60: =IF(COUNT(C61:C64)=0,"",SUM(C61:C64)) | D60: =IF(COUNT(D61:D64)=0,"",SUM(D61:D64)) -> 15.166667 | E60: =IF(COUNT(E61:E64)=0,"",SUM(E61:E64)) -> 17.083333 | F60: =IF(COUNT(F61:F64)=0,"",SUM(F61:F64)) -> 37.583333 | G60: =IF(COUNT(G61:G64)=0,"",SUM(G61:G64)) -> 39 | H60: =IF(COUNT(H61:H64)=0,"",SUM(H61:H64)) -> 34.166667 | I60: =IF(COUNT(I61:I64)=0,"",SUM(I61:I64)) -> 39 | ... L60: =IF(COUNT(L61:L64)=0,"",SUM(L61:L64)) -> 36
A61: Desarrollo Organizacional y Compensaciones | D61: =IFERROR(AVERAGE('2023'!G87:R87),"") -> 6.1666667 | E61: =IFERROR(AVERAGE('2023'!G88:R88),"") -> 6.25 | F61: =IFERROR(AVERAGE('2024'!G91:R91),"") -> 16.833333 | G61: =IFERROR(AVERAGE('2024'!G92:R92),"") -> 16 | H61: =IFERROR(AVERAGE('2025'!G73:R73),"") -> 15.083333 | I61: =IFERROR(AVERAGE('2025'!G74:R74),"") -> 17 | J61: =IFERROR(AVERAGE('2026'!G71:K71),"") -> 14 | K61: =IFERROR(AVERAGE('2026'!G72:K72),"") -> 16 | L61: =IFERROR(AVERAGE('2026'!G72:R72),"") -> 16
A62: Efectividad Organizacional | D62: =IFERROR(AVERAGE('2023'!G89:R89),"") -> 6.1666667 | E62: =IFERROR(AVERAGE('2023'!G90:R90),"") -> 7.0833333 | F62: =IFERROR(AVERAGE('2024'!G93:R93),"") -> 13.25 | G62: =IFERROR(AVERAGE('2024'!G94:R94),"") -> 15 | H62: =IFERROR(AVERAGE('2025'!G75:R75),"") -> 12.25 | I62: =IFERROR(AVERAGE('2025'!G76:R76),"") -> 15 | J62: =IFERROR(AVERAGE('2026'!G73:K73),"") -> 12.6 | K62: =IFERROR(AVERAGE('2026'!G74:K74),"") -> 13 | L62: =IFERROR(AVERAGE('2026'!G74:R74),"") -> 13
A63: Relaciones Laborales | D63: =IFERROR(AVERAGE('2023'!G91:R91),"") -> 0.83333333 | E63: =IFERROR(AVERAGE('2023'!G92:R92),"") -> 0.83333333 | F63: =IFERROR(AVERAGE('2024'!G95:R95),"") -> 1.9166667 | G63: =IFERROR(AVERAGE('2024'!G96:R96),"") -> 2 | H63: =IFERROR(AVERAGE('2025'!G77:R77),"") -> 1.8333333 | I63: =IFERROR(AVERAGE('2025'!G78:R78),"") -> 2 | J63: =IFERROR(AVERAGE('2026'!G75:K75),"") -> 1.8 | K63: =IFERROR(AVERAGE('2026'!G76:K76),"") -> 2 | L63: =IFERROR(AVERAGE('2026'!G76:R76),"") -> 2
A64: Vicepresidencia Personas y Organización | D64: =IFERROR(AVERAGE('2023'!G93:R93),"") -> 2 | E64: =IFERROR(AVERAGE('2023'!G94:R94),"") -> 2.9166667 | F64: =IFERROR(AVERAGE('2024'!G97:R97),"") -> 5.5833333 | G64: =IFERROR(AVERAGE('2024'!G98:R98),"") -> 6 | H64: =IFERROR(AVERAGE('2025'!G79:R79),"") -> 5 | I64: =IFERROR(AVERAGE('2025'!G80:R80),"") -> 5 | J64: =IFERROR(AVERAGE('2026'!G77:K77),"") -> 4.8 | K64: =IFERROR(AVERAGE('2026'!G78:K78),"") -> 5 | L64: =IFERROR(AVERAGE('2026'!G78:R78),"") -> 5
A65: Vicepresidencia Planificación y Servicios Técnicos | B65: =IF(COUNT(B66:B75)=0,"",SUM(B66:B75)) | C65: =IF(COUNT(C66:C75)=0,"",SUM(C66:C75)) | D65: =IF(COUNT(D66:D75)=0,"",SUM(D66:D75)) -> 11.416667 | E65: =IF(COUNT(E66:E75)=0,"",SUM(E66:E75)) -> 0 | F65: =IF(COUNT(F66:F75)=0,"",SUM(F66:F75)) -> 27.416667 | G65: =IF(COUNT(G66:G75)=0,"",SUM(G66:G75)) -> 29.833333 | H65: =IF(COUNT(H66:H75)=0,"",SUM(H66:H75)) -> 27.583333 | I65: =IF(COUNT(I66:I75)=0,"",SUM(I66:I75)) -> 32.75 | ... L65: =IF(COUNT(L66:L75)=0,"",SUM(L66:L75)) -> 30
A66: Excelencia Operacional | F66: =IFERROR(AVERAGE('2024'!G99:R99),"") -> 4.6666667 | G66: =IFERROR(AVERAGE('2024'!G100:R100),"") -> 6.8333333 | H66: =IFERROR(AVERAGE('2025'!G81:R81),"") -> 5 | I66: =IFERROR(AVERAGE('2025'!G82:R82),"") -> 5 | J66: =IFERROR(AVERAGE('2026'!G79:K79),"") -> 4.8 | K66: =IFERROR(AVERAGE('2026'!G80:K80),"") -> 4 | L66: =IFERROR(AVERAGE('2026'!G80:R80),"") -> 4
A67: Mantenimiento | F67: =IFERROR(AVERAGE('2024'!G101:R101),"") -> 2.25 | G67: =IFERROR(AVERAGE('2024'!G102:R102),"") -> 0 | H67: =IFERROR(AVERAGE('2025'!G83:R83),"") -> 2.75 | I67: =IFERROR(AVERAGE('2025'!G84:R84),"") -> 3 | J67: =IFERROR(AVERAGE('2026'!G81:K81),"") -> 2.8 | K67: =IFERROR(AVERAGE('2026'!G82:K82),"") -> 3 | L67: =IFERROR(AVERAGE('2026'!G82:R82),"") -> 3
A68: Mineria | F68: =IFERROR(AVERAGE('2024'!G103:R103),"") -> 4 | G68: =IFERROR(AVERAGE('2024'!G104:R104),"") -> 0 | H68: =IFERROR(AVERAGE('2025'!G85:R85),"") -> 0.75 | I68: =IFERROR(AVERAGE('2025'!G86:R86),"") -> 6
A69: Planificación Minera | H69: =IFERROR(AVERAGE('2025'!G87:R87),"") -> 6.5 | J69: =IFERROR(AVERAGE('2026'!G83:K83),"") -> 8.4 | K69: =IFERROR(AVERAGE('2026'!G84:K84),"") -> 10 | L69: =IFERROR(AVERAGE('2026'!G84:R84),"") -> 10
A70: Planificación Minera Metalúrgica | D70: =IFERROR(AVERAGE('2023'!G97:R97),"") -> 2 | E70: =IFERROR(AVERAGE('2023'!G98:R98),"") -> 0 | F70: =IFERROR(AVERAGE('2024'!G105:R105),"") -> 4.5833333 | G70: =IFERROR(AVERAGE('2024'!G106:R106),"") -> 5 | H70: =IFERROR(AVERAGE('2025'!G88:R88),"") -> 0.58333333 | I70: =IFERROR(AVERAGE('2025'!G89:R89),"") -> 5
A71: Procesos | D71: =IFERROR(AVERAGE('2023'!G99:R99),"") -> 0 | E71: =IFERROR(AVERAGE('2023'!G100:R100),"") -> 0 | F71: =IFERROR(AVERAGE('2024'!G107:R107),"") -> 1.9166667 | G71: =IFERROR(AVERAGE('2024'!G108:R108),"") -> 0 | H71: =IFERROR(AVERAGE('2025'!G90:R90),"") -> 2.25 | I71: =IFERROR(AVERAGE('2025'!G91:R91),"") -> 3 | J71: =IFERROR(AVERAGE('2026'!G85:K85),"") -> 2.6 | K71: =IFERROR(AVERAGE('2026'!G86:K86),"") -> 5 | L71: =IFERROR(AVERAGE('2026'!G86:R86),"") -> 5
A72: Recursos Hídricos | D72: =IFERROR(AVERAGE('2023'!G101:R101),"") -> 1.0833333 | E72: =IFERROR(AVERAGE('2023'!G102:R102),"") -> 0 | F72: =IFERROR(AVERAGE('2024'!G109:R109),"") -> 3 | G72: =IFERROR(AVERAGE('2024'!G110:R110),"") -> 3 | H72: =IFERROR(AVERAGE('2025'!G92:R92),"") -> 3 | I72: =IFERROR(AVERAGE('2025'!G93:R93),"") -> 3 | J72: =IFERROR(AVERAGE('2026'!G87:K87),"") -> 3 | K72: =IFERROR(AVERAGE('2026'!G88:K88),"") -> 3 | L72: =IFERROR(AVERAGE('2026'!G88:R88),"") -> 3
A73: Relaves | D73: =IFERROR(AVERAGE('2023'!G103:R103),"") -> 1.5 | E73: =IFERROR(AVERAGE('2023'!G104:R104),"") -> 0 | F73: =IFERROR(AVERAGE('2024'!G111:R111),"") -> 2.5833333 | G73: =IFERROR(AVERAGE('2024'!G112:R112),"") -> 3 | H73: =IFERROR(AVERAGE('2025'!G94:R94),"") -> 4 | I73: =IFERROR(AVERAGE('2025'!G95:R95),"") -> 3.75 | J73: =IFERROR(AVERAGE('2026'!G89:K89),"") -> 4 | K73: =IFERROR(AVERAGE('2026'!G90:K90),"") -> 4 | L73: =IFERROR(AVERAGE('2026'!G90:R90),"") -> 4
A74: Mantenimiento y Excelencia Operacional | D74: =IFERROR(AVERAGE('2023'!G95:R95),"") -> 2.0833333 | E74: =IFERROR(AVERAGE('2023'!G96:R96),"") -> 0
A75: Vicepresidencia Planificación y Servicios Técnicos | D75: =IFERROR(AVERAGE('2023'!G105:R105),"") -> 4.75 | E75: =IFERROR(AVERAGE('2023'!G106:R106),"") -> 0 | F75: =IFERROR(AVERAGE('2024'!G113:R113),"") -> 4.4166667 | G75: =IFERROR(AVERAGE('2024'!G114:R114),"") -> 12 | H75: =IFERROR(AVERAGE('2025'!G96:R96),"") -> 2.75 | I75: =IFERROR(AVERAGE('2025'!G97:R97),"") -> 4 | J75: =IFERROR(AVERAGE('2026'!G91:K91),"") -> 3 | K75: =IFERROR(AVERAGE('2026'!G92:K92),"") -> 1 | L75: =IFERROR(AVERAGE('2026'!G92:R92),"") -> 1
A76: Vicepresidencia Sustentabilidad | B76: =IF(COUNT(B77:B79)=0,"",SUM(B77:B79)) | C76: =IF(COUNT(C77:C79)=0,"",SUM(C77:C79)) | D76: =IF(COUNT(D77:D79)=0,"",SUM(D77:D79)) | E76: =IF(COUNT(E77:E79)=0,"",SUM(E77:E79)) | F76: =IF(COUNT(F77:F79)=0,"",SUM(F77:F79)) -> 6.25 | G76: =IF(COUNT(G77:G79)=0,"",SUM(G77:G79)) -> 0 | H76: =IF(COUNT(H77:H79)=0,"",SUM(H77:H79)) -> 15.75 | I76: =IF(COUNT(I77:I79)=0,"",SUM(I77:I79)) -> 17 | ... L76: =IF(COUNT(L77:L79)=0,"",SUM(L77:L79)) -> 15
A77: Medio Ambiente | F77: =IFERROR(AVERAGE('2024'!G115:R115),"") -> 2.4166667 | G77: =IFERROR(AVERAGE('2024'!G116:R116),"") -> 0 | H77: =IFERROR(AVERAGE('2025'!G98:R98),"") -> 5.5833333 | I77: =IFERROR(AVERAGE('2025'!G99:R99),"") -> 7 | J77: =IFERROR(AVERAGE('2026'!G93:K93),"") -> 6.8 | K77: =IFERROR(AVERAGE('2026'!G94:K94),"") -> 4 | L77: =IFERROR(AVERAGE('2026'!G94:R94),"") -> 4
A78: Seguridad y Salud Ocupacional | F78: =IFERROR(AVERAGE('2024'!G117:R117),"") -> 1.6666667 | G78: =IFERROR(AVERAGE('2024'!G118:R118),"") -> 0 | H78: =IFERROR(AVERAGE('2025'!G100:R100),"") -> 4 | I78: =IFERROR(AVERAGE('2025'!G101:R101),"") -> 4 | J78: =IFERROR(AVERAGE('2026'!G95:K95),"") -> 4 | K78: =IFERROR(AVERAGE('2026'!G96:K96),"") -> 4 | L78: =IFERROR(AVERAGE('2026'!G96:R96),"") -> 4
A79: Vicepresidencia Sustentabilidad | F79: =IFERROR(AVERAGE('2024'!G119:R119),"") -> 2.1666667 | G79: =IFERROR(AVERAGE('2024'!G120:R120),"") -> 0 | H79: =IFERROR(AVERAGE('2025'!G102:R102),"") -> 6.1666667 | I79: =IFERROR(AVERAGE('2025'!G103:R103),"") -> 6 | J79: =IFERROR(AVERAGE('2026'!G97:K97),"") -> 7 | K79: =IFERROR(AVERAGE('2026'!G98:K98),"") -> 7 | L79: =IFERROR(AVERAGE('2026'!G98:R98),"") -> 7
A80: Vicepresidencia Asuntos Corporativos y Sustentabilidad | B80: =IF(COUNT(B81:B87)=0,"",SUM(B81:B87)) -> 61.666667 | C80: =IF(COUNT(C81:C87)=0,"",SUM(C81:C87)) -> 66.5 | D80: =IF(COUNT(D81:D87)=0,"",SUM(D81:D87)) -> 63 | E80: =IF(COUNT(E81:E87)=0,"",SUM(E81:E87)) -> 66.25 | F80: =IF(COUNT(F81:F87)=0,"",SUM(F81:F87)) -> 35.666667 | G80: =IF(COUNT(G81:G87)=0,"",SUM(G81:G87)) -> 67.75 | H80: =IF(COUNT(H81:H87)=0,"",SUM(H81:H87)) | I80: =IF(COUNT(I81:I87)=0,"",SUM(I81:I87)) | ... L80: =IF(COUNT(L81:L87)=0,"",SUM(L81:L87))
A81: Asuntos Públicos Corporativo | B81: =IFERROR(AVERAGE('2022'!H14:S14),"") -> 7 | C81: =IFERROR(AVERAGE('2022'!H15:S15),"") -> 13.5 | D81: =IFERROR(AVERAGE('2023'!G13:R13),"") -> 5.6666667 | E81: =IFERROR(AVERAGE('2023'!G14:R14),"") -> 8 | F81: =IFERROR(AVERAGE('2024'!G13:R13),"") -> 2.75 | G81: =IFERROR(AVERAGE('2024'!G14:R14),"") -> 14
A82: Asuntos Publicos MLP | B82: =IFERROR(AVERAGE('2022'!H16:S16),"") -> 19.916667 | C82: =IFERROR(AVERAGE('2022'!H17:S17),"") -> 21 | D82: =IFERROR(AVERAGE('2023'!G15:R15),"") -> 20.5 | E82: =IFERROR(AVERAGE('2023'!G16:R16),"") -> 22 | F82: =IFERROR(AVERAGE('2024'!G15:R15),"") -> 10.333333 | G82: =IFERROR(AVERAGE('2024'!G16:R16),"") -> 20
A83: Asuntos Públicos Norte | B83: =IFERROR(AVERAGE('2022'!H18:S18),"") -> 13.416667 | C83: =IFERROR(AVERAGE('2022'!H19:S19),"") -> 8 | D83: =IFERROR(AVERAGE('2023'!G17:R17),"") -> 13.583333 | E83: =IFERROR(AVERAGE('2023'!G18:R18),"") -> 14 | F83: =IFERROR(AVERAGE('2024'!G17:R17),"") -> 7.4166667 | G83: =IFERROR(AVERAGE('2024'!G18:R18),"") -> 8
A84: Comunicaciones | B84: =IFERROR(AVERAGE('2022'!H20:S20),"") -> 5.5 | C84: =IFERROR(AVERAGE('2022'!H21:S21),"") -> 7 | D84: =IFERROR(AVERAGE('2023'!G19:R19),"") -> 7 | E84: =IFERROR(AVERAGE('2023'!G20:R20),"") -> 7 | F84: =IFERROR(AVERAGE('2024'!G19:R19),"") -> 4.6666667 | G84: =IFERROR(AVERAGE('2024'!G20:R20),"") -> 8
A85: Medio Ambiente | B85: =IFERROR(AVERAGE('2022'!H22:S22),"") -> 7 | C85: =IFERROR(AVERAGE('2022'!H23:S23),"") -> 8 | D85: =IFERROR(AVERAGE('2023'!G21:R21),"") -> 6 | E85: =IFERROR(AVERAGE('2023'!G22:R22),"") -> 6.25 | F85: =IFERROR(AVERAGE('2024'!G21:R21),"") -> 4.0833333 | G85: =IFERROR(AVERAGE('2024'!G22:R22),"") -> 7
A86: SSO | B86: =IFERROR(AVERAGE('2022'!H24:S24),"") -> 4.6666667 | C86: =IFERROR(AVERAGE('2022'!H25:S25),"") -> 5 | D86: =IFERROR(AVERAGE('2023'!G23:R23),"") -> 4.4166667 | E86: =IFERROR(AVERAGE('2023'!G24:R24),"") -> 5 | F86: =IFERROR(AVERAGE('2024'!G23:R23),"") -> 2.3333333 | G86: =IFERROR(AVERAGE('2024'!G24:R24),"") -> 4
A87: Vicepresidencia Asuntos Corporativos y Sustentabilidad | B87: =IFERROR(AVERAGE('2022'!H26:S26),"") -> 4.1666667 | C87: =IFERROR(AVERAGE('2022'!H27:S27),"") -> 4 | D87: =IFERROR(AVERAGE('2023'!G25:R25),"") -> 5.8333333 | E87: =IFERROR(AVERAGE('2023'!G26:R26),"") -> 4 | F87: =IFERROR(AVERAGE('2024'!G25:R25),"") -> 4.0833333 | G87: =IFERROR(AVERAGE('2024'!G26:R26),"") -> 6.75
A88: Vicepresidencia Recursos Humanos | B88: =IF(COUNT(B89:B95)=0,"",SUM(B89:B95)) -> 35.833333 | C88: =IF(COUNT(C89:C95)=0,"",SUM(C89:C95)) -> 40.25 | D88: =IF(COUNT(D89:D95)=0,"",SUM(D89:D95)) -> 18.416667 | E88: =IF(COUNT(E89:E95)=0,"",SUM(E89:E95)) -> 23.916667 | F88: =IF(COUNT(F89:F95)=0,"",SUM(F89:F95)) | G88: =IF(COUNT(G89:G95)=0,"",SUM(G89:G95)) | H88: =IF(COUNT(H89:H95)=0,"",SUM(H89:H95)) | I88: =IF(COUNT(I89:I95)=0,"",SUM(I89:I95)) | ... L88: =IF(COUNT(L89:L95)=0,"",SUM(L89:L95))
A89: Desarrollo Organizacional y Compensaciones | B89: =IFERROR(AVERAGE('2022'!H86:S86),"") -> 2.1666667 | C89: =IFERROR(AVERAGE('2022'!H87:S87),"") -> 0 | D89: =IFERROR(AVERAGE('2023'!G107:R107),"") -> 6.4166667 | E89: =IFERROR(AVERAGE('2023'!G108:R108),"") -> 8.75
A90: Efectividad Organizacional | B90: =IFERROR(AVERAGE('2022'!H88:S88),"") -> 1.6666667 | C90: =IFERROR(AVERAGE('2022'!H89:S89),"") -> 0 | D90: =IFERROR(AVERAGE('2023'!G109:R109),"") -> 6.9166667 | E90: =IFERROR(AVERAGE('2023'!G110:R110),"") -> 9.9166667
A91: Relaciones Laborales | B91: =IFERROR(AVERAGE('2022'!H90:S90),"") -> 1 | C91: =IFERROR(AVERAGE('2022'!H91:S91),"") -> 1 | D91: =IFERROR(AVERAGE('2023'!G111:R111),"") -> 1 | E91: =IFERROR(AVERAGE('2023'!G112:R112),"") -> 1.1666667
A92: Remuneraciones y Gestión de Recursos Humanos | B92: =IFERROR(AVERAGE('2022'!H92:S92),"") -> 14.833333 | C92: =IFERROR(AVERAGE('2022'!H93:S93),"") -> 20 | D92: =IFERROR(AVERAGE('2023'!G113:R113),"") -> 1.6666667 | E92: =IFERROR(AVERAGE('2023'!G114:R114),"") -> 0
A93: Compensaciones | B93: =IFERROR(AVERAGE('2022'!H82:S82),"") -> 2.5 | C93: =IFERROR(AVERAGE('2022'!H83:S83),"") -> 3
A94: Desarrollo Organizacional | B94: =IFERROR(AVERAGE('2022'!H84:S84),"") -> 10.25 | C94: =IFERROR(AVERAGE('2022'!H85:S85),"") -> 14.25
A95: Vicepresidencia Recursos Humanos | B95: =IFERROR(AVERAGE('2022'!H94:S94),"") -> 3.4166667 | C95: =IFERROR(AVERAGE('2022'!H95:S95),"") -> 2 | D95: =IFERROR(AVERAGE('2023'!G115:R115),"") -> 2.4166667 | E95: =IFERROR(AVERAGE('2023'!G116:R116),"") -> 4.0833333 | M95: =
A96: TOTAL DOTACIÓN PROPIA ACT. CORPORATIVA | B96: =IFERROR(AVERAGE('2022'!H4:S4),"") -> 386.66667 | C96: =IFERROR(AVERAGE('2022'!H5:S5),"") -> 409.08333 | D96: =IFERROR(AVERAGE('2023'!G3:R3),"") -> 391.25 | E96: =IFERROR(AVERAGE('2023'!G4:R4),"") -> 415.75 | F96: =IFERROR(AVERAGE('2024'!G3:R3),"") -> 417.66667 | G96: =IFERROR(AVERAGE('2024'!G4:R4),"") -> 430.5 | H96: =IFERROR(AVERAGE('2025'!G3:R3),"") -> 417.91667 | I96: =IFERROR(AVERAGE('2025'!G4:R4),"") -> 456.25 | J96: =IFERROR(AVERAGE('2026'!G3:K3),"") -> 416.4 | K96: =IFERROR(AVERAGE('2026'!G4:K4),"") -> 443 | L96: =IFERROR(AVERAGE('2026'!G4:R4),"") -> 443
A98: Nota: total por VP = suma de sus gerencias + 'Dirección VP' (personal de la dirección, fila aditiva en origen). Valores = promedio de 12 meses (Dotación Propia Actividad Corporativa). Celdas vacías = la VP/Gerencia no existía ese año. Verde = enlaces a hojas anuales.

Sheet Consolidado Contratista
A1: Dotación Histórica AMSA — Consolidado Contratista por Vicepresidencia y Gerencia 2022–2026
A2: Dotación Contratista Actividad Corporativa · Promedio anual (N°) · Real vs Presupuesto · (Permanente + Temporal)
A4: Vicepresidencia / Gerencia | B4: 2022 | D4: 2023 | F4: 2024 | H4: 2025 | J4: 2026 YTD | L4: 2026 FY
B5: Real | C5: Ppto | D5: Real | E5: Ppto | F5: Real | G5: Ppto | H5: Real | I5: Ppto | J5: Real | K5: Ppto | L5: Ppto
A6: Auditoria | B6: =IF(COUNT(B7:B7)=0,"",SUM(B7:B7)) | C6: =IF(COUNT(C7:C7)=0,"",SUM(C7:C7)) | D6: =IF(COUNT(D7:D7)=0,"",SUM(D7:D7)) | E6: =IF(COUNT(E7:E7)=0,"",SUM(E7:E7)) | F6: =IF(COUNT(F7:F7)=0,"",SUM(F7:F7)) -> 0.25 | G6: =IF(COUNT(G7:G7)=0,"",SUM(G7:G7)) -> 1 | H6: =IF(COUNT(H7:H7)=0,"",SUM(H7:H7)) -> 2.25 | I6: =IF(COUNT(I7:I7)=0,"",SUM(I7:I7)) -> 1 | ... L6: =IF(COUNT(L7:L7)=0,"",SUM(L7:L7)) -> 1.5
A7: Auditoria | F7: =IFERROR(AVERAGE('2024'!G132:R132),"") -> 0.25 | G7: =IFERROR(AVERAGE('2024'!G133:R133),"") -> 1 | H7: =IFERROR(AVERAGE('2025'!G116:R116),"") -> 2.25 | I7: =IFERROR(AVERAGE('2025'!G117:R117),"") -> 1 | J7: =IFERROR(AVERAGE('2026'!G110:K110),"") -> 3 | K7: =IFERROR(AVERAGE('2026'!G111:K111),"") -> 1.8 | L7: =IFERROR(AVERAGE('2026'!G111:R111),"") -> 1.5
A8: Vicepresidencia de Asuntos Corporativos | B8: =IF(COUNT(B9:B10)=0,"",SUM(B9:B10)) | C8: =IF(COUNT(C9:C10)=0,"",SUM(C9:C10)) | D8: =IF(COUNT(D9:D10)=0,"",SUM(D9:D10)) | E8: =IF(COUNT(E9:E10)=0,"",SUM(E9:E10)) | F8: =IF(COUNT(F9:F10)=0,"",SUM(F9:F10)) | G8: =IF(COUNT(G9:G10)=0,"",SUM(G9:G10)) | H8: =IF(COUNT(H9:H10)=0,"",SUM(H9:H10)) -> 2 | I8: =IF(COUNT(I9:I10)=0,"",SUM(I9:I10)) -> 2 | ... L8: =IF(COUNT(L9:L10)=0,"",SUM(L9:L10)) -> 3
A9: Asuntos Públicos Corporativo | H9: =IFERROR(AVERAGE('2025'!G118:R118),"") -> 1 | I9: =IFERROR(AVERAGE('2025'!G119:R119),"") -> 1 | J9: =IFERROR(AVERAGE('2026'!G112:K112),"") -> 1.8 | K9: =IFERROR(AVERAGE('2026'!G113:K113),"") -> 2 | L9: =IFERROR(AVERAGE('2026'!G113:R113),"") -> 2
A10: Asuntos Publicos MLP | H10: =IFERROR(AVERAGE('2025'!G120:R120),"") -> 1 | I10: =IFERROR(AVERAGE('2025'!G121:R121),"") -> 1 | J10: =IFERROR(AVERAGE('2026'!G114:K114),"") -> 1 | K10: =IFERROR(AVERAGE('2026'!G115:K115),"") -> 1 | L10: =IFERROR(AVERAGE('2026'!G115:R115),"") -> 1
A11: Vicepresidencia de Proyectos | B11: =IF(COUNT(B12:B14)=0,"",SUM(B12:B14)) | C11: =IF(COUNT(C12:C14)=0,"",SUM(C12:C14)) | D11: =IF(COUNT(D12:D14)=0,"",SUM(D12:D14)) | E11: =IF(COUNT(E12:E14)=0,"",SUM(E12:E14)) | F11: =IF(COUNT(F12:F14)=0,"",SUM(F12:F14)) -> 21.054167 | G11: =IF(COUNT(G12:G14)=0,"",SUM(G12:G14)) -> 14 | H11: =IF(COUNT(H12:H14)=0,"",SUM(H12:H14)) -> 1.25 | I11: =IF(COUNT(I12:I14)=0,"",SUM(I12:I14)) -> 1 | ... L11: =IF(COUNT(L12:L14)=0,"",SUM(L12:L14)) -> 2
A12: Habilitadores CMZ | F12: =IFERROR(AVERAGE('2024'!G142:R142),0)+IFERROR(AVERAGE('2024'!G143:R143),0) -> 13.698333 | G12: =IFERROR(AVERAGE('2024'!G144:R144),"") -> 0
A13: Proyecto MLP Largo plazo | F13: =IFERROR(AVERAGE('2024'!G145:R145),"") -> 5.6891667 | G13: =IFERROR(AVERAGE('2024'!G146:R146),"") -> 12
A14: Vicepresidencia de Proyectos + Proyecto INCO + Proyecto Estudio | F14: =IFERROR(AVERAGE('2024'!G147:R147),0)+IFERROR(AVERAGE('2024'!G149:R149),0) -> 1.6666667 | G14: =IFERROR(AVERAGE('2024'!G148:R148),0)+IFERROR(AVERAGE('2024'!G150:R150),0) -> 2 | H14: =IFERROR(AVERAGE('2025'!G122:R122),"") -> 1.25 | I14: =IFERROR(AVERAGE('2025'!G123:R123),"") -> 1 | J14: =IFERROR(AVERAGE('2026'!G116:K116),"") -> 0.6 | K14: =IFERROR(AVERAGE('2026'!G117:K117),"") -> 2 | L14: =IFERROR(AVERAGE('2026'!G117:R117),"") -> 2
A15: Vicepresidencia Desarrollo | B15: =IF(COUNT(B16:B16)=0,"",SUM(B16:B16)) | C15: =IF(COUNT(C16:C16)=0,"",SUM(C16:C16)) | D15: =IF(COUNT(D16:D16)=0,"",SUM(D16:D16)) | E15: =IF(COUNT(E16:E16)=0,"",SUM(E16:E16)) | F15: =IF(COUNT(F16:F16)=0,"",SUM(F16:F16)) | G15: =IF(COUNT(G16:G16)=0,"",SUM(G16:G16)) | H15: =IF(COUNT(H16:H16)=0,"",SUM(H16:H16)) | I15: =IF(COUNT(I16:I16)=0,"",SUM(I16:I16)) | ... L15: =IF(COUNT(L16:L16)=0,"",SUM(L16:L16)) -> 4
A16: Vicepresidencia Desarrollo | J16: =IFERROR(AVERAGE('2026'!G118:K118),"") -> 4.6 | K16: =IFERROR(AVERAGE('2026'!G119:K119),"") -> 4 | L16: =IFERROR(AVERAGE('2026'!G119:R119),"") -> 4
A17: Vicepresidencia Estrategia e Innovación | B17: =IF(COUNT(B18:B21)=0,"",SUM(B18:B21)) -> 51.833333 | C17: =IF(COUNT(C18:C21)=0,"",SUM(C18:C21)) -> 52 | D17: =IF(COUNT(D18:D21)=0,"",SUM(D18:D21)) -> 24 | E17: =IF(COUNT(E18:E21)=0,"",SUM(E18:E21)) -> 24 | F17: =IF(COUNT(F18:F21)=0,"",SUM(F18:F21)) -> 26 | G17: =IF(COUNT(G18:G21)=0,"",SUM(G18:G21)) -> 26 | H17: =IF(COUNT(H18:H21)=0,"",SUM(H18:H21)) -> 24.833333 | I17: =IF(COUNT(I18:I21)=0,"",SUM(I18:I21)) -> 24 | ... L17: =IF(COUNT(L18:L21)=0,"",SUM(L18:L21)) -> 24
A18: Proyecto Descarbonización | H18: =IFERROR(AVERAGE('2025'!G124:R124),"") -> 0.66666667 | J18: =IFERROR(AVERAGE('2026'!G120:K120),"") -> 1 | K18: =IFERROR(AVERAGE('2026'!G121:K121),"") -> 1 | L18: =IFERROR(AVERAGE('2026'!G121:R121),"") -> 1
A19: Tecnologia | F19: =IFERROR(AVERAGE('2024'!G151:R151),"") -> 24 | G19: =IFERROR(AVERAGE('2024'!G152:R152),"") -> 24 | H19: =IFERROR(AVERAGE('2025'!G125:R125),"") -> 24 | I19: =IFERROR(AVERAGE('2025'!G126:R126),"") -> 24 | J19: =IFERROR(AVERAGE('2026'!G122:K122),"") -> 23.4 | K19: =IFERROR(AVERAGE('2026'!G123:K123),"") -> 23 | L19: =IFERROR(AVERAGE('2026'!G123:R123),"") -> 23
A20: TICA | B20: =IFERROR(AVERAGE('2022'!H112:S112),"") -> 51.833333 | C20: =IFERROR(AVERAGE('2022'!H113:S113),"") -> 52 | D20: =IFERROR(AVERAGE('2023'!G150:R150),0)+IFERROR(AVERAGE('2023'!G152:R152),0) -> 24 | E20: =IFERROR(AVERAGE('2023'!G151:R151),0)+IFERROR(AVERAGE('2023'!G153:R153),0) -> 24
A21: Vicepresidencia Estrategia e Innovación | F21: =IFERROR(AVERAGE('2024'!G153:R153),"") -> 2 | G21: =IFERROR(AVERAGE('2024'!G154:R154),"") -> 2 | H21: =IFERROR(AVERAGE('2025'!G127:R127),"") -> 0.16666667
A22: Vicepresidencia Finanzas | B22: =IF(COUNT(B23:B27)=0,"",SUM(B23:B27)) -> 13.166667 | C22: =IF(COUNT(C23:C27)=0,"",SUM(C23:C27)) -> 13.083333 | D22: =IF(COUNT(D23:D27)=0,"",SUM(D23:D27)) -> 72.25 | E22: =IF(COUNT(E23:E27)=0,"",SUM(E23:E27)) -> 71.75 | F22: =IF(COUNT(F23:F27)=0,"",SUM(F23:F27)) -> 22 | G22: =IF(COUNT(G23:G27)=0,"",SUM(G23:G27)) -> 27 | H22: =IF(COUNT(H23:H27)=0,"",SUM(H23:H27)) -> 7.5833333 | I22: =IF(COUNT(I23:I27)=0,"",SUM(I23:I27)) -> 22 | ... L22: =IF(COUNT(L23:L27)=0,"",SUM(L23:L27)) -> 10
A23: Abastecimiento | B23: =IFERROR(AVERAGE('2022'!H114:S114),"") -> 8.4166667 | C23: =IFERROR(AVERAGE('2022'!H115:S115),"") -> 8.0833333 | D23: =IFERROR(AVERAGE('2023'!G154:R154),0)+IFERROR(AVERAGE('2023'!G156:R156),0) -> 58.916667 | E23: =IFERROR(AVERAGE('2023'!G155:R155),0)+IFERROR(AVERAGE('2023'!G157:R157),0) -> 56 | F23: =IFERROR(AVERAGE('2024'!G155:R155),"") -> 15.833333 | G23: =IFERROR(AVERAGE('2024'!G156:R156),"") -> 17 | I23: =IFERROR(AVERAGE('2025'!G128:R128),"") -> 13
A24: Finanzas e Impuestos + Planificación Financiera | B24: =IFERROR(AVERAGE('2022'!H118:S118),"") -> 2.75 | C24: =IFERROR(AVERAGE('2022'!H119:S119),"") -> 3 | D24: =IFERROR(AVERAGE('2023'!G162:R162),0)+IFERROR(AVERAGE('2023'!G164:R164),0) -> 1.3333333 | E24: =IFERROR(AVERAGE('2023'!G163:R163),0)+IFERROR(AVERAGE('2023'!G165:R165),0) -> 3 | F24: =IFERROR(AVERAGE('2024'!G159:R159),"") -> 1.1666667 | G24: =IFERROR(AVERAGE('2024'!G160:R160),"") -> 3 | H24: =IFERROR(AVERAGE('2025'!G129:R129),"") -> 1.0833333 | I24: =IFERROR(AVERAGE('2025'!G130:R130),"") -> 3 | J24: =IFERROR(AVERAGE('2026'!G124:K124),"") -> 1 | K24: =IFERROR(AVERAGE('2026'!G125:K125),"") -> 3 | L24: =IFERROR(AVERAGE('2026'!G125:R125),"") -> 3
A25: Riesgo Compliance y Control Interno | D25: =IFERROR(AVERAGE('2023'!G166:R166),0)+IFERROR(AVERAGE('2023'!G168:R168),0) -> 1 | E25: =IFERROR(AVERAGE('2023'!G167:R167),0)+IFERROR(AVERAGE('2023'!G169:R169),0) -> 1 | F25: =IFERROR(AVERAGE('2024'!G161:R161),"") -> 3.8333333 | G25: =IFERROR(AVERAGE('2024'!G162:R162),"") -> 4 | H25: =IFERROR(AVERAGE('2025'!G131:R131),"") -> 5.0833333 | I25: =IFERROR(AVERAGE('2025'!G132:R132),"") -> 4 | J25: =IFERROR(AVERAGE('2026'!G126:K126),"") -> 4.2 | K25: =IFERROR(AVERAGE('2026'!G127:K127),"") -> 6 | L25: =IFERROR(AVERAGE('2026'!G127:R127),"") -> 6
A26: Contabilidad | B26: =IFERROR(AVERAGE('2022'!H116:S116),"") -> 2 | C26: =IFERROR(AVERAGE('2022'!H117:S117),"") -> 2 | D26: =IFERROR(AVERAGE('2023'!G158:R158),0)+IFERROR(AVERAGE('2023'!G160:R160),0) -> 11 | E26: =IFERROR(AVERAGE('2023'!G159:R159),0)+IFERROR(AVERAGE('2023'!G161:R161),0) -> 11.75 | F26: =IFERROR(AVERAGE('2024'!G157:R157),"") -> 0.083333333 | G26: =IFERROR(AVERAGE('2024'!G158:R158),"") -> 1
A27: Vicepresidencia Finanzas | F27: =IFERROR(AVERAGE('2024'!G163:R163),"") -> 1.0833333 | G27: =IFERROR(AVERAGE('2024'!G164:R164),"") -> 2 | H27: =IFERROR(AVERAGE('2025'!G133:R133),"") -> 1.4166667 | I27: =IFERROR(AVERAGE('2025'!G134:R134),"") -> 2 | J27: =IFERROR(AVERAGE('2026'!G128:K128),"") -> 1 | K27: =IFERROR(AVERAGE('2026'!G129:K129),"") -> 1 | L27: =IFERROR(AVERAGE('2026'!G129:R129),"") -> 1
A28: Vicepresidencia Legal | B28: =IF(COUNT(B29:B29)=0,"",SUM(B29:B29)) -> 3 | C28: =IF(COUNT(C29:C29)=0,"",SUM(C29:C29)) -> 3 | D28: =IF(COUNT(D29:D29)=0,"",SUM(D29:D29)) -> 3 | E28: =IF(COUNT(E29:E29)=0,"",SUM(E29:E29)) -> 3 | F28: =IF(COUNT(F29:F29)=0,"",SUM(F29:F29)) -> 3 | G28: =IF(COUNT(G29:G29)=0,"",SUM(G29:G29)) -> 3 | H28: =IF(COUNT(H29:H29)=0,"",SUM(H29:H29)) -> 2.3333333 | I28: =IF(COUNT(I29:I29)=0,"",SUM(I29:I29)) -> 3 | ... L28: =IF(COUNT(L29:L29)=0,"",SUM(L29:L29)) -> 3
A29: Propiedad Minera | B29: =IFERROR(AVERAGE('2022'!H120:S120),"") -> 3 | C29: =IFERROR(AVERAGE('2022'!H121:S121),"") -> 3 | D29: =IFERROR(AVERAGE('2023'!G170:R170),0)+IFERROR(AVERAGE('2023'!G172:R172),0) -> 3 | E29: =IFERROR(AVERAGE('2023'!G171:R171),0)+IFERROR(AVERAGE('2023'!G173:R173),0) -> 3 | F29: =IFERROR(AVERAGE('2024'!G165:R165),"") -> 3 | G29: =IFERROR(AVERAGE('2024'!G166:R166),"") -> 3 | H29: =IFERROR(AVERAGE('2025'!G135:R135),"") -> 2.3333333 | I29: =IFERROR(AVERAGE('2025'!G136:R136),"") -> 3 | J29: =IFERROR(AVERAGE('2026'!G130:K130),"") -> 2 | K29: =IFERROR(AVERAGE('2026'!G131:K131),"") -> 3 | L29: =IFERROR(AVERAGE('2026'!G131:R131),"") -> 3
A30: Vicepresidencia Personas y Organización | B30: =IF(COUNT(B31:B32)=0,"",SUM(B31:B32)) | C30: =IF(COUNT(C31:C32)=0,"",SUM(C31:C32)) | D30: =IF(COUNT(D31:D32)=0,"",SUM(D31:D32)) -> 12.5 | E30: =IF(COUNT(E31:E32)=0,"",SUM(E31:E32)) -> 14.583333 | F30: =IF(COUNT(F31:F32)=0,"",SUM(F31:F32)) -> 33.333333 | G30: =IF(COUNT(G31:G32)=0,"",SUM(G31:G32)) -> 34 | H30: =IF(COUNT(H31:H32)=0,"",SUM(H31:H32)) -> 34 | I30: =IF(COUNT(I31:I32)=0,"",SUM(I31:I32)) -> 34 | ... L30: =IF(COUNT(L31:L32)=0,"",SUM(L31:L32)) -> 35
A31: Desarrollo Organizacional y Compensaciones | F31: =IFERROR(AVERAGE('2024'!G167:R167),"") -> 33.333333 | G31: =IFERROR(AVERAGE('2024'!G168:R168),"") -> 34 | H31: =IFERROR(AVERAGE('2025'!G137:R137),"") -> 34 | I31: =IFERROR(AVERAGE('2025'!G138:R138),"") -> 34 | J31: =IFERROR(AVERAGE('2026'!G132:K132),"") -> 35 | K31: =IFERROR(AVERAGE('2026'!G133:K133),"") -> 35 | L31: =IFERROR(AVERAGE('2026'!G133:R133),"") -> 35
A32: Remuneraciones y Gestión de Recursos Humanos | D32: =IFERROR(AVERAGE('2023'!G174:R174),"") -> 12.5 | E32: =IFERROR(AVERAGE('2023'!G175:R175),"") -> 14.583333
A33: Vicepresidencia Sustentabilidad | B33: =IF(COUNT(B34:B35)=0,"",SUM(B34:B35)) | C33: =IF(COUNT(C34:C35)=0,"",SUM(C34:C35)) | D33: =IF(COUNT(D34:D35)=0,"",SUM(D34:D35)) | E33: =IF(COUNT(E34:E35)=0,"",SUM(E34:E35)) | F33: =IF(COUNT(F34:F35)=0,"",SUM(F34:F35)) | G33: =IF(COUNT(G34:G35)=0,"",SUM(G34:G35)) | H33: =IF(COUNT(H34:H35)=0,"",SUM(H34:H35)) -> 11.791667 | I33: =IF(COUNT(I34:I35)=0,"",SUM(I34:I35)) -> 14.083333 | ... L33: =IF(COUNT(L34:L35)=0,"",SUM(L34:L35)) -> 10
A34: Medio Ambiente | H34: =IFERROR(AVERAGE('2025'!G139:R139),"") -> 4.375 | I34: =IFERROR(AVERAGE('2025'!G140:R140),"") -> 6.0833333 | J34: =IFERROR(AVERAGE('2026'!G134:K134),"") -> 5 | K34: =IFERROR(AVERAGE('2026'!G135:K135),"") -> 5 | L34: =IFERROR(AVERAGE('2026'!G135:R135),"") -> 5
A35: Seguridad y Salud Ocupacional | H35: =IFERROR(AVERAGE('2025'!G141:R141),"") -> 7.4166667 | I35: =IFERROR(AVERAGE('2025'!G142:R142),"") -> 8 | J35: =IFERROR(AVERAGE('2026'!G136:K136),"") -> 6.2 | K35: =IFERROR(AVERAGE('2026'!G137:K137),"") -> 5 | L35: =IFERROR(AVERAGE('2026'!G137:R137),"") -> 5
A36: Vicepresidencia Asuntos Corporativos y Sustentabilidad | B36: =IF(COUNT(B37:B41)=0,"",SUM(B37:B41)) -> 14.49 | C36: =IF(COUNT(C37:C41)=0,"",SUM(C37:C41)) -> 14 | D36: =IF(COUNT(D37:D41)=0,"",SUM(D37:D41)) -> 16.284167 | E36: =IF(COUNT(E37:E41)=0,"",SUM(E37:E41)) -> 15 | F36: =IF(COUNT(F37:F41)=0,"",SUM(F37:F41)) -> 14.083333 | G36: =IF(COUNT(G37:G41)=0,"",SUM(G37:G41)) -> 11.25 | H36: =IF(COUNT(H37:H41)=0,"",SUM(H37:H41)) | I36: =IF(COUNT(I37:I41)=0,"",SUM(I37:I41)) | ... L36: =IF(COUNT(L37:L41)=0,"",SUM(L37:L41))
A37: Asuntos Públicos Corporativo | B37: =IFERROR(AVERAGE('2022'!H104:S104),"") -> 1 | C37: =IFERROR(AVERAGE('2022'!H105:S105),"") -> 1 | D37: =IFERROR(AVERAGE('2023'!G130:R130),0)+IFERROR(AVERAGE('2023'!G132:R132),0) -> 1.65 | E37: =IFERROR(AVERAGE('2023'!G131:R131),0)+IFERROR(AVERAGE('2023'!G133:R133),0) -> 2 | F37: =IFERROR(AVERAGE('2024'!G134:R134),"") -> 1 | G37: =IFERROR(AVERAGE('2024'!G135:R135),"") -> 1
A38: Asuntos Publicos MLP | D38: =IFERROR(AVERAGE('2023'!G134:R134),0)+IFERROR(AVERAGE('2023'!G136:R136),0) -> 0.83333333 | E38: =IFERROR(AVERAGE('2023'!G135:R135),0)+IFERROR(AVERAGE('2023'!G137:R137),0) -> 1 | F38: =IFERROR(AVERAGE('2024'!G136:R136),"") -> 1 | G38: =IFERROR(AVERAGE('2024'!G137:R137),"") -> 1
A39: Medio Ambiente | B39: =IFERROR(AVERAGE('2022'!H108:S108),"") -> 1.75 | C39: =IFERROR(AVERAGE('2022'!H109:S109),"") -> 3 | D39: =IFERROR(AVERAGE('2023'!G142:R142),0)+IFERROR(AVERAGE('2023'!G144:R144),0) -> 2.75 | E39: =IFERROR(AVERAGE('2023'!G143:R143),0)+IFERROR(AVERAGE('2023'!G145:R145),0) -> 3 | F39: =IFERROR(AVERAGE('2024'!G138:R138),"") -> 4.5833333 | G39: =IFERROR(AVERAGE('2024'!G139:R139),"") -> 3
A40: SSO | B40: =IFERROR(AVERAGE('2022'!H110:S110),"") -> 9.8333333 | C40: =IFERROR(AVERAGE('2022'!H111:S111),"") -> 9 | D40: =IFERROR(AVERAGE('2023'!G146:R146),0)+IFERROR(AVERAGE('2023'!G148:R148),0) -> 11.050833 | E40: =IFERROR(AVERAGE('2023'!G147:R147),0)+IFERROR(AVERAGE('2023'!G149:R149),0) -> 9 | F40: =IFERROR(AVERAGE('2024'!G140:R140),"") -> 7.5 | G40: =IFERROR(AVERAGE('2024'!G141:R141),"") -> 6.25
A41: Comunicaciones | B41: =IFERROR(AVERAGE('2022'!H106:S106),"") -> 1.9066667 | C41: =IFERROR(AVERAGE('2022'!H107:S107),"") -> 1 | D41: =IFERROR(AVERAGE('2023'!G138:R138),0)+IFERROR(AVERAGE('2023'!G140:R140),0) -> 0 | E41: =IFERROR(AVERAGE('2023'!G139:R139),0)+IFERROR(AVERAGE('2023'!G141:R141),0) -> 0
A42: Vicepresidencia Recursos Humanos | B42: =IF(COUNT(B43:B44)=0,"",SUM(B43:B44)) -> 37 | C42: =IF(COUNT(C43:C44)=0,"",SUM(C43:C44)) -> 49 | D42: =IF(COUNT(D43:D44)=0,"",SUM(D43:D44)) -> 20.75 | E42: =IF(COUNT(E43:E44)=0,"",SUM(E43:E44)) -> 22.416667 | F42: =IF(COUNT(F43:F44)=0,"",SUM(F43:F44)) | G42: =IF(COUNT(G43:G44)=0,"",SUM(G43:G44)) | H42: =IF(COUNT(H43:H44)=0,"",SUM(H43:H44)) | I42: =IF(COUNT(I43:I44)=0,"",SUM(I43:I44)) | ... L42: =IF(COUNT(L43:L44)=0,"",SUM(L43:L44))
A43: Desarrollo Organizacional | D43: =IFERROR(AVERAGE('2023'!G176:R176),0)+IFERROR(AVERAGE('2023'!G178:R178),0) -> 2 | E43: =IFERROR(AVERAGE('2023'!G177:R177),0)+IFERROR(AVERAGE('2023'!G179:R179),0) -> 2
A44: Remuneraciones y Gestión de Recursos Humanos | B44: =IFERROR(AVERAGE('2022'!H122:S122),"") -> 37 | C44: =IFERROR(AVERAGE('2022'!H123:S123),"") -> 49 | D44: =IFERROR(AVERAGE('2023'!G180:R180),0)+IFERROR(AVERAGE('2023'!G182:R182),0) -> 18.75 | E44: =IFERROR(AVERAGE('2023'!G181:R181),0)+IFERROR(AVERAGE('2023'!G183:R183),0) -> 20.416667
A45: TOTAL DOTACIÓN CONTRATISTA ACT. CORPORATIVA | B45: =N(B6)+N(B8)+N(B11)+N(B15)+N(B17)+N(B22)+N(B28)+N(B30)+N(B33)+N(B36)+N(B42) -> 119.49 | C45: =N(C6)+N(C8)+N(C11)+N(C15)+N(C17)+N(C22)+N(C28)+N(C30)+N(C33)+N(C36)+N(C42) -> 131.08333 | D45: =N(D6)+N(D8)+N(D11)+N(D15)+N(D17)+N(D22)+N(D28)+N(D30)+N(D33)+N(D36)+N(D42) -> 148.78417 | E45: =N(E6)+N(E8)+N(E11)+N(E15)+N(E17)+N(E22)+N(E28)+N(E30)+N(E33)+N(E36)+N(E42) -> 150.75 | F45: =N(F6)+N(F8)+N(F11)+N(F15)+N(F17)+N(F22)+N(F28)+N(F30)+N(F33)+N(F36)+N(F42) -> 119.72083 | G45: =N(G6)+N(G8)+N(G11)+N(G15)+N(G17)+N(G22)+N(G28)+N(G30)+N(G33)+N(G36)+N(G42) -> 116.25 | H45: =N(H6)+N(H8)+N(H11)+N(H15)+N(H17)+N(H22)+N(H28)+N(H30)+N(H33)+N(H36)+N(H42) -> 86.041667 | I45: =N(I6)+N(I8)+N(I11)+N(I15)+N(I17)+N(I22)+N(I28)+N(I30)+N(I33)+N(I36)+N(I42) -> 101.08333 | ... L45: =N(L6)+N(L8)+N(L11)+N(L15)+N(L17)+N(L22)+N(L28)+N(L30)+N(L33)+N(L36)+N(L42) -> 92.5
A47: Nota: Dotación Contratista Actividad Corporativa (Permanente + Temporal). Total por VP = suma de gerencias + 'Dirección VP'. Valores = promedio de 12 meses. Vacío = no existía ese año. Verde = enlaces a hojas anuales.

Sheet 2026
B1: Libro Dotación Minera AMSA
B3: Total Dotación Propia Actividad Corporativa | F3: Real | G3: 420 | H3: 419 | I3: 420 | J3: 415 | K3: 408 | L3: 0 | M3: 0 | N3: 0 | O3: 0 | P3: 0 | Q3: 0 | R3: 0 | U3: =+AVERAGE(G3:K3) -> 416.4
F4: Ppto | G4: 443 | H4: 443 | I4: 443 | J4: 443 | K4: 443 | L4: 443 | M4: 443 | N4: 443 | O4: 443 | P4: 443 | Q4: 443 | R4: 443 | U4: =+AVERAGE(G4:K4) -> 443
U5: =+AVERAGE(G5:K5) -> #DIV/0!
B6: Propia | F6: N° | G6: 202601 | H6: 202602 | I6: 202603 | J6: 202604 | K6: 202605 | L6: 202606 | M6: 202607 | N6: 202608 | O6: 202609 | P6: 202610 | Q6: 202611 | R6: 202612 | U6: =+AVERAGE(G6:K6) -> #DIV/0!
B7: Auditoria | D7: Auditoria | F7: Real | G7: 15 | H7: 15 | I7: 15 | J7: 15 | K7: 15 | L7: 0 | M7: 0 | N7: 0 | O7: 0 | P7: 0 | Q7: 0 | R7: 0 | U7: =+AVERAGE(G7:K7) -> 15
F8: Ppto | G8: 15 | H8: 15 | I8: 15 | J8: 15 | K8: 15 | L8: 15 | M8: 15 | N8: 15 | O8: 15 | P8: 15 | Q8: 15 | R8: 15 | U8: =+AVERAGE(G8:K8) -> 15
B9: Directorio | D9: Directorio | F9: Real | G9: 3 | H9: 3 | I9: 3 | J9: 3 | K9: 3 | L9: 0 | M9: 0 | N9: 0 | O9: 0 | P9: 0 | Q9: 0 | R9: 0 | U9: =+AVERAGE(G9:K9) -> 3
F10: Ppto | G10: 3 | H10: 3 | I10: 3 | J10: 3 | K10: 3 | L10: 3 | M10: 3 | N10: 3 | O10: 3 | P10: 3 | Q10: 3 | R10: 3 | U10: =+AVERAGE(G10:K10) -> 3
B11: Presidencia Ejecutiva | D11: Presidencia Ejecutiva | F11: Real | G11: 2 | H11: 2 | I11: 2 | J11: 2 | K11: 2 | L11: 0 | M11: 0 | N11: 0 | O11: 0 | P11: 0 | Q11: 0 | R11: 0 | U11: =+AVERAGE(G11:K11) -> 2
F12: Ppto | G12: 2 | H12: 2 | I12: 2 | J12: 2 | K12: 2 | L12: 2 | M12: 2 | N12: 2 | O12: 2 | P12: 2 | Q12: 2 | R12: 2 | U12: =+AVERAGE(G12:K12) -> 2
B13: Vicepresidencia ComercializaciÃ³n | D13: Ventas CÃ¡todos Molibdeno y Hedge | F13: Real | G13: 5 | H13: 5 | I13: 5 | J13: 5 | K13: 5 | L13: 0 | M13: 0 | N13: 0 | O13: 0 | P13: 0 | Q13: 0 | R13: 0 | U13: =+AVERAGE(G13:K13) -> 5
F14: Ppto | G14: 5 | H14: 5 | I14: 5 | J14: 5 | K14: 5 | L14: 5 | M14: 5 | N14: 5 | O14: 5 | P14: 5 | Q14: 5 | R14: 5 | U14: =+AVERAGE(G14:K14) -> 5
D15: Ventas Concentrado Acido | F15: Real | G15: 5 | H15: 5 | I15: 5 | J15: 5 | K15: 5 | L15: 0 | M15: 0 | N15: 0 | O15: 0 | P15: 0 | Q15: 0 | R15: 0 | U15: =+AVERAGE(G15:K15) -> 5
F16: Ppto | G16: 5 | H16: 5 | I16: 5 | J16: 5 | K16: 5 | L16: 5 | M16: 5 | N16: 5 | O16: 5 | P16: 5 | Q16: 5 | R16: 5 | U16: =+AVERAGE(G16:K16) -> 5
D17: Vicepresidencia ComercializaciÃ³n | F17: Real | G17: 9 | H17: 9 | I17: 9 | J17: 9 | K17: 9 | L17: 0 | M17: 0 | N17: 0 | O17: 0 | P17: 0 | Q17: 0 | R17: 0 | U17: =+AVERAGE(G17:K17) -> 9
F18: Ppto | G18: 9 | H18: 9 | I18: 9 | J18: 9 | K18: 9 | L18: 9 | M18: 9 | N18: 9 | O18: 9 | P18: 9 | Q18: 9 | R18: 9 | U18: =+AVERAGE(G18:K18) -> 9
D19: Asuntos Publicos MLP | F19: Real | G19: 19 | H19: 18 | I19: 18 | J19: 17 | K19: 15 | L19: 0 | M19: 0 | N19: 0 | O19: 0 | P19: 0 | Q19: 0 | R19: 0 | U19: =+AVERAGE(G19:K19) -> 17.4
F20: Ppto | G20: 18 | H20: 18 | I20: 18 | J20: 18 | K20: 18 | L20: 18 | M20: 18 | N20: 18 | O20: 18 | P20: 18 | Q20: 18 | R20: 18 | U20: =+AVERAGE(G20:K20) -> 18
D21: Asuntos PÃºblicos Norte | F21: Real | G21: 12 | H21: 14 | I21: 13 | J21: 13 | K21: 13 | L21: 0 | M21: 0 | N21: 0 | O21: 0 | P21: 0 | Q21: 0 | R21: 0 | U21: =+AVERAGE(G21:K21) -> 13
F22: Ppto | G22: 15 | H22: 15 | I22: 15 | J22: 15 | K22: 15 | L22: 15 | M22: 15 | N22: 15 | O22: 15 | P22: 15 | Q22: 15 | R22: 15 | U22: =+AVERAGE(G22:K22) -> 15
D23: Comunicaciones | F23: Real | G23: 7 | H23: 8 | I23: 8 | J23: 8 | K23: 8 | L23: 0 | M23: 0 | N23: 0 | O23: 0 | P23: 0 | Q23: 0 | R23: 0 | U23: =+AVERAGE(G23:K23) -> 7.8
F24: Ppto | G24: 8 | H24: 8 | I24: 8 | J24: 8 | K24: 8 | L24: 8 | M24: 8 | N24: 8 | O24: 8 | P24: 8 | Q24: 8 | R24: 8 | U24: =+AVERAGE(G24:K24) -> 8
D25: Vicepresidencia Asuntos Corporativos | F25: Real | G25: 10 | H25: 10 | I25: 10 | J25: 11 | K25: 11 | L25: 0 | M25: 0 | N25: 0 | O25: 0 | P25: 0 | Q25: 0 | R25: 0 | U25: =+AVERAGE(G25:K25) -> 10.4
F26: Ppto | G26: 11 | H26: 11 | I26: 11 | J26: 11 | K26: 11 | L26: 11 | M26: 11 | N26: 11 | O26: 11 | P26: 11 | Q26: 11 | R26: 11 | U26: =+AVERAGE(G26:K26) -> 11
B27: Vicepresidencia de Proyectos | D27: Finanzas VPP | F27: Real | G27: 14 | H27: 13 | I27: 13 | J27: 12 | K27: 13 | L27: 0 | M27: 0 | N27: 0 | O27: 0 | P27: 0 | Q27: 0 | R27: 0 | U27: =+AVERAGE(G27:K27) -> 13
F28: Ppto | G28: 14 | H28: 14 | I28: 14 | J28: 14 | K28: 14 | L28: 14 | M28: 14 | N28: 14 | O28: 14 | P28: 14 | Q28: 14 | R28: 14 | U28: =+AVERAGE(G28:K28) -> 14
D29: Ingenieria y Construccion | F29: Real | G29: 2 | H29: 2 | I29: 2 | J29: 2 | K29: 2 | L29: 0 | M29: 0 | N29: 0 | O29: 0 | P29: 0 | Q29: 0 | R29: 0 | U29: =+AVERAGE(G29:K29) -> 2
F30: Ppto | G30: 5 | H30: 5 | I30: 5 | J30: 5 | K30: 5 | L30: 5 | M30: 5 | N30: 5 | O30: 5 | P30: 5 | Q30: 5 | R30: 5 | U30: =+AVERAGE(G30:K30) -> 5
D31: Vicepresidencia de Proyectos + Proyecto INCO + Proyecto Estudio | F31: Real | G31: 10 | H31: 10 | I31: 10 | J31: 9 | K31: 8 | L31: 0 | M31: 0 | N31: 0 | O31: 0 | P31: 0 | Q31: 0 | R31: 0 | U31: =+AVERAGE(G31:K31) -> 9.4
F32: Ppto | G32: 8 | H32: 8 | I32: 8 | J32: 8 | K32: 8 | L32: 8 | M32: 8 | N32: 8 | O32: 8 | P32: 8 | Q32: 8 | R32: 8 | U32: =+AVERAGE(G32:K32) -> 8
B33: Vicepresidencia Desarrollo | D33: AdministraciÃ³n MIC | F33: Real | G33: 2 | H33: 2 | I33: 2 | J33: 2 | K33: 2 | L33: 0 | M33: 0 | N33: 0 | O33: 0 | P33: 0 | Q33: 0 | R33: 0 | U33: =+AVERAGE(G33:K33) -> 2
F34: Ppto | G34: 2 | H34: 2 | I34: 2 | J34: 2 | K34: 2 | L34: 2 | M34: 2 | N34: 2 | O34: 2 | P34: 2 | Q34: 2 | R34: 2 | U34: =+AVERAGE(G34:K34) -> 2
D35: Desarrollo | F35: Real | G35: 9 | H35: 9 | I35: 9 | J35: 8 | K35: 6 | L35: 0 | M35: 0 | N35: 0 | O35: 0 | P35: 0 | Q35: 0 | R35: 0 | U35: =+AVERAGE(G35:K35) -> 8.2
F36: Ppto | G36: 9 | H36: 9 | I36: 9 | J36: 9 | K36: 9 | L36: 9 | M36: 9 | N36: 9 | O36: 9 | P36: 9 | Q36: 9 | R36: 9 | U36: =+AVERAGE(G36:K36) -> 9
D37: Vicepresidencia Desarrollo | F37: Real | G37: 10 | H37: 9 | I37: 9 | J37: 8 | K37: 3 | L37: 0 | M37: 0 | N37: 0 | O37: 0 | P37: 0 | Q37: 0 | R37: 0 | U37: =+AVERAGE(G37:K37) -> 7.8
F38: Ppto | G38: 10 | H38: 10 | I38: 10 | J38: 10 | K38: 10 | L38: 10 | M38: 10 | N38: 10 | O38: 10 | P38: 10 | Q38: 10 | R38: 10 | U38: =+AVERAGE(G38:K38) -> 10
B39: Vicepresidencia Estrategia e InnovaciÃ³n | D39: Data y AnalÃ­tica Avanzada | F39: Real | G39: 8 | H39: 8 | I39: 8 | J39: 8 | K39: 9 | L39: 0 | M39: 0 | N39: 0 | O39: 0 | P39: 0 | Q39: 0 | R39: 0 | U39: =+AVERAGE(G39:K39) -> 8.2
F40: Ppto | G40: 8 | H40: 8 | I40: 8 | J40: 8 | K40: 8 | L40: 8 | M40: 8 | N40: 8 | O40: 8 | P40: 8 | Q40: 8 | R40: 8 | U40: =+AVERAGE(G40:K40) -> 8
D41: InnovaciÃ³n + EnergÃ­a y Recursos HÃ­dricos | F41: Real | G41: 5 | H41: 5 | I41: 5 | J41: 5 | K41: 4 | L41: 0 | M41: 0 | N41: 0 | O41: 0 | P41: 0 | Q41: 0 | R41: 0 | U41: =+AVERAGE(G41:K41) -> 4.8
F42: Ppto | G42: 5 | H42: 5 | I42: 5 | J42: 5 | K42: 5 | L42: 5 | M42: 5 | N42: 5 | O42: 5 | P42: 5 | Q42: 5 | R42: 5 | U42: =+AVERAGE(G42:K42) -> 5
D43: Proyecto DescarbonizaciÃ³n | F43: Real | G43: 5 | H43: 5 | I43: 5 | J43: 5 | K43: 5 | L43: 0 | M43: 0 | N43: 0 | O43: 0 | P43: 0 | Q43: 0 | R43: 0 | U43: =+AVERAGE(G43:K43) -> 5
F44: Ppto | G44: 5 | H44: 5 | I44: 5 | J44: 5 | K44: 5 | L44: 5 | M44: 5 | N44: 5 | O44: 5 | P44: 5 | Q44: 5 | R44: 5 | U44: =+AVERAGE(G44:K44) -> 5
D45: Tecnologia | F45: Real | G45: 51 | H45: 52 | I45: 52 | J45: 51 | K45: 52 | L45: 0 | M45: 0 | N45: 0 | O45: 0 | P45: 0 | Q45: 0 | R45: 0 | U45: =+AVERAGE(G45:K45) -> 51.6
F46: Ppto | G46: 57 | H46: 57 | I46: 57 | J46: 57 | K46: 57 | L46: 57 | M46: 57 | N46: 57 | O46: 57 | P46: 57 | Q46: 57 | R46: 57 | U46: =+AVERAGE(G46:K46) -> 57
D47: Vicepresidencia Estrategia e InnovaciÃ³n | F47: Real | G47: 4 | H47: 5 | I47: 5 | J47: 5 | K47: 5 | L47: 0 | M47: 0 | N47: 0 | O47: 0 | P47: 0 | Q47: 0 | R47: 0 | U47: =+AVERAGE(G47:K47) -> 4.8
F48: Ppto | G48: 6 | H48: 6 | I48: 6 | J48: 6 | K48: 6 | L48: 6 | M48: 6 | N48: 6 | O48: 6 | P48: 6 | Q48: 6 | R48: 6 | U48: =+AVERAGE(G48:K48) -> 6
B49: Vicepresidencia Finanzas | D49: Abastecimiento | F49: Real | G49: 32 | H49: 31 | I49: 30 | J49: 29 | K49: 30 | L49: 0 | M49: 0 | N49: 0 | O49: 0 | P49: 0 | Q49: 0 | R49: 0 | U49: =+AVERAGE(G49:K49) -> 30.4
F50: Ppto | G50: 33 | H50: 33 | I50: 33 | J50: 33 | K50: 33 | L50: 33 | M50: 33 | N50: 33 | O50: 33 | P50: 33 | Q50: 33 | R50: 33 | U50: =+AVERAGE(G50:K50) -> 33
D51: Contabilidad | F51: Real | G51: 34 | H51: 32 | I51: 32 | J51: 33 | K51: 33 | L51: 0 | M51: 0 | N51: 0 | O51: 0 | P51: 0 | Q51: 0 | R51: 0 | U51: =+AVERAGE(G51:K51) -> 32.8
F52: Ppto | G52: 34 | H52: 34 | I52: 34 | J52: 34 | K52: 34 | L52: 34 | M52: 34 | N52: 34 | O52: 34 | P52: 34 | Q52: 34 | R52: 34 | U52: =+AVERAGE(G52:K52) -> 34
D53: EnergÃ­a y Servicios EstratÃ©gicos | F53: Real | G53: 3 | H53: 3 | I53: 3 | J53: 3 | K53: 3 | L53: 0 | M53: 0 | N53: 0 | O53: 0 | P53: 0 | Q53: 0 | R53: 0 | U53: =+AVERAGE(G53:K53) -> 3
F54: Ppto | G54: 3 | H54: 3 | I54: 3 | J54: 3 | K54: 3 | L54: 3 | M54: 3 | N54: 3 | O54: 3 | P54: 3 | Q54: 3 | R54: 3 | U54: =+AVERAGE(G54:K54) -> 3
D55: Finanzas e Impuestos + PlanificaciÃ³n Financiera | F55: Real | G55: 27 | H55: 27 | I55: 27 | J55: 26 | K55: 25 | L55: 0 | M55: 0 | N55: 0 | O55: 0 | P55: 0 | Q55: 0 | R55: 0 | U55: =+AVERAGE(G55:K55) -> 26.4
F56: Ppto | G56: 27 | H56: 27 | I56: 27 | J56: 27 | K56: 27 | L56: 27 | M56: 27 | N56: 27 | O56: 27 | P56: 27 | Q56: 27 | R56: 27 | U56: =+AVERAGE(G56:K56) -> 27
D57: Planificacion y Control de Gestion | F57: Real | G57: 9 | H57: 9 | I57: 9 | J57: 9 | K57: 10 | L57: 0 | M57: 0 | N57: 0 | O57: 0 | P57: 0 | Q57: 0 | R57: 0 | U57: =+AVERAGE(G57:K57) -> 9.2
F58: Ppto | G58: 10 | H58: 10 | I58: 10 | J58: 10 | K58: 10 | L58: 10 | M58: 10 | N58: 10 | O58: 10 | P58: 10 | Q58: 10 | R58: 10 | U58: =+AVERAGE(G58:K58) -> 10
D59: Riesgo Compliance y Control Interno | F59: Real | G59: 7 | H59: 8 | I59: 8 | J59: 9 | K59: 5 | L59: 0 | M59: 0 | N59: 0 | O59: 0 | P59: 0 | Q59: 0 | R59: 0 | U59: =+AVERAGE(G59:K59) -> 7.4
F60: Ppto | G60: 10 | H60: 10 | I60: 10 | J60: 10 | K60: 10 | L60: 10 | M60: 10 | N60: 10 | O60: 10 | P60: 10 | Q60: 10 | R60: 10 | U60: =+AVERAGE(G60:K60) -> 10
D61: Vicepresidencia Finanzas | F61: Real | G61: 2 | H61: 1 | I61: 1 | J61: 2 | K61: 2 | L61: 0 | M61: 0 | N61: 0 | O61: 0 | P61: 0 | Q61: 0 | R61: 0 | U61: =+AVERAGE(G61:K61) -> 1.6
F62: Ppto | G62: 2 | H62: 2 | I62: 2 | J62: 2 | K62: 2 | L62: 2 | M62: 2 | N62: 2 | O62: 2 | P62: 2 | Q62: 2 | R62: 2 | U62: =+AVERAGE(G62:K62) -> 2
B63: Vicepresidencia Legal | D63: Legal | F63: Real | G63: 6 | H63: 6 | I63: 6 | J63: 6 | K63: 5 | L63: 0 | M63: 0 | N63: 0 | O63: 0 | P63: 0 | Q63: 0 | R63: 0 | U63: =+AVERAGE(G63:K63) -> 5.8
F64: Ppto | G64: 9 | H64: 9 | I64: 9 | J64: 9 | K64: 9 | L64: 9 | M64: 9 | N64: 9 | O64: 9 | P64: 9 | Q64: 9 | R64: 9 | U64: =+AVERAGE(G64:K64) -> 9
D65: Propiedad Minera | F65: Real | G65: 9 | H65: 9 | I65: 9 | J65: 9 | K65: 9 | L65: 0 | M65: 0 | N65: 0 | O65: 0 | P65: 0 | Q65: 0 | R65: 0 | U65: =+AVERAGE(G65:K65) -> 9
F66: Ppto | G66: 9 | H66: 9 | I66: 9 | J66: 9 | K66: 9 | L66: 9 | M66: 9 | N66: 9 | O66: 9 | P66: 9 | Q66: 9 | R66: 9 | U66: =+AVERAGE(G66:K66) -> 9
D67: Vicepresidencia Legal | F67: Real | G67: 3 | H67: 3 | I67: 3 | J67: 3 | K67: 7 | L67: 0 | M67: 0 | N67: 0 | O67: 0 | P67: 0 | Q67: 0 | R67: 0 | U67: =+AVERAGE(G67:K67) -> 3.8
F68: Ppto | G68: 2 | H68: 2 | I68: 2 | J68: 2 | K68: 2 | L68: 2 | M68: 2 | N68: 2 | O68: 2 | P68: 2 | Q68: 2 | R68: 2 | U68: =+AVERAGE(G68:K68) -> 2
B69: Vicepresidencia Operaciones | D69: Vicepresidencia Operaciones | F69: Real | G69: 3 | H69: 3 | I69: 3 | J69: 3 | K69: 3 | L69: 0 | M69: 0 | N69: 0 | O69: 0 | P69: 0 | Q69: 0 | R69: 0 | U69: =+AVERAGE(G69:K69) -> 3
F70: Ppto | G70: 3 | H70: 3 | I70: 3 | J70: 3 | K70: 3 | L70: 3 | M70: 3 | N70: 3 | O70: 3 | P70: 3 | Q70: 3 | R70: 3 | U70: =+AVERAGE(G70:K70) -> 3
B71: Vicepresidencia Personas y OrganizaciÃ³n | D71: Desarrollo Organizacional y Compensaciones | F71: Real | G71: 13 | H71: 14 | I71: 15 | J71: 14 | K71: 14 | L71: 0 | M71: 0 | N71: 0 | O71: 0 | P71: 0 | Q71: 0 | R71: 0 | U71: =+AVERAGE(G71:K71) -> 14
F72: Ppto | G72: 16 | H72: 16 | I72: 16 | J72: 16 | K72: 16 | L72: 16 | M72: 16 | N72: 16 | O72: 16 | P72: 16 | Q72: 16 | R72: 16 | U72: =+AVERAGE(G72:K72) -> 16
D73: Efectividad Organizacional | F73: Real | G73: 13 | H73: 13 | I73: 12 | J73: 12 | K73: 13 | L73: 0 | M73: 0 | N73: 0 | O73: 0 | P73: 0 | Q73: 0 | R73: 0 | U73: =+AVERAGE(G73:K73) -> 12.6
F74: Ppto | G74: 13 | H74: 13 | I74: 13 | J74: 13 | K74: 13 | L74: 13 | M74: 13 | N74: 13 | O74: 13 | P74: 13 | Q74: 13 | R74: 13 | U74: =+AVERAGE(G74:K74) -> 13
D75: Relaciones Laborales | F75: Real | G75: 1 | H75: 2 | I75: 2 | J75: 2 | K75: 2 | L75: 0 | M75: 0 | N75: 0 | O75: 0 | P75: 0 | Q75: 0 | R75: 0 | U75: =+AVERAGE(G75:K75) -> 1.8
F76: Ppto | G76: 2 | H76: 2 | I76: 2 | J76: 2 | K76: 2 | L76: 2 | M76: 2 | N76: 2 | O76: 2 | P76: 2 | Q76: 2 | R76: 2 | U76: =+AVERAGE(G76:K76) -> 2
D77: Vicepresidencia Personas y OrganizaciÃ³n | F77: Real | G77: 5 | H77: 4 | I77: 4 | J77: 5 | K77: 6 | L77: 0 | M77: 0 | N77: 0 | O77: 0 | P77: 0 | Q77: 0 | R77: 0 | U77: =+AVERAGE(G77:K77) -> 4.8
F78: Ppto | G78: 5 | H78: 5 | I78: 5 | J78: 5 | K78: 5 | L78: 5 | M78: 5 | N78: 5 | O78: 5 | P78: 5 | Q78: 5 | R78: 5 | U78: =+AVERAGE(G78:K78) -> 5
B79: Vicepresidencia PlanificaciÃ³n y Servicios TÃ©cnicos | D79: Excelencia Operacional | F79: Real | G79: 5 | H79: 5 | I79: 5 | J79: 5 | K79: 4 | L79: 0 | M79: 0 | N79: 0 | O79: 0 | P79: 0 | Q79: 0 | R79: 0 | U79: =+AVERAGE(G79:K79) -> 4.8
F80: Ppto | G80: 4 | H80: 4 | I80: 4 | J80: 4 | K80: 4 | L80: 4 | M80: 4 | N80: 4 | O80: 4 | P80: 4 | Q80: 4 | R80: 4 | U80: =+AVERAGE(G80:K80) -> 4
D81: Mantenimiento | F81: Real | G81: 3 | H81: 3 | I81: 3 | J81: 3 | K81: 2 | L81: 0 | M81: 0 | N81: 0 | O81: 0 | P81: 0 | Q81: 0 | R81: 0 | U81: =+AVERAGE(G81:K81) -> 2.8
F82: Ppto | G82: 3 | H82: 3 | I82: 3 | J82: 3 | K82: 3 | L82: 3 | M82: 3 | N82: 3 | O82: 3 | P82: 3 | Q82: 3 | R82: 3 | U82: =+AVERAGE(G82:K82) -> 3
D83: PlanificaciÃ³n Minera | F83: Real | G83: 8 | H83: 7 | I83: 9 | J83: 9 | K83: 9 | L83: 0 | M83: 0 | N83: 0 | O83: 0 | P83: 0 | Q83: 0 | R83: 0 | U83: =+AVERAGE(G83:K83) -> 8.4
F84: Ppto | G84: 10 | H84: 10 | I84: 10 | J84: 10 | K84: 10 | L84: 10 | M84: 10 | N84: 10 | O84: 10 | P84: 10 | Q84: 10 | R84: 10 | U84: =+AVERAGE(G84:K84) -> 10
D85: Procesos | F85: Real | G85: 2 | H85: 2 | I85: 3 | J85: 3 | K85: 3 | L85: 0 | M85: 0 | N85: 0 | O85: 0 | P85: 0 | Q85: 0 | R85: 0 | U85: =+AVERAGE(G85:K85) -> 2.6
F86: Ppto | G86: 5 | H86: 5 | I86: 5 | J86: 5 | K86: 5 | L86: 5 | M86: 5 | N86: 5 | O86: 5 | P86: 5 | Q86: 5 | R86: 5 | U86: =+AVERAGE(G86:K86) -> 5
D87: Recursos HÃ­dricos | F87: Real | G87: 3 | H87: 3 | I87: 3 | J87: 3 | K87: 3 | L87: 0 | M87: 0 | N87: 0 | O87: 0 | P87: 0 | Q87: 0 | R87: 0 | U87: =+AVERAGE(G87:K87) -> 3
F88: Ppto | G88: 3 | H88: 3 | I88: 3 | J88: 3 | K88: 3 | L88: 3 | M88: 3 | N88: 3 | O88: 3 | P88: 3 | Q88: 3 | R88: 3 | U88: =+AVERAGE(G88:K88) -> 3
D89: Relaves | F89: Real | G89: 4 | H89: 4 | I89: 4 | J89: 4 | K89: 4 | L89: 0 | M89: 0 | N89: 0 | O89: 0 | P89: 0 | Q89: 0 | R89: 0 | U89: =+AVERAGE(G89:K89) -> 4
F90: Ppto | G90: 4 | H90: 4 | I90: 4 | J90: 4 | K90: 4 | L90: 4 | M90: 4 | N90: 4 | O90: 4 | P90: 4 | Q90: 4 | R90: 4 | U90: =+AVERAGE(G90:K90) -> 4
D91: Vicepresidencia PlanificaciÃ³n y Servicios TÃ©cnicos | F91: Real | G91: 3 | H91: 3 | I91: 3 | J91: 3 | K91: 3 | L91: 0 | M91: 0 | N91: 0 | O91: 0 | P91: 0 | Q91: 0 | R91: 0 | U91: =+AVERAGE(G91:K91) -> 3
F92: Ppto | G92: 1 | H92: 1 | I92: 1 | J92: 1 | K92: 1 | L92: 1 | M92: 1 | N92: 1 | O92: 1 | P92: 1 | Q92: 1 | R92: 1 | U92: =+AVERAGE(G92:K92) -> 1
B93: Vicepresidencia Sustentabilidad | D93: Medio Ambiente | F93: Real | G93: 7 | H93: 7 | I93: 7 | J93: 6 | K93: 7 | L93: 0 | M93: 0 | N93: 0 | O93: 0 | P93: 0 | Q93: 0 | R93: 0 | U93: =+AVERAGE(G93:K93) -> 6.8
F94: Ppto | G94: 4 | H94: 4 | I94: 4 | J94: 4 | K94: 4 | L94: 4 | M94: 4 | N94: 4 | O94: 4 | P94: 4 | Q94: 4 | R94: 4 | U94: =+AVERAGE(G94:K94) -> 4
D95: Seguridad y Salud Ocupacional | F95: Real | G95: 4 | H95: 4 | I95: 4 | J95: 4 | K95: 4 | L95: 0 | M95: 0 | N95: 0 | O95: 0 | P95: 0 | Q95: 0 | R95: 0 | U95: =+AVERAGE(G95:K95) -> 4
F96: Ppto | G96: 4 | H96: 4 | I96: 4 | J96: 4 | K96: 4 | L96: 4 | M96: 4 | N96: 4 | O96: 4 | P96: 4 | Q96: 4 | R96: 4 | U96: =+AVERAGE(G96:K96) -> 4
D97: Vicepresidencia Sustentabilidad | F97: Real | G97: 7 | H97: 7 | I97: 7 | J97: 7 | K97: 7 | L97: 0 | M97: 0 | N97: 0 | O97: 0 | P97: 0 | Q97: 0 | R97: 0 | U97: =+AVERAGE(G97:K97) -> 7
F98: Ppto | G98: 7 | H98: 7 | I98: 7 | J98: 7 | K98: 7 | L98: 7 | M98: 7 | N98: 7 | O98: 7 | P98: 7 | Q98: 7 | R98: 7 | U98: =+AVERAGE(G98:K98) -> 7
U99: =+AVERAGE(G99:K99) -> #DIV/0!
B100: Total Dotación Contratista Act. Corporativa | F100: Real | G100: 88 | H100: 93 | I100: 90 | J100: 92 | K100: 87 | L100: 0 | M100: 0 | N100: 0 | O100: 0 | P100: 0 | Q100: 0 | R100: 0 | U100: =+AVERAGE(G100:K100) -> 90
F101: Ppto | G101: 94 | H101: 94 | I101: 94 | J101: 91 | K101: 91 | L101: 94 | M101: 94 | N101: 94 | O101: 91 | P101: 91 | Q101: 91 | R101: 91 | U101: =+AVERAGE(G101:K101) -> 92.8
...

Sheet 2025
B1: Libro Dotación Minera AMSA
B3: Total Dotación Propia Actividad Corporativa | F3: Real | G3: 421 | H3: 421 | I3: 417 | J3: 414 | K3: 415 | L3: 415 | M3: 417 | N3: 419 | O3: 417 | P3: 419 | Q3: 420 | R3: 420 | T3: =+R3 -> 420 | U3: =+AVERAGE(G3:R3) -> 417.91667 | V3: 421 | X3: 428 | Y3: 414 | Z3: 418 | AA3: 419 | AD3: 420 | AE3: 429
F4: Ppto | G4: 454 | H4: 454 | I4: 454 | J4: 457 | K4: 457 | L4: 457 | M4: 457 | N4: 457 | O4: 457 | P4: 457 | Q4: 457 | R4: 457 | T4: =+R4 -> 457 | U4: =+AVERAGE(G4:R4) -> 456.25 | V4: 457 | X4: 454 | Y4: 457 | Z4: 457 | AA4: 457 | AD4: 457 | AE4: 457
T5: =+R5 -> 0 | U5: =+AVERAGE(G5:R5) -> #DIV/0!
B6: Propia | F6: N° | G6: 202501 | H6: 202502 | I6: 202503 | J6: 202504 | K6: 202505 | L6: 202506 | M6: 202507 | N6: 202508 | O6: 202509 | P6: 202510 | Q6: 202511 | R6: 202512 | T6: =+R6 -> 202512 | U6: =+AVERAGE(G6:R6) -> #DIV/0! | V6: FY | X6: Q1 | Y6: Q2 | Z6: Q3 | AA6: Q4 | AD6: MES | AE6: YTD
B7: Auditoria | D7: Auditoria | F7: Real | G7: 13 | H7: 13 | I7: 14 | J7: 14 | K7: 14 | L7: 15 | M7: 15 | N7: 15 | O7: 15 | P7: 15 | Q7: 15 | R7: 15 | T7: =+R7 -> 15 | U7: =+AVERAGE(G7:R7) -> 14.416667 | V7: 14 | X7: 13 | Y7: 14 | Z7: 15 | AA7: 15 | AD7: 15 | AE7: 14
F8: Ppto | G8: 15 | H8: 15 | I8: 15 | J8: 15 | K8: 15 | L8: 15 | M8: 15 | N8: 15 | O8: 15 | P8: 15 | Q8: 15 | R8: 15 | T8: =+R8 -> 15 | U8: =+AVERAGE(G8:R8) -> 15 | V8: 15 | X8: 15 | Y8: 15 | Z8: 15 | AA8: 15 | AD8: 15 | AE8: 15
B9: Directorio | D9: Directorio | F9: Real | G9: 3 | H9: 3 | I9: 3 | J9: 3 | K9: 3 | L9: 3 | M9: 3 | N9: 3 | O9: 3 | P9: 3 | Q9: 3 | R9: 3 | T9: =+R9 -> 3 | U9: =+AVERAGE(G9:R9) -> 3 | V9: 3 | X9: 3 | Y9: 3 | Z9: 3 | AA9: 3 | AD9: 3 | AE9: 3
F10: Ppto | G10: 3 | H10: 3 | I10: 3 | J10: 3 | K10: 3 | L10: 3 | M10: 3 | N10: 3 | O10: 3 | P10: 3 | Q10: 3 | R10: 3 | T10: =+R10 -> 3 | U10: =+AVERAGE(G10:R10) -> 3 | V10: 3 | X10: 3 | Y10: 3 | Z10: 3 | AA10: 3 | AD10: 3 | AE10: 3
B11: Presidencia Ejecutiva | D11: Presidencia Ejecutiva | F11: Real | G11: 2 | H11: 2 | I11: 2 | J11: 2 | K11: 2 | L11: 2 | M11: 2 | N11: 2 | O11: 2 | P11: 2 | Q11: 2 | R11: 2 | T11: =+R11 -> 2 | U11: =+AVERAGE(G11:R11) -> 2 | V11: 2 | X11: 2 | Y11: 2 | Z11: 2 | AA11: 2 | AD11: 2 | AE11: 2
F12: Ppto | G12: 2 | H12: 2 | I12: 2 | J12: 2 | K12: 2 | L12: 2 | M12: 2 | N12: 2 | O12: 2 | P12: 2 | Q12: 2 | R12: 2 | T12: =+R12 -> 2 | U12: =+AVERAGE(G12:R12) -> 2 | V12: 2 | X12: 2 | Y12: 2 | Z12: 2 | AA12: 2 | AD12: 2 | AE12: 2
B13: Vicepresidencia Comercialización | D13: Ventas CÃ¡todos Molibdeno y Hedge | F13: Real | G13: 5 | H13: 5 | I13: 5 | J13: 5 | K13: 5 | L13: 5 | M13: 5 | N13: 5 | O13: 5 | P13: 5 | Q13: 5 | R13: 5 | T13: =+R13 -> 5 | U13: =+AVERAGE(G13:R13) -> 5 | V13: 5 | X13: 5 | Y13: 5 | Z13: 5 | AA13: 5 | AD13: 5 | AE13: 5
F14: Ppto | G14: 5 | H14: 5 | I14: 5 | J14: 5 | K14: 5 | L14: 5 | M14: 5 | N14: 5 | O14: 5 | P14: 5 | Q14: 5 | R14: 5 | T14: =+R14 -> 5 | U14: =+AVERAGE(G14:R14) -> 5 | V14: 5 | X14: 5 | Y14: 5 | Z14: 5 | AA14: 5 | AD14: 5 | AE14: 5
D15: Ventas Concentrado Acido | F15: Real | G15: 5 | H15: 5 | I15: 4 | J15: 5 | K15: 5 | L15: 5 | M15: 5 | N15: 5 | O15: 5 | P15: 5 | Q15: 5 | R15: 5 | T15: =+R15 -> 5 | U15: =+AVERAGE(G15:R15) -> 4.9166667 | V15: 5 | X15: 5 | Y15: 5 | Z15: 5 | AA15: 5 | AD15: 5 | AE15: 5
F16: Ppto | G16: 5 | H16: 5 | I16: 5 | J16: 5 | K16: 5 | L16: 5 | M16: 5 | N16: 5 | O16: 5 | P16: 5 | Q16: 5 | R16: 5 | T16: =+R16 -> 5 | U16: =+AVERAGE(G16:R16) -> 5 | V16: 5 | X16: 5 | Y16: 5 | Z16: 5 | AA16: 5 | AD16: 5 | AE16: 5
D17: Vicepresidencia ComercializaciÃ³n | F17: Real | G17: 8 | H17: 8 | I17: 9 | J17: 9 | K17: 9 | L17: 9 | M17: 9 | N17: 9 | O17: 9 | P17: 9 | Q17: 9 | R17: 9 | T17: =+R17 -> 9 | U17: =+AVERAGE(G17:R17) -> 8.8333333 | V17: 9 | X17: 8 | Y17: 9 | Z17: 9 | AA17: 9 | AD17: 9 | AE17: 9
F18: Ppto | G18: 10 | H18: 10 | I18: 10 | J18: 10 | K18: 10 | L18: 10 | M18: 10 | N18: 10 | O18: 10 | P18: 10 | Q18: 10 | R18: 10 | T18: =+R18 -> 10 | U18: =+AVERAGE(G18:R18) -> 10 | V18: 10 | X18: 10 | Y18: 10 | Z18: 10 | AA18: 10 | AD18: 10 | AE18: 10
B19: Vicepresidencia de Asuntos Corporativos | D19: Asuntos PÃºblicos Corporativo | F19: Real | G19: 3 | H19: 3 | I19: 3 | J19: 3 | K19: 3 | L19: 3 | M19: 3 | N19: 3 | O19: 2 | P19: 0 | Q19: 0 | R19: 0 | T19: =+R19 -> 0 | U19: =+AVERAGE(G19:R19) -> 2.1666667 | V19: 2 | X19: 3 | Y19: 3 | Z19: 3 | AA19: 0 | AD19: 0 | AE19: 3
F20: Ppto | G20: 5 | H20: 5 | I20: 5 | J20: 5 | K20: 5 | L20: 5 | M20: 5 | N20: 5 | O20: 5 | P20: 5 | Q20: 5 | R20: 5 | T20: =+R20 -> 5 | U20: =+AVERAGE(G20:R20) -> 5 | V20: 5 | X20: 5 | Y20: 5 | Z20: 5 | AA20: 5 | AD20: 5 | AE20: 5
D21: Asuntos PÃºblicos Norte | F21: Real | G21: 13 | H21: 13 | I21: 13 | J21: 13 | K21: 13 | L21: 13 | M21: 13 | N21: 12 | O21: 12 | P21: 11 | Q21: 11 | R21: 12 | T21: =+R21 -> 12 | U21: =+AVERAGE(G21:R21) -> 12.416667 | V21: 12 | X21: 13 | Y21: 13 | Z21: 12 | AA21: 11 | AD21: 12 | AE21: 12
F22: Ppto | G22: 13 | H22: 13 | I22: 13 | J22: 13 | K22: 13 | L22: 13 | M22: 13 | N22: 13 | O22: 13 | P22: 13 | Q22: 13 | R22: 13 | T22: =+R22 -> 13 | U22: =+AVERAGE(G22:R22) -> 13 | V22: 13 | X22: 13 | Y22: 13 | Z22: 13 | AA22: 13 | AD22: 13 | AE22: 13
D23: Asuntos Publicos MLP | F23: Real | G23: 19 | H23: 18 | I23: 17 | J23: 17 | K23: 19 | L23: 19 | M23: 19 | N23: 19 | O23: 19 | P23: 19 | Q23: 19 | R23: 19 | T23: =+R23 -> 19 | U23: =+AVERAGE(G23:R23) -> 18.583333 | V23: 19 | X23: 18 | Y23: 18 | Z23: 19 | AA23: 19 | AD23: 19 | AE23: 19
F24: Ppto | G24: 20 | H24: 20 | I24: 20 | J24: 20 | K24: 20 | L24: 20 | M24: 20 | N24: 20 | O24: 20 | P24: 20 | Q24: 20 | R24: 20 | T24: =+R24 -> 20 | U24: =+AVERAGE(G24:R24) -> 20 | V24: 20 | X24: 20 | Y24: 20 | Z24: 20 | AA24: 20 | AD24: 20 | AE24: 20
D25: Comunicaciones | F25: Real | G25: 8 | H25: 8 | I25: 8 | J25: 8 | K25: 8 | L25: 8 | M25: 8 | N25: 7 | O25: 7 | P25: 7 | Q25: 7 | R25: 7 | T25: =+R25 -> 7 | U25: =+AVERAGE(G25:R25) -> 7.5833333 | V25: 8 | X25: 8 | Y25: 8 | Z25: 7 | AA25: 7 | AD25: 7 | AE25: 8
F26: Ppto | G26: 8 | H26: 8 | I26: 8 | J26: 8 | K26: 8 | L26: 8 | M26: 8 | N26: 8 | O26: 8 | P26: 8 | Q26: 8 | R26: 8 | T26: =+R26 -> 8 | U26: =+AVERAGE(G26:R26) -> 8 | V26: 8 | X26: 8 | Y26: 8 | Z26: 8 | AA26: 8 | AD26: 8 | AE26: 8
D27: Vicepresidencia Asuntos Corporativos | F27: Real | G27: 3 | H27: 3 | I27: 4 | J27: 4 | K27: 4 | L27: 4 | M27: 4 | N27: 4 | O27: 4 | P27: 6 | Q27: 7 | R27: 7 | T27: =+R27 -> 7 | U27: =+AVERAGE(G27:R27) -> 4.5 | V27: 5 | X27: 3 | Y27: 4 | Z27: 4 | AA27: 7 | AD27: 7 | AE27: 5
F28: Ppto | G28: 3 | H28: 3 | I28: 3 | J28: 3 | K28: 3 | L28: 3 | M28: 3 | N28: 3 | O28: 3 | P28: 3 | Q28: 3 | R28: 3 | T28: =+R28 -> 3 | U28: =+AVERAGE(G28:R28) -> 3 | V28: 3 | X28: 3 | Y28: 3 | Z28: 3 | AA28: 3 | AD28: 3 | AE28: 3
B29: Vicepresidencia de Proyectos | D29: Finanzas VPP | F29: Real | G29: 11 | H29: 11 | I29: 11 | J29: 11 | K29: 12 | L29: 11 | M29: 11 | N29: 12 | O29: 13 | P29: 14 | Q29: 14 | R29: 15 | T29: =+R29 -> 15 | U29: =+AVERAGE(G29:R29) -> 12.166667 | V29: 12 | X29: 11 | Y29: 11 | Z29: 12 | AA29: 14 | AD29: 15 | AE29: 12
F30: Ppto | G30: 14 | H30: 14 | I30: 14 | J30: 14 | K30: 14 | L30: 14 | M30: 14 | N30: 14 | O30: 14 | P30: 14 | Q30: 14 | R30: 14 | T30: =+R30 -> 14 | U30: =+AVERAGE(G30:R30) -> 14 | V30: 14 | X30: 14 | Y30: 14 | Z30: 14 | AA30: 14 | AD30: 14 | AE30: 14
D31: Ingenieria y Construccion | F31: Real | G31: 3 | H31: 3 | I31: 2 | J31: 2 | K31: 2 | L31: 2 | M31: 2 | N31: 2 | O31: 2 | P31: 2 | Q31: 2 | R31: 2 | T31: =+R31 -> 2 | U31: =+AVERAGE(G31:R31) -> 2.1666667 | V31: 2 | X31: 3 | Y31: 2 | Z31: 2 | AA31: 2 | AD31: 2 | AE31: 2
F32: Ppto | G32: 5 | H32: 5 | I32: 5 | J32: 5 | K32: 5 | L32: 5 | M32: 5 | N32: 5 | O32: 5 | P32: 5 | Q32: 5 | R32: 5 | T32: =+R32 -> 5 | U32: =+AVERAGE(G32:R32) -> 5 | V32: 5 | X32: 5 | Y32: 5 | Z32: 5 | AA32: 5 | AD32: 5 | AE32: 5
D33: Vicepresidencia de Proyectos + Proyecto INCO + Proyecto Estudio | F33: Real | G33: 8 | H33: 8 | I33: 7 | J33: 7 | K33: 7 | L33: 9 | M33: 10 | N33: 11 | O33: 11 | P33: 11 | Q33: 12 | R33: 11 | T33: =+R33 -> 11 | U33: =+AVERAGE(G33:R33) -> 9.3333333 | V33: 9 | X33: 8 | Y33: 8 | Z33: 11 | AA33: 11 | AD33: 11 | AE33: 9
F34: Ppto | G34: 8 | H34: 8 | I34: 8 | J34: 8 | K34: 8 | L34: 8 | M34: 8 | N34: 8 | O34: 8 | P34: 8 | Q34: 8 | R34: 8 | T34: =+R34 -> 8 | U34: =+AVERAGE(G34:R34) -> 8 | V34: 8 | X34: 8 | Y34: 8 | Z34: 8 | AA34: 8 | AD34: 8 | AE34: 8
B35: Vicepresidencia Desarrollo | D35: AdministraciÃ³n MIC | F35: Real | G35: 2 | H35: 2 | I35: 2 | J35: 2 | K35: 2 | L35: 2 | M35: 2 | N35: 2 | O35: 2 | P35: 2 | Q35: 2 | R35: 2 | T35: =+R35 -> 2 | U35: =+AVERAGE(G35:R35) -> 2 | V35: 2 | X35: 2 | Y35: 2 | Z35: 2 | AA35: 2 | AD35: 2 | AE35: 2
F36: Ppto | G36: 3 | H36: 3 | I36: 3 | J36: 3 | K36: 3 | L36: 3 | M36: 3 | N36: 3 | O36: 3 | P36: 3 | Q36: 3 | R36: 3 | T36: =+R36 -> 3 | U36: =+AVERAGE(G36:R36) -> 3 | V36: 3 | X36: 3 | Y36: 3 | Z36: 3 | AA36: 3 | AD36: 3 | AE36: 3
D37: Desarrollo | F37: Real | G37: 9 | H37: 9 | I37: 9 | J37: 9 | K37: 9 | L37: 9 | M37: 9 | N37: 9 | O37: 9 | P37: 9 | Q37: 9 | R37: 9 | T37: =+R37 -> 9 | U37: =+AVERAGE(G37:R37) -> 9 | V37: 9 | X37: 9 | Y37: 9 | Z37: 9 | AA37: 9 | AD37: 9 | AE37: 9
F38: Ppto | G38: 9 | H38: 9 | I38: 9 | J38: 9 | K38: 9 | L38: 9 | M38: 9 | N38: 9 | O38: 9 | P38: 9 | Q38: 9 | R38: 9 | T38: =+R38 -> 9 | U38: =+AVERAGE(G38:R38) -> 9 | V38: 9 | X38: 9 | Y38: 9 | Z38: 9 | AA38: 9 | AD38: 9 | AE38: 9
D39: Vicepresidencia Desarrollo | F39: Real | G39: 11 | H39: 11 | I39: 11 | J39: 11 | K39: 10 | L39: 10 | M39: 10 | N39: 10 | O39: 10 | P39: 10 | Q39: 10 | R39: 10 | T39: =+R39 -> 10 | U39: =+AVERAGE(G39:R39) -> 10.333333 | V39: 10 | X39: 11 | Y39: 10 | Z39: 10 | AA39: 10 | AD39: 10 | AE39: 10
F40: Ppto | G40: 10 | H40: 10 | I40: 10 | J40: 10 | K40: 10 | L40: 10 | M40: 10 | N40: 10 | O40: 10 | P40: 10 | Q40: 10 | R40: 10 | T40: =+R40 -> 10 | U40: =+AVERAGE(G40:R40) -> 10 | V40: 10 | X40: 10 | Y40: 10 | Z40: 10 | AA40: 10 | AD40: 10 | AE40: 10
B41: Vicepresidencia Estrategia e InnovaciÃ³n | D41: Data y AnalÃ­tica Avanzada | F41: Real | G41: 8 | H41: 8 | I41: 8 | J41: 8 | K41: 8 | L41: 8 | M41: 8 | N41: 8 | O41: 8 | P41: 8 | Q41: 8 | R41: 8 | T41: =+R41 -> 8 | U41: =+AVERAGE(G41:R41) -> 8 | V41: 8 | X41: 8 | Y41: 8 | Z41: 8 | AA41: 8 | AD41: 8 | AE41: 8
F42: Ppto | G42: 8 | H42: 8 | I42: 8 | J42: 8 | K42: 8 | L42: 8 | M42: 8 | N42: 8 | O42: 8 | P42: 8 | Q42: 8 | R42: 8 | T42: =+R42 -> 8 | U42: =+AVERAGE(G42:R42) -> 8 | V42: 8 | X42: 8 | Y42: 8 | Z42: 8 | AA42: 8 | AD42: 8 | AE42: 8
D43: InnovaciÃ³n + EnergÃ­a y Recursos HÃ­dricos | F43: Real | G43: 6 | H43: 6 | I43: 6 | J43: 5 | K43: 5 | L43: 5 | M43: 5 | N43: 5 | O43: 5 | P43: 5 | Q43: 5 | R43: 5 | T43: =+R43 -> 5 | U43: =+AVERAGE(G43:R43) -> 5.25 | V43: 5 | X43: 6 | Y43: 5 | Z43: 5 | AA43: 5 | AD43: 5 | AE43: 5
F44: Ppto | G44: 6 | H44: 6 | I44: 6 | J44: 6 | K44: 6 | L44: 6 | M44: 6 | N44: 6 | O44: 6 | P44: 6 | Q44: 6 | R44: 6 | T44: =+R44 -> 6 | U44: =+AVERAGE(G44:R44) -> 6 | V44: 6 | X44: 6 | Y44: 6 | Z44: 6 | AA44: 6 | AD44: 6 | AE44: 6
D45: Proyecto DescarbonizaciÃ³n | F45: Real | G45: 5 | H45: 5 | I45: 5 | J45: 5 | K45: 5 | L45: 5 | M45: 4 | N45: 5 | O45: 5 | P45: 5 | Q45: 5 | R45: 5 | T45: =+R45 -> 5 | U45: =+AVERAGE(G45:R45) -> 4.9166667 | V45: 5 | X45: 5 | Y45: 5 | Z45: 5 | AA45: 5 | AD45: 5 | AE45: 5
F46: Ppto | G46: 5 | H46: 5 | I46: 5 | J46: 5 | K46: 5 | L46: 5 | M46: 5 | N46: 5 | O46: 5 | P46: 5 | Q46: 5 | R46: 5 | T46: =+R46 -> 5 | U46: =+AVERAGE(G46:R46) -> 5 | V46: 5 | X46: 5 | Y46: 5 | Z46: 5 | AA46: 5 | AD46: 5 | AE46: 5
D47: Tecnologia | F47: Real | G47: 55 | H47: 56 | I47: 58 | J47: 53 | K47: 51 | L47: 52 | M47: 52 | N47: 52 | O47: 50 | P47: 52 | Q47: 50 | R47: 51 | T47: =+R47 -> 51 | U47: =+AVERAGE(G47:R47) -> 52.666667 | V47: 53 | X47: 56 | Y47: 52 | Z47: 51 | AA47: 51 | AD47: 51 | AE47: 53
F48: Ppto | G48: 56 | H48: 56 | I48: 56 | J48: 56 | K48: 56 | L48: 56 | M48: 56 | N48: 56 | O48: 56 | P48: 56 | Q48: 56 | R48: 56 | T48: =+R48 -> 56 | U48: =+AVERAGE(G48:R48) -> 56 | V48: 56 | X48: 56 | Y48: 56 | Z48: 56 | AA48: 56 | AD48: 56 | AE48: 56
D49: Vicepresidencia Estrategia e InnovaciÃ³n | F49: Real | G49: 5 | H49: 5 | I49: 5 | J49: 5 | K49: 5 | L49: 5 | M49: 5 | N49: 5 | O49: 4 | P49: 4 | Q49: 4 | R49: 4 | T49: =+R49 -> 4 | U49: =+AVERAGE(G49:R49) -> 4.6666667 | V49: 5 | X49: 5 | Y49: 5 | Z49: 5 | AA49: 4 | AD49: 4 | AE49: 5
F50: Ppto | G50: 5 | H50: 5 | I50: 5 | J50: 6 | K50: 6 | L50: 6 | M50: 6 | N50: 6 | O50: 6 | P50: 6 | Q50: 6 | R50: 6 | T50: =+R50 -> 6 | U50: =+AVERAGE(G50:R50) -> 5.75 | V50: 6 | X50: 5 | Y50: 6 | Z50: 6 | AA50: 6 | AD50: 6 | AE50: 6
B51: Vicepresidencia Finanzas | D51: Abastecimiento | F51: Real | G51: 32 | H51: 32 | I51: 31 | J51: 31 | K51: 30 | L51: 30 | M51: 32 | N51: 32 | O51: 32 | P51: 32 | Q51: 33 | R51: 33 | T51: =+R51 -> 33 | U51: =+AVERAGE(G51:R51) -> 31.666667 | V51: 32 | X51: 32 | Y51: 30 | Z51: 32 | AA51: 33 | AD51: 33 | AE51: 32
F52: Ppto | G52: 38 | H52: 38 | I52: 38 | J52: 38 | K52: 38 | L52: 38 | M52: 38 | N52: 38 | O52: 38 | P52: 38 | Q52: 38 | R52: 38 | T52: =+R52 -> 38 | U52: =+AVERAGE(G52:R52) -> 38 | V52: 38 | X52: 38 | Y52: 38 | Z52: 38 | AA52: 38 | AD52: 38 | AE52: 38
D53: Contabilidad | F53: Real | G53: 33 | H53: 33 | I53: 32 | J53: 33 | K53: 33 | L53: 33 | M53: 33 | N53: 33 | O53: 33 | P53: 33 | Q53: 34 | R53: 34 | T53: =+R53 -> 34 | U53: =+AVERAGE(G53:R53) -> 33.083333 | V53: 33 | X53: 33 | Y53: 33 | Z53: 33 | AA53: 34 | AD53: 34 | AE53: 33
F54: Ppto | G54: 36 | H54: 36 | I54: 36 | J54: 36 | K54: 36 | L54: 36 | M54: 36 | N54: 36 | O54: 36 | P54: 36 | Q54: 36 | R54: 36 | T54: =+R54 -> 36 | U54: =+AVERAGE(G54:R54) -> 36 | V54: 36 | X54: 36 | Y54: 36 | Z54: 36 | AA54: 36 | AD54: 36 | AE54: 36
D55: EnergÃ­a y Servicios EstratÃ©gicos | F55: Real | G55: 3 | H55: 3 | I55: 3 | J55: 3 | K55: 3 | L55: 3 | M55: 3 | N55: 3 | O55: 3 | P55: 3 | Q55: 3 | R55: 3 | T55: =+R55 -> 3 | U55: =+AVERAGE(G55:R55) -> 3 | V55: 3 | X55: 3 | Y55: 3 | Z55: 3 | AA55: 3 | AD55: 3 | AE55: 3
F56: Ppto | G56: 3 | H56: 3 | I56: 3 | J56: 3 | K56: 3 | L56: 3 | M56: 3 | N56: 3 | O56: 3 | P56: 3 | Q56: 3 | R56: 3 | T56: =+R56 -> 3 | U56: =+AVERAGE(G56:R56) -> 3 | V56: 3 | X56: 3 | Y56: 3 | Z56: 3 | AA56: 3 | AD56: 3 | AE56: 3
D57: Finanzas e Impuestos + PlanificaciÃ³n Financiera | F57: Real | G57: 28 | H57: 27 | I57: 26 | J57: 26 | K57: 26 | L57: 26 | M57: 25 | N57: 26 | O57: 27 | P57: 26 | Q57: 26 | R57: 26 | T57: =+R57 -> 26 | U57: =+AVERAGE(G57:R57) -> 26.25 | V57: 26 | X57: 27 | Y57: 26 | Z57: 26 | AA57: 26 | AD57: 26 | AE57: 26
F58: Ppto | G58: 28 | H58: 28 | I58: 28 | J58: 28 | K58: 28 | L58: 28 | M58: 28 | N58: 28 | O58: 28 | P58: 28 | Q58: 28 | R58: 28 | T58: =+R58 -> 28 | U58: =+AVERAGE(G58:R58) -> 28 | V58: 28 | X58: 28 | Y58: 28 | Z58: 28 | AA58: 28 | AD58: 28 | AE58: 28
D59: Gerencia Competitividad | F59: Ppto | G59: 3 | H59: 3 | I59: 3 | J59: 3 | K59: 3 | L59: 3 | M59: 3 | N59: 3 | O59: 3 | P59: 3 | Q59: 3 | R59: 3 | T59: =+R59 -> 3 | U59: =+AVERAGE(G59:R59) -> 3 | V59: 0 | X59: 3 | Y59: 3 | Z59: 3 | AA59: 3 | AD59: 0 | AE59: 0
D60: Planificacion y Control de Gestion | F60: Real | G60: 9 | H60: 9 | I60: 10 | J60: 10 | K60: 10 | L60: 10 | M60: 10 | N60: 10 | O60: 10 | P60: 10 | Q60: 10 | R60: 8 | T60: =+R60 -> 8 | U60: =+AVERAGE(G60:R60) -> 9.6666667 | V60: 3 | X60: 9 | Y60: 10 | Z60: 10 | AA60: 9 | AD60: 3 | AE60: 3
F61: Ppto | G61: 9 | H61: 9 | I61: 9 | J61: 10 | K61: 10 | L61: 10 | M61: 10 | N61: 10 | O61: 10 | P61: 10 | Q61: 10 | R61: 10 | T61: =+R61 -> 10 | U61: =+AVERAGE(G61:R61) -> 9.75 | V61: 10 | X61: 9 | Y61: 10 | Z61: 10 | AA61: 10 | AD61: 8 | AE61: 10
D62: Riesgo Compliance y Control Interno | F62: Real | G62: 9 | H62: 9 | I62: 10 | J62: 10 | K62: 10 | L62: 10 | M62: 10 | N62: 9 | O62: 9 | P62: 9 | Q62: 8 | R62: 8 | T62: =+R62 -> 8 | U62: =+AVERAGE(G62:R62) -> 9.25 | V62: 10 | X62: 9 | Y62: 10 | Z62: 9 | AA62: 8 | AD62: 10 | AE62: 10
F63: Ppto | G63: 9 | H63: 9 | I63: 9 | J63: 9 | K63: 9 | L63: 9 | M63: 9 | N63: 9 | O63: 9 | P63: 9 | Q63: 9 | R63: 9 | T63: =+R63 -> 9 | U63: =+AVERAGE(G63:R63) -> 9 | V63: 9 | X63: 9 | Y63: 9 | Z63: 9 | AA63: 9 | AD63: 8 | AE63: 9
D64: Vicepresidencia Finanzas | F64: Real | G64: 2 | H64: 2 | I64: 2 | J64: 2 | K64: 2 | L64: 2 | M64: 2 | N64: 2 | O64: 2 | P64: 2 | Q64: 2 | R64: 2 | T64: =+R64 -> 2 | U64: =+AVERAGE(G64:R64) -> 2 | V64: 9 | X64: 2 | Y64: 2 | Z64: 2 | AA64: 2 | AD64: 9 | AE64: 9
F65: Ppto | G65: 2 | H65: 2 | I65: 2 | J65: 2 | K65: 2 | L65: 2 | M65: 2 | N65: 2 | O65: 2 | P65: 2 | Q65: 2 | R65: 2 | T65: =+R65 -> 2 | U65: =+AVERAGE(G65:R65) -> 2 | V65: 2 | X65: 2 | Y65: 2 | Z65: 2 | AA65: 2 | AD65: 2 | AE65: 2
B66: Vicepresidencia Legal | D66: Legal | F66: Real | G66: 8 | H66: 8 | I66: 8 | J66: 8 | K66: 8 | L66: 8 | M66: 7 | N66: 7 | O66: 7 | P66: 7 | Q66: 7 | R66: 7 | T66: =+R66 -> 7 | U66: =+AVERAGE(G66:R66) -> 7.5 | V66: 2 | X66: 8 | Y66: 8 | Z66: 7 | AA66: 7 | AD66: 2 | AE66: 2
F67: Ppto | G67: 9 | H67: 9 | I67: 9 | J67: 9 | K67: 9 | L67: 9 | M67: 9 | N67: 9 | O67: 9 | P67: 9 | Q67: 9 | R67: 9 | T67: =+R67 -> 9 | U67: =+AVERAGE(G67:R67) -> 9 | V67: 8 | X67: 9 | Y67: 9 | Z67: 9 | AA67: 9 | AD67: 7 | AE67: 8
D68: Propiedad Minera | F68: Real | G68: 9 | H68: 9 | I68: 9 | J68: 9 | K68: 9 | L68: 9 | M68: 9 | N68: 9 | O68: 9 | P68: 9 | Q68: 9 | R68: 9 | T68: =+R68 -> 9 | U68: =+AVERAGE(G68:R68) -> 9 | V68: 9 | X68: 9 | Y68: 9 | Z68: 9 | AA68: 9 | AD68: 9 | AE68: 9
F69: Ppto | G69: 9 | H69: 9 | I69: 9 | J69: 9 | K69: 9 | L69: 9 | M69: 9 | N69: 9 | O69: 9 | P69: 9 | Q69: 9 | R69: 9 | T69: =+R69 -> 9 | U69: =+AVERAGE(G69:R69) -> 9 | V69: 9 | X69: 9 | Y69: 9 | Z69: 9 | AA69: 9 | AD69: 9 | AE69: 9
D70: Vicepresidencia Legal | F70: Real | G70: 2 | H70: 2 | I70: 2 | J70: 2 | K70: 2 | L70: 2 | M70: 2 | N70: 2 | O70: 2 | P70: 2 | Q70: 2 | R70: 3 | T70: =+R70 -> 3 | U70: =+AVERAGE(G70:R70) -> 2.0833333 | V70: 9 | X70: 2 | Y70: 2 | Z70: 2 | AA70: 2 | AD70: 9 | AE70: 9
F71: Ppto | G71: 2 | H71: 2 | I71: 2 | J71: 2 | K71: 2 | L71: 2 | M71: 2 | N71: 2 | O71: 2 | P71: 2 | Q71: 2 | R71: 2 | T71: =+R71 -> 2 | U71: =+AVERAGE(G71:R71) -> 2 | V71: 2 | X71: 2 | Y71: 2 | Z71: 2 | AA71: 2 | AD71: 3 | AE71: 2
B72: Vicepresidencia Operaciones | D72: Vicepresidencia Operaciones | F72: Real | G72: 3 | H72: 3 | I72: 3 | J72: 3 | K72: 3 | L72: 3 | M72: 3 | N72: 3 | O72: 3 | P72: 3 | Q72: 3 | R72: 3 | T72: =+R72 -> 3 | U72: =+AVERAGE(G72:R72) -> 3 | V72: 2 | X72: 3 | Y72: 3 | Z72: 3 | AA72: 3 | AD72: 2 | AE72: 2
B73: Vicepresidencia Personas y OrganizaciÃ³n | D73: Desarrollo Organizacional y Compensaciones | F73: Real | G73: 16 | H73: 16 | I73: 16 | J73: 16 | K73: 16 | L73: 15 | M73: 15 | N73: 15 | O73: 15 | P73: 14 | Q73: 14 | R73: 13 | T73: =+R73 -> 13 | U73: =+AVERAGE(G73:R73) -> 15.083333 | V73: 3 | X73: 16 | Y73: 16 | Z73: 15 | AA73: 14 | AD73: 3 | AE73: 3
F74: Ppto | G74: 17 | H74: 17 | I74: 17 | J74: 17 | K74: 17 | L74: 17 | M74: 17 | N74: 17 | O74: 17 | P74: 17 | Q74: 17 | R74: 17 | T74: =+R74 -> 17 | U74: =+AVERAGE(G74:R74) -> 17 | V74: 15 | X74: 17 | Y74: 17 | Z74: 17 | AA74: 17 | AD74: 13 | AE74: 15
D75: Efectividad Organizacional | F75: Real | G75: 14 | H75: 14 | I75: 9 | J75: 9 | K75: 12 | L75: 12 | M75: 12 | N75: 13 | O75: 13 | P75: 13 | Q75: 13 | R75: 13 | T75: =+R75 -> 13 | U75: =+AVERAGE(G75:R75) -> 12.25 | V75: 17 | X75: 12 | Y75: 11 | Z75: 13 | AA75: 13 | AD75: 17 | AE75: 17
F76: Ppto | G76: 15 | H76: 15 | I76: 15 | J76: 15 | K76: 15 | L76: 15 | M76: 15 | N76: 15 | O76: 15 | P76: 15 | Q76: 15 | R76: 15 | T76: =+R76 -> 15 | U76: =+AVERAGE(G76:R76) -> 15 | V76: 12 | X76: 15 | Y76: 15 | Z76: 15 | AA76: 15 | AD76: 13 | AE76: 12
D77: Relaciones Laborales | F77: Real | G77: 1 | H77: 1 | I77: 2 | J77: 2 | K77: 2 | L77: 2 | M77: 2 | N77: 2 | O77: 2 | P77: 2 | Q77: 2 | R77: 2 | T77: =+R77 -> 2 | U77: =+AVERAGE(G77:R77) -> 1.8333333 | V77: 15 | X77: 1 | Y77: 2 | Z77: 2 | AA77: 2 | AD77: 15 | AE77: 15
F78: Ppto | G78: 2 | H78: 2 | I78: 2 | J78: 2 | K78: 2 | L78: 2 | M78: 2 | N78: 2 | O78: 2 | P78: 2 | Q78: 2 | R78: 2 | T78: =+R78 -> 2 | U78: =+AVERAGE(G78:R78) -> 2 | V78: 2 | X78: 2 | Y78: 2 | Z78: 2 | AA78: 2 | AD78: 2 | AE78: 2
D79: Vicepresidencia Personas y OrganizaciÃ³n | F79: Real | G79: 5 | H79: 5 | I79: 5 | J79: 5 | K79: 5 | L79: 5 | M79: 5 | N79: 5 | O79: 5 | P79: 5 | Q79: 5 | R79: 5 | T79: =+R79 -> 5 | U79: =+AVERAGE(G79:R79) -> 5 | V79: 2 | X79: 5 | Y79: 5 | Z79: 5 | AA79: 5 | AD79: 2 | AE79: 2
F80: Ppto | G80: 5 | H80: 5 | I80: 5 | J80: 5 | K80: 5 | L80: 5 | M80: 5 | N80: 5 | O80: 5 | P80: 5 | Q80: 5 | R80: 5 | T80: =+R80 -> 5 | U80: =+AVERAGE(G80:R80) -> 5 | V80: 5 | X80: 5 | Y80: 5 | Z80: 5 | AA80: 5 | AD80: 5 | AE80: 5
B81: Vicepresidencia PlanificaciÃ³n y Servicios TÃ©cnicos | D81: Excelencia Operacional | F81: Real | G81: 5 | H81: 5 | I81: 5 | J81: 5 | K81: 5 | L81: 5 | M81: 5 | N81: 5 | O81: 5 | P81: 5 | Q81: 5 | R81: 5 | T81: =+R81 -> 5 | U81: =+AVERAGE(G81:R81) -> 5 | V81: 5 | X81: 5 | Y81: 5 | Z81: 5 | AA81: 5 | AD81: 5 | AE81: 5
F82: Ppto | G82: 5 | H82: 5 | I82: 5 | J82: 5 | K82: 5 | L82: 5 | M82: 5 | N82: 5 | O82: 5 | P82: 5 | Q82: 5 | R82: 5 | T82: =+R82 -> 5 | U82: =+AVERAGE(G82:R82) -> 5 | V82: 5 | X82: 5 | Y82: 5 | Z82: 5 | AA82: 5 | AD82: 5 | AE82: 5
D83: Mantenimiento | F83: Real | G83: 3 | H83: 3 | I83: 3 | J83: 3 | K83: 3 | L83: 3 | M83: 2 | N83: 2 | O83: 2 | P83: 3 | Q83: 3 | R83: 3 | T83: =+R83 -> 3 | U83: =+AVERAGE(G83:R83) -> 2.75 | V83: 5 | X83: 3 | Y83: 3 | Z83: 2 | AA83: 3 | AD83: 5 | AE83: 5
F84: Ppto | G84: 3 | H84: 3 | I84: 3 | J84: 3 | K84: 3 | L84: 3 | M84: 3 | N84: 3 | O84: 3 | P84: 3 | Q84: 3 | R84: 3 | T84: =+R84 -> 3 | U84: =+AVERAGE(G84:R84) -> 3 | V84: 3 | X84: 3 | Y84: 3 | Z84: 3 | AA84: 3 | AD84: 3 | AE84: 3
D85: Mineria | F85: Real | G85: 4 | H85: 5 | I85: 0 | J85: 0 | K85: 0 | L85: 0 | M85: 0 | N85: 0 | O85: 0 | P85: 0 | Q85: 0 | R85: 0 | T85: =+R85 -> 0 | U85: =+AVERAGE(G85:R85) -> 0.75 | V85: 3 | X85: 5 | Y85: 0 | Z85: 0 | AA85: 0 | AD85: 3 | AE85: 3
F86: Ppto | G86: 6 | H86: 6 | I86: 6 | J86: 6 | K86: 6 | L86: 6 | M86: 6 | N86: 6 | O86: 6 | P86: 6 | Q86: 6 | R86: 6 | T86: =+R86 -> 6 | U86: =+AVERAGE(G86:R86) -> 6 | V86: 1 | X86: 6 | Y86: 6 | Z86: 6 | AA86: 6 | AD86: 0 | AE86: 5
D87: PlanificaciÃ³n Minera | F87: Real | G87: 0 | H87: 0 | I87: 8 | J87: 8 | K87: 8 | L87: 8 | M87: 8 | N87: 8 | O87: 8 | P87: 8 | Q87: 7 | R87: 7 | T87: =+R87 -> 7 | U87: =+AVERAGE(G87:R87) -> 6.5 | V87: 6 | X87: 8 | Y87: 8 | Z87: 8 | AA87: 7 | AD87: 6 | AE87: 6
D88: PlanificaciÃ³n Minera MetalÃºrgica | F88: Real | G88: 4 | H88: 3 | I88: 0 | J88: 0 | K88: 0 | L88: 0 | M88: 0 | N88: 0 | O88: 0 | P88: 0 | Q88: 0 | R88: 0 | T88: =+R88 -> 0 | U88: =+AVERAGE(G88:R88) -> 0.58333333 | V88: 8 | X88: 4 | Y88: 0 | Z88: 0 | AA88: 0 | AD88: 7 | AE88: 8
F89: Ppto | G89: 5 | H89: 5 | I89: 5 | J89: 5 | K89: 5 | L89: 5 | M89: 5 | N89: 5 | O89: 5 | P89: 5 | Q89: 5 | R89: 5 | T89: =+R89 -> 5 | U89: =+AVERAGE(G89:R89) -> 5 | V89: 1 | X89: 5 | Y89: 5 | Z89: 5 | AA89: 5 | AD89: 0 | AE89: 4
D90: Procesos | F90: Real | G90: 2 | H90: 2 | I90: 2 | J90: 3 | K90: 3 | L90: 3 | M90: 2 | N90: 2 | O90: 2 | P90: 2 | Q90: 2 | R90: 2 | T90: =+R90 -> 2 | U90: =+AVERAGE(G90:R90) -> 2.25 | V90: 5 | X90: 2 | Y90: 3 | Z90: 2 | AA90: 2 | AD90: 5 | AE90: 5
F91: Ppto | G91: 3 | H91: 3 | I91: 3 | J91: 3 | K91: 3 | L91: 3 | M91: 3 | N91: 3 | O91: 3 | P91: 3 | Q91: 3 | R91: 3 | T91: =+R91 -> 3 | U91: =+AVERAGE(G91:R91) -> 3 | V91: 2 | X91: 3 | Y91: 3 | Z91: 3 | AA91: 3 | AD91: 2 | AE91: 2
D92: Recursos HÃ­dricos | F92: Real | G92: 3 | H92: 3 | I92: 3 | J92: 3 | K92: 3 | L92: 3 | M92: 3 | N92: 3 | O92: 3 | P92: 3 | Q92: 3 | R92: 3 | T92: =+R92 -> 3 | U92: =+AVERAGE(G92:R92) -> 3 | V92: 3 | X92: 3 | Y92: 3 | Z92: 3 | AA92: 3 | AD92: 3 | AE92: 3
F93: Ppto | G93: 3 | H93: 3 | I93: 3 | J93: 3 | K93: 3 | L93: 3 | M93: 3 | N93: 3 | O93: 3 | P93: 3 | Q93: 3 | R93: 3 | T93: =+R93 -> 3 | U93: =+AVERAGE(G93:R93) -> 3 | V93: 3 | X93: 3 | Y93: 3 | Z93: 3 | AA93: 3 | AD93: 3 | AE93: 3
D94: Relaves | F94: Real | G94: 4 | H94: 4 | I94: 4 | J94: 4 | K94: 4 | L94: 4 | M94: 4 | N94: 4 | O94: 4 | P94: 4 | Q94: 4 | R94: 4 | T94: =+R94 -> 4 | U94: =+AVERAGE(G94:R94) -> 4 | V94: 3 | X94: 4 | Y94: 4 | Z94: 4 | AA94: 4 | AD94: 3 | AE94: 3
F95: Ppto | G95: 3 | H95: 3 | I95: 3 | J95: 4 | K95: 4 | L95: 4 | M95: 4 | N95: 4 | O95: 4 | P95: 4 | Q95: 4 | R95: 4 | T95: =+R95 -> 4 | U95: =+AVERAGE(G95:R95) -> 3.75 | V95: 4 | X95: 3 | Y95: 4 | Z95: 4 | AA95: 4 | AD95: 4 | AE95: 4
D96: Vicepresidencia PlanificaciÃ³n y Servicios TÃ©cnicos | F96: Real | G96: 2 | H96: 3 | I96: 3 | J96: 3 | K96: 2 | L96: 2 | M96: 3 | N96: 3 | O96: 3 | P96: 3 | Q96: 3 | R96: 3 | T96: =+R96 -> 3 | U96: =+AVERAGE(G96:R96) -> 2.75 | V96: 4 | X96: 3 | Y96: 2 | Z96: 3 | AA96: 3 | AD96: 4 | AE96: 4
F97: Ppto | G97: 4 | H97: 4 | I97: 4 | J97: 4 | K97: 4 | L97: 4 | M97: 4 | N97: 4 | O97: 4 | P97: 4 | Q97: 4 | R97: 4 | T97: =+R97 -> 4 | U97: =+AVERAGE(G97:R97) -> 4 | V97: 3 | X97: 4 | Y97: 4 | Z97: 4 | AA97: 4 | AD97: 3 | AE97: 3
B98: Vicepresidencia Sustentabilidad | D98: Medio Ambiente | F98: Real | G98: 5 | H98: 5 | I98: 5 | J98: 5 | K98: 5 | L98: 4 | M98: 6 | N98: 6 | O98: 6 | P98: 6 | Q98: 7 | R98: 7 | T98: =+R98 -> 7 | U98: =+AVERAGE(G98:R98) -> 5.5833333 | V98: 4 | X98: 5 | Y98: 5 | Z98: 6 | AA98: 7 | AD98: 4 | AE98: 4
F99: Ppto | G99: 7 | H99: 7 | I99: 7 | J99: 7 | K99: 7 | L99: 7 | M99: 7 | N99: 7 | O99: 7 | P99: 7 | Q99: 7 | R99: 7 | T99: =+R99 -> 7 | U99: =+AVERAGE(G99:R99) -> 7 | V99: 6 | X99: 7 | Y99: 7 | Z99: 7 | AA99: 7 | AD99: 7 | AE99: 6
D100: Seguridad y Salud Ocupacional | F100: Real | G100: 4 | H100: 4 | I100: 4 | J100: 4 | K100: 4 | L100: 4 | M100: 4 | N100: 4 | O100: 4 | P100: 4 | Q100: 4 | R100: 4 | T100: =+R100 -> 4 | U100: =+AVERAGE(G100:R100) -> 4 | V100: 7 | X100: 4 | Y100: 4 | Z100: 4 | AA100: 4 | AD100: 7 | AE100: 7
F101: Ppto | G101: 4 | H101: 4 | I101: 4 | J101: 4 | K101: 4 | L101: 4 | M101: 4 | N101: 4 | O101: 4 | P101: 4 | Q101: 4 | R101: 4 | T101: =+R101 -> 4 | U101: =+AVERAGE(G101:R101) -> 4 | V101: 4 | X101: 4 | Y101: 4 | Z101: 4 | AA101: 4 | AD101: 4 | AE101: 4
...

Sheet 2024
B1: Libro Dotación Minera AMSA
B3: Total Dotación Propia Actividad Corporativa | F3: Real | G3: 398 | H3: 401 | I3: 404 | J3: 414 | K3: 416 | L3: 422 | M3: 429 | N3: 429 | O3: 426 | P3: 423 | Q3: 424 | R3: 426 | T3: 426 | U3: =+AVERAGE(G3:R3) -> 417.66667 | V3: 448 | X3: 406 | Y3: 417 | Z3: 493 | AA3: 425 | AC3: 426 | AD3: 488
F4: Ppto | G4: 428 | H4: 428 | I4: 429 | J4: 432 | K4: 432 | L4: 432 | M4: 432 | N4: 432 | O4: 431 | P4: 430 | Q4: 430 | R4: 430 | T4: 430 | U4: =+AVERAGE(G4:R4) -> 430.5 | V4: 431 | X4: 428 | Y4: 432 | Z4: 432 | AA4: 430 | AC4: 430 | AD4: 431
B6: Propia | F6: N° | G6: 202401 | H6: 202402 | I6: 202403 | J6: 202404 | K6: 202405 | L6: 202406 | M6: 202407 | N6: 202408 | O6: 202409 | P6: 202410 | Q6: 202411 | R6: 202412 | T6: MES | U6: YTD | V6: FY | X6: Q1 | Y6: Q2 | Z6: Q3 | AA6: Q4 | AC6: MES | AD6: YTD
B7: Auditoria | D7: Auditoria | F7: Real | G7: 11 | H7: 12 | I7: 14 | J7: 14 | K7: 14 | L7: 14 | M7: 14 | N7: 14 | O7: 14 | P7: 14 | Q7: 13 | R7: 13 | T7: 13 | U7: 13 | V7: 13 | X7: 12 | Y7: 14 | Z7: 14 | AA7: 13 | AC7: 13 | AD7: 13
F8: Ppto | G8: 14 | H8: 14 | I8: 14 | J8: 14 | K8: 14 | L8: 14 | M8: 14 | N8: 14 | O8: 14 | P8: 14 | Q8: 14 | R8: 14 | T8: 14 | U8: 14 | V8: 14 | X8: 14 | Y8: 14 | Z8: 14 | AA8: 14 | AC8: 14 | AD8: 14
B9: Directorio | D9: Directorio | F9: Real | G9: 3 | H9: 3 | I9: 3 | J9: 3 | K9: 3 | L9: 3 | M9: 3 | N9: 3 | O9: 3 | P9: 3 | Q9: 3 | R9: 3 | T9: 3 | U9: 3 | V9: 3 | X9: 3 | Y9: 3 | Z9: 3 | AA9: 3 | AC9: 3 | AD9: 3
F10: Ppto | G10: 3 | H10: 3 | I10: 3 | J10: 3 | K10: 3 | L10: 3 | M10: 3 | N10: 3 | O10: 3 | P10: 3 | Q10: 3 | R10: 3 | T10: 3 | U10: 3 | V10: 3 | X10: 3 | Y10: 3 | Z10: 3 | AA10: 3 | AC10: 3 | AD10: 3
B11: Presidencia Ejecutiva | D11: Presidencia Ejecutiva | F11: Real | G11: 2 | H11: 2 | I11: 2 | J11: 2 | K11: 2 | L11: 2 | M11: 2 | N11: 2 | O11: 2 | P11: 2 | Q11: 2 | R11: 2 | T11: 2 | U11: 2 | V11: 2 | X11: 2 | Y11: 2 | Z11: 2 | AA11: 2 | AC11: 2 | AD11: 2
F12: Ppto | G12: 2 | H12: 2 | I12: 2 | J12: 2 | K12: 2 | L12: 2 | M12: 2 | N12: 2 | O12: 2 | P12: 2 | Q12: 2 | R12: 2 | T12: 2 | U12: 2 | V12: 2 | X12: 2 | Y12: 2 | Z12: 2 | AA12: 2 | AC12: 2 | AD12: 2
B13: Vicepresidencia Asuntos Corporativos y Sustentabilidad | D13: Asuntos Públicos Corporativo | F13: Real | G13: 5 | H13: 5 | I13: 5 | J13: 5 | K13: 5 | L13: 4 | M13: 4 | N13: 0 | O13: 0 | P13: 0 | Q13: 0 | R13: 0 | T13: 0 | U13: 5 | V13: 3 | X13: 5 | Y13: 5 | Z13: 4 | AA13: 0 | AC13: 0 | AD13: 5
F14: Ppto | G14: 14 | H14: 14 | I14: 14 | J14: 14 | K14: 14 | L14: 14 | M14: 14 | N14: 14 | O14: 14 | P14: 14 | Q14: 14 | R14: 14 | T14: 14 | U14: 14 | V14: 14 | X14: 14 | Y14: 14 | Z14: 14 | AA14: 14 | AC14: 14 | AD14: 14
D15: Asuntos Publicos MLP | F15: Real | G15: 17 | H15: 17 | I15: 18 | J15: 18 | K15: 18 | L15: 18 | M15: 18 | N15: 0 | O15: 0 | P15: 0 | Q15: 0 | R15: 0 | T15: 0 | U15: 18 | V15: 10 | X15: 17 | Y15: 18 | Z15: 18 | AA15: 0 | AC15: 0 | AD15: 18
F16: Ppto | G16: 20 | H16: 20 | I16: 20 | J16: 20 | K16: 20 | L16: 20 | M16: 20 | N16: 20 | O16: 20 | P16: 20 | Q16: 20 | R16: 20 | T16: 20 | U16: 20 | V16: 20 | X16: 20 | Y16: 20 | Z16: 20 | AA16: 20 | AC16: 20 | AD16: 20
D17: Asuntos Públicos Norte | F17: Real | G17: 12 | H17: 13 | I17: 12 | J17: 13 | K17: 13 | L17: 13 | M17: 13 | N17: 0 | O17: 0 | P17: 0 | Q17: 0 | R17: 0 | T17: 0 | U17: 13 | V17: 7 | X17: 12 | Y17: 13 | Z17: 13 | AA17: 0 | AC17: 0 | AD17: 13
F18: Ppto | G18: 8 | H18: 8 | I18: 8 | J18: 8 | K18: 8 | L18: 8 | M18: 8 | N18: 8 | O18: 8 | P18: 8 | Q18: 8 | R18: 8 | T18: 8 | U18: 8 | V18: 8 | X18: 8 | Y18: 8 | Z18: 8 | AA18: 8 | AC18: 8 | AD18: 8
D19: Comunicaciones | F19: Real | G19: 8 | H19: 8 | I19: 8 | J19: 8 | K19: 8 | L19: 8 | M19: 8 | N19: 0 | O19: 0 | P19: 0 | Q19: 0 | R19: 0 | T19: 0 | U19: 8 | V19: 5 | X19: 8 | Y19: 8 | Z19: 8 | AA19: 0 | AC19: 0 | AD19: 8
F20: Ppto | G20: 8 | H20: 8 | I20: 8 | J20: 8 | K20: 8 | L20: 8 | M20: 8 | N20: 8 | O20: 8 | P20: 8 | Q20: 8 | R20: 8 | T20: 8 | U20: 8 | V20: 8 | X20: 8 | Y20: 8 | Z20: 8 | AA20: 8 | AC20: 8 | AD20: 8
D21: Medio Ambiente | F21: Real | G21: 7 | H21: 7 | I21: 7 | J21: 7 | K21: 7 | L21: 7 | M21: 7 | N21: 0 | O21: 0 | P21: 0 | Q21: 0 | R21: 0 | T21: 0 | U21: 7 | V21: 4 | X21: 7 | Y21: 7 | Z21: 7 | AA21: 0 | AC21: 0 | AD21: 7
F22: Ppto | G22: 7 | H22: 7 | I22: 7 | J22: 7 | K22: 7 | L22: 7 | M22: 7 | N22: 7 | O22: 7 | P22: 7 | Q22: 7 | R22: 7 | T22: 7 | U22: 7 | V22: 7 | X22: 7 | Y22: 7 | Z22: 7 | AA22: 7 | AC22: 7 | AD22: 7
D23: SSO | F23: Real | G23: 4 | H23: 4 | I23: 4 | J23: 4 | K23: 4 | L23: 4 | M23: 4 | N23: 0 | O23: 0 | P23: 0 | Q23: 0 | R23: 0 | T23: 0 | U23: 4 | V23: 2 | X23: 4 | Y23: 4 | Z23: 4 | AA23: 0 | AC23: 0 | AD23: 4
F24: Ppto | G24: 4 | H24: 4 | I24: 4 | J24: 4 | K24: 4 | L24: 4 | M24: 4 | N24: 4 | O24: 4 | P24: 4 | Q24: 4 | R24: 4 | T24: 4 | U24: 4 | V24: 4 | X24: 4 | Y24: 4 | Z24: 4 | AA24: 4 | AC24: 4 | AD24: 4
D25: Vicepresidencia Asuntos Corporativos y Sustentabilidad | F25: Real | G25: 7 | H25: 7 | I25: 7 | J25: 7 | K25: 7 | L25: 7 | M25: 7 | N25: 0 | O25: 0 | P25: 0 | Q25: 0 | R25: 0 | T25: 0 | U25: 7 | V25: 4 | X25: 7 | Y25: 7 | Z25: 7 | AA25: 0 | AC25: 0 | AD25: 7
F26: Ppto | G26: 6 | H26: 6 | I26: 6 | J26: 7 | K26: 7 | L26: 7 | M26: 7 | N26: 7 | O26: 7 | P26: 7 | Q26: 7 | R26: 7 | T26: 7 | U26: 7 | V26: 7 | X26: 6 | Y26: 7 | Z26: 7 | AA26: 7 | AC26: 7 | AD26: 7
B27: Vicepresidencia Comercialización | D27: Ventas Cátodos Molibdeno y Hedge | F27: Real | G27: 4 | H27: 4 | I27: 5 | J27: 5 | K27: 5 | L27: 5 | M27: 5 | N27: 5 | O27: 5 | P27: 5 | Q27: 5 | R27: 5 | T27: 5 | U27: 5 | V27: 5 | X27: 4 | Y27: 5 | Z27: 5 | AA27: 5 | AC27: 5 | AD27: 5
F28: Ppto | G28: 5 | H28: 5 | I28: 5 | J28: 6 | K28: 6 | L28: 6 | M28: 6 | N28: 6 | O28: 6 | P28: 6 | Q28: 6 | R28: 6 | T28: 6 | U28: 6 | V28: 6 | X28: 5 | Y28: 6 | Z28: 6 | AA28: 6 | AC28: 6 | AD28: 6
D29: Ventas Concentrado Acido | F29: Real | G29: 4 | H29: 4 | I29: 4 | J29: 4 | K29: 5 | L29: 5 | M29: 5 | N29: 5 | O29: 5 | P29: 5 | Q29: 5 | R29: 5 | T29: 5 | U29: 5 | V29: 5 | X29: 4 | Y29: 5 | Z29: 5 | AA29: 5 | AC29: 5 | AD29: 5
F30: Ppto | G30: 4 | H30: 4 | I30: 4 | J30: 4 | K30: 4 | L30: 4 | M30: 4 | N30: 4 | O30: 4 | P30: 4 | Q30: 4 | R30: 4 | T30: 4 | U30: 4 | V30: 4 | X30: 4 | Y30: 4 | Z30: 4 | AA30: 4 | AC30: 4 | AD30: 4
D31: Vicepresidencia Comercialización | F31: Real | G31: 10 | H31: 10 | I31: 10 | J31: 10 | K31: 9 | L31: 9 | M31: 9 | N31: 9 | O31: 9 | P31: 9 | Q31: 9 | R31: 9 | T31: 9 | U31: 9 | V31: 9 | X31: 10 | Y31: 9 | Z31: 9 | AA31: 9 | AC31: 9 | AD31: 9
F32: Ppto | G32: 10 | H32: 10 | I32: 10 | J32: 10 | K32: 10 | L32: 10 | M32: 10 | N32: 10 | O32: 10 | P32: 10 | Q32: 10 | R32: 10 | T32: 10 | U32: 10 | V32: 10 | X32: 10 | Y32: 10 | Z32: 10 | AA32: 10 | AC32: 10 | AD32: 10
B33: Vicepresidencia de Asuntos Corporativos | D33: Asuntos Públicos Corporativo | F33: Real | G33: 0 | H33: 0 | I33: 0 | J33: 0 | K33: 0 | L33: 0 | M33: 0 | N33: 4 | O33: 4 | P33: 4 | Q33: 4 | R33: 4 | T33: 4 | U33: 4 | V33: 3 | X33: 0 | Y33: 0 | Z33: 4 | AA33: 4 | AC33: 4 | AD33: 4
F34: Ppto | G34: 0 | H34: 0 | I34: 0 | J34: 0 | K34: 0 | L34: 0 | M34: 0 | N34: 0 | O34: 0 | P34: 0 | Q34: 0 | R34: 0 | T34: 0 | U34: 0 | V34: 0 | X34: 0 | Y34: 0 | Z34: 0 | AA34: 0 | AC34: 0 | AD34: 0
D35: Asuntos Publicos MLP | F35: Real | G35: 0 | H35: 0 | I35: 0 | J35: 0 | K35: 0 | L35: 0 | M35: 0 | N35: 19 | O35: 19 | P35: 19 | Q35: 20 | R35: 20 | T35: 20 | U35: 19 | V35: 16 | X35: 0 | Y35: 0 | Z35: 19 | AA35: 20 | AC35: 20 | AD35: 19
F36: Ppto | G36: 0 | H36: 0 | I36: 0 | J36: 0 | K36: 0 | L36: 0 | M36: 0 | N36: 0 | O36: 0 | P36: 0 | Q36: 0 | R36: 0 | T36: 0 | U36: 0 | V36: 0 | X36: 0 | Y36: 0 | Z36: 0 | AA36: 0 | AC36: 0 | AD36: 0
D37: Asuntos Públicos Norte | F37: Real | G37: 0 | H37: 0 | I37: 0 | J37: 0 | K37: 0 | L37: 0 | M37: 0 | N37: 14 | O37: 14 | P37: 13 | Q37: 13 | R37: 13 | T37: 13 | U37: 13 | V37: 11 | X37: 0 | Y37: 0 | Z37: 14 | AA37: 13 | AC37: 13 | AD37: 13
F38: Ppto | G38: 0 | H38: 0 | I38: 0 | J38: 0 | K38: 0 | L38: 0 | M38: 0 | N38: 0 | O38: 0 | P38: 0 | Q38: 0 | R38: 0 | T38: 0 | U38: 0 | V38: 0 | X38: 0 | Y38: 0 | Z38: 0 | AA38: 0 | AC38: 0 | AD38: 0
D39: Comunicaciones | F39: Real | G39: 0 | H39: 0 | I39: 0 | J39: 0 | K39: 0 | L39: 0 | M39: 0 | N39: 8 | O39: 8 | P39: 8 | Q39: 8 | R39: 8 | T39: 8 | U39: 8 | V39: 7 | X39: 0 | Y39: 0 | Z39: 8 | AA39: 8 | AC39: 8 | AD39: 8
F40: Ppto | G40: 0 | H40: 0 | I40: 0 | J40: 0 | K40: 0 | L40: 0 | M40: 0 | N40: 0 | O40: 0 | P40: 0 | Q40: 0 | R40: 0 | T40: 0 | U40: 0 | V40: 0 | X40: 0 | Y40: 0 | Z40: 0 | AA40: 0 | AC40: 0 | AD40: 0
D41: Vicepresidencia Asuntos Corporativos | F41: Real | G41: 0 | H41: 0 | I41: 0 | J41: 0 | K41: 0 | L41: 0 | M41: 0 | N41: 2 | O41: 2 | P41: 2 | Q41: 3 | R41: 3 | T41: 3 | U41: 2 | V41: 2 | X41: 0 | Y41: 0 | Z41: 2 | AA41: 3 | AC41: 3 | AD41: 2
F42: Ppto | G42: 0 | H42: 0 | I42: 0 | J42: 0 | K42: 0 | L42: 0 | M42: 0 | N42: 0 | O42: 0 | P42: 0 | Q42: 0 | R42: 0 | T42: 0 | U42: 0 | V42: 0 | X42: 0 | Y42: 0 | Z42: 0 | AA42: 0 | AC42: 0 | AD42: 0
B43: Vicepresidencia de Proyectos | D43: Finanzas VPP | F43: Real | G43: 6 | H43: 6 | I43: 6 | J43: 7 | K43: 8 | L43: 7 | M43: 7 | N43: 7 | O43: 6 | P43: 7 | Q43: 12 | R43: 12 | T43: 12 | U43: 8 | V43: 8 | X43: 6 | Y43: 7 | Z43: 7 | AA43: 10 | AC43: 12 | AD43: 8
F44: Ppto | G44: 7 | H44: 7 | I44: 7 | J44: 7 | K44: 7 | L44: 7 | M44: 7 | N44: 7 | O44: 7 | P44: 7 | Q44: 7 | R44: 7 | T44: 7 | U44: 7 | V44: 7 | X44: 7 | Y44: 7 | Z44: 7 | AA44: 7 | AC44: 7 | AD44: 7
D45: Ingenieria y Construccion | F45: Real | G45: 4 | H45: 4 | I45: 4 | J45: 4 | K45: 3 | L45: 3 | M45: 3 | N45: 3 | O45: 3 | P45: 3 | Q45: 3 | R45: 3 | T45: 3 | U45: 3 | V45: 3 | X45: 4 | Y45: 3 | Z45: 3 | AA45: 3 | AC45: 3 | AD45: 3
F46: Ppto | G46: 5 | H46: 5 | I46: 5 | J46: 5 | K46: 5 | L46: 5 | M46: 5 | N46: 5 | O46: 5 | P46: 5 | Q46: 5 | R46: 5 | T46: 5 | U46: 5 | V46: 5 | X46: 5 | Y46: 5 | Z46: 5 | AA46: 5 | AC46: 5 | AD46: 5
D47: Proyecto MLP Largo Plazo | F47: Real | G47: 0 | H47: 0 | I47: 0 | J47: 0 | K47: 0 | L47: 0 | M47: 0 | N47: 0 | O47: 0 | P47: 0 | Q47: 0 | R47: 0 | T47: 0 | U47: 0 | V47: 0 | X47: 0 | Y47: 0 | Z47: 0 | AA47: 0 | AC47: 0 | AD47: 0
F48: Ppto | G48: 0 | H48: 0 | I48: 0 | J48: 0 | K48: 0 | L48: 0 | M48: 0 | N48: 0 | O48: 0 | P48: 0 | Q48: 0 | R48: 0 | T48: 0 | U48: 0 | V48: 0 | X48: 0 | Y48: 0 | Z48: 0 | AA48: 0 | AC48: 0 | AD48: 0
D49: Vicepresidencia de Proyectos + Proyecto INCO + Proyecto Estudio | F49: Real | G49: 2 | H49: 4 | I49: 4 | J49: 4 | K49: 4 | L49: 3 | M49: 3 | N49: 3 | O49: 3 | P49: 3 | Q49: 8 | R49: 8 | T49: 8 | U49: 4 | V49: 4 | X49: 3 | Y49: 4 | Z49: 3 | AA49: 6 | AC49: 8 | AD49: 4
F50: Ppto | G50: 2 | H50: 2 | I50: 2 | J50: 2 | K50: 2 | L50: 2 | M50: 2 | N50: 2 | O50: 2 | P50: 2 | Q50: 2 | R50: 2 | T50: 2 | U50: 2 | V50: 2 | X50: 2 | Y50: 2 | Z50: 2 | AA50: 2 | AC50: 2 | AD50: 2
B51: Vicepresidencia Desarrollo | D51: Administración MIC | F51: Real | G51: 2 | H51: 2 | I51: 2 | J51: 2 | K51: 2 | L51: 2 | M51: 2 | N51: 2 | O51: 2 | P51: 2 | Q51: 2 | R51: 2 | T51: 2 | U51: 2 | V51: 2 | X51: 2 | Y51: 2 | Z51: 2 | AA51: 2 | AC51: 2 | AD51: 2
F52: Ppto | G52: 2 | H52: 2 | I52: 2 | J52: 3 | K52: 3 | L52: 3 | M52: 3 | N52: 3 | O52: 3 | P52: 3 | Q52: 3 | R52: 3 | T52: 3 | U52: 3 | V52: 3 | X52: 2 | Y52: 3 | Z52: 3 | AA52: 3 | AC52: 3 | AD52: 3
D53: Desarrollo | F53: Real | G53: 9 | H53: 9 | I53: 9 | J53: 9 | K53: 9 | L53: 9 | M53: 9 | N53: 9 | O53: 9 | P53: 9 | Q53: 9 | R53: 9 | T53: 9 | U53: 9 | V53: 9 | X53: 9 | Y53: 9 | Z53: 9 | AA53: 9 | AC53: 9 | AD53: 9
F54: Ppto | G54: 9 | H54: 9 | I54: 9 | J54: 9 | K54: 9 | L54: 9 | M54: 9 | N54: 9 | O54: 9 | P54: 9 | Q54: 9 | R54: 9 | T54: 9 | U54: 9 | V54: 9 | X54: 9 | Y54: 9 | Z54: 9 | AA54: 9 | AC54: 9 | AD54: 9
D55: Vicepresidencia Desarrollo | F55: Real | G55: 4 | H55: 4 | I55: 3 | J55: 3 | K55: 4 | L55: 8 | M55: 9 | N55: 10 | O55: 10 | P55: 10 | Q55: 11 | R55: 11 | T55: 11 | U55: 7 | V55: 7 | X55: 4 | Y55: 5 | Z55: 10 | AA55: 11 | AC55: 11 | AD55: 7
F56: Ppto | G56: 5 | H56: 5 | I56: 5 | J56: 5 | K56: 5 | L56: 5 | M56: 5 | N56: 5 | O56: 5 | P56: 5 | Q56: 5 | R56: 5 | T56: 5 | U56: 5 | V56: 5 | X56: 5 | Y56: 5 | Z56: 5 | AA56: 5 | AC56: 5 | AD56: 5
B57: Vicepresidencia Estrategia e Innovación | D57: Data y Analítica Avanzada | F57: Real | G57: 7 | H57: 7 | I57: 7 | J57: 8 | K57: 8 | L57: 8 | M57: 8 | N57: 8 | O57: 8 | P57: 8 | Q57: 8 | R57: 8 | T57: 8 | U57: 8 | V57: 8 | X57: 7 | Y57: 8 | Z57: 8 | AA57: 8 | AC57: 8 | AD57: 8
F58: Ppto | G58: 8 | H58: 8 | I58: 8 | J58: 8 | K58: 8 | L58: 8 | M58: 8 | N58: 8 | O58: 8 | P58: 8 | Q58: 8 | R58: 8 | T58: 8 | U58: 8 | V58: 8 | X58: 8 | Y58: 8 | Z58: 8 | AA58: 8 | AC58: 8 | AD58: 8
D59: Innovación + Energía y Recursos Hídricos | F59: Real | G59: 7 | H59: 6 | I59: 6 | J59: 6 | K59: 5 | L59: 6 | M59: 6 | N59: 6 | O59: 6 | P59: 6 | Q59: 6 | R59: 6 | T59: 6 | U59: 6 | V59: 6 | X59: 6 | Y59: 6 | Z59: 6 | AA59: 6 | AC59: 6 | AD59: 6
F60: Ppto | G60: 6 | H60: 6 | I60: 6 | J60: 6 | K60: 6 | L60: 6 | M60: 6 | N60: 6 | O60: 6 | P60: 6 | Q60: 6 | R60: 6 | T60: 6 | U60: 6 | V60: 6 | X60: 6 | Y60: 6 | Z60: 6 | AA60: 6 | AC60: 6 | AD60: 6
D61: Proyecto Descarbonización | F61: Real | G61: 4 | H61: 5 | I61: 5 | J61: 5 | K61: 5 | L61: 5 | M61: 5 | N61: 5 | O61: 5 | P61: 5 | Q61: 5 | R61: 5 | T61: 5 | U61: 5 | V61: 5 | X61: 5 | Y61: 5 | Z61: 5 | AA61: 5 | AC61: 5 | AD61: 5
F62: Ppto | G62: 0 | H62: 0 | I62: 0 | J62: 0 | K62: 0 | L62: 0 | M62: 0 | N62: 0 | O62: 0 | P62: 0 | Q62: 0 | R62: 0 | T62: 0 | U62: 0 | V62: 0 | X62: 0 | Y62: 0 | Z62: 0 | AA62: 0 | AC62: 0 | AD62: 0
D63: Tecnologia | F63: Real | G63: 52 | H63: 52 | I63: 51 | J63: 54 | K63: 55 | L63: 55 | M63: 55 | N63: 55 | O63: 55 | P63: 55 | Q63: 55 | R63: 56 | T63: 56 | U63: 54 | V63: 54 | X63: 52 | Y63: 55 | Z63: 55 | AA63: 55 | AC63: 56 | AD63: 54
F64: Ppto | G64: 56 | H64: 56 | I64: 56 | J64: 56 | K64: 56 | L64: 56 | M64: 56 | N64: 56 | O64: 55 | P64: 54 | Q64: 54 | R64: 54 | T64: 54 | U64: 55 | V64: 55 | X64: 56 | Y64: 56 | Z64: 56 | AA64: 54 | AC64: 54 | AD64: 55
D65: Vicepresidencia Estrategia e Innovación | F65: Real | G65: 5 | H65: 5 | I65: 6 | J65: 6 | K65: 6 | L65: 6 | M65: 6 | N65: 7 | O65: 6 | P65: 6 | Q65: 6 | R65: 5 | T65: 5 | U65: 6 | V65: 6 | X65: 5 | Y65: 6 | Z65: 6 | AA65: 6 | AC65: 5 | AD65: 6
F66: Ppto | G66: 9 | H66: 9 | I66: 9 | J66: 9 | K66: 9 | L66: 9 | M66: 9 | N66: 9 | O66: 9 | P66: 9 | Q66: 9 | R66: 9 | T66: 9 | U66: 9 | V66: 9 | X66: 9 | Y66: 9 | Z66: 9 | AA66: 9 | AC66: 9 | AD66: 9
B67: Vicepresidencia Finanzas | D67: Abastecimiento | F67: Real | G67: 37 | H67: 36 | I67: 35 | J67: 34 | K67: 34 | L67: 35 | M67: 37 | N67: 37 | O67: 37 | P67: 37 | Q67: 33 | R67: 32 | T67: 32 | U67: 35 | V67: 35 | X67: 36 | Y67: 34 | Z67: 37 | AA67: 34 | AC67: 32 | AD67: 35
F68: Ppto | G68: 38 | H68: 38 | I68: 38 | J68: 38 | K68: 38 | L68: 38 | M68: 38 | N68: 38 | O68: 38 | P68: 38 | Q68: 38 | R68: 38 | T68: 38 | U68: 38 | V68: 38 | X68: 38 | Y68: 38 | Z68: 38 | AA68: 38 | AC68: 38 | AD68: 38
D69: Contabilidad | F69: Real | G69: 36 | H69: 36 | I69: 35 | J69: 36 | K69: 36 | L69: 35 | M69: 35 | N69: 35 | O69: 33 | P69: 33 | Q69: 33 | R69: 33 | T69: 33 | U69: 35 | V69: 35 | X69: 36 | Y69: 36 | Z69: 34 | AA69: 33 | AC69: 33 | AD69: 35
F70: Ppto | G70: 36 | H70: 36 | I70: 36 | J70: 36 | K70: 36 | L70: 36 | M70: 36 | N70: 36 | O70: 36 | P70: 36 | Q70: 36 | R70: 36 | T70: 36 | U70: 36 | V70: 36 | X70: 36 | Y70: 36 | Z70: 36 | AA70: 36 | AC70: 36 | AD70: 36
D71: Energia y Recursos Hidricos | F71: Real | G71: 2 | H71: 2 | I71: 2 | J71: 2 | K71: 2 | L71: 3 | M71: 3 | N71: 0 | O71: 0 | P71: 0 | Q71: 0 | R71: 0 | T71: 0 | U71: 2 | V71: 1 | X71: 2 | Y71: 2 | Z71: 3 | AA71: 0 | AC71: 0 | AD71: 2
F72: Ppto | G72: 2 | H72: 2 | I72: 2 | J72: 2 | K72: 2 | L72: 2 | M72: 2 | N72: 2 | O72: 2 | P72: 2 | Q72: 2 | R72: 2 | T72: 2 | U72: 2 | V72: 2 | X72: 2 | Y72: 2 | Z72: 2 | AA72: 2 | AC72: 2 | AD72: 2
D73: Energía y Servicios Estratégicos | F73: Real | G73: 0 | H73: 0 | I73: 0 | J73: 0 | K73: 0 | L73: 0 | M73: 0 | N73: 3 | O73: 3 | P73: 3 | Q73: 3 | R73: 3 | T73: 3 | U73: 3 | V73: 3 | X73: 0 | Y73: 0 | Z73: 3 | AA73: 3 | AC73: 3 | AD73: 3
D74: Finanzas e Impuestos + Planificación Financiera | F74: Real | G74: 26 | H74: 26 | I74: 27 | J74: 27 | K74: 27 | L74: 28 | M74: 28 | N74: 26 | O74: 28 | P74: 28 | Q74: 28 | R74: 28 | T74: 28 | U74: 27 | V74: 27 | X74: 26 | Y74: 27 | Z74: 27 | AA74: 28 | AC74: 28 | AD74: 27
F75: Ppto | G75: 28 | H75: 28 | I75: 28 | J75: 28 | K75: 28 | L75: 28 | M75: 28 | N75: 28 | O75: 28 | P75: 28 | Q75: 28 | R75: 28 | T75: 28 | U75: 28 | V75: 28 | X75: 28 | Y75: 28 | Z75: 28 | AA75: 28 | AC75: 28 | AD75: 28
D76: Gerencia Competitividad | F76: Real | G76: 0 | H76: 0 | I76: 0 | J76: 0 | K76: 0 | L76: 0 | M76: 0 | N76: 3 | O76: 3 | P76: 3 | Q76: 2 | R76: 0 | T76: 0 | U76: 3 | V76: 3 | X76: 0 | Y76: 0 | Z76: 3 | AA76: 3 | AC76: 0 | AD76: 3
D77: Planificacion y Control de Gestion | F77: Real | G77: 10 | H77: 9 | I77: 9 | J77: 9 | K77: 9 | L77: 10 | M77: 10 | N77: 9 | O77: 9 | P77: 9 | Q77: 7 | R77: 9 | T77: 9 | U77: 9 | V77: 9 | X77: 9 | Y77: 9 | Z77: 9 | AA77: 8 | AC77: 9 | AD77: 9
F78: Ppto | G78: 10 | H78: 10 | I78: 10 | J78: 10 | K78: 10 | L78: 10 | M78: 10 | N78: 10 | O78: 10 | P78: 10 | Q78: 10 | R78: 10 | T78: 10 | U78: 10 | V78: 10 | X78: 10 | Y78: 10 | Z78: 10 | AA78: 10 | AC78: 10 | AD78: 10
D79: Riesgo Compliance y Control Interno | F79: Real | G79: 8 | H79: 8 | I79: 9 | J79: 8 | K79: 9 | L79: 9 | M79: 9 | N79: 9 | O79: 9 | P79: 8 | Q79: 8 | R79: 8 | T79: 8 | U79: 9 | V79: 9 | X79: 8 | Y79: 9 | Z79: 9 | AA79: 8 | AC79: 8 | AD79: 9
F80: Ppto | G80: 9 | H80: 9 | I80: 9 | J80: 9 | K80: 9 | L80: 9 | M80: 9 | N80: 9 | O80: 9 | P80: 9 | Q80: 9 | R80: 9 | T80: 9 | U80: 9 | V80: 9 | X80: 9 | Y80: 9 | Z80: 9 | AA80: 9 | AC80: 9 | AD80: 9
D81: Vicepresidencia Finanzas | F81: Real | G81: 3 | H81: 3 | I81: 4 | J81: 5 | K81: 5 | L81: 5 | M81: 5 | N81: 2 | O81: 2 | P81: 2 | Q81: 2 | R81: 2 | T81: 2 | U81: 3 | V81: 3 | X81: 3 | Y81: 5 | Z81: 3 | AA81: 2 | AC81: 2 | AD81: 3
F82: Ppto | G82: 3 | H82: 3 | I82: 3 | J82: 3 | K82: 3 | L82: 3 | M82: 3 | N82: 3 | O82: 3 | P82: 3 | Q82: 3 | R82: 3 | T82: 3 | U82: 3 | V82: 3 | X82: 3 | Y82: 3 | Z82: 3 | AA82: 3 | AC82: 3 | AD82: 3
B83: Vicepresidencia Legal | D83: Legal | F83: Real | G83: 8 | H83: 7 | I83: 8 | J83: 8 | K83: 8 | L83: 8 | M83: 9 | N83: 8 | O83: 8 | P83: 8 | Q83: 8 | R83: 8 | T83: 8 | U83: 8 | V83: 8 | X83: 8 | Y83: 8 | Z83: 8 | AA83: 8 | AC83: 8 | AD83: 8
F84: Ppto | G84: 9 | H84: 9 | I84: 9 | J84: 9 | K84: 9 | L84: 9 | M84: 9 | N84: 9 | O84: 9 | P84: 9 | Q84: 9 | R84: 9 | T84: 9 | U84: 9 | V84: 9 | X84: 9 | Y84: 9 | Z84: 9 | AA84: 9 | AC84: 9 | AD84: 9
D85: Propiedad Minera | F85: Real | G85: 9 | H85: 9 | I85: 9 | J85: 9 | K85: 9 | L85: 9 | M85: 9 | N85: 9 | O85: 9 | P85: 9 | Q85: 9 | R85: 9 | T85: 9 | U85: 9 | V85: 9 | X85: 9 | Y85: 9 | Z85: 9 | AA85: 9 | AC85: 9 | AD85: 9
F86: Ppto | G86: 9 | H86: 9 | I86: 9 | J86: 9 | K86: 9 | L86: 9 | M86: 9 | N86: 9 | O86: 9 | P86: 9 | Q86: 9 | R86: 9 | T86: 9 | U86: 9 | V86: 9 | X86: 9 | Y86: 9 | Z86: 9 | AA86: 9 | AC86: 9 | AD86: 9
D87: Vicepresidencia Legal | F87: Real | G87: 2 | H87: 2 | I87: 2 | J87: 2 | K87: 2 | L87: 2 | M87: 2 | N87: 2 | O87: 2 | P87: 2 | Q87: 2 | R87: 2 | T87: 2 | U87: 2 | V87: 2 | X87: 2 | Y87: 2 | Z87: 2 | AA87: 2 | AC87: 2 | AD87: 2
F88: Ppto | G88: 2 | H88: 2 | I88: 2 | J88: 2 | K88: 2 | L88: 2 | M88: 2 | N88: 2 | O88: 2 | P88: 2 | Q88: 2 | R88: 2 | T88: 2 | U88: 2 | V88: 2 | X88: 2 | Y88: 2 | Z88: 2 | AA88: 2 | AC88: 2 | AD88: 2
B89: Vicepresidencia Operaciones | D89: Vicepresidencia Operaciones | F89: Real | G89: 0 | H89: 0 | I89: 0 | J89: 0 | K89: 0 | L89: 0 | M89: 0 | N89: 3 | O89: 3 | P89: 3 | Q89: 3 | R89: 3 | T89: 3 | U89: 3 | V89: 3 | X89: 0 | Y89: 0 | Z89: 3 | AA89: 3 | AC89: 3 | AD89: 3
F90: Ppto | G90: 0 | H90: 0 | I90: 0 | J90: 0 | K90: 0 | L90: 0 | M90: 0 | N90: 0 | O90: 0 | P90: 0 | Q90: 0 | R90: 0 | T90: 0 | U90: 0 | V90: 0 | X90: 0 | Y90: 0 | Z90: 0 | AA90: 0 | AC90: 0 | AD90: 0
B91: Vicepresidencia Personas y Organización | D91: Desarrollo Organizacional y Compensaciones | F91: Real | G91: 16 | H91: 17 | I91: 17 | J91: 17 | K91: 17 | L91: 17 | M91: 17 | N91: 17 | O91: 17 | P91: 17 | Q91: 17 | R91: 16 | T91: 16 | U91: 17 | V91: 17 | X91: 17 | Y91: 17 | Z91: 17 | AA91: 17 | AC91: 16 | AD91: 17
F92: Ppto | G92: 16 | H92: 16 | I92: 16 | J92: 16 | K92: 16 | L92: 16 | M92: 16 | N92: 16 | O92: 16 | P92: 16 | Q92: 16 | R92: 16 | T92: 16 | U92: 16 | V92: 16 | X92: 16 | Y92: 16 | Z92: 16 | AA92: 16 | AC92: 16 | AD92: 16
D93: Efectividad Organizacional | F93: Real | G93: 14 | H93: 14 | I93: 13 | J93: 13 | K93: 13 | L93: 12 | M93: 13 | N93: 14 | O93: 13 | P93: 13 | Q93: 13 | R93: 14 | T93: 14 | U93: 13 | V93: 13 | X93: 14 | Y93: 13 | Z93: 13 | AA93: 13 | AC93: 14 | AD93: 13
F94: Ppto | G94: 15 | H94: 15 | I94: 15 | J94: 15 | K94: 15 | L94: 15 | M94: 15 | N94: 15 | O94: 15 | P94: 15 | Q94: 15 | R94: 15 | T94: 15 | U94: 15 | V94: 15 | X94: 15 | Y94: 15 | Z94: 15 | AA94: 15 | AC94: 15 | AD94: 15
D95: Relaciones Laborales | F95: Real | G95: 2 | H95: 2 | I95: 2 | J95: 2 | K95: 2 | L95: 2 | M95: 2 | N95: 2 | O95: 2 | P95: 2 | Q95: 2 | R95: 1 | T95: 1 | U95: 2 | V95: 2 | X95: 2 | Y95: 2 | Z95: 2 | AA95: 2 | AC95: 1 | AD95: 2
F96: Ppto | G96: 2 | H96: 2 | I96: 2 | J96: 2 | K96: 2 | L96: 2 | M96: 2 | N96: 2 | O96: 2 | P96: 2 | Q96: 2 | R96: 2 | T96: 2 | U96: 2 | V96: 2 | X96: 2 | Y96: 2 | Z96: 2 | AA96: 2 | AC96: 2 | AD96: 2
D97: Vicepresidencia Personas y Organización | F97: Real | G97: 5 | H97: 5 | I97: 5 | J97: 6 | K97: 6 | L97: 6 | M97: 6 | N97: 6 | O97: 6 | P97: 6 | Q97: 5 | R97: 5 | T97: 5 | U97: 6 | V97: 6 | X97: 5 | Y97: 6 | Z97: 6 | AA97: 5 | AC97: 5 | AD97: 6
F98: Ppto | G98: 6 | H98: 6 | I98: 6 | J98: 6 | K98: 6 | L98: 6 | M98: 6 | N98: 6 | O98: 6 | P98: 6 | Q98: 6 | R98: 6 | T98: 6 | U98: 6 | V98: 6 | X98: 6 | Y98: 6 | Z98: 6 | AA98: 6 | AC98: 6 | AD98: 6
B99: Vicepresidencia Planificación y Servicios Técnicos | D99: Excelencia Operacional | F99: Real | G99: 5 | H99: 5 | I99: 2 | J99: 4 | K99: 5 | L99: 5 | M99: 5 | N99: 5 | O99: 5 | P99: 5 | Q99: 5 | R99: 5 | T99: 5 | U99: 5 | V99: 5 | X99: 4 | Y99: 5 | Z99: 5 | AA99: 5 | AC99: 5 | AD99: 5
F100: Ppto | G100: 6 | H100: 6 | I100: 7 | J100: 7 | K100: 7 | L100: 7 | M100: 7 | N100: 7 | O100: 7 | P100: 7 | Q100: 7 | R100: 7 | T100: 7 | U100: 7 | V100: 7 | X100: 6 | Y100: 7 | Z100: 7 | AA100: 7 | AC100: 7 | AD100: 7
D101: Mantenimiento | F101: Real | G101: 0 | H101: 0 | I101: 2 | J101: 2 | K101: 2 | L101: 3 | M101: 3 | N101: 3 | O101: 3 | P101: 3 | Q101: 3 | R101: 3 | T101: 3 | U101: 3 | V101: 2 | X101: 2 | Y101: 2 | Z101: 3 | AA101: 3 | AC101: 3 | AD101: 3
F102: Ppto | G102: 0 | H102: 0 | I102: 0 | J102: 0 | K102: 0 | L102: 0 | M102: 0 | N102: 0 | O102: 0 | P102: 0 | Q102: 0 | R102: 0 | T102: 0 | U102: 0 | V102: 0 | X102: 0 | Y102: 0 | Z102: 0 | AA102: 0 | AC102: 0 | AD102: 0
...

Sheet 2023
G1: 646 | H1: 646 | I1: 631 | J1: 628 | K1: 630 | L1: 639 | M1: 644 | N1: 648 | O1: 649 | P1: 662 | Q1: 665 | R1: 675 | S1: 646.91667
G2: 737 | H2: 751 | I2: 741 | J2: 728 | K2: 735 | L2: 734 | M2: 730 | N2: 731 | O2: 732 | P2: 736 | Q2: 746 | R2: 746 | S2: 737.25
B3: Total Dotación Propia Actividad Corporativa | F3: Real | G3: 387 | H3: 387 | I3: 387 | J3: 385 | K3: 386 | L3: 393 | M3: 391 | N3: 394 | O3: 397 | P3: 397 | Q3: 393 | R3: 398 | S3: 391.25 | T3: 398 | U3: 459 | V3: 448 | X3: 389 | Y3: 392 | Z3: 429 | AA3: 396
F4: Ppto | G4: 420 | H4: 420 | I4: 420 | J4: 415 | K4: 415 | L4: 415 | M4: 414 | N4: 414 | O4: 414 | P4: 414 | Q4: 414 | R4: 414 | S4: 415.75 | T4: 414 | U4: 456 | V4: 456 | X4: 420 | Y4: 415 | Z4: 455 | AA4: 414
S5: #DIV/0!
B6: Propia | F6: N° | G6: 202301 | H6: 202302 | I6: 202303 | J6: 202304 | K6: 202305 | L6: 202306 | M6: 202307 | N6: 202308 | O6: 202309 | P6: 202310 | Q6: 202311 | R6: 202312 | S6: #DIV/0! | T6: MES | U6: YTD | V6: FY | X6: Q1 | Y6: Q2 | Z6: Q3 | AA6: Q4
B7: Auditoria | D7: Auditoria | F7: Real | G7: 12 | H7: 12 | I7: 12 | J7: 12 | K7: 12 | L7: 12 | M7: 12 | N7: 11 | O7: 11 | P7: 11 | Q7: 11 | R7: 10 | S7: 11.5 | T7: 10 | U7: 12 | V7: 12 | X7: 12 | Y7: 12 | Z7: 11 | AA7: 11
F8: Ppto | G8: 12 | H8: 12 | I8: 12 | J8: 12 | K8: 12 | L8: 12 | M8: 12 | N8: 12 | O8: 12 | P8: 12 | Q8: 12 | R8: 12 | S8: 12 | T8: 12 | U8: 12 | V8: 12 | X8: 12 | Y8: 12 | Z8: 12 | AA8: 12
B9: Directorio | D9: Directorio | F9: Real | G9: 3 | H9: 3 | I9: 3 | J9: 3 | K9: 3 | L9: 3 | M9: 3 | N9: 3 | O9: 3 | P9: 3 | Q9: 3 | R9: 3 | S9: 3 | T9: 3 | U9: 3 | V9: 3 | X9: 3 | Y9: 3 | Z9: 3 | AA9: 3
F10: Ppto | G10: 3 | H10: 3 | I10: 3 | J10: 3 | K10: 3 | L10: 3 | M10: 3 | N10: 3 | O10: 3 | P10: 3 | Q10: 3 | R10: 3 | S10: 3 | T10: 3 | U10: 3 | V10: 3 | X10: 3 | Y10: 3 | Z10: 3 | AA10: 3
B11: Presidencia Ejecutiva | D11: Presidencia Ejecutiva | F11: Real | G11: 2 | H11: 2 | I11: 2 | J11: 2 | K11: 2 | L11: 2 | M11: 2 | N11: 2 | O11: 2 | P11: 2 | Q11: 2 | R11: 2 | S11: 2 | T11: 2 | U11: 2 | V11: 2 | X11: 2 | Y11: 2 | Z11: 2 | AA11: 2
F12: Ppto | G12: 2 | H12: 2 | I12: 2 | J12: 2 | K12: 2 | L12: 2 | M12: 2 | N12: 2 | O12: 2 | P12: 2 | Q12: 2 | R12: 2 | S12: 2 | T12: 2 | U12: 2 | V12: 2 | X12: 2 | Y12: 2 | Z12: 2 | AA12: 2
B13: Vicepresidencia Asuntos Corporativos y Sustentabilidad | D13: Asuntos Públicos Corporativo | F13: Real | G13: 7 | H13: 7 | I13: 6 | J13: 6 | K13: 6 | L13: 7 | M13: 6 | N13: 4 | O13: 4 | P13: 5 | Q13: 5 | R13: 5 | S13: 5.6666667 | T13: 5 | U13: 6 | V13: 6 | X13: 7 | Y13: 6 | Z13: 5 | AA13: 5
F14: Ppto | G14: 8 | H14: 8 | I14: 8 | J14: 8 | K14: 8 | L14: 8 | M14: 8 | N14: 8 | O14: 8 | P14: 8 | Q14: 8 | R14: 8 | S14: 8 | T14: 8 | U14: 8 | V14: 8 | X14: 8 | Y14: 8 | Z14: 8 | AA14: 8
D15: Asuntos Publicos MLP | F15: Real | G15: 19 | H15: 21 | I15: 21 | J15: 21 | K15: 21 | L15: 22 | M15: 21 | N15: 21 | O15: 21 | P15: 20 | Q15: 19 | R15: 19 | S15: 20.5 | T15: 19 | U15: 21 | V15: 21 | X15: 20 | Y15: 21 | Z15: 21 | AA15: 19
F16: Ppto | G16: 22 | H16: 22 | I16: 22 | J16: 22 | K16: 22 | L16: 22 | M16: 22 | N16: 22 | O16: 22 | P16: 22 | Q16: 22 | R16: 22 | S16: 22 | T16: 22 | U16: 22 | V16: 22 | X16: 22 | Y16: 22 | Z16: 22 | AA16: 22
D17: Asuntos Públicos Norte | F17: Real | G17: 14 | H17: 14 | I17: 14 | J17: 14 | K17: 14 | L17: 14 | M17: 14 | N17: 14 | O17: 14 | P17: 13 | Q17: 12 | R17: 12 | S17: 13.583333 | T17: 12 | U17: 14 | V17: 14 | X17: 14 | Y17: 14 | Z17: 14 | AA17: 12
F18: Ppto | G18: 14 | H18: 14 | I18: 14 | J18: 14 | K18: 14 | L18: 14 | M18: 14 | N18: 14 | O18: 14 | P18: 14 | Q18: 14 | R18: 14 | S18: 14 | T18: 14 | U18: 14 | V18: 14 | X18: 14 | Y18: 14 | Z18: 14 | AA18: 14
D19: Comunicaciones | F19: Real | G19: 7 | H19: 7 | I19: 7 | J19: 7 | K19: 7 | L19: 7 | M19: 7 | N19: 7 | O19: 7 | P19: 7 | Q19: 7 | R19: 7 | S19: 7 | T19: 7 | U19: 7 | V19: 7 | X19: 7 | Y19: 7 | Z19: 7 | AA19: 7
F20: Ppto | G20: 7 | H20: 7 | I20: 7 | J20: 7 | K20: 7 | L20: 7 | M20: 7 | N20: 7 | O20: 7 | P20: 7 | Q20: 7 | R20: 7 | S20: 7 | T20: 7 | U20: 7 | V20: 7 | X20: 7 | Y20: 7 | Z20: 7 | AA20: 7
D21: Medio Ambiente | F21: Real | G21: 7 | H21: 7 | I21: 7 | J21: 5 | K21: 5 | L21: 5 | M21: 5 | N21: 6 | O21: 6 | P21: 6 | Q21: 6 | R21: 7 | S21: 6 | T21: 7 | U21: 6 | V21: 6 | X21: 7 | Y21: 5 | Z21: 6 | AA21: 6
F22: Ppto | G22: 7 | H22: 7 | I22: 7 | J22: 6 | K22: 6 | L22: 6 | M22: 6 | N22: 6 | O22: 6 | P22: 6 | Q22: 6 | R22: 6 | S22: 6.25 | T22: 6 | U22: 6 | V22: 6 | X22: 7 | Y22: 6 | Z22: 6 | AA22: 6
D23: SSO | F23: Real | G23: 5 | H23: 5 | I23: 5 | J23: 5 | K23: 5 | L23: 4 | M23: 4 | N23: 4 | O23: 4 | P23: 4 | Q23: 4 | R23: 4 | S23: 4.4166667 | T23: 4 | U23: 4 | V23: 4 | X23: 5 | Y23: 5 | Z23: 4 | AA23: 4
F24: Ppto | G24: 5 | H24: 5 | I24: 5 | J24: 5 | K24: 5 | L24: 5 | M24: 5 | N24: 5 | O24: 5 | P24: 5 | Q24: 5 | R24: 5 | S24: 5 | T24: 5 | U24: 5 | V24: 5 | X24: 5 | Y24: 5 | Z24: 5 | AA24: 5
D25: Vicepresidencia Asuntos Corporativos y Sustentabilidad | F25: Real | G25: 5 | H25: 4 | I25: 5 | J25: 5 | K25: 5 | L25: 5 | M25: 6 | N25: 7 | O25: 7 | P25: 7 | Q25: 7 | R25: 7 | S25: 5.8333333 | T25: 7 | U25: 6 | V25: 6 | X25: 5 | Y25: 5 | Z25: 7 | AA25: 7
F26: Ppto | G26: 4 | H26: 4 | I26: 4 | J26: 4 | K26: 4 | L26: 4 | M26: 4 | N26: 4 | O26: 4 | P26: 4 | Q26: 4 | R26: 4 | S26: 4 | T26: 4 | U26: 4 | V26: 4 | X26: 4 | Y26: 4 | Z26: 4 | AA26: 4
B27: Vicepresidencia Comercialización | D27: Ventas Cátodos Molibdeno y Hedge | F27: Real | G27: 5 | H27: 5 | I27: 4 | J27: 4 | K27: 4 | L27: 4 | M27: 4 | N27: 4 | O27: 4 | P27: 4 | Q27: 4 | R27: 4 | S27: 4.1666667 | T27: 4 | U27: 4 | V27: 4 | X27: 5 | Y27: 4 | Z27: 4 | AA27: 4
F28: Ppto | G28: 5 | H28: 5 | I28: 5 | J28: 4 | K28: 4 | L28: 4 | M28: 4 | N28: 4 | O28: 4 | P28: 4 | Q28: 4 | R28: 4 | S28: 4.25 | T28: 4 | U28: 4 | V28: 4 | X28: 5 | Y28: 4 | Z28: 4 | AA28: 4
D29: Ventas Concentrado Acido | F29: Real | G29: 4 | H29: 4 | I29: 4 | J29: 4 | K29: 4 | L29: 4 | M29: 4 | N29: 4 | O29: 4 | P29: 4 | Q29: 4 | R29: 4 | S29: 4 | T29: 4 | U29: 4 | V29: 4 | X29: 4 | Y29: 4 | Z29: 4 | AA29: 4
F30: Ppto | G30: 4 | H30: 4 | I30: 4 | J30: 4 | K30: 4 | L30: 4 | M30: 4 | N30: 4 | O30: 4 | P30: 4 | Q30: 4 | R30: 4 | S30: 4 | T30: 4 | U30: 4 | V30: 4 | X30: 4 | Y30: 4 | Z30: 4 | AA30: 4
D31: Vicepresidencia Comercialización | F31: Real | G31: 10 | H31: 10 | I31: 10 | J31: 10 | K31: 10 | L31: 10 | M31: 10 | N31: 10 | O31: 10 | P31: 10 | Q31: 10 | R31: 10 | S31: 10 | T31: 10 | U31: 10 | V31: 10 | X31: 10 | Y31: 10 | Z31: 10 | AA31: 10
F32: Ppto | G32: 10 | H32: 10 | I32: 11 | J32: 11 | K32: 11 | L32: 11 | M32: 11 | N32: 11 | O32: 11 | P32: 11 | Q32: 11 | R32: 11 | S32: 10.833333 | T32: 11 | U32: 11 | V32: 11 | X32: 10 | Y32: 11 | Z32: 11 | AA32: 11
B33: Vicepresidencia de Proyectos | D33: Finanzas VPP | F33: Real | G33: 6 | H33: 6 | I33: 6 | J33: 6 | K33: 6 | L33: 6 | M33: 6 | N33: 6 | O33: 6 | P33: 6 | Q33: 7 | R33: 7 | S33: 6.1666667 | T33: 7 | U33: 6 | V33: 6 | X33: 6 | Y33: 6 | Z33: 6 | AA33: 7
F34: Ppto | G34: 7 | H34: 7 | I34: 7 | J34: 7 | K34: 7 | L34: 7 | M34: 7 | N34: 7 | O34: 7 | P34: 7 | Q34: 7 | R34: 7 | S34: 7 | T34: 7 | U34: 7 | V34: 7 | X34: 7 | Y34: 7 | Z34: 7 | AA34: 7
D35: Ingenieria y Construccion | F35: Real | G35: 4 | H35: 4 | I35: 4 | J35: 6 | K35: 5 | L35: 3 | M35: 3 | N35: 3 | O35: 4 | P35: 4 | Q35: 4 | R35: 4 | S35: 4 | T35: 4 | U35: 4 | V35: 4 | X35: 4 | Y35: 5 | Z35: 3 | AA35: 4
F36: Ppto | G36: 5 | H36: 5 | I36: 5 | J36: 5 | K36: 5 | L36: 5 | M36: 5 | N36: 5 | O36: 5 | P36: 5 | Q36: 5 | R36: 5 | S36: 5 | T36: 5 | U36: 5 | V36: 5 | X36: 5 | Y36: 5 | Z36: 5 | AA36: 5
D37: Vicepresidencia de Proyectos + Proyecto INCO + Proyecto Estudio | F37: Real | G37: 2 | H37: 2 | I37: 2 | J37: 2 | K37: 2 | L37: 2 | M37: 2 | N37: 2 | O37: 3 | P37: 3 | Q37: 2 | R37: 2 | S37: 2.1666667 | T37: 2 | U37: 2 | V37: 2 | X37: 2 | Y37: 2 | Z37: 2 | AA37: 2
F38: Ppto | G38: 2 | H38: 2 | I38: 2 | J38: 2 | K38: 2 | L38: 2 | M38: 2 | N38: 2 | O38: 2 | P38: 2 | Q38: 2 | R38: 2 | S38: 2 | T38: 2 | U38: 2 | V38: 2 | X38: 2 | Y38: 2 | Z38: 2 | AA38: 2
B39: Vicepresidencia Desarrollo | D39: Administración MIC | F39: Real | G39: 3 | H39: 3 | I39: 3 | J39: 3 | K39: 3 | L39: 3 | M39: 3 | N39: 3 | O39: 3 | P39: 2 | Q39: 2 | R39: 2 | S39: 2.75 | T39: 2 | U39: 3 | V39: 3 | X39: 3 | Y39: 3 | Z39: 3 | AA39: 2
F40: Ppto | G40: 4 | H40: 4 | I40: 4 | J40: 4 | K40: 4 | L40: 4 | M40: 3 | N40: 3 | O40: 3 | P40: 3 | Q40: 3 | R40: 3 | S40: 3.5 | T40: 3 | U40: 4 | V40: 4 | X40: 4 | Y40: 4 | Z40: 3 | AA40: 3
D41: Desarrollo | F41: Real | G41: 9 | H41: 9 | I41: 9 | J41: 9 | K41: 9 | L41: 9 | M41: 9 | N41: 9 | O41: 9 | P41: 9 | Q41: 9 | R41: 9 | S41: 9 | T41: 9 | U41: 9 | V41: 9 | X41: 9 | Y41: 9 | Z41: 9 | AA41: 9
F42: Ppto | G42: 9 | H42: 9 | I42: 9 | J42: 9 | K42: 9 | L42: 9 | M42: 9 | N42: 9 | O42: 9 | P42: 9 | Q42: 9 | R42: 9 | S42: 9 | T42: 9 | U42: 9 | V42: 9 | X42: 9 | Y42: 9 | Z42: 9 | AA42: 9
D43: Exploraciones Global | F43: Real | G43: 0 | H43: 0 | I43: 0 | J43: 0 | K43: 0 | L43: 0 | M43: 2 | N43: 2 | O43: 2 | P43: 0 | Q43: 0 | R43: 0 | S43: 0.5 | T43: 0 | U43: 2 | V43: 2 | X43: 0 | Y43: 0 | Z43: 2 | AA43: 0
F44: Ppto | G44: 0 | H44: 0 | I44: 0 | J44: 0 | K44: 0 | L44: 0 | M44: 0 | N44: 0 | O44: 0 | P44: 0 | Q44: 0 | R44: 0 | S44: 0 | T44: 0 | U44: 0 | V44: 0 | X44: 0 | Y44: 0 | Z44: 0 | AA44: 0
D45: Geología | F45: Real | G45: 0 | H45: 0 | I45: 0 | J45: 0 | K45: 0 | L45: 0 | M45: 1 | N45: 1 | O45: 1 | P45: 0 | Q45: 0 | R45: 0 | S45: 0.25 | T45: 0 | U45: 0 | V45: 0 | X45: 0 | Y45: 0 | Z45: 1 | AA45: 0
F46: Ppto | G46: 0 | H46: 0 | I46: 0 | J46: 0 | K46: 0 | L46: 0 | M46: 0 | N46: 0 | O46: 0 | P46: 0 | Q46: 0 | R46: 0 | S46: 0 | T46: 0 | U46: 1 | V46: 1 | X46: 0 | Y46: 0 | Z46: 0 | AA46: 0
D47: Vicepresidencia Desarrollo | F47: Real | G47: 5 | H47: 5 | I47: 5 | J47: 6 | K47: 6 | L47: 7 | M47: 4 | N47: 4 | O47: 4 | P47: 4 | Q47: 4 | R47: 4 | S47: 4.8333333 | T47: 0 | U47: 0 | V47: 0 | X47: 5 | Y47: 6 | Z47: 4 | AA47: 4
F48: Ppto | G48: 5 | H48: 5 | I48: 5 | J48: 5 | K48: 5 | L48: 5 | M48: 5 | N48: 5 | O48: 5 | P48: 5 | Q48: 5 | R48: 5 | S48: 5 | T48: 4 | U48: 5 | V48: 5 | X48: 5 | Y48: 5 | Z48: 5 | AA48: 5
B49: Vicepresidencia Estrategia e Innovación | D49: Data y Analítica Avanzada | F49: Real | G49: 5 | H49: 5 | I49: 5 | J49: 6 | K49: 6 | L49: 7 | M49: 7 | N49: 7 | O49: 8 | P49: 8 | Q49: 8 | R49: 8 | S49: 6.6666667 | T49: 5 | U49: 5 | V49: 5 | X49: 5 | Y49: 6 | Z49: 7 | AA49: 8
F50: Ppto | G50: 5 | H50: 5 | I50: 5 | J50: 5 | K50: 5 | L50: 5 | M50: 5 | N50: 5 | O50: 5 | P50: 5 | Q50: 5 | R50: 5 | S50: 5 | T50: 8 | U50: 7 | V50: 7 | X50: 5 | Y50: 5 | Z50: 5 | AA50: 5
D51: Estrategia Recursos Mineros | F51: Real | G51: 4 | H51: 4 | I51: 4 | J51: 4 | K51: 4 | L51: 4 | M51: 0 | N51: 0 | O51: 0 | P51: 0 | Q51: 0 | R51: 0 | S51: 2 | T51: 5 | U51: 5 | V51: 5 | X51: 4 | Y51: 4 | Z51: 0 | AA51: 0
F52: Ppto | G52: 4 | H52: 4 | I52: 4 | J52: 4 | K52: 4 | L52: 4 | M52: 4 | N52: 4 | O52: 4 | P52: 4 | Q52: 4 | R52: 4 | S52: 4 | T52: 0 | U52: 4 | V52: 2 | X52: 4 | Y52: 4 | Z52: 4 | AA52: 4
D53: Innovación + Energía y Recursos Hídricos | F53: Real | G53: 9 | H53: 10 | I53: 11 | J53: 11 | K53: 11 | L53: 10 | M53: 9 | N53: 9 | O53: 8 | P53: 6 | Q53: 7 | R53: 8 | S53: 9.0833333 | T53: 4 | U53: 4 | V53: 4 | X53: 10 | Y53: 11 | Z53: 9 | AA53: 7
F54: Ppto | G54: 14 | H54: 14 | I54: 14 | J54: 14 | K54: 14 | L54: 14 | M54: 14 | N54: 14 | O54: 14 | P54: 14 | Q54: 14 | R54: 14 | S54: 14 | T54: 8 | U54: 9 | V54: 9 | X54: 14 | Y54: 14 | Z54: 14 | AA54: 14
D55: TICA | F55: Real | G55: 53 | H55: 50 | I55: 48 | J55: 48 | K55: 48 | L55: 53 | M55: 53 | N55: 53 | O55: 53 | P55: 54 | Q55: 53 | R55: 53 | S55: 51.583333 | T55: 14 | U55: 14 | V55: 14 | X55: 50 | Y55: 50 | Z55: 53 | AA55: 53
F56: Ppto | G56: 56 | H56: 56 | I56: 56 | J56: 56 | K56: 56 | L56: 56 | M56: 56 | N56: 56 | O56: 56 | P56: 56 | Q56: 56 | R56: 56 | S56: 56 | T56: 53 | U56: 52 | V56: 52 | X56: 56 | Y56: 56 | Z56: 56 | AA56: 56
D57: Vicepresidencia Estrategia e Innovación | F57: Real | G57: 6 | H57: 6 | I57: 6 | J57: 6 | K57: 6 | L57: 6 | M57: 7 | N57: 7 | O57: 7 | P57: 7 | Q57: 8 | R57: 8 | S57: 6.6666667 | T57: 56 | U57: 56 | V57: 56 | X57: 6 | Y57: 6 | Z57: 7 | AA57: 8
F58: Ppto | G58: 6 | H58: 6 | I58: 6 | J58: 6 | K58: 6 | L58: 6 | M58: 6 | N58: 6 | O58: 6 | P58: 6 | Q58: 6 | R58: 6 | S58: 6 | T58: 8 | U58: 7 | V58: 7 | X58: 6 | Y58: 6 | Z58: 6 | AA58: 6
B59: Vicepresidencia Finanzas | D59: Abastecimiento | F59: Real | G59: 33 | H59: 36 | I59: 37 | J59: 36 | K59: 36 | L59: 36 | M59: 36 | N59: 37 | O59: 37 | P59: 37 | Q59: 37 | R59: 37 | S59: 36.25 | T59: 6 | U59: 6 | V59: 6 | X59: 35 | Y59: 36 | Z59: 37 | AA59: 37
F60: Ppto | G60: 38 | H60: 38 | I60: 38 | J60: 38 | K60: 38 | L60: 38 | M60: 38 | N60: 38 | O60: 38 | P60: 38 | Q60: 38 | R60: 38 | S60: 38 | T60: 37 | U60: 36 | V60: 36 | X60: 38 | Y60: 38 | Z60: 38 | AA60: 38
D61: Contabilidad | F61: Real | G61: 35 | H61: 35 | I61: 35 | J61: 34 | K61: 34 | L61: 34 | M61: 35 | N61: 35 | O61: 35 | P61: 36 | Q61: 35 | R61: 36 | S61: 34.916667 | T61: 38 | U61: 38 | V61: 38 | X61: 35 | Y61: 34 | Z61: 35 | AA61: 36
F62: Ppto | G62: 37 | H62: 37 | I62: 36 | J62: 36 | K62: 36 | L62: 36 | M62: 36 | N62: 36 | O62: 36 | P62: 36 | Q62: 36 | R62: 36 | S62: 36.166667 | T62: 36 | U62: 35 | V62: 35 | X62: 37 | Y62: 36 | Z62: 36 | AA62: 36
D63: Energia y Recursos Hidricos | F63: Real | G63: 0 | H63: 0 | I63: 0 | J63: 0 | K63: 0 | L63: 0 | M63: 0 | N63: 0 | O63: 0 | P63: 2 | Q63: 2 | R63: 2 | S63: 0.5 | T63: 36 | U63: 36 | V63: 36 | X63: 0 | Y63: 0 | Z63: 0 | AA63: 2
F64: Ppto | G64: 0 | H64: 0 | I64: 0 | J64: 0 | K64: 0 | L64: 0 | M64: 0 | N64: 0 | O64: 0 | P64: 0 | Q64: 0 | R64: 0 | S64: 0 | T64: 2 | U64: 2 | V64: 2 | X64: 0 | Y64: 0 | Z64: 0 | AA64: 0
D65: Finanzas e Impuestos + Planificación Financiera | F65: Real | G65: 26 | H65: 26 | I65: 25 | J65: 25 | K65: 25 | L65: 24 | M65: 23 | N65: 23 | O65: 22 | P65: 24 | Q65: 24 | R65: 25 | S65: 24.333333 | T65: 0 | U65: 0 | V65: 0 | X65: 26 | Y65: 25 | Z65: 23 | AA65: 24
F66: Ppto | G66: 26 | H66: 26 | I66: 26 | J66: 26 | K66: 26 | L66: 26 | M66: 26 | N66: 26 | O66: 26 | P66: 26 | Q66: 26 | R66: 26 | S66: 26 | T66: 25 | U66: 24 | V66: 24 | X66: 26 | Y66: 26 | Z66: 26 | AA66: 26
D67: Planificacion y Control de Gestion | F67: Real | G67: 10 | H67: 10 | I67: 10 | J67: 10 | K67: 10 | L67: 10 | M67: 10 | N67: 10 | O67: 9 | P67: 10 | Q67: 10 | R67: 10 | S67: 9.9166667 | T67: 26 | U67: 26 | V67: 26 | X67: 10 | Y67: 10 | Z67: 10 | AA67: 10
F68: Ppto | G68: 10 | H68: 10 | I68: 10 | J68: 10 | K68: 10 | L68: 10 | M68: 10 | N68: 10 | O68: 10 | P68: 10 | Q68: 10 | R68: 10 | S68: 10 | T68: 10 | U68: 10 | V68: 10 | X68: 10 | Y68: 10 | Z68: 10 | AA68: 10
D69: Riesgo Compliance y Control Interno | F69: Real | G69: 7 | H69: 8 | I69: 7 | J69: 7 | K69: 8 | L69: 8 | M69: 8 | N69: 8 | O69: 8 | P69: 8 | Q69: 8 | R69: 8 | S69: 7.75 | T69: 10 | U69: 10 | V69: 10 | X69: 7 | Y69: 8 | Z69: 8 | AA69: 8
F70: Ppto | G70: 9 | H70: 9 | I70: 9 | J70: 8 | K70: 8 | L70: 8 | M70: 8 | N70: 8 | O70: 8 | P70: 8 | Q70: 8 | R70: 8 | S70: 8.25 | T70: 8 | U70: 8 | V70: 8 | X70: 9 | Y70: 8 | Z70: 8 | AA70: 8
D71: Vicepresidencia Finanzas | F71: Real | G71: 2 | H71: 2 | I71: 2 | J71: 2 | K71: 2 | L71: 2 | M71: 2 | N71: 3 | O71: 3 | P71: 3 | Q71: 2 | R71: 3 | S71: 2.3333333 | T71: 8 | U71: 8 | V71: 8 | X71: 2 | Y71: 2 | Z71: 3 | AA71: 3
F72: Ppto | G72: 2 | H72: 2 | I72: 2 | J72: 2 | K72: 2 | L72: 2 | M72: 2 | N72: 2 | O72: 2 | P72: 2 | Q72: 2 | R72: 2 | S72: 2 | T72: 3 | U72: 2 | V72: 2 | X72: 2 | Y72: 2 | Z72: 2 | AA72: 2
B73: Vicepresidencia Legal | D73: Legal | F73: Real | G73: 8 | H73: 8 | I73: 8 | J73: 8 | K73: 8 | L73: 8 | M73: 7 | N73: 7 | O73: 8 | P73: 8 | Q73: 8 | R73: 8 | S73: 7.8333333 | T73: 2 | U73: 2 | V73: 2 | X73: 8 | Y73: 8 | Z73: 7 | AA73: 8
F74: Ppto | G74: 9 | H74: 9 | I74: 9 | J74: 9 | K74: 9 | L74: 9 | M74: 9 | N74: 9 | O74: 9 | P74: 9 | Q74: 9 | R74: 9 | S74: 9 | T74: 8 | U74: 8 | V74: 8 | X74: 9 | Y74: 9 | Z74: 9 | AA74: 9
D75: Propiedad Minera | F75: Real | G75: 8 | H75: 8 | I75: 9 | J75: 9 | K75: 9 | L75: 9 | M75: 9 | N75: 9 | O75: 9 | P75: 9 | Q75: 9 | R75: 9 | S75: 8.8333333 | T75: 9 | U75: 9 | V75: 9 | X75: 8 | Y75: 9 | Z75: 9 | AA75: 9
F76: Ppto | G76: 9 | H76: 9 | I76: 9 | J76: 9 | K76: 9 | L76: 9 | M76: 9 | N76: 9 | O76: 9 | P76: 9 | Q76: 9 | R76: 9 | S76: 9 | T76: 9 | U76: 9 | V76: 9 | X76: 9 | Y76: 9 | Z76: 9 | AA76: 9
D77: Vicepresidencia Legal | F77: Real | G77: 2 | H77: 2 | I77: 2 | J77: 2 | K77: 2 | L77: 2 | M77: 2 | N77: 2 | O77: 2 | P77: 2 | Q77: 2 | R77: 2 | S77: 2 | T77: 9 | U77: 9 | V77: 9 | X77: 2 | Y77: 2 | Z77: 2 | AA77: 2
F78: Ppto | G78: 2 | H78: 2 | I78: 2 | J78: 2 | K78: 2 | L78: 2 | M78: 2 | N78: 2 | O78: 2 | P78: 2 | Q78: 2 | R78: 2 | S78: 2 | T78: 2 | U78: 2 | V78: 2 | X78: 2 | Y78: 2 | Z78: 2 | AA78: 2
B79: Vicepresidencia Operaciones | D79: Mantenimiento y Excelencia Operacional | F79: Real | G79: 6 | H79: 6 | I79: 5 | J79: 5 | K79: 5 | L79: 5 | M79: 0 | N79: 0 | O79: 0 | P79: 0 | Q79: 0 | R79: 0 | S79: 2.6666667 | T79: 2 | U79: 2 | V79: 2 | X79: 6 | Y79: 5 | Z79: 0 | AA79: 0
F80: Ppto | G80: 6 | H80: 6 | I80: 6 | J80: 5 | K80: 5 | L80: 5 | M80: 5 | N80: 5 | O80: 5 | P80: 5 | Q80: 5 | R80: 5 | S80: 5.25 | T80: 0 | U80: 5 | V80: 3 | X80: 6 | Y80: 5 | Z80: 5 | AA80: 5
D81: Minería | F81: Real | G81: 4 | H81: 4 | I81: 5 | J81: 4 | K81: 4 | L81: 4 | M81: 0 | N81: 0 | O81: 0 | P81: 0 | Q81: 0 | R81: 0 | S81: 2.0833333 | T81: 5 | U81: 5 | V81: 5 | X81: 4 | Y81: 4 | Z81: 0 | AA81: 0
F82: Ppto | G82: 3 | H82: 3 | I82: 3 | J82: 3 | K82: 3 | L82: 3 | M82: 3 | N82: 3 | O82: 3 | P82: 3 | Q82: 3 | R82: 3 | S82: 3 | T82: 0 | U82: 4 | V82: 2 | X82: 3 | Y82: 3 | Z82: 3 | AA82: 3
D83: Procesos + Tanques y Releves | F83: Real | G83: 4 | H83: 4 | I83: 4 | J83: 4 | K83: 5 | L83: 4 | M83: 0 | N83: 0 | O83: 0 | P83: 0 | Q83: 0 | R83: 0 | S83: 2.0833333 | T83: 3 | U83: 3 | V83: 3 | X83: 4 | Y83: 4 | Z83: 0 | AA83: 0
F84: Ppto | G84: 5 | H84: 5 | I84: 5 | J84: 4 | K84: 4 | L84: 4 | M84: 4 | N84: 4 | O84: 4 | P84: 4 | Q84: 4 | R84: 4 | S84: 4.25 | T84: 0 | U84: 4 | V84: 2 | X84: 5 | Y84: 4 | Z84: 4 | AA84: 4
D85: Vicepresidencia Operaciones | F85: Real | G85: 3 | H85: 3 | I85: 3 | J85: 3 | K85: 3 | L85: 2 | M85: 0 | N85: 0 | O85: 0 | P85: 0 | Q85: 0 | R85: 0 | S85: 1.4166667 | T85: 4 | U85: 4 | V85: 4 | X85: 3 | Y85: 3 | Z85: 0 | AA85: 0
F86: Ppto | G86: 3 | H86: 3 | I86: 3 | J86: 3 | K86: 3 | L86: 3 | M86: 3 | N86: 3 | O86: 3 | P86: 3 | Q86: 3 | R86: 3 | S86: 3 | T86: 0 | U86: 3 | V86: 1 | X86: 3 | Y86: 3 | Z86: 3 | AA86: 3
B87: Vicepresidencia Personas y Organización | D87: Desarrollo Organizacional y Compensaciones | F87: Real | G87: 0 | H87: 0 | I87: 0 | J87: 0 | K87: 0 | L87: 0 | M87: 0 | N87: 13 | O87: 14 | P87: 15 | Q87: 16 | R87: 16 | S87: 6.1666667 | T87: 3 | U87: 3 | V87: 3 | X87: 0 | Y87: 0 | Z87: 14 | AA87: 16
F88: Ppto | G88: 0 | H88: 0 | I88: 0 | J88: 0 | K88: 0 | L88: 0 | M88: 0 | N88: 15 | O88: 15 | P88: 15 | Q88: 15 | R88: 15 | S88: 6.25 | T88: 16 | U88: 15 | V88: 15 | X88: 0 | Y88: 0 | Z88: 15 | AA88: 15
D89: Efectividad Organizacional | F89: Real | G89: 0 | H89: 0 | I89: 0 | J89: 0 | K89: 0 | L89: 0 | M89: 0 | N89: 15 | O89: 15 | P89: 15 | Q89: 14 | R89: 15 | S89: 6.1666667 | T89: 15 | U89: 15 | V89: 15 | X89: 0 | Y89: 0 | Z89: 15 | AA89: 15
F90: Ppto | G90: 0 | H90: 0 | I90: 0 | J90: 0 | K90: 0 | L90: 0 | M90: 0 | N90: 17 | O90: 17 | P90: 17 | Q90: 17 | R90: 17 | S90: 7.0833333 | T90: 15 | U90: 15 | V90: 15 | X90: 0 | Y90: 0 | Z90: 17 | AA90: 17
D91: Relaciones Laborales | F91: Real | G91: 0 | H91: 0 | I91: 0 | J91: 0 | K91: 0 | L91: 0 | M91: 0 | N91: 2 | O91: 2 | P91: 2 | Q91: 2 | R91: 2 | S91: 0.83333333 | T91: 17 | U91: 17 | V91: 17 | X91: 0 | Y91: 0 | Z91: 2 | AA91: 2
F92: Ppto | G92: 0 | H92: 0 | I92: 0 | J92: 0 | K92: 0 | L92: 0 | M92: 0 | N92: 2 | O92: 2 | P92: 2 | Q92: 2 | R92: 2 | S92: 0.83333333 | T92: 2 | U92: 2 | V92: 2 | X92: 0 | Y92: 0 | Z92: 2 | AA92: 2
D93: Vicepresidencia Personas y Organización | F93: Real | G93: 0 | H93: 0 | I93: 0 | J93: 0 | K93: 0 | L93: 0 | M93: 0 | N93: 4 | O93: 5 | P93: 5 | Q93: 5 | R93: 5 | S93: 2 | T93: 2 | U93: 2 | V93: 2 | X93: 0 | Y93: 0 | Z93: 5 | AA93: 5
F94: Ppto | G94: 0 | H94: 0 | I94: 0 | J94: 0 | K94: 0 | L94: 0 | M94: 0 | N94: 7 | O94: 7 | P94: 7 | Q94: 7 | R94: 7 | S94: 2.9166667 | T94: 5 | U94: 5 | V94: 5 | X94: 0 | Y94: 0 | Z94: 7 | AA94: 7
B95: Vicepresidencia Planificación y Servicios Técnicos | D95: Mantenimiento y Excelencia Operacional | F95: Real | G95: 0 | H95: 0 | I95: 0 | J95: 0 | K95: 0 | L95: 0 | M95: 5 | N95: 5 | O95: 5 | P95: 4 | Q95: 3 | R95: 3 | S95: 2.0833333 | T95: 7 | U95: 7 | V95: 7 | X95: 0 | Y95: 0 | Z95: 5 | AA95: 3
F96: Ppto | G96: 0 | H96: 0 | I96: 0 | J96: 0 | K96: 0 | L96: 0 | M96: 0 | N96: 0 | O96: 0 | P96: 0 | Q96: 0 | R96: 0 | S96: 0 | T96: 3 | U96: 4 | V96: 4 | X96: 0 | Y96: 0 | Z96: 0 | AA96: 0
D97: Planificación Minera Metalúrgica | F97: Real | G97: 0 | H97: 0 | I97: 0 | J97: 0 | K97: 0 | L97: 0 | M97: 4 | N97: 4 | O97: 4 | P97: 4 | Q97: 4 | R97: 4 | S97: 2 | T97: 0 | U97: 0 | V97: 0 | X97: 0 | Y97: 0 | Z97: 4 | AA97: 4
F98: Ppto | G98: 0 | H98: 0 | I98: 0 | J98: 0 | K98: 0 | L98: 0 | M98: 0 | N98: 0 | O98: 0 | P98: 0 | Q98: 0 | R98: 0 | S98: 0 | T98: 4 | U98: 4 | V98: 4 | X98: 0 | Y98: 0 | Z98: 0 | AA98: 0
D99: Procesos | F99: Real | G99: 0 | H99: 0 | I99: 0 | J99: 0 | K99: 0 | L99: 0 | M99: 0 | N99: 0 | O99: 0 | P99: 0 | Q99: 0 | R99: 0 | S99: 0 | T99: 0 | U99: 0 | V99: 0 | X99: 0 | Y99: 0 | Z99: 0 | AA99: 0
F100: Ppto | G100: 0 | H100: 0 | I100: 0 | J100: 0 | K100: 0 | L100: 0 | M100: 0 | N100: 0 | O100: 0 | P100: 0 | Q100: 0 | R100: 0 | S100: 0 | T100: 0 | U100: 0 | V100: 0 | X100: 0 | Y100: 0 | Z100: 0 | AA100: 0
...

Sheet 2022
B1: Libro Dotación Minera AMSA
H2: =+H4+H126+H152 -> 643 | I2: =+I4+I126+I152 -> 635 | J2: =+J4+J126+J152 -> 637 | K2: =+K4+K126+K152 -> 632 | L2: =+L4+L126+L152 -> 638 | M2: =+M4+M126+M152 -> 630 | N2: =+N4+N126+N152 -> 637 | O2: =+O4+O126+O152 -> 642 | ... S2: =+S4+S126+S152 -> 630
H3: =+H2-H173 -> 0 | I3: =+I2-I173 -> 0 | J3: =+J2-J173 -> 0 | K3: =+K2-K173 -> 0 | L3: =+L2-L173 -> 0 | M3: =+M2-M173 -> 0 | N3: =+N2-N173 -> 0 | O3: =+O2-O173 -> 0 | ... S3: =+S2-S173 -> 0
B4: Total Dotación Propia Actividad Corporativa | F4: Real | H4: 385 | I4: 384 | J4: 387 | K4: 383 | L4: 389 | M4: 383 | N4: 389 | O4: 390 | P4: 389 | Q4: 390 | R4: 386 | S4: 385 | U4: 385 | V4: 395 | W4: 394 | Y4: 387 | Z4: 387 | AA4: 390 | AB4: 396
F5: Ppto | H5: 417 | I5: 417 | J5: 416 | K5: 409 | L5: 407 | M5: 407 | N5: 406 | O5: 406 | P5: 406 | Q5: 406 | R5: 406 | S5: 406 | U5: 406 | V5: 409 | W5: 409 | Y5: 417 | Z5: 408 | AA5: 406 | AB5: 406
B7: Propia | F7: N° | H7: 202201 | I7: 202202 | J7: 202203 | K7: 202204 | L7: 202205 | M7: 202206 | N7: 202207 | O7: 202208 | P7: 202209 | Q7: 202210 | R7: 202211 | S7: 202212 | U7: MES | V7: YTD | W7: FY | Y7: Q1 | Z7: Q2 | AA7: Q3 | AB7: Q4
B8: Auditoria | D8: Auditoria | F8: Real | H8: 11 | I8: 11 | J8: 11 | K8: 11 | L8: 12 | M8: 12 | N8: 12 | O8: 12 | P8: 12 | Q8: 12 | R8: 12 | S8: 12 | U8: 12 | V8: 12 | W8: 12 | Y8: 11 | Z8: 12 | AA8: 12 | AB8: 12
F9: Ppto | H9: 12 | I9: 12 | J9: 12 | K9: 12 | L9: 12 | M9: 12 | N9: 12 | O9: 12 | P9: 12 | Q9: 12 | R9: 12 | S9: 12 | U9: 12 | V9: 12 | W9: 12 | Y9: 12 | Z9: 12 | AA9: 12 | AB9: 12
B10: Directorio | D10: Directorio | F10: Real | H10: 3 | I10: 3 | J10: 3 | K10: 3 | L10: 3 | M10: 3 | N10: 3 | O10: 3 | P10: 3 | Q10: 3 | R10: 3 | S10: 3 | U10: 3 | V10: 3 | W10: 3 | Y10: 3 | Z10: 3 | AA10: 3 | AB10: 3
F11: Ppto | H11: 3 | I11: 3 | J11: 3 | K11: 3 | L11: 3 | M11: 3 | N11: 3 | O11: 3 | P11: 3 | Q11: 3 | R11: 3 | S11: 3 | U11: 3 | V11: 3 | W11: 3 | Y11: 3 | Z11: 3 | AA11: 3 | AB11: 3
B12: Presidencia Ejecutiva | D12: Presidencia Ejecutiva | F12: Real | H12: 1 | I12: 1 | J12: 2 | K12: 2 | L12: 2 | M12: 2 | N12: 2 | O12: 2 | P12: 2 | Q12: 2 | R12: 2 | S12: 2 | U12: 2 | V12: 2 | W12: 2 | Y12: 1 | Z12: 2 | AA12: 2 | AB12: 2
F13: Ppto | H13: 2 | I13: 2 | J13: 2 | K13: 2 | L13: 2 | M13: 2 | N13: 2 | O13: 2 | P13: 2 | Q13: 2 | R13: 2 | S13: 2 | U13: 2 | V13: 2 | W13: 2 | Y13: 2 | Z13: 2 | AA13: 2 | AB13: 2
B14: Vicepresidencia Asuntos Corporativos y Sustentabilidad | D14: Asuntos Públicos Corporativo | F14: Real | H14: 7 | I14: 7 | J14: 7 | K14: 7 | L14: 7 | M14: 7 | N14: 7 | O14: 7 | P14: 7 | Q14: 7 | R14: 7 | S14: 7 | U14: 7 | V14: 7 | W14: 7 | Y14: 7 | Z14: 7 | AA14: 7 | AB14: 7
F15: Ppto | H15: 14 | I15: 14 | J15: 14 | K15: 14 | L15: 14 | M15: 14 | N15: 13 | O15: 13 | P15: 13 | Q15: 13 | R15: 13 | S15: 13 | U15: 13 | V15: 14 | W15: 14 | Y15: 14 | Z15: 14 | AA15: 13 | AB15: 13
D16: Asuntos Publicos MLP | F16: Real | H16: 21 | I16: 20 | J16: 21 | K16: 21 | L16: 20 | M16: 20 | N16: 20 | O16: 20 | P16: 20 | Q16: 20 | R16: 18 | S16: 18 | U16: 18 | V16: 20 | W16: 20 | Y16: 21 | Z16: 20 | AA16: 20 | AB16: 19
F17: Ppto | H17: 21 | I17: 21 | J17: 21 | K17: 21 | L17: 21 | M17: 21 | N17: 21 | O17: 21 | P17: 21 | Q17: 21 | R17: 21 | S17: 21 | U17: 21 | V17: 21 | W17: 21 | Y17: 21 | Z17: 21 | AA17: 21 | AB17: 21
D18: Asuntos Públicos Norte | F18: Real | H18: 12 | I18: 11 | J18: 13 | K18: 13 | L18: 14 | M18: 14 | N18: 14 | O18: 14 | P18: 14 | Q18: 14 | R18: 14 | S18: 14 | U18: 14 | V18: 13 | W18: 13 | Y18: 12 | Z18: 14 | AA18: 14 | AB18: 14
F19: Ppto | H19: 8 | I19: 8 | J19: 8 | K19: 8 | L19: 8 | M19: 8 | N19: 8 | O19: 8 | P19: 8 | Q19: 8 | R19: 8 | S19: 8 | U19: 8 | V19: 8 | W19: 8 | Y19: 8 | Z19: 8 | AA19: 8 | AB19: 8
D20: Comunicaciones | F20: Real | H20: 4 | I20: 4 | J20: 4 | K20: 5 | L20: 5 | M20: 5 | N20: 6 | O20: 6 | P20: 6 | Q20: 7 | R20: 7 | S20: 7 | U20: 7 | V20: 6 | W20: 6 | Y20: 4 | Z20: 5 | AA20: 6 | AB20: 7
F21: Ppto | H21: 7 | I21: 7 | J21: 7 | K21: 7 | L21: 7 | M21: 7 | N21: 7 | O21: 7 | P21: 7 | Q21: 7 | R21: 7 | S21: 7 | U21: 7 | V21: 7 | W21: 7 | Y21: 7 | Z21: 7 | AA21: 7 | AB21: 7
D22: Medio Ambiente | F22: Real | H22: 7 | I22: 7 | J22: 7 | K22: 7 | L22: 7 | M22: 7 | N22: 7 | O22: 7 | P22: 7 | Q22: 7 | R22: 7 | S22: 7 | U22: 7 | V22: 7 | W22: 7 | Y22: 7 | Z22: 7 | AA22: 7 | AB22: 7
F23: Ppto | H23: 8 | I23: 8 | J23: 8 | K23: 8 | L23: 8 | M23: 8 | N23: 8 | O23: 8 | P23: 8 | Q23: 8 | R23: 8 | S23: 8 | U23: 8 | V23: 8 | W23: 8 | Y23: 8 | Z23: 8 | AA23: 8 | AB23: 8
D24: SSO | F24: Real | H24: 4 | I24: 4 | J24: 4 | K24: 4 | L24: 5 | M24: 5 | N24: 5 | O24: 6 | P24: 4 | Q24: 5 | R24: 5 | S24: 5 | U24: 5 | V24: 5 | W24: 5 | Y24: 4 | Z24: 5 | AA24: 5 | AB24: 5
F25: Ppto | H25: 5 | I25: 5 | J25: 5 | K25: 5 | L25: 5 | M25: 5 | N25: 5 | O25: 5 | P25: 5 | Q25: 5 | R25: 5 | S25: 5 | U25: 5 | V25: 5 | W25: 5 | Y25: 5 | Z25: 5 | AA25: 5 | AB25: 5
D26: Vicepresidencia Asuntos Corporativos y Sustentabilidad | F26: Real | H26: 3 | I26: 3 | J26: 3 | K26: 3 | L26: 4 | M26: 4 | N26: 5 | O26: 5 | P26: 5 | Q26: 5 | R26: 5 | S26: 5 | U26: 5 | V26: 4 | W26: 4 | Y26: 3 | Z26: 4 | AA26: 5 | AB26: 5
F27: Ppto | H27: 4 | I27: 4 | J27: 4 | K27: 4 | L27: 4 | M27: 4 | N27: 4 | O27: 4 | P27: 4 | Q27: 4 | R27: 4 | S27: 4 | U27: 4 | V27: 4 | W27: 4 | Y27: 4 | Z27: 4 | AA27: 4 | AB27: 4
B28: Vicepresidencia Comercialización | D28: Ventas Cátodos Molibdeno y Hedge | F28: Real | H28: 6 | I28: 6 | J28: 6 | K28: 5 | L28: 5 | M28: 5 | N28: 5 | O28: 5 | P28: 5 | Q28: 5 | R28: 5 | S28: 5 | U28: 5 | V28: 5 | W28: 5 | Y28: 6 | Z28: 5 | AA28: 5 | AB28: 5
F29: Ppto | H29: 6 | I29: 6 | J29: 6 | K29: 6 | L29: 6 | M29: 6 | N29: 6 | O29: 6 | P29: 6 | Q29: 6 | R29: 6 | S29: 6 | U29: 6 | V29: 6 | W29: 6 | Y29: 6 | Z29: 6 | AA29: 6 | AB29: 6
D30: Ventas Concentrado Acido | F30: Real | H30: 4 | I30: 4 | J30: 4 | K30: 4 | L30: 4 | M30: 4 | N30: 4 | O30: 4 | P30: 4 | Q30: 4 | R30: 4 | S30: 4 | U30: 4 | V30: 4 | W30: 4 | Y30: 4 | Z30: 4 | AA30: 4 | AB30: 4
F31: Ppto | H31: 3 | I31: 3 | J31: 3 | K31: 3 | L31: 3 | M31: 3 | N31: 3 | O31: 3 | P31: 3 | Q31: 3 | R31: 3 | S31: 3 | U31: 3 | V31: 3 | W31: 3 | Y31: 3 | Z31: 3 | AA31: 3 | AB31: 3
D32: Vicepresidencia Comercialización | F32: Real | H32: 9 | I32: 9 | J32: 9 | K32: 10 | L32: 10 | M32: 10 | N32: 10 | O32: 10 | P32: 10 | Q32: 10 | R32: 10 | S32: 10 | U32: 10 | V32: 10 | W32: 10 | Y32: 9 | Z32: 10 | AA32: 10 | AB32: 10
F33: Ppto | H33: 10 | I33: 10 | J33: 10 | K33: 10 | L33: 10 | M33: 10 | N33: 10 | O33: 10 | P33: 10 | Q33: 10 | R33: 10 | S33: 10 | U33: 10 | V33: 10 | W33: 10 | Y33: 10 | Z33: 10 | AA33: 10 | AB33: 10
B34: Vicepresidencia de Proyectos | D34: Finanzas VPP | F34: Real | H34: 7 | I34: 7 | J34: 7 | K34: 7 | L34: 7 | M34: 7 | N34: 7 | O34: 7 | P34: 7 | Q34: 7 | R34: 7 | S34: 7 | U34: 7 | V34: 7 | W34: 7 | Y34: 7 | Z34: 7 | AA34: 7 | AB34: 7
F35: Ppto | H35: 8 | I35: 8 | J35: 8 | K35: 8 | L35: 8 | M35: 8 | N35: 8 | O35: 8 | P35: 8 | Q35: 8 | R35: 8 | S35: 8 | U35: 8 | V35: 8 | W35: 8 | Y35: 8 | Z35: 8 | AA35: 8 | AB35: 8
D36: Ingenieria y Construccion | F36: Real | H36: 4 | I36: 4 | J36: 4 | K36: 4 | L36: 4 | M36: 4 | N36: 4 | O36: 4 | P36: 4 | Q36: 4 | R36: 4 | S36: 4 | U36: 4 | V36: 4 | W36: 4 | Y36: 4 | Z36: 4 | AA36: 4 | AB36: 4
F37: Ppto | H37: 5 | I37: 5 | J37: 5 | K37: 5 | L37: 5 | M37: 5 | N37: 5 | O37: 5 | P37: 5 | Q37: 5 | R37: 5 | S37: 5 | U37: 5 | V37: 5 | W37: 5 | Y37: 5 | Z37: 5 | AA37: 5 | AB37: 5
D38: Vicepresidencia de Proyectos + Proyecto INCO | F38: Real | H38: 2 | I38: 2 | J38: 2 | K38: 2 | L38: 2 | M38: 3 | N38: 3 | O38: 3 | P38: 2 | Q38: 2 | R38: 2 | S38: 2 | U38: 2 | V38: 2 | W38: 2 | Y38: 2 | Z38: 2 | AA38: 3 | AB38: 2
F39: Ppto | H39: 2 | I39: 2 | J39: 2 | K39: 2 | L39: 2 | M39: 2 | N39: 2 | O39: 2 | P39: 2 | Q39: 2 | R39: 2 | S39: 2 | U39: 2 | V39: 2 | W39: 2 | Y39: 2 | Z39: 2 | AA39: 2 | AB39: 2
B40: Vicepresidencia Desarrollo | D40: Administración MIC | F40: Real | H40: 5 | I40: 5 | J40: 5 | K40: 4 | L40: 4 | M40: 4 | N40: 5 | O40: 5 | P40: 5 | Q40: 5 | R40: 5 | S40: 4 | U40: 4 | V40: 5 | W40: 5 | Y40: 5 | Z40: 4 | AA40: 5 | AB40: 5
F41: Ppto | H41: 5 | I41: 5 | J41: 5 | K41: 5 | L41: 3 | M41: 3 | N41: 3 | O41: 3 | P41: 3 | Q41: 3 | R41: 3 | S41: 3 | U41: 3 | V41: 4 | W41: 4 | Y41: 5 | Z41: 4 | AA41: 3 | AB41: 3
D42: Desarrollo | F42: Real | H42: 8 | I42: 8 | J42: 7 | K42: 7 | L42: 7 | M42: 7 | N42: 8 | O42: 8 | P42: 9 | Q42: 9 | R42: 9 | S42: 9 | U42: 9 | V42: 8 | W42: 8 | Y42: 8 | Z42: 7 | AA42: 8 | AB42: 9
F43: Ppto | H43: 9 | I43: 9 | J43: 9 | K43: 9 | L43: 9 | M43: 9 | N43: 9 | O43: 9 | P43: 9 | Q43: 9 | R43: 9 | S43: 9 | U43: 9 | V43: 9 | W43: 9 | Y43: 9 | Z43: 9 | AA43: 9 | AB43: 9
D44: Vicepresidencia Desarrollo | F44: Real | H44: 4 | I44: 4 | J44: 4 | K44: 4 | L44: 4 | M44: 4 | N44: 4 | O44: 4 | P44: 4 | Q44: 5 | R44: 5 | S44: 5 | U44: 5 | V44: 4 | W44: 4 | Y44: 4 | Z44: 4 | AA44: 4 | AB44: 5
F45: Ppto | H45: 5 | I45: 5 | J45: 5 | K45: 5 | L45: 5 | M45: 5 | N45: 5 | O45: 5 | P45: 5 | Q45: 5 | R45: 5 | S45: 5 | U45: 5 | V45: 5 | W45: 5 | Y45: 5 | Z45: 5 | AA45: 5 | AB45: 5
B46: Vicepresidencia Estrategia e Innovación | D46: Data y Analítica Avanzada | F46: Real | H46: 5 | I46: 5 | J46: 5 | K46: 6 | L46: 6 | M46: 5 | N46: 5 | O46: 5 | P46: 5 | Q46: 5 | R46: 5 | S46: 5 | U46: 5 | V46: 5 | W46: 5 | Y46: 5 | Z46: 6 | AA46: 5 | AB46: 5
F47: Ppto | H47: 6 | I47: 6 | J47: 6 | K47: 5 | L47: 5 | M47: 5 | N47: 5 | O47: 5 | P47: 5 | Q47: 5 | R47: 5 | S47: 5 | U47: 5 | V47: 5 | W47: 5 | Y47: 6 | Z47: 5 | AA47: 5 | AB47: 5
D48: Estrategia Recursos Mineros | F48: Real | H48: 4 | I48: 4 | J48: 4 | K48: 4 | L48: 4 | M48: 3 | N48: 4 | O48: 4 | P48: 4 | Q48: 4 | R48: 4 | S48: 4 | U48: 4 | V48: 4 | W48: 4 | Y48: 4 | Z48: 4 | AA48: 4 | AB48: 4
F49: Ppto | H49: 4 | I49: 4 | J49: 4 | K49: 4 | L49: 4 | M49: 4 | N49: 4 | O49: 4 | P49: 4 | Q49: 4 | R49: 4 | S49: 4 | U49: 4 | V49: 4 | W49: 4 | Y49: 4 | Z49: 4 | AA49: 4 | AB49: 4
D50: Innovación + Energía y Recursos Hídricos | F50: Real | H50: 11 | I50: 11 | J50: 10 | K50: 9 | L50: 9 | M50: 9 | N50: 10 | O50: 11 | P50: 11 | Q50: 11 | R50: 11 | S50: 9 | U50: 9 | V50: 10 | W50: 10 | Y50: 11 | Z50: 9 | AA50: 11 | AB50: 10
F51: Ppto | H51: 12 | I51: 12 | J51: 12 | K51: 12 | L51: 12 | M51: 12 | N51: 12 | O51: 12 | P51: 12 | Q51: 12 | R51: 12 | S51: 12 | U51: 12 | V51: 12 | W51: 12 | Y51: 12 | Z51: 12 | AA51: 12 | AB51: 12
D52: TICA | F52: Real | H52: 55 | I52: 54 | J52: 54 | K52: 54 | L52: 55 | M52: 54 | N52: 53 | O52: 53 | P52: 54 | Q52: 54 | R52: 53 | S52: 54 | U52: 54 | V52: 54 | W52: 54 | Y52: 54 | Z52: 54 | AA52: 53 | AB52: 54
F53: Ppto | H53: 55 | I53: 55 | J53: 55 | K53: 55 | L53: 55 | M53: 55 | N53: 55 | O53: 55 | P53: 55 | Q53: 55 | R53: 55 | S53: 55 | U53: 55 | V53: 55 | W53: 55 | Y53: 55 | Z53: 55 | AA53: 55 | AB53: 55
D54: Vicepresidencia Estrategia e Innovación | F54: Real | H54: 5 | I54: 6 | J54: 6 | K54: 6 | L54: 6 | M54: 6 | N54: 6 | O54: 6 | P54: 6 | Q54: 6 | R54: 6 | S54: 6 | U54: 6 | V54: 6 | W54: 6 | Y54: 6 | Z54: 6 | AA54: 6 | AB54: 6
F55: Ppto | H55: 7 | I55: 7 | J55: 7 | K55: 7 | L55: 7 | M55: 7 | N55: 7 | O55: 7 | P55: 7 | Q55: 7 | R55: 7 | S55: 7 | U55: 7 | V55: 7 | W55: 7 | Y55: 7 | Z55: 7 | AA55: 7 | AB55: 7
B56: Vicepresidencia Finanzas | D56: Abastecimiento | F56: Real | H56: 37 | I56: 37 | J56: 34 | K56: 33 | L56: 33 | M56: 33 | N56: 34 | O56: 34 | P56: 34 | Q56: 34 | R56: 33 | S56: 33 | U56: 33 | V56: 34 | W56: 34 | Y56: 36 | Z56: 33 | AA56: 34 | AB56: 33
F57: Ppto | H57: 39 | I57: 39 | J57: 38 | K57: 37 | L57: 37 | M57: 37 | N57: 37 | O57: 37 | P57: 37 | Q57: 37 | R57: 37 | S57: 37 | U57: 37 | V57: 37 | W57: 37 | Y57: 39 | Z57: 37 | AA57: 37 | AB57: 37
D58: Contabilidad | F58: Real | H58: 29 | I58: 29 | J58: 31 | K58: 30 | L58: 31 | M58: 31 | N58: 33 | O58: 33 | P58: 33 | Q58: 33 | R58: 33 | S58: 33 | U58: 33 | V58: 32 | W58: 32 | Y58: 30 | Z58: 31 | AA58: 33 | AB58: 33
F59: Ppto | H59: 30 | I59: 30 | J59: 30 | K59: 30 | L59: 30 | M59: 30 | N59: 30 | O59: 30 | P59: 30 | Q59: 30 | R59: 30 | S59: 30 | U59: 30 | V59: 30 | W59: 30 | Y59: 30 | Z59: 30 | AA59: 30 | AB59: 30
D60: Finanzas e Impuestos + Planificación Financiera | F60: Real | H60: 24 | I60: 22 | J60: 26 | K60: 26 | L60: 26 | M60: 26 | N60: 26 | O60: 26 | P60: 26 | Q60: 26 | R60: 26 | S60: 26 | U60: 26 | V60: 26 | W60: 26 | Y60: 24 | Z60: 26 | AA60: 26 | AB60: 26
F61: Ppto | H61: 28 | I61: 28 | J61: 28 | K61: 26 | L61: 26 | M61: 26 | N61: 26 | O61: 26 | P61: 26 | Q61: 26 | R61: 26 | S61: 26 | U61: 26 | V61: 27 | W61: 27 | Y61: 28 | Z61: 26 | AA61: 26 | AB61: 26
D62: Planificacion y Control de Gestion | F62: Real | H62: 10 | I62: 11 | J62: 11 | K62: 10 | L62: 10 | M62: 9 | N62: 9 | O62: 9 | P62: 9 | Q62: 9 | R62: 10 | S62: 10 | U62: 10 | V62: 10 | W62: 10 | Y62: 11 | Z62: 10 | AA62: 9 | AB62: 10
F63: Ppto | H63: 11 | I63: 11 | J63: 11 | K63: 10 | L63: 10 | M63: 10 | N63: 10 | O63: 10 | P63: 10 | Q63: 10 | R63: 10 | S63: 10 | U63: 10 | V63: 10 | W63: 10 | Y63: 11 | Z63: 10 | AA63: 10 | AB63: 10
D64: Riesgo Compliance y Control Interno | F64: Real | H64: 6 | I64: 7 | J64: 8 | K64: 8 | L64: 8 | M64: 8 | N64: 8 | O64: 7 | P64: 7 | Q64: 7 | R64: 7 | S64: 7 | U64: 7 | V64: 7 | W64: 7 | Y64: 7 | Z64: 8 | AA64: 7 | AB64: 7
F65: Ppto | H65: 8 | I65: 8 | J65: 8 | K65: 8 | L65: 8 | M65: 8 | N65: 8 | O65: 8 | P65: 8 | Q65: 8 | R65: 8 | S65: 8 | U65: 8 | V65: 8 | W65: 8 | Y65: 8 | Z65: 8 | AA65: 8 | AB65: 8
D66: Vicepresidencia Finanzas | F66: Real | H66: 4 | I66: 5 | J66: 2 | K66: 2 | L66: 2 | M66: 2 | N66: 2 | O66: 2 | P66: 2 | Q66: 2 | R66: 2 | S66: 2 | U66: 2 | V66: 2 | W66: 2 | Y66: 4 | Z66: 2 | AA66: 2 | AB66: 2
F67: Ppto | H67: 2 | I67: 2 | J67: 2 | K67: 2 | L67: 2 | M67: 2 | N67: 2 | O67: 2 | P67: 2 | Q67: 2 | R67: 2 | S67: 2 | U67: 2 | V67: 2 | W67: 2 | Y67: 2 | Z67: 2 | AA67: 2 | AB67: 2
B68: Vicepresidencia Legal | D68: Legal | F68: Real | H68: 7 | I68: 7 | J68: 7 | K68: 7 | L68: 7 | M68: 7 | N68: 7 | O68: 7 | P68: 7 | Q68: 7 | R68: 7 | S68: 7 | U68: 7 | V68: 7 | W68: 7 | Y68: 7 | Z68: 7 | AA68: 7 | AB68: 7
F69: Ppto | H69: 8 | I69: 8 | J69: 8 | K69: 8 | L69: 8 | M69: 8 | N69: 8 | O69: 8 | P69: 8 | Q69: 8 | R69: 8 | S69: 8 | U69: 8 | V69: 8 | W69: 8 | Y69: 8 | Z69: 8 | AA69: 8 | AB69: 8
D70: Propiedad Minera | F70: Real | H70: 8 | I70: 8 | J70: 8 | K70: 8 | L70: 8 | M70: 8 | N70: 8 | O70: 8 | P70: 8 | Q70: 8 | R70: 8 | S70: 8 | U70: 8 | V70: 8 | W70: 8 | Y70: 8 | Z70: 8 | AA70: 8 | AB70: 8
F71: Ppto | H71: 9 | I71: 9 | J71: 9 | K71: 9 | L71: 9 | M71: 9 | N71: 9 | O71: 9 | P71: 9 | Q71: 9 | R71: 9 | S71: 9 | U71: 9 | V71: 9 | W71: 9 | Y71: 9 | Z71: 9 | AA71: 9 | AB71: 9
D72: Vicepresidencia Legal | F72: Real | H72: 2 | I72: 2 | J72: 2 | K72: 2 | L72: 2 | M72: 2 | N72: 2 | O72: 2 | P72: 2 | Q72: 2 | R72: 2 | S72: 2 | U72: 2 | V72: 2 | W72: 2 | Y72: 2 | Z72: 2 | AA72: 2 | AB72: 2
F73: Ppto | H73: 2 | I73: 2 | J73: 2 | K73: 2 | L73: 2 | M73: 2 | N73: 2 | O73: 2 | P73: 2 | Q73: 2 | R73: 2 | S73: 2 | U73: 2 | V73: 2 | W73: 2 | Y73: 2 | Z73: 2 | AA73: 2 | AB73: 2
B74: Vicepresidencia Operaciones | D74: Mantenimiento y Excelencia Operacional | F74: Real | H74: 5 | I74: 5 | J74: 5 | K74: 6 | L74: 6 | M74: 6 | N74: 6 | O74: 6 | P74: 6 | Q74: 6 | R74: 6 | S74: 6 | U74: 6 | V74: 6 | W74: 6 | Y74: 5 | Z74: 6 | AA74: 6 | AB74: 6
F75: Ppto | H75: 6 | I75: 6 | J75: 6 | K75: 6 | L75: 6 | M75: 6 | N75: 6 | O75: 6 | P75: 6 | Q75: 6 | R75: 6 | S75: 6 | U75: 6 | V75: 6 | W75: 6 | Y75: 6 | Z75: 6 | AA75: 6 | AB75: 6
D76: Minería | F76: Real | H76: 4 | I76: 4 | J76: 4 | K76: 4 | L76: 4 | M76: 3 | N76: 3 | O76: 3 | P76: 3 | Q76: 3 | R76: 3 | S76: 3 | U76: 3 | V76: 3 | W76: 3 | Y76: 4 | Z76: 4 | AA76: 3 | AB76: 3
F77: Ppto | H77: 4 | I77: 4 | J77: 4 | K77: 3 | L77: 3 | M77: 3 | N77: 3 | O77: 3 | P77: 3 | Q77: 3 | R77: 3 | S77: 3 | U77: 3 | V77: 3 | W77: 3 | Y77: 4 | Z77: 3 | AA77: 3 | AB77: 3
D78: Procesos + Tanques y Releves | F78: Real | H78: 5 | I78: 5 | J78: 5 | K78: 5 | L78: 5 | M78: 5 | N78: 4 | O78: 4 | P78: 4 | Q78: 4 | R78: 4 | S78: 4 | U78: 4 | V78: 5 | W78: 5 | Y78: 5 | Z78: 5 | AA78: 4 | AB78: 4
F79: Ppto | H79: 6 | I79: 6 | J79: 6 | K79: 6 | L79: 6 | M79: 6 | N79: 6 | O79: 6 | P79: 6 | Q79: 6 | R79: 6 | S79: 6 | U79: 6 | V79: 6 | W79: 6 | Y79: 6 | Z79: 6 | AA79: 6 | AB79: 6
D80: Vicepresidencia Operaciones | F80: Real | H80: 3 | I80: 3 | J80: 4 | K80: 3 | L80: 3 | M80: 3 | N80: 3 | O80: 3 | P80: 3 | Q80: 3 | R80: 3 | S80: 3 | U80: 3 | V80: 3 | W80: 3 | Y80: 3 | Z80: 3 | AA80: 3 | AB80: 3
F81: Ppto | H81: 2 | I81: 2 | J81: 2 | K81: 2 | L81: 2 | M81: 2 | N81: 2 | O81: 2 | P81: 2 | Q81: 2 | R81: 2 | S81: 2 | U81: 2 | V81: 2 | W81: 2 | Y81: 2 | Z81: 2 | AA81: 2 | AB81: 2
B82: Vicepresidencia Recursos Humanos | D82: Compensaciones | F82: Real | H82: 3 | I82: 3 | J82: 3 | K82: 3 | L82: 3 | M82: 3 | N82: 3 | O82: 3 | P82: 3 | Q82: 3 | R82: 0 | S82: 0 | U82: 0 | V82: 3 | W82: 3 | Y82: 3 | Z82: 3 | AA82: 3 | AB82: 3
F83: Ppto | H83: 3 | I83: 3 | J83: 3 | K83: 3 | L83: 3 | M83: 3 | N83: 3 | O83: 3 | P83: 3 | Q83: 3 | R83: 3 | S83: 3 | U83: 3 | V83: 3 | W83: 3 | Y83: 3 | Z83: 3 | AA83: 3 | AB83: 3
D84: Desarrollo Organizacional | F84: Real | H84: 14 | I84: 14 | J84: 14 | K84: 14 | L84: 15 | M84: 14 | N84: 13 | O84: 9 | P84: 8 | Q84: 8 | R84: 0 | S84: 0 | U84: 0 | V84: 12 | W84: 13 | Y84: 14 | Z84: 14 | AA84: 10 | AB84: 8
F85: Ppto | H85: 15 | I85: 15 | J85: 15 | K85: 14 | L85: 14 | M85: 14 | N85: 14 | O85: 14 | P85: 14 | Q85: 14 | R85: 14 | S85: 14 | U85: 14 | V85: 14 | W85: 14 | Y85: 15 | Z85: 14 | AA85: 14 | AB85: 14
D86: Desarrollo Organizacional y Compensaciones | F86: Real | H86: 0 | I86: 0 | J86: 0 | K86: 0 | L86: 0 | M86: 0 | N86: 0 | O86: 1 | P86: 1 | Q86: 1 | R86: 11 | S86: 12 | U86: 12 | V86: 5 | W86: 4 | Y86: 0 | Z86: 0 | AA86: 1 | AB86: 8
F87: Ppto | H87: 0 | I87: 0 | J87: 0 | K87: 0 | L87: 0 | M87: 0 | N87: 0 | O87: 0 | P87: 0 | Q87: 0 | R87: 0 | S87: 0 | U87: 0 | V87: 0 | W87: 0 | Y87: 0 | Z87: 0 | AA87: 0 | AB87: 0
D88: Efectividad Organizacional | F88: Real | H88: 0 | I88: 0 | J88: 0 | K88: 0 | L88: 0 | M88: 0 | N88: 0 | O88: 4 | P88: 4 | Q88: 4 | R88: 4 | S88: 4 | U88: 4 | V88: 4 | W88: 3 | Y88: 0 | Z88: 0 | AA88: 4 | AB88: 4
F89: Ppto | H89: 0 | I89: 0 | J89: 0 | K89: 0 | L89: 0 | M89: 0 | N89: 0 | O89: 0 | P89: 0 | Q89: 0 | R89: 0 | S89: 0 | U89: 0 | V89: 0 | W89: 0 | Y89: 0 | Z89: 0 | AA89: 0 | AB89: 0
D90: Relaciones Laborales | F90: Real | H90: 2 | I90: 1 | J90: 1 | K90: 1 | L90: 1 | M90: 1 | N90: 1 | O90: 1 | P90: 2 | Q90: 0 | R90: 0 | S90: 1 | U90: 1 | V90: 1 | W90: 1 | Y90: 1 | Z90: 1 | AA90: 1 | AB90: 1
F91: Ppto | H91: 1 | I91: 1 | J91: 1 | K91: 1 | L91: 1 | M91: 1 | N91: 1 | O91: 1 | P91: 1 | Q91: 1 | R91: 1 | S91: 1 | U91: 1 | V91: 1 | W91: 1 | Y91: 1 | Z91: 1 | AA91: 1 | AB91: 1
D92: Remuneraciones y Gestión de Recursos Humanos | F92: Real | H92: 18 | I92: 18 | J92: 17 | K92: 17 | L92: 17 | M92: 16 | N92: 16 | O92: 12 | P92: 12 | Q92: 12 | R92: 12 | S92: 11 | U92: 11 | V92: 15 | W92: 15 | Y92: 18 | Z92: 17 | AA92: 13 | AB92: 12
F93: Ppto | H93: 20 | I93: 20 | J93: 20 | K93: 20 | L93: 20 | M93: 20 | N93: 20 | O93: 20 | P93: 20 | Q93: 20 | R93: 20 | S93: 20 | U93: 20 | V93: 20 | W93: 20 | Y93: 20 | Z93: 20 | AA93: 20 | AB93: 20
D94: Vicepresidencia Recursos Humanos | F94: Real | H94: 2 | I94: 3 | J94: 3 | K94: 2 | L94: 2 | M94: 2 | N94: 2 | O94: 5 | P94: 5 | Q94: 5 | R94: 5 | S94: 5 | U94: 5 | V94: 3 | W94: 3 | Y94: 3 | Z94: 2 | AA94: 4 | AB94: 5
F95: Ppto | H95: 2 | I95: 2 | J95: 2 | K95: 2 | L95: 2 | M95: 2 | N95: 2 | O95: 2 | P95: 2 | Q95: 2 | R95: 2 | S95: 2 | U95: 2 | V95: 2 | W95: 2 | Y95: 2 | Z95: 2 | AA95: 2 | AB95: 2
B96: Total Dotación Contratista Act. Corporativa | F96: Real | H96: 133 | I96: 130 | J96: 134 | K96: 114 | L96: 112 | M96: 113 | N96: 116 | O96: 115 | P96: 115 | Q96: 115 | R96: 123 | S96: 114 | U96: 114 | V96: 120 | W96: 120 | Y96: 132 | Z96: 113 | AA96: 115 | AB96: 117
F97: Ppto | H97: 131 | I97: 131 | J97: 132 | K97: 131 | L97: 131 | M97: 131 | N97: 131 | O97: 131 | P97: 131 | Q97: 131 | R97: 131 | S97: 131 | U97: 131 | V97: 131 | W97: 131 | Y97: 131 | Z97: 131 | AA97: 131 | AB97: 131
B98: Total Dotación Contratista Perm. | F98: Real | H98: 131 | I98: 128 | J98: 132 | K98: 112 | L98: 110 | M98: 111 | N98: 114 | O98: 113 | P98: 113 | Q98: 113 | R98: 120.88 | S98: 112 | U98: 112 | V98: 118 | W98: 118 | Y98: 130 | Z98: 111 | AA98: 113 | AB98: 115
F99: Ppto | H99: 129 | I99: 129 | J99: 130 | K99: 129 | L99: 129 | M99: 129 | N99: 129 | O99: 129 | P99: 129 | Q99: 129 | R99: 129 | S99: 129 | U99: 129 | V99: 129 | W99: 129 | Y99: 129 | Z99: 129 | AA99: 129 | AB99: 129
B100: Total Dotación Contratista Temp. | F100: Real | H100: 2 | I100: 2 | J100: 2 | K100: 2 | L100: 2 | M100: 2 | N100: 2 | O100: 2 | P100: 2 | Q100: 2 | R100: 2 | S100: 2 | U100: 2 | V100: 2 | W100: 2 | Y100: 2 | Z100: 2 | AA100: 2 | AB100: 2
F101: Ppto | H101: 2 | I101: 2 | J101: 2 | K101: 2 | L101: 2 | M101: 2 | N101: 2 | O101: 2 | P101: 2 | Q101: 2 | R101: 2 | S101: 2 | U101: 2 | V101: 2 | W101: 2 | Y101: 2 | Z101: 2 | AA101: 2 | AB101: 2
...
